# javap snapshot - Minecraft 26.1.2 client.jar
# Class: net.minecraft.client.model.animal.equine.AbstractEquineModel
# Pilot entry: net.minecraft.client.model.animal.equine.AbstractEquineModel
# Factory method: createBodyMesh
# Command: javap -c -constants
# Content: full class disassembly
# Generated: 2026-05-19T05:02:11.1385695-04:00
Compiled from "AbstractEquineModel.java"
public abstract class net.minecraft.client.model.animal.equine.AbstractEquineModel<T extends net.minecraft.client.renderer.entity.state.EquineRenderState> extends net.minecraft.client.model.EntityModel<T> {
  protected static final java.lang.String HEAD_PARTS;

  protected final net.minecraft.client.model.geom.ModelPart body;

  protected final net.minecraft.client.model.geom.ModelPart headParts;

  protected final net.minecraft.client.model.geom.ModelPart rightHindLeg;

  protected final net.minecraft.client.model.geom.ModelPart leftHindLeg;

  protected final net.minecraft.client.model.geom.ModelPart rightFrontLeg;

  protected final net.minecraft.client.model.geom.ModelPart leftFrontLeg;

  public net.minecraft.client.model.animal.equine.AbstractEquineModel(net.minecraft.client.model.geom.ModelPart);
    Code:
       0: aload_0
       1: aload_1
       2: invokespecial #3                  // Method net/minecraft/client/model/EntityModel."<init>":(Lnet/minecraft/client/model/geom/ModelPart;)V
       5: aload_0
       6: aload_1
       7: ldc           #11                 // String body
       9: invokevirtual #13                 // Method net/minecraft/client/model/geom/ModelPart.getChild:(Ljava/lang/String;)Lnet/minecraft/client/model/geom/ModelPart;
      12: putfield      #19                 // Field body:Lnet/minecraft/client/model/geom/ModelPart;
      15: aload_0
      16: aload_1
      17: ldc           #24                 // String head_parts
      19: invokevirtual #13                 // Method net/minecraft/client/model/geom/ModelPart.getChild:(Ljava/lang/String;)Lnet/minecraft/client/model/geom/ModelPart;
      22: putfield      #26                 // Field headParts:Lnet/minecraft/client/model/geom/ModelPart;
      25: aload_0
      26: aload_1
      27: ldc           #29                 // String right_hind_leg
      29: invokevirtual #13                 // Method net/minecraft/client/model/geom/ModelPart.getChild:(Ljava/lang/String;)Lnet/minecraft/client/model/geom/ModelPart;
      32: putfield      #31                 // Field rightHindLeg:Lnet/minecraft/client/model/geom/ModelPart;
      35: aload_0
      36: aload_1
      37: ldc           #34                 // String left_hind_leg
      39: invokevirtual #13                 // Method net/minecraft/client/model/geom/ModelPart.getChild:(Ljava/lang/String;)Lnet/minecraft/client/model/geom/ModelPart;
      42: putfield      #36                 // Field leftHindLeg:Lnet/minecraft/client/model/geom/ModelPart;
      45: aload_0
      46: aload_1
      47: ldc           #39                 // String right_front_leg
      49: invokevirtual #13                 // Method net/minecraft/client/model/geom/ModelPart.getChild:(Ljava/lang/String;)Lnet/minecraft/client/model/geom/ModelPart;
      52: putfield      #41                 // Field rightFrontLeg:Lnet/minecraft/client/model/geom/ModelPart;
      55: aload_0
      56: aload_1
      57: ldc           #44                 // String left_front_leg
      59: invokevirtual #13                 // Method net/minecraft/client/model/geom/ModelPart.getChild:(Ljava/lang/String;)Lnet/minecraft/client/model/geom/ModelPart;
      62: putfield      #46                 // Field leftFrontLeg:Lnet/minecraft/client/model/geom/ModelPart;
      65: aload_0
      66: aload_0
      67: getfield      #19                 // Field body:Lnet/minecraft/client/model/geom/ModelPart;
      70: ldc           #49                 // String tail
      72: invokevirtual #13                 // Method net/minecraft/client/model/geom/ModelPart.getChild:(Ljava/lang/String;)Lnet/minecraft/client/model/geom/ModelPart;
      75: putfield      #51                 // Field tail:Lnet/minecraft/client/model/geom/ModelPart;
      78: return

  public net.minecraft.client.model.animal.equine.AbstractEquineModel(net.minecraft.client.model.geom.ModelPart, net.minecraft.client.model.geom.ModelPart, net.minecraft.client.model.geom.ModelPart, net.minecraft.client.model.geom.ModelPart, net.minecraft.client.model.geom.ModelPart, net.minecraft.client.model.geom.ModelPart, net.minecraft.client.model.geom.ModelPart);
    Code:
       0: aload_0
       1: aload_1
       2: invokespecial #3                  // Method net/minecraft/client/model/EntityModel."<init>":(Lnet/minecraft/client/model/geom/ModelPart;)V
       5: aload_0
       6: aload_1
       7: ldc           #11                 // String body
       9: invokevirtual #13                 // Method net/minecraft/client/model/geom/ModelPart.getChild:(Ljava/lang/String;)Lnet/minecraft/client/model/geom/ModelPart;
      12: putfield      #19                 // Field body:Lnet/minecraft/client/model/geom/ModelPart;
      15: aload_0
      16: aload_2
      17: putfield      #26                 // Field headParts:Lnet/minecraft/client/model/geom/ModelPart;
      20: aload_0
      21: aload_3
      22: putfield      #31                 // Field rightHindLeg:Lnet/minecraft/client/model/geom/ModelPart;
      25: aload_0
      26: aload         5
      28: putfield      #36                 // Field leftHindLeg:Lnet/minecraft/client/model/geom/ModelPart;
      31: aload_0
      32: aload         4
      34: putfield      #41                 // Field rightFrontLeg:Lnet/minecraft/client/model/geom/ModelPart;
      37: aload_0
      38: aload         6
      40: putfield      #46                 // Field leftFrontLeg:Lnet/minecraft/client/model/geom/ModelPart;
      43: aload_0
      44: aload         7
      46: putfield      #51                 // Field tail:Lnet/minecraft/client/model/geom/ModelPart;
      49: return

  public static net.minecraft.client.model.geom.builders.MeshDefinition createBodyMesh(net.minecraft.client.model.geom.builders.CubeDeformation);
    Code:
       0: new           #53                 // class net/minecraft/client/model/geom/builders/MeshDefinition
       3: dup
       4: invokespecial #55                 // Method net/minecraft/client/model/geom/builders/MeshDefinition."<init>":()V
       7: astore_1
       8: aload_1
       9: invokevirtual #58                 // Method net/minecraft/client/model/geom/builders/MeshDefinition.getRoot:()Lnet/minecraft/client/model/geom/builders/PartDefinition;
      12: astore_2
      13: aload_2
      14: ldc           #11                 // String body
      16: invokestatic  #62                 // Method net/minecraft/client/model/geom/builders/CubeListBuilder.create:()Lnet/minecraft/client/model/geom/builders/CubeListBuilder;
      19: iconst_0
      20: bipush        32
      22: invokevirtual #68                 // Method net/minecraft/client/model/geom/builders/CubeListBuilder.texOffs:(II)Lnet/minecraft/client/model/geom/builders/CubeListBuilder;
      25: ldc           #72                 // float -5.0f
      27: ldc           #73                 // float -8.0f
      29: ldc           #74                 // float -17.0f
      31: ldc           #75                 // float 10.0f
      33: ldc           #75                 // float 10.0f
      35: ldc           #76                 // float 22.0f
      37: new           #77                 // class net/minecraft/client/model/geom/builders/CubeDeformation
      40: dup
      41: ldc           #79                 // float 0.05f
      43: invokespecial #80                 // Method net/minecraft/client/model/geom/builders/CubeDeformation."<init>":(F)V
      46: invokevirtual #83                 // Method net/minecraft/client/model/geom/builders/CubeListBuilder.addBox:(FFFFFFLnet/minecraft/client/model/geom/builders/CubeDeformation;)Lnet/minecraft/client/model/geom/builders/CubeListBuilder;
      49: fconst_0
      50: ldc           #87                 // float 11.0f
      52: ldc           #88                 // float 5.0f
      54: invokestatic  #89                 // Method net/minecraft/client/model/geom/PartPose.offset:(FFF)Lnet/minecraft/client/model/geom/PartPose;
      57: invokevirtual #95                 // Method net/minecraft/client/model/geom/builders/PartDefinition.addOrReplaceChild:(Ljava/lang/String;Lnet/minecraft/client/model/geom/builders/CubeListBuilder;Lnet/minecraft/client/model/geom/PartPose;)Lnet/minecraft/client/model/geom/builders/PartDefinition;
      60: astore_3
      61: aload_2
      62: ldc           #24                 // String head_parts
      64: invokestatic  #62                 // Method net/minecraft/client/model/geom/builders/CubeListBuilder.create:()Lnet/minecraft/client/model/geom/builders/CubeListBuilder;
      67: iconst_0
      68: bipush        35
      70: invokevirtual #68                 // Method net/minecraft/client/model/geom/builders/CubeListBuilder.texOffs:(II)Lnet/minecraft/client/model/geom/builders/CubeListBuilder;
      73: ldc           #101                // float -2.05f
      75: ldc           #102                // float -6.0f
      77: ldc           #103                // float -2.0f
      79: ldc           #104                // float 4.0f
      81: ldc           #105                // float 12.0f
      83: ldc           #106                // float 7.0f
      85: invokevirtual #107                // Method net/minecraft/client/model/geom/builders/CubeListBuilder.addBox:(FFFFFF)Lnet/minecraft/client/model/geom/builders/CubeListBuilder;
      88: fconst_0
      89: ldc           #104                // float 4.0f
      91: ldc           #110                // float -12.0f
      93: ldc           #111                // float 0.5235988f
      95: fconst_0
      96: fconst_0
      97: invokestatic  #112                // Method net/minecraft/client/model/geom/PartPose.offsetAndRotation:(FFFFFF)Lnet/minecraft/client/model/geom/PartPose;
     100: invokevirtual #95                 // Method net/minecraft/client/model/geom/builders/PartDefinition.addOrReplaceChild:(Ljava/lang/String;Lnet/minecraft/client/model/geom/builders/CubeListBuilder;Lnet/minecraft/client/model/geom/PartPose;)Lnet/minecraft/client/model/geom/builders/PartDefinition;
     103: astore        4
     105: aload         4
     107: ldc           #116                // String head
     109: invokestatic  #62                 // Method net/minecraft/client/model/geom/builders/CubeListBuilder.create:()Lnet/minecraft/client/model/geom/builders/CubeListBuilder;
     112: iconst_0
     113: bipush        13
     115: invokevirtual #68                 // Method net/minecraft/client/model/geom/builders/CubeListBuilder.texOffs:(II)Lnet/minecraft/client/model/geom/builders/CubeListBuilder;
     118: ldc           #118                // float -3.0f
     120: ldc           #119                // float -11.0f
     122: ldc           #103                // float -2.0f
     124: ldc           #120                // float 6.0f
     126: ldc           #88                 // float 5.0f
     128: ldc           #106                // float 7.0f
     130: aload_0
     131: invokevirtual #83                 // Method net/minecraft/client/model/geom/builders/CubeListBuilder.addBox:(FFFFFFLnet/minecraft/client/model/geom/builders/CubeDeformation;)Lnet/minecraft/client/model/geom/builders/CubeListBuilder;
     134: getstatic     #121                // Field net/minecraft/client/model/geom/PartPose.ZERO:Lnet/minecraft/client/model/geom/PartPose;
     137: invokevirtual #95                 // Method net/minecraft/client/model/geom/builders/PartDefinition.addOrReplaceChild:(Ljava/lang/String;Lnet/minecraft/client/model/geom/builders/CubeListBuilder;Lnet/minecraft/client/model/geom/PartPose;)Lnet/minecraft/client/model/geom/builders/PartDefinition;
     140: astore        5
     142: aload         4
     144: ldc           #125                // String mane
     146: invokestatic  #62                 // Method net/minecraft/client/model/geom/builders/CubeListBuilder.create:()Lnet/minecraft/client/model/geom/builders/CubeListBuilder;
     149: bipush        56
     151: bipush        36
     153: invokevirtual #68                 // Method net/minecraft/client/model/geom/builders/CubeListBuilder.texOffs:(II)Lnet/minecraft/client/model/geom/builders/CubeListBuilder;
     156: ldc           #127                // float -1.0f
     158: ldc           #119                // float -11.0f
     160: ldc           #128                // float 5.01f
     162: fconst_2
     163: ldc           #129                // float 16.0f
     165: fconst_2
     166: aload_0
     167: invokevirtual #83                 // Method net/minecraft/client/model/geom/builders/CubeListBuilder.addBox:(FFFFFFLnet/minecraft/client/model/geom/builders/CubeDeformation;)Lnet/minecraft/client/model/geom/builders/CubeListBuilder;
     170: getstatic     #121                // Field net/minecraft/client/model/geom/PartPose.ZERO:Lnet/minecraft/client/model/geom/PartPose;
     173: invokevirtual #95                 // Method net/minecraft/client/model/geom/builders/PartDefinition.addOrReplaceChild:(Ljava/lang/String;Lnet/minecraft/client/model/geom/builders/CubeListBuilder;Lnet/minecraft/client/model/geom/PartPose;)Lnet/minecraft/client/model/geom/builders/PartDefinition;
     176: pop
     177: aload         4
     179: ldc           #130                // String upper_mouth
     181: invokestatic  #62                 // Method net/minecraft/client/model/geom/builders/CubeListBuilder.create:()Lnet/minecraft/client/model/geom/builders/CubeListBuilder;
     184: iconst_0
     185: bipush        25
     187: invokevirtual #68                 // Method net/minecraft/client/model/geom/builders/CubeListBuilder.texOffs:(II)Lnet/minecraft/client/model/geom/builders/CubeListBuilder;
     190: ldc           #103                // float -2.0f
     192: ldc           #119                // float -11.0f
     194: ldc           #132                // float -7.0f
     196: ldc           #104                // float 4.0f
     198: ldc           #88                 // float 5.0f
     200: ldc           #88                 // float 5.0f
     202: aload_0
     203: invokevirtual #83                 // Method net/minecraft/client/model/geom/builders/CubeListBuilder.addBox:(FFFFFFLnet/minecraft/client/model/geom/builders/CubeDeformation;)Lnet/minecraft/client/model/geom/builders/CubeListBuilder;
     206: getstatic     #121                // Field net/minecraft/client/model/geom/PartPose.ZERO:Lnet/minecraft/client/model/geom/PartPose;
     209: invokevirtual #95                 // Method net/minecraft/client/model/geom/builders/PartDefinition.addOrReplaceChild:(Ljava/lang/String;Lnet/minecraft/client/model/geom/builders/CubeListBuilder;Lnet/minecraft/client/model/geom/PartPose;)Lnet/minecraft/client/model/geom/builders/PartDefinition;
     212: pop
     213: aload_2
     214: ldc           #34                 // String left_hind_leg
     216: invokestatic  #62                 // Method net/minecraft/client/model/geom/builders/CubeListBuilder.create:()Lnet/minecraft/client/model/geom/builders/CubeListBuilder;
     219: bipush        48
     221: bipush        21
     223: invokevirtual #68                 // Method net/minecraft/client/model/geom/builders/CubeListBuilder.texOffs:(II)Lnet/minecraft/client/model/geom/builders/CubeListBuilder;
     226: invokevirtual #133                // Method net/minecraft/client/model/geom/builders/CubeListBuilder.mirror:()Lnet/minecraft/client/model/geom/builders/CubeListBuilder;
     229: ldc           #118                // float -3.0f
     231: ldc           #136                // float -1.01f
     233: ldc           #127                // float -1.0f
     235: ldc           #104                // float 4.0f
     237: ldc           #87                 // float 11.0f
     239: ldc           #104                // float 4.0f
     241: aload_0
     242: invokevirtual #83                 // Method net/minecraft/client/model/geom/builders/CubeListBuilder.addBox:(FFFFFFLnet/minecraft/client/model/geom/builders/CubeDeformation;)Lnet/minecraft/client/model/geom/builders/CubeListBuilder;
     245: ldc           #104                // float 4.0f
     247: ldc           #137                // float 14.0f
     249: ldc           #106                // float 7.0f
     251: invokestatic  #89                 // Method net/minecraft/client/model/geom/PartPose.offset:(FFF)Lnet/minecraft/client/model/geom/PartPose;
     254: invokevirtual #95                 // Method net/minecraft/client/model/geom/builders/PartDefinition.addOrReplaceChild:(Ljava/lang/String;Lnet/minecraft/client/model/geom/builders/CubeListBuilder;Lnet/minecraft/client/model/geom/PartPose;)Lnet/minecraft/client/model/geom/builders/PartDefinition;
     257: pop
     258: aload_2
     259: ldc           #29                 // String right_hind_leg
     261: invokestatic  #62                 // Method net/minecraft/client/model/geom/builders/CubeListBuilder.create:()Lnet/minecraft/client/model/geom/builders/CubeListBuilder;
     264: bipush        48
     266: bipush        21
     268: invokevirtual #68                 // Method net/minecraft/client/model/geom/builders/CubeListBuilder.texOffs:(II)Lnet/minecraft/client/model/geom/builders/CubeListBuilder;
     271: ldc           #127                // float -1.0f
     273: ldc           #136                // float -1.01f
     275: ldc           #127                // float -1.0f
     277: ldc           #104                // float 4.0f
     279: ldc           #87                 // float 11.0f
     281: ldc           #104                // float 4.0f
     283: aload_0
     284: invokevirtual #83                 // Method net/minecraft/client/model/geom/builders/CubeListBuilder.addBox:(FFFFFFLnet/minecraft/client/model/geom/builders/CubeDeformation;)Lnet/minecraft/client/model/geom/builders/CubeListBuilder;
     287: ldc           #138                // float -4.0f
     289: ldc           #137                // float 14.0f
     291: ldc           #106                // float 7.0f
     293: invokestatic  #89                 // Method net/minecraft/client/model/geom/PartPose.offset:(FFF)Lnet/minecraft/client/model/geom/PartPose;
     296: invokevirtual #95                 // Method net/minecraft/client/model/geom/builders/PartDefinition.addOrReplaceChild:(Ljava/lang/String;Lnet/minecraft/client/model/geom/builders/CubeListBuilder;Lnet/minecraft/client/model/geom/PartPose;)Lnet/minecraft/client/model/geom/builders/PartDefinition;
     299: pop
     300: aload_2
     301: ldc           #44                 // String left_front_leg
     303: invokestatic  #62                 // Method net/minecraft/client/model/geom/builders/CubeListBuilder.create:()Lnet/minecraft/client/model/geom/builders/CubeListBuilder;
     306: bipush        48
     308: bipush        21
     310: invokevirtual #68                 // Method net/minecraft/client/model/geom/builders/CubeListBuilder.texOffs:(II)Lnet/minecraft/client/model/geom/builders/CubeListBuilder;
     313: invokevirtual #133                // Method net/minecraft/client/model/geom/builders/CubeListBuilder.mirror:()Lnet/minecraft/client/model/geom/builders/CubeListBuilder;
     316: ldc           #118                // float -3.0f
     318: ldc           #136                // float -1.01f
     320: ldc           #139                // float -1.9f
     322: ldc           #104                // float 4.0f
     324: ldc           #87                 // float 11.0f
     326: ldc           #104                // float 4.0f
     328: aload_0
     329: invokevirtual #83                 // Method net/minecraft/client/model/geom/builders/CubeListBuilder.addBox:(FFFFFFLnet/minecraft/client/model/geom/builders/CubeDeformation;)Lnet/minecraft/client/model/geom/builders/CubeListBuilder;
     332: ldc           #104                // float 4.0f
     334: ldc           #137                // float 14.0f
     336: ldc           #140                // float -10.0f
     338: invokestatic  #89                 // Method net/minecraft/client/model/geom/PartPose.offset:(FFF)Lnet/minecraft/client/model/geom/PartPose;
     341: invokevirtual #95                 // Method net/minecraft/client/model/geom/builders/PartDefinition.addOrReplaceChild:(Ljava/lang/String;Lnet/minecraft/client/model/geom/builders/CubeListBuilder;Lnet/minecraft/client/model/geom/PartPose;)Lnet/minecraft/client/model/geom/builders/PartDefinition;
     344: pop
     345: aload_2
     346: ldc           #39                 // String right_front_leg
     348: invokestatic  #62                 // Method net/minecraft/client/model/geom/builders/CubeListBuilder.create:()Lnet/minecraft/client/model/geom/builders/CubeListBuilder;
     351: bipush        48
     353: bipush        21
     355: invokevirtual #68                 // Method net/minecraft/client/model/geom/builders/CubeListBuilder.texOffs:(II)Lnet/minecraft/client/model/geom/builders/CubeListBuilder;
     358: ldc           #127                // float -1.0f
     360: ldc           #136                // float -1.01f
     362: ldc           #139                // float -1.9f
     364: ldc           #104                // float 4.0f
     366: ldc           #87                 // float 11.0f
     368: ldc           #104                // float 4.0f
     370: aload_0
     371: invokevirtual #83                 // Method net/minecraft/client/model/geom/builders/CubeListBuilder.addBox:(FFFFFFLnet/minecraft/client/model/geom/builders/CubeDeformation;)Lnet/minecraft/client/model/geom/builders/CubeListBuilder;
     374: ldc           #138                // float -4.0f
     376: ldc           #137                // float 14.0f
     378: ldc           #140                // float -10.0f
     380: invokestatic  #89                 // Method net/minecraft/client/model/geom/PartPose.offset:(FFF)Lnet/minecraft/client/model/geom/PartPose;
     383: invokevirtual #95                 // Method net/minecraft/client/model/geom/builders/PartDefinition.addOrReplaceChild:(Ljava/lang/String;Lnet/minecraft/client/model/geom/builders/CubeListBuilder;Lnet/minecraft/client/model/geom/PartPose;)Lnet/minecraft/client/model/geom/builders/PartDefinition;
     386: pop
     387: aload_3
     388: ldc           #49                 // String tail
     390: invokestatic  #62                 // Method net/minecraft/client/model/geom/builders/CubeListBuilder.create:()Lnet/minecraft/client/model/geom/builders/CubeListBuilder;
     393: bipush        42
     395: bipush        36
     397: invokevirtual #68                 // Method net/minecraft/client/model/geom/builders/CubeListBuilder.texOffs:(II)Lnet/minecraft/client/model/geom/builders/CubeListBuilder;
     400: ldc           #141                // float -1.5f
     402: fconst_0
     403: fconst_0
     404: ldc           #142                // float 3.0f
     406: ldc           #137                // float 14.0f
     408: ldc           #104                // float 4.0f
     410: aload_0
     411: invokevirtual #83                 // Method net/minecraft/client/model/geom/builders/CubeListBuilder.addBox:(FFFFFFLnet/minecraft/client/model/geom/builders/CubeDeformation;)Lnet/minecraft/client/model/geom/builders/CubeListBuilder;
     414: fconst_0
     415: ldc           #72                 // float -5.0f
     417: fconst_2
     418: ldc           #111                // float 0.5235988f
     420: fconst_0
     421: fconst_0
     422: invokestatic  #112                // Method net/minecraft/client/model/geom/PartPose.offsetAndRotation:(FFFFFF)Lnet/minecraft/client/model/geom/PartPose;
     425: invokevirtual #95                 // Method net/minecraft/client/model/geom/builders/PartDefinition.addOrReplaceChild:(Ljava/lang/String;Lnet/minecraft/client/model/geom/builders/CubeListBuilder;Lnet/minecraft/client/model/geom/PartPose;)Lnet/minecraft/client/model/geom/builders/PartDefinition;
     428: pop
     429: aload         5
     431: ldc           #143                // String left_ear
     433: invokestatic  #62                 // Method net/minecraft/client/model/geom/builders/CubeListBuilder.create:()Lnet/minecraft/client/model/geom/builders/CubeListBuilder;
     436: bipush        19
     438: bipush        16
     440: invokevirtual #68                 // Method net/minecraft/client/model/geom/builders/CubeListBuilder.texOffs:(II)Lnet/minecraft/client/model/geom/builders/CubeListBuilder;
     443: ldc           #145                // float 0.55f
     445: ldc           #146                // float -13.0f
     447: ldc           #104                // float 4.0f
     449: fconst_2
     450: ldc           #142                // float 3.0f
     452: fconst_1
     453: new           #77                 // class net/minecraft/client/model/geom/builders/CubeDeformation
     456: dup
     457: ldc           #147                // float -0.001f
     459: invokespecial #80                 // Method net/minecraft/client/model/geom/builders/CubeDeformation."<init>":(F)V
     462: invokevirtual #83                 // Method net/minecraft/client/model/geom/builders/CubeListBuilder.addBox:(FFFFFFLnet/minecraft/client/model/geom/builders/CubeDeformation;)Lnet/minecraft/client/model/geom/builders/CubeListBuilder;
     465: getstatic     #121                // Field net/minecraft/client/model/geom/PartPose.ZERO:Lnet/minecraft/client/model/geom/PartPose;
     468: invokevirtual #95                 // Method net/minecraft/client/model/geom/builders/PartDefinition.addOrReplaceChild:(Ljava/lang/String;Lnet/minecraft/client/model/geom/builders/CubeListBuilder;Lnet/minecraft/client/model/geom/PartPose;)Lnet/minecraft/client/model/geom/builders/PartDefinition;
     471: pop
     472: aload         5
     474: ldc           #148                // String right_ear
     476: invokestatic  #62                 // Method net/minecraft/client/model/geom/builders/CubeListBuilder.create:()Lnet/minecraft/client/model/geom/builders/CubeListBuilder;
     479: bipush        19
     481: bipush        16
     483: invokevirtual #68                 // Method net/minecraft/client/model/geom/builders/CubeListBuilder.texOffs:(II)Lnet/minecraft/client/model/geom/builders/CubeListBuilder;
     486: ldc           #150                // float -2.55f
     488: ldc           #146                // float -13.0f
     490: ldc           #104                // float 4.0f
     492: fconst_2
     493: ldc           #142                // float 3.0f
     495: fconst_1
     496: new           #77                 // class net/minecraft/client/model/geom/builders/CubeDeformation
     499: dup
     500: ldc           #147                // float -0.001f
     502: invokespecial #80                 // Method net/minecraft/client/model/geom/builders/CubeDeformation."<init>":(F)V
     505: invokevirtual #83                 // Method net/minecraft/client/model/geom/builders/CubeListBuilder.addBox:(FFFFFFLnet/minecraft/client/model/geom/builders/CubeDeformation;)Lnet/minecraft/client/model/geom/builders/CubeListBuilder;
     508: getstatic     #121                // Field net/minecraft/client/model/geom/PartPose.ZERO:Lnet/minecraft/client/model/geom/PartPose;
     511: invokevirtual #95                 // Method net/minecraft/client/model/geom/builders/PartDefinition.addOrReplaceChild:(Ljava/lang/String;Lnet/minecraft/client/model/geom/builders/CubeListBuilder;Lnet/minecraft/client/model/geom/PartPose;)Lnet/minecraft/client/model/geom/builders/PartDefinition;
     514: pop
     515: aload_1
     516: areturn

  public void setupAnim(T);
    Code:
       0: aload_0
       1: aload_1
       2: invokespecial #151                // Method net/minecraft/client/model/EntityModel.setupAnim:(Ljava/lang/Object;)V
       5: aload_1
       6: getfield      #155                // Field net/minecraft/client/renderer/entity/state/EquineRenderState.yRot:F
       9: ldc           #161                // float -20.0f
      11: ldc           #162                // float 20.0f
      13: invokestatic  #163                // Method net/minecraft/util/Mth.clamp:(FFF)F
      16: fstore_2
      17: aload_1
      18: getfield      #167                // Field net/minecraft/client/renderer/entity/state/EquineRenderState.xRot:F
      21: ldc           #170                // float 0.017453292f
      23: fmul
      24: fstore_3
      25: aload_1
      26: getfield      #171                // Field net/minecraft/client/renderer/entity/state/EquineRenderState.walkAnimationSpeed:F
      29: fstore        4
      31: aload_1
      32: getfield      #174                // Field net/minecraft/client/renderer/entity/state/EquineRenderState.walkAnimationPos:F
      35: fstore        5
      37: fload         4
      39: ldc           #177                // float 0.2f
      41: fcmpl
      42: ifle          63
      45: fload_3
      46: fload         5
      48: ldc           #178                // float 0.8f
      50: fmul
      51: f2d
      52: invokestatic  #179                // Method net/minecraft/util/Mth.cos:(D)F
      55: ldc           #183                // float 0.15f
      57: fmul
      58: fload         4
      60: fmul
      61: fadd
      62: fstore_3
      63: aload_1
      64: getfield      #184                // Field net/minecraft/client/renderer/entity/state/EquineRenderState.eatAnimation:F
      67: fstore        6
      69: aload_1
      70: getfield      #187                // Field net/minecraft/client/renderer/entity/state/EquineRenderState.standAnimation:F
      73: fstore        7
      75: fconst_1
      76: fload         7
      78: fsub
      79: fstore        8
      81: aload_1
      82: getfield      #190                // Field net/minecraft/client/renderer/entity/state/EquineRenderState.feedingAnimation:F
      85: fstore        9
      87: aload_1
      88: getfield      #193                // Field net/minecraft/client/renderer/entity/state/EquineRenderState.animateTail:Z
      91: istore        10
      93: aload_0
      94: getfield      #26                 // Field headParts:Lnet/minecraft/client/model/geom/ModelPart;
      97: ldc           #111                // float 0.5235988f
      99: fload_3
     100: fadd
     101: putfield      #197                // Field net/minecraft/client/model/geom/ModelPart.xRot:F
     104: aload_0
     105: getfield      #26                 // Field headParts:Lnet/minecraft/client/model/geom/ModelPart;
     108: fload_2
     109: ldc           #170                // float 0.017453292f
     111: fmul
     112: putfield      #198                // Field net/minecraft/client/model/geom/ModelPart.yRot:F
     115: aload_1
     116: getfield      #199                // Field net/minecraft/client/renderer/entity/state/EquineRenderState.isInWater:Z
     119: ifeq          127
     122: ldc           #177                // float 0.2f
     124: goto          128
     127: fconst_1
     128: fstore        11
     130: fload         11
     132: fload         5
     134: fmul
     135: ldc           #202                // float 0.6662f
     137: fmul
     138: ldc           #203                // float 3.1415927f
     140: fadd
     141: f2d
     142: invokestatic  #179                // Method net/minecraft/util/Mth.cos:(D)F
     145: fstore        12
     147: fload         12
     149: ldc           #178                // float 0.8f
     151: fmul
     152: fload         4
     154: fmul
     155: fstore        13
     157: fconst_1
     158: fload         7
     160: fload         6
     162: invokestatic  #204                // Method java/lang/Math.max:(FF)F
     165: fsub
     166: ldc           #111                // float 0.5235988f
     168: fload_3
     169: fadd
     170: fload         9
     172: aload_1
     173: getfield      #210                // Field net/minecraft/client/renderer/entity/state/EquineRenderState.ageInTicks:F
     176: f2d
     177: invokestatic  #213                // Method net/minecraft/util/Mth.sin:(D)F
     180: fmul
     181: ldc           #79                 // float 0.05f
     183: fmul
     184: fadd
     185: fmul
     186: fstore        14
     188: aload_0
     189: getfield      #26                 // Field headParts:Lnet/minecraft/client/model/geom/ModelPart;
     192: fload         7
     194: ldc           #216                // float 0.2617994f
     196: fload_3
     197: fadd
     198: fmul
     199: fload         6
     201: ldc           #217                // float 2.1816616f
     203: aload_1
     204: getfield      #210                // Field net/minecraft/client/renderer/entity/state/EquineRenderState.ageInTicks:F
     207: f2d
     208: invokestatic  #213                // Method net/minecraft/util/Mth.sin:(D)F
     211: ldc           #79                 // float 0.05f
     213: fmul
     214: fadd
     215: fmul
     216: fadd
     217: fload         14
     219: fadd
     220: putfield      #197                // Field net/minecraft/client/model/geom/ModelPart.xRot:F
     223: aload_0
     224: getfield      #26                 // Field headParts:Lnet/minecraft/client/model/geom/ModelPart;
     227: fload         7
     229: fload_2
     230: fmul
     231: ldc           #170                // float 0.017453292f
     233: fmul
     234: fconst_1
     235: fload         7
     237: fload         6
     239: invokestatic  #204                // Method java/lang/Math.max:(FF)F
     242: fsub
     243: aload_0
     244: getfield      #26                 // Field headParts:Lnet/minecraft/client/model/geom/ModelPart;
     247: getfield      #198                // Field net/minecraft/client/model/geom/ModelPart.yRot:F
     250: fmul
     251: fadd
     252: putfield      #198                // Field net/minecraft/client/model/geom/ModelPart.yRot:F
     255: aload_0
     256: fload         6
     258: fload         7
     260: invokevirtual #218                // Method animateHeadPartsPlacement:(FF)V
     263: aload_0
     264: getfield      #19                 // Field body:Lnet/minecraft/client/model/geom/ModelPart;
     267: fload         7
     269: ldc           #222                // float -0.7853982f
     271: fmul
     272: fload         8
     274: aload_0
     275: getfield      #19                 // Field body:Lnet/minecraft/client/model/geom/ModelPart;
     278: getfield      #197                // Field net/minecraft/client/model/geom/ModelPart.xRot:F
     281: fmul
     282: fadd
     283: putfield      #197                // Field net/minecraft/client/model/geom/ModelPart.xRot:F
     286: aload_0
     287: getfield      #46                 // Field leftFrontLeg:Lnet/minecraft/client/model/geom/ModelPart;
     290: dup
     291: getfield      #223                // Field net/minecraft/client/model/geom/ModelPart.y:F
     294: aload_0
     295: invokevirtual #226                // Method getLegStandingYOffset:()F
     298: fload         7
     300: fmul
     301: fsub
     302: putfield      #223                // Field net/minecraft/client/model/geom/ModelPart.y:F
     305: aload_0
     306: getfield      #46                 // Field leftFrontLeg:Lnet/minecraft/client/model/geom/ModelPart;
     309: dup
     310: getfield      #230                // Field net/minecraft/client/model/geom/ModelPart.z:F
     313: aload_0
     314: invokevirtual #233                // Method getLegStandingZOffset:()F
     317: fload         7
     319: fmul
     320: fadd
     321: putfield      #230                // Field net/minecraft/client/model/geom/ModelPart.z:F
     324: aload_0
     325: getfield      #41                 // Field rightFrontLeg:Lnet/minecraft/client/model/geom/ModelPart;
     328: aload_0
     329: getfield      #46                 // Field leftFrontLeg:Lnet/minecraft/client/model/geom/ModelPart;
     332: getfield      #223                // Field net/minecraft/client/model/geom/ModelPart.y:F
     335: putfield      #223                // Field net/minecraft/client/model/geom/ModelPart.y:F
     338: aload_0
     339: getfield      #41                 // Field rightFrontLeg:Lnet/minecraft/client/model/geom/ModelPart;
     342: aload_0
     343: getfield      #46                 // Field leftFrontLeg:Lnet/minecraft/client/model/geom/ModelPart;
     346: getfield      #230                // Field net/minecraft/client/model/geom/ModelPart.z:F
     349: putfield      #230                // Field net/minecraft/client/model/geom/ModelPart.z:F
     352: aload_0
     353: invokevirtual #236                // Method getLegStandAngle:()F
     356: fload         7
     358: fmul
     359: fstore        15
     361: aload_1
     362: getfield      #210                // Field net/minecraft/client/renderer/entity/state/EquineRenderState.ageInTicks:F
     365: ldc           #239                // float 0.6f
     367: fmul
     368: ldc           #203                // float 3.1415927f
     370: fadd
     371: f2d
     372: invokestatic  #179                // Method net/minecraft/util/Mth.cos:(D)F
     375: fstore        16
     377: aload_0
     378: invokevirtual #240                // Method getLegStandingXRotOffset:()F
     381: fstore        17
     383: fload         17
     385: fload         16
     387: fadd
     388: fload         7
     390: fmul
     391: fload         13
     393: fload         8
     395: fmul
     396: fadd
     397: fstore        18
     399: fload         17
     401: fload         16
     403: fsub
     404: fload         7
     406: fmul
     407: fload         13
     409: fload         8
     411: fmul
     412: fsub
     413: fstore        19
     415: aload_0
     416: getfield      #36                 // Field leftHindLeg:Lnet/minecraft/client/model/geom/ModelPart;
     419: fload         15
     421: fload         12
     423: ldc           #243                // float 0.5f
     425: fmul
     426: fload         4
     428: fmul
     429: fload         8
     431: fmul
     432: fsub
     433: putfield      #197                // Field net/minecraft/client/model/geom/ModelPart.xRot:F
     436: aload_0
     437: getfield      #31                 // Field rightHindLeg:Lnet/minecraft/client/model/geom/ModelPart;
     440: fload         15
     442: fload         12
     444: ldc           #243                // float 0.5f
     446: fmul
     447: fload         4
     449: fmul
     450: fload         8
     452: fmul
     453: fadd
     454: putfield      #197                // Field net/minecraft/client/model/geom/ModelPart.xRot:F
     457: aload_0
     458: getfield      #46                 // Field leftFrontLeg:Lnet/minecraft/client/model/geom/ModelPart;
     461: fload         18
     463: putfield      #197                // Field net/minecraft/client/model/geom/ModelPart.xRot:F
     466: aload_0
     467: getfield      #41                 // Field rightFrontLeg:Lnet/minecraft/client/model/geom/ModelPart;
     470: fload         19
     472: putfield      #197                // Field net/minecraft/client/model/geom/ModelPart.xRot:F
     475: aload_0
     476: fload         7
     478: invokevirtual #244                // Method offsetLegPositionWhenStanding:(F)V
     481: aload_1
     482: getfield      #247                // Field net/minecraft/client/renderer/entity/state/EquineRenderState.ageScale:F
     485: fstore        20
     487: aload_0
     488: getfield      #51                 // Field tail:Lnet/minecraft/client/model/geom/ModelPart;
     491: aload_0
     492: invokevirtual #250                // Method getTailXRotOffset:()F
     495: ldc           #111                // float 0.5235988f
     497: fadd
     498: fload         4
     500: ldc           #253                // float 0.75f
     502: fmul
     503: fadd
     504: putfield      #197                // Field net/minecraft/client/model/geom/ModelPart.xRot:F
     507: aload_0
     508: getfield      #51                 // Field tail:Lnet/minecraft/client/model/geom/ModelPart;
     511: dup
     512: getfield      #223                // Field net/minecraft/client/model/geom/ModelPart.y:F
     515: fload         4
     517: fload         20
     519: fmul
     520: fadd
     521: putfield      #223                // Field net/minecraft/client/model/geom/ModelPart.y:F
     524: aload_0
     525: getfield      #51                 // Field tail:Lnet/minecraft/client/model/geom/ModelPart;
     528: dup
     529: getfield      #230                // Field net/minecraft/client/model/geom/ModelPart.z:F
     532: fload         4
     534: fconst_2
     535: fmul
     536: fload         20
     538: fmul
     539: fadd
     540: putfield      #230                // Field net/minecraft/client/model/geom/ModelPart.z:F
     543: iload         10
     545: ifeq          569
     548: aload_0
     549: getfield      #51                 // Field tail:Lnet/minecraft/client/model/geom/ModelPart;
     552: aload_1
     553: getfield      #210                // Field net/minecraft/client/renderer/entity/state/EquineRenderState.ageInTicks:F
     556: ldc           #254                // float 0.7f
     558: fmul
     559: f2d
     560: invokestatic  #179                // Method net/minecraft/util/Mth.cos:(D)F
     563: putfield      #198                // Field net/minecraft/client/model/geom/ModelPart.yRot:F
     566: goto          577
     569: aload_0
     570: getfield      #51                 // Field tail:Lnet/minecraft/client/model/geom/ModelPart;
     573: fconst_0
     574: putfield      #198                // Field net/minecraft/client/model/geom/ModelPart.yRot:F
     577: return

  protected void offsetLegPositionWhenStanding(float);
    Code:
       0: return

  protected float getLegStandAngle();
    Code:
       0: ldc           #216                // float 0.2617994f
       2: freturn

  protected float getLegStandingYOffset();
    Code:
       0: ldc           #105                // float 12.0f
       2: freturn

  protected float getLegStandingZOffset();
    Code:
       0: ldc           #104                // float 4.0f
       2: freturn

  protected float getLegStandingXRotOffset();
    Code:
       0: ldc           #255                // float -1.0471976f
       2: freturn

  protected float getTailXRotOffset();
    Code:
       0: fconst_0
       1: freturn

  protected void animateHeadPartsPlacement(float, float);
    Code:
       0: aload_0
       1: getfield      #26                 // Field headParts:Lnet/minecraft/client/model/geom/ModelPart;
       4: dup
       5: getfield      #223                // Field net/minecraft/client/model/geom/ModelPart.y:F
       8: fload_1
       9: fload_2
      10: fconst_0
      11: ldc           #73                 // float -8.0f
      13: invokestatic  #256                // Method net/minecraft/util/Mth.lerp:(FFF)F
      16: ldc           #106                // float 7.0f
      18: invokestatic  #256                // Method net/minecraft/util/Mth.lerp:(FFF)F
      21: fadd
      22: putfield      #223                // Field net/minecraft/client/model/geom/ModelPart.y:F
      25: aload_0
      26: getfield      #26                 // Field headParts:Lnet/minecraft/client/model/geom/ModelPart;
      29: fload_2
      30: aload_0
      31: getfield      #26                 // Field headParts:Lnet/minecraft/client/model/geom/ModelPart;
      34: getfield      #230                // Field net/minecraft/client/model/geom/ModelPart.z:F
      37: ldc           #138                // float -4.0f
      39: invokestatic  #256                // Method net/minecraft/util/Mth.lerp:(FFF)F
      42: putfield      #230                // Field net/minecraft/client/model/geom/ModelPart.z:F
      45: return

  public void setupAnim(java.lang.Object);
    Code:
       0: aload_0
       1: aload_1
       2: checkcast     #156                // class net/minecraft/client/renderer/entity/state/EquineRenderState
       5: invokevirtual #259                // Method setupAnim:(Lnet/minecraft/client/renderer/entity/state/EquineRenderState;)V
       8: return
}
