Compiled from "AbstractSignRenderer.java"
public abstract class net.minecraft.client.renderer.blockentity.AbstractSignRenderer<S extends net.minecraft.client.renderer.blockentity.state.SignRenderState> implements net.minecraft.client.renderer.blockentity.BlockEntityRenderer<net.minecraft.world.level.block.entity.SignBlockEntity, S> {
  private static final int BLACK_TEXT_OUTLINE_COLOR = -988212;

  private static final int OUTLINE_RENDER_DISTANCE;

  private final net.minecraft.client.gui.Font font;

  private final net.minecraft.client.resources.model.sprite.SpriteGetter sprites;

  public net.minecraft.client.renderer.blockentity.AbstractSignRenderer(net.minecraft.client.renderer.blockentity.BlockEntityRendererProvider$Context);
    Code:
       0: aload_0
       1: invokespecial #1                  // Method java/lang/Object."<init>":()V
       4: aload_0
       5: aload_1
       6: invokevirtual #7                  // Method net/minecraft/client/renderer/blockentity/BlockEntityRendererProvider$Context.font:()Lnet/minecraft/client/gui/Font;
       9: putfield      #13                 // Field font:Lnet/minecraft/client/gui/Font;
      12: aload_0
      13: aload_1
      14: invokevirtual #18                 // Method net/minecraft/client/renderer/blockentity/BlockEntityRendererProvider$Context.sprites:()Lnet/minecraft/client/resources/model/sprite/SpriteGetter;
      17: putfield      #22                 // Field sprites:Lnet/minecraft/client/resources/model/sprite/SpriteGetter;
      20: return

  protected abstract net.minecraft.client.model.Model$Simple getSignModel(S);

  protected abstract net.minecraft.client.resources.model.sprite.SpriteId getSignSprite(net.minecraft.world.level.block.state.properties.WoodType);

  public void submit(S, com.mojang.blaze3d.vertex.PoseStack, net.minecraft.client.renderer.SubmitNodeCollector, net.minecraft.client.renderer.state.level.CameraRenderState);
    Code:
       0: aload_0
       1: aload_1
       2: aload_2
       3: aload_1
       4: getfield      #25                 // Field net/minecraft/client/renderer/blockentity/state/SignRenderState.breakProgress:Lnet/minecraft/client/renderer/feature/ModelFeatureRenderer$CrumblingOverlay;
       7: aload_3
       8: invokevirtual #31                 // Method submitSignWithText:(Lnet/minecraft/client/renderer/blockentity/state/SignRenderState;Lcom/mojang/blaze3d/vertex/PoseStack;Lnet/minecraft/client/renderer/feature/ModelFeatureRenderer$CrumblingOverlay;Lnet/minecraft/client/renderer/SubmitNodeCollector;)V
      11: return

  private void submitSignWithText(S, com.mojang.blaze3d.vertex.PoseStack, net.minecraft.client.renderer.feature.ModelFeatureRenderer$CrumblingOverlay, net.minecraft.client.renderer.SubmitNodeCollector);
    Code:
       0: aload_0
       1: aload_1
       2: invokevirtual #35                 // Method getSignModel:(Lnet/minecraft/client/renderer/blockentity/state/SignRenderState;)Lnet/minecraft/client/model/Model$Simple;
       5: astore        5
       7: aload_2
       8: invokevirtual #39                 // Method com/mojang/blaze3d/vertex/PoseStack.pushPose:()V
      11: aload_2
      12: aload_1
      13: getfield      #44                 // Field net/minecraft/client/renderer/blockentity/state/SignRenderState.transformations:Lnet/minecraft/client/renderer/blockentity/state/SignRenderState$SignTransformations;
      16: invokevirtual #48                 // Method net/minecraft/client/renderer/blockentity/state/SignRenderState$SignTransformations.body:()Lcom/mojang/math/Transformation;
      19: invokevirtual #54                 // Method com/mojang/blaze3d/vertex/PoseStack.mulPose:(Lcom/mojang/math/Transformation;)V
      22: aload_0
      23: aload_2
      24: aload_1
      25: getfield      #58                 // Field net/minecraft/client/renderer/blockentity/state/SignRenderState.lightCoords:I
      28: aload_1
      29: getfield      #62                 // Field net/minecraft/client/renderer/blockentity/state/SignRenderState.woodType:Lnet/minecraft/world/level/block/state/properties/WoodType;
      32: aload         5
      34: aload_3
      35: aload         4
      37: invokevirtual #66                 // Method submitSign:(Lcom/mojang/blaze3d/vertex/PoseStack;ILnet/minecraft/world/level/block/state/properties/WoodType;Lnet/minecraft/client/model/Model$Simple;Lnet/minecraft/client/renderer/feature/ModelFeatureRenderer$CrumblingOverlay;Lnet/minecraft/client/renderer/SubmitNodeCollector;)V
      40: aload_2
      41: invokevirtual #70                 // Method com/mojang/blaze3d/vertex/PoseStack.popPose:()V
      44: aload_1
      45: getfield      #73                 // Field net/minecraft/client/renderer/blockentity/state/SignRenderState.frontText:Lnet/minecraft/world/level/block/entity/SignText;
      48: ifnull        82
      51: aload_2
      52: invokevirtual #39                 // Method com/mojang/blaze3d/vertex/PoseStack.pushPose:()V
      55: aload_2
      56: aload_1
      57: getfield      #44                 // Field net/minecraft/client/renderer/blockentity/state/SignRenderState.transformations:Lnet/minecraft/client/renderer/blockentity/state/SignRenderState$SignTransformations;
      60: invokevirtual #77                 // Method net/minecraft/client/renderer/blockentity/state/SignRenderState$SignTransformations.frontText:()Lcom/mojang/math/Transformation;
      63: invokevirtual #54                 // Method com/mojang/blaze3d/vertex/PoseStack.mulPose:(Lcom/mojang/math/Transformation;)V
      66: aload_0
      67: aload_1
      68: aload_2
      69: aload         4
      71: aload_1
      72: getfield      #73                 // Field net/minecraft/client/renderer/blockentity/state/SignRenderState.frontText:Lnet/minecraft/world/level/block/entity/SignText;
      75: invokevirtual #79                 // Method submitSignText:(Lnet/minecraft/client/renderer/blockentity/state/SignRenderState;Lcom/mojang/blaze3d/vertex/PoseStack;Lnet/minecraft/client/renderer/SubmitNodeCollector;Lnet/minecraft/world/level/block/entity/SignText;)V
      78: aload_2
      79: invokevirtual #70                 // Method com/mojang/blaze3d/vertex/PoseStack.popPose:()V
      82: aload_1
      83: getfield      #83                 // Field net/minecraft/client/renderer/blockentity/state/SignRenderState.backText:Lnet/minecraft/world/level/block/entity/SignText;
      86: ifnull        120
      89: aload_2
      90: invokevirtual #39                 // Method com/mojang/blaze3d/vertex/PoseStack.pushPose:()V
      93: aload_2
      94: aload_1
      95: getfield      #44                 // Field net/minecraft/client/renderer/blockentity/state/SignRenderState.transformations:Lnet/minecraft/client/renderer/blockentity/state/SignRenderState$SignTransformations;
      98: invokevirtual #86                 // Method net/minecraft/client/renderer/blockentity/state/SignRenderState$SignTransformations.backText:()Lcom/mojang/math/Transformation;
     101: invokevirtual #54                 // Method com/mojang/blaze3d/vertex/PoseStack.mulPose:(Lcom/mojang/math/Transformation;)V
     104: aload_0
     105: aload_1
     106: aload_2
     107: aload         4
     109: aload_1
     110: getfield      #83                 // Field net/minecraft/client/renderer/blockentity/state/SignRenderState.backText:Lnet/minecraft/world/level/block/entity/SignText;
     113: invokevirtual #79                 // Method submitSignText:(Lnet/minecraft/client/renderer/blockentity/state/SignRenderState;Lcom/mojang/blaze3d/vertex/PoseStack;Lnet/minecraft/client/renderer/SubmitNodeCollector;Lnet/minecraft/world/level/block/entity/SignText;)V
     116: aload_2
     117: invokevirtual #70                 // Method com/mojang/blaze3d/vertex/PoseStack.popPose:()V
     120: return

  protected void submitSign(com.mojang.blaze3d.vertex.PoseStack, int, net.minecraft.world.level.block.state.properties.WoodType, net.minecraft.client.model.Model$Simple, net.minecraft.client.renderer.feature.ModelFeatureRenderer$CrumblingOverlay, net.minecraft.client.renderer.SubmitNodeCollector);
    Code:
       0: aload_0
       1: aload_3
       2: invokevirtual #88                 // Method getSignSprite:(Lnet/minecraft/world/level/block/state/properties/WoodType;)Lnet/minecraft/client/resources/model/sprite/SpriteId;
       5: astore        7
       7: aload         6
       9: aload         4
      11: getstatic     #92                 // Field net/minecraft/util/Unit.INSTANCE:Lnet/minecraft/util/Unit;
      14: aload_1
      15: iload_2
      16: getstatic     #98                 // Field net/minecraft/client/renderer/texture/OverlayTexture.NO_OVERLAY:I
      19: iconst_m1
      20: aload         7
      22: aload_0
      23: getfield      #22                 // Field sprites:Lnet/minecraft/client/resources/model/sprite/SpriteGetter;
      26: iconst_0
      27: aload         5
      29: invokeinterface #105,  11         // InterfaceMethod net/minecraft/client/renderer/SubmitNodeCollector.submitModel:(Lnet/minecraft/client/model/Model;Ljava/lang/Object;Lcom/mojang/blaze3d/vertex/PoseStack;IIILnet/minecraft/client/resources/model/sprite/SpriteId;Lnet/minecraft/client/resources/model/sprite/SpriteGetter;ILnet/minecraft/client/renderer/feature/ModelFeatureRenderer$CrumblingOverlay;)V
      34: return

  private void submitSignText(S, com.mojang.blaze3d.vertex.PoseStack, net.minecraft.client.renderer.SubmitNodeCollector, net.minecraft.world.level.block.entity.SignText);
    Code:
       0: aload         4
       2: invokestatic  #111                // Method getDarkColor:(Lnet/minecraft/world/level/block/entity/SignText;)I
       5: istore        5
       7: iconst_4
       8: aload_1
       9: getfield      #117                // Field net/minecraft/client/renderer/blockentity/state/SignRenderState.textLineHeight:I
      12: imul
      13: iconst_2
      14: idiv
      15: istore        6
      17: aload         4
      19: aload_1
      20: getfield      #120                // Field net/minecraft/client/renderer/blockentity/state/SignRenderState.isTextFilteringEnabled:Z
      23: aload_0
      24: aload_1
      25: invokedynamic #124,  0            // InvokeDynamic #0:apply:(Lnet/minecraft/client/renderer/blockentity/AbstractSignRenderer;Lnet/minecraft/client/renderer/blockentity/state/SignRenderState;)Ljava/util/function/Function;
      30: invokevirtual #128                // Method net/minecraft/world/level/block/entity/SignText.getRenderMessages:(ZLjava/util/function/Function;)[Lnet/minecraft/util/FormattedCharSequence;
      33: astore        7
      35: aload         4
      37: invokevirtual #132                // Method net/minecraft/world/level/block/entity/SignText.hasGlowingText:()Z
      40: ifeq          85
      43: aload         4
      45: invokevirtual #136                // Method net/minecraft/world/level/block/entity/SignText.getColor:()Lnet/minecraft/world/item/DyeColor;
      48: invokevirtual #140                // Method net/minecraft/world/item/DyeColor.getTextColor:()I
      51: istore        8
      53: iload         8
      55: getstatic     #146                // Field net/minecraft/world/item/DyeColor.BLACK:Lnet/minecraft/world/item/DyeColor;
      58: invokevirtual #140                // Method net/minecraft/world/item/DyeColor.getTextColor:()I
      61: if_icmpeq     71
      64: aload_1
      65: getfield      #150                // Field net/minecraft/client/renderer/blockentity/state/SignRenderState.drawOutline:Z
      68: ifeq          75
      71: iconst_1
      72: goto          76
      75: iconst_0
      76: istore        9
      78: ldc           #155                // int 15728880
      80: istore        10
      82: goto          98
      85: iload         5
      87: istore        8
      89: iconst_0
      90: istore        9
      92: aload_1
      93: getfield      #58                 // Field net/minecraft/client/renderer/blockentity/state/SignRenderState.lightCoords:I
      96: istore        10
      98: iconst_0
      99: istore        11
     101: iload         11
     103: iconst_4
     104: if_icmpge     177
     107: aload         7
     109: iload         11
     111: aaload
     112: astore        12
     114: aload_0
     115: getfield      #13                 // Field font:Lnet/minecraft/client/gui/Font;
     118: aload         12
     120: invokevirtual #156                // Method net/minecraft/client/gui/Font.width:(Lnet/minecraft/util/FormattedCharSequence;)I
     123: ineg
     124: iconst_2
     125: idiv
     126: i2f
     127: fstore        13
     129: aload_3
     130: aload_2
     131: fload         13
     133: iload         11
     135: aload_1
     136: getfield      #117                // Field net/minecraft/client/renderer/blockentity/state/SignRenderState.textLineHeight:I
     139: imul
     140: iload         6
     142: isub
     143: i2f
     144: aload         12
     146: iconst_0
     147: getstatic     #162                // Field net/minecraft/client/gui/Font$DisplayMode.POLYGON_OFFSET:Lnet/minecraft/client/gui/Font$DisplayMode;
     150: iload         10
     152: iload         8
     154: iconst_0
     155: iload         9
     157: ifeq          165
     160: iload         5
     162: goto          166
     165: iconst_0
     166: invokeinterface #168,  11         // InterfaceMethod net/minecraft/client/renderer/SubmitNodeCollector.submitText:(Lcom/mojang/blaze3d/vertex/PoseStack;FFLnet/minecraft/util/FormattedCharSequence;ZLnet/minecraft/client/gui/Font$DisplayMode;IIII)V
     171: iinc          11, 1
     174: goto          101
     177: return

  private static boolean isOutlineVisible(net.minecraft.core.BlockPos);
    Code:
       0: invokestatic  #172                // Method net/minecraft/client/Minecraft.getInstance:()Lnet/minecraft/client/Minecraft;
       3: astore_1
       4: aload_1
       5: getfield      #178                // Field net/minecraft/client/Minecraft.player:Lnet/minecraft/client/player/LocalPlayer;
       8: astore_2
       9: aload_2
      10: ifnull        35
      13: aload_1
      14: getfield      #182                // Field net/minecraft/client/Minecraft.options:Lnet/minecraft/client/Options;
      17: invokevirtual #186                // Method net/minecraft/client/Options.getCameraType:()Lnet/minecraft/client/CameraType;
      20: invokevirtual #192                // Method net/minecraft/client/CameraType.isFirstPerson:()Z
      23: ifeq          35
      26: aload_2
      27: invokevirtual #197                // Method net/minecraft/client/player/LocalPlayer.isScoping:()Z
      30: ifeq          35
      33: iconst_1
      34: ireturn
      35: aload_1
      36: invokevirtual #202                // Method net/minecraft/client/Minecraft.getCameraEntity:()Lnet/minecraft/world/entity/Entity;
      39: astore_3
      40: aload_3
      41: ifnull        62
      44: aload_3
      45: aload_0
      46: invokestatic  #206                // Method net/minecraft/world/phys/Vec3.atCenterOf:(Lnet/minecraft/core/Vec3i;)Lnet/minecraft/world/phys/Vec3;
      49: invokevirtual #212                // Method net/minecraft/world/entity/Entity.distanceToSqr:(Lnet/minecraft/world/phys/Vec3;)D
      52: getstatic     #218                // Field OUTLINE_RENDER_DISTANCE:I
      55: i2d
      56: dcmpg
      57: ifge          62
      60: iconst_1
      61: ireturn
      62: iconst_0
      63: ireturn

  public static int getDarkColor(net.minecraft.world.level.block.entity.SignText);
    Code:
       0: aload_0
       1: invokevirtual #136                // Method net/minecraft/world/level/block/entity/SignText.getColor:()Lnet/minecraft/world/item/DyeColor;
       4: invokevirtual #140                // Method net/minecraft/world/item/DyeColor.getTextColor:()I
       7: istore_1
       8: iload_1
       9: getstatic     #146                // Field net/minecraft/world/item/DyeColor.BLACK:Lnet/minecraft/world/item/DyeColor;
      12: invokevirtual #140                // Method net/minecraft/world/item/DyeColor.getTextColor:()I
      15: if_icmpne     28
      18: aload_0
      19: invokevirtual #132                // Method net/minecraft/world/level/block/entity/SignText.hasGlowingText:()Z
      22: ifeq          28
      25: ldc           #221                // int -988212
      27: ireturn
      28: iload_1
      29: ldc           #222                // float 0.4f
      31: invokestatic  #223                // Method net/minecraft/util/ARGB.scaleRGB:(IF)I
      34: ireturn

  public void extractRenderState(net.minecraft.world.level.block.entity.SignBlockEntity, S, float, net.minecraft.world.phys.Vec3, net.minecraft.client.renderer.feature.ModelFeatureRenderer$CrumblingOverlay);
    Code:
       0: aload_0
       1: aload_1
       2: aload_2
       3: fload_3
       4: aload         4
       6: aload         5
       8: invokespecial #229                // InterfaceMethod net/minecraft/client/renderer/blockentity/BlockEntityRenderer.extractRenderState:(Lnet/minecraft/world/level/block/entity/BlockEntity;Lnet/minecraft/client/renderer/blockentity/state/BlockEntityRenderState;FLnet/minecraft/world/phys/Vec3;Lnet/minecraft/client/renderer/feature/ModelFeatureRenderer$CrumblingOverlay;)V
      11: aload_2
      12: aload_1
      13: invokevirtual #235                // Method net/minecraft/world/level/block/entity/SignBlockEntity.getMaxTextLineWidth:()I
      16: putfield      #240                // Field net/minecraft/client/renderer/blockentity/state/SignRenderState.maxTextLineWidth:I
      19: aload_2
      20: aload_1
      21: invokevirtual #243                // Method net/minecraft/world/level/block/entity/SignBlockEntity.getTextLineHeight:()I
      24: putfield      #117                // Field net/minecraft/client/renderer/blockentity/state/SignRenderState.textLineHeight:I
      27: aload_2
      28: aload_1
      29: invokevirtual #246                // Method net/minecraft/world/level/block/entity/SignBlockEntity.getFrontText:()Lnet/minecraft/world/level/block/entity/SignText;
      32: putfield      #73                 // Field net/minecraft/client/renderer/blockentity/state/SignRenderState.frontText:Lnet/minecraft/world/level/block/entity/SignText;
      35: aload_2
      36: aload_1
      37: invokevirtual #250                // Method net/minecraft/world/level/block/entity/SignBlockEntity.getBackText:()Lnet/minecraft/world/level/block/entity/SignText;
      40: putfield      #83                 // Field net/minecraft/client/renderer/blockentity/state/SignRenderState.backText:Lnet/minecraft/world/level/block/entity/SignText;
      43: aload_2
      44: invokestatic  #172                // Method net/minecraft/client/Minecraft.getInstance:()Lnet/minecraft/client/Minecraft;
      47: invokevirtual #253                // Method net/minecraft/client/Minecraft.isTextFilteringEnabled:()Z
      50: putfield      #120                // Field net/minecraft/client/renderer/blockentity/state/SignRenderState.isTextFilteringEnabled:Z
      53: aload_2
      54: aload_1
      55: invokevirtual #255                // Method net/minecraft/world/level/block/entity/SignBlockEntity.getBlockPos:()Lnet/minecraft/core/BlockPos;
      58: invokestatic  #259                // Method isOutlineVisible:(Lnet/minecraft/core/BlockPos;)Z
      61: putfield      #150                // Field net/minecraft/client/renderer/blockentity/state/SignRenderState.drawOutline:Z
      64: aload_2
      65: aload_1
      66: invokevirtual #263                // Method net/minecraft/world/level/block/entity/SignBlockEntity.getBlockState:()Lnet/minecraft/world/level/block/state/BlockState;
      69: invokevirtual #267                // Method net/minecraft/world/level/block/state/BlockState.getBlock:()Lnet/minecraft/world/level/block/Block;
      72: invokestatic  #273                // Method net/minecraft/world/level/block/SignBlock.getWoodType:(Lnet/minecraft/world/level/block/Block;)Lnet/minecraft/world/level/block/state/properties/WoodType;
      75: putfield      #62                 // Field net/minecraft/client/renderer/blockentity/state/SignRenderState.woodType:Lnet/minecraft/world/level/block/state/properties/WoodType;
      78: return

  public void submit(net.minecraft.client.renderer.blockentity.state.BlockEntityRenderState, com.mojang.blaze3d.vertex.PoseStack, net.minecraft.client.renderer.SubmitNodeCollector, net.minecraft.client.renderer.state.level.CameraRenderState);
    Code:
       0: aload_0
       1: aload_1
       2: checkcast     #26                 // class net/minecraft/client/renderer/blockentity/state/SignRenderState
       5: aload_2
       6: aload_3
       7: aload         4
       9: invokevirtual #279                // Method submit:(Lnet/minecraft/client/renderer/blockentity/state/SignRenderState;Lcom/mojang/blaze3d/vertex/PoseStack;Lnet/minecraft/client/renderer/SubmitNodeCollector;Lnet/minecraft/client/renderer/state/level/CameraRenderState;)V
      12: return

  public void extractRenderState(net.minecraft.world.level.block.entity.BlockEntity, net.minecraft.client.renderer.blockentity.state.BlockEntityRenderState, float, net.minecraft.world.phys.Vec3, net.minecraft.client.renderer.feature.ModelFeatureRenderer$CrumblingOverlay);
    Code:
       0: aload_0
       1: aload_1
       2: checkcast     #236                // class net/minecraft/world/level/block/entity/SignBlockEntity
       5: aload_2
       6: checkcast     #26                 // class net/minecraft/client/renderer/blockentity/state/SignRenderState
       9: fload_3
      10: aload         4
      12: aload         5
      14: invokevirtual #283                // Method extractRenderState:(Lnet/minecraft/world/level/block/entity/SignBlockEntity;Lnet/minecraft/client/renderer/blockentity/state/SignRenderState;FLnet/minecraft/world/phys/Vec3;Lnet/minecraft/client/renderer/feature/ModelFeatureRenderer$CrumblingOverlay;)V
      17: return

  private net.minecraft.util.FormattedCharSequence lambda$submitSignText$0(net.minecraft.client.renderer.blockentity.state.SignRenderState, net.minecraft.network.chat.Component);
    Code:
       0: aload_0
       1: getfield      #13                 // Field font:Lnet/minecraft/client/gui/Font;
       4: aload_2
       5: aload_1
       6: getfield      #240                // Field net/minecraft/client/renderer/blockentity/state/SignRenderState.maxTextLineWidth:I
       9: invokevirtual #286                // Method net/minecraft/client/gui/Font.split:(Lnet/minecraft/network/chat/FormattedText;I)Ljava/util/List;
      12: astore_3
      13: aload_3
      14: invokeinterface #290,  1          // InterfaceMethod java/util/List.isEmpty:()Z
      19: ifeq          28
      22: getstatic     #295                // Field net/minecraft/util/FormattedCharSequence.EMPTY:Lnet/minecraft/util/FormattedCharSequence;
      25: goto          38
      28: aload_3
      29: iconst_0
      30: invokeinterface #301,  2          // InterfaceMethod java/util/List.get:(I)Ljava/lang/Object;
      35: checkcast     #296                // class net/minecraft/util/FormattedCharSequence
      38: areturn

  static {};
    Code:
       0: bipush        16
       2: invokestatic  #305                // Method net/minecraft/util/Mth.square:(I)I
       5: putstatic     #218                // Field OUTLINE_RENDER_DISTANCE:I
       8: return
}
