# javap snapshot - Minecraft 26.1.2 client.jar
# Class: net.minecraft.client.model.animal.wolf.AdultWolfModel
# Pilot entry: net.minecraft.client.model.animal.wolf.AdultWolfModel
# Factory method: createBodyLayer
# Command: javap -c -constants
# Content: full class disassembly
# Generated: 2026-05-19T05:03:22.9357233-04:00
Compiled from "AdultWolfModel.java"
public class net.minecraft.client.model.animal.wolf.AdultWolfModel extends net.minecraft.client.model.animal.wolf.WolfModel {
  public net.minecraft.client.model.animal.wolf.AdultWolfModel(net.minecraft.client.model.geom.ModelPart);
    Code:
       0: aload_0
       1: aload_1
       2: invokespecial #1                  // Method net/minecraft/client/model/animal/wolf/WolfModel."<init>":(Lnet/minecraft/client/model/geom/ModelPart;)V
       5: aload_0
       6: aload_0
       7: getfield      #7                  // Field head:Lnet/minecraft/client/model/geom/ModelPart;
      10: ldc           #13                 // String real_head
      12: invokevirtual #15                 // Method net/minecraft/client/model/geom/ModelPart.getChild:(Ljava/lang/String;)Lnet/minecraft/client/model/geom/ModelPart;
      15: putfield      #21                 // Field realHead:Lnet/minecraft/client/model/geom/ModelPart;
      18: aload_0
      19: aload_1
      20: ldc           #24                 // String upper_body
      22: invokevirtual #15                 // Method net/minecraft/client/model/geom/ModelPart.getChild:(Ljava/lang/String;)Lnet/minecraft/client/model/geom/ModelPart;
      25: putfield      #26                 // Field upperBody:Lnet/minecraft/client/model/geom/ModelPart;
      28: aload_0
      29: aload_0
      30: getfield      #29                 // Field tail:Lnet/minecraft/client/model/geom/ModelPart;
      33: ldc           #32                 // String real_tail
      35: invokevirtual #15                 // Method net/minecraft/client/model/geom/ModelPart.getChild:(Ljava/lang/String;)Lnet/minecraft/client/model/geom/ModelPart;
      38: putfield      #34                 // Field realTail:Lnet/minecraft/client/model/geom/ModelPart;
      41: return

  public static net.minecraft.client.model.geom.builders.MeshDefinition createBodyLayer(net.minecraft.client.model.geom.builders.CubeDeformation);
    Code:
       0: new           #37                 // class net/minecraft/client/model/geom/builders/MeshDefinition
       3: dup
       4: invokespecial #39                 // Method net/minecraft/client/model/geom/builders/MeshDefinition."<init>":()V
       7: astore_1
       8: aload_1
       9: invokevirtual #42                 // Method net/minecraft/client/model/geom/builders/MeshDefinition.getRoot:()Lnet/minecraft/client/model/geom/builders/PartDefinition;
      12: astore_2
      13: ldc           #46                 // float 13.5f
      15: fstore_3
      16: aload_2
      17: ldc           #49                 // String head
      19: invokestatic  #50                 // Method net/minecraft/client/model/geom/builders/CubeListBuilder.create:()Lnet/minecraft/client/model/geom/builders/CubeListBuilder;
      22: ldc           #56                 // float -1.0f
      24: ldc           #46                 // float 13.5f
      26: ldc           #57                 // float -7.0f
      28: invokestatic  #58                 // Method net/minecraft/client/model/geom/PartPose.offset:(FFF)Lnet/minecraft/client/model/geom/PartPose;
      31: invokevirtual #64                 // Method net/minecraft/client/model/geom/builders/PartDefinition.addOrReplaceChild:(Ljava/lang/String;Lnet/minecraft/client/model/geom/builders/CubeListBuilder;Lnet/minecraft/client/model/geom/PartPose;)Lnet/minecraft/client/model/geom/builders/PartDefinition;
      34: astore        4
      36: aload         4
      38: ldc           #13                 // String real_head
      40: invokestatic  #50                 // Method net/minecraft/client/model/geom/builders/CubeListBuilder.create:()Lnet/minecraft/client/model/geom/builders/CubeListBuilder;
      43: iconst_0
      44: iconst_0
      45: invokevirtual #70                 // Method net/minecraft/client/model/geom/builders/CubeListBuilder.texOffs:(II)Lnet/minecraft/client/model/geom/builders/CubeListBuilder;
      48: ldc           #74                 // float -2.0f
      50: ldc           #75                 // float -3.0f
      52: ldc           #74                 // float -2.0f
      54: ldc           #76                 // float 6.0f
      56: ldc           #76                 // float 6.0f
      58: ldc           #77                 // float 4.0f
      60: aload_0
      61: invokevirtual #78                 // Method net/minecraft/client/model/geom/builders/CubeListBuilder.addBox:(FFFFFFLnet/minecraft/client/model/geom/builders/CubeDeformation;)Lnet/minecraft/client/model/geom/builders/CubeListBuilder;
      64: bipush        16
      66: bipush        14
      68: invokevirtual #70                 // Method net/minecraft/client/model/geom/builders/CubeListBuilder.texOffs:(II)Lnet/minecraft/client/model/geom/builders/CubeListBuilder;
      71: ldc           #74                 // float -2.0f
      73: ldc           #82                 // float -5.0f
      75: fconst_0
      76: fconst_2
      77: fconst_2
      78: fconst_1
      79: aload_0
      80: invokevirtual #78                 // Method net/minecraft/client/model/geom/builders/CubeListBuilder.addBox:(FFFFFFLnet/minecraft/client/model/geom/builders/CubeDeformation;)Lnet/minecraft/client/model/geom/builders/CubeListBuilder;
      83: bipush        16
      85: bipush        14
      87: invokevirtual #70                 // Method net/minecraft/client/model/geom/builders/CubeListBuilder.texOffs:(II)Lnet/minecraft/client/model/geom/builders/CubeListBuilder;
      90: fconst_2
      91: ldc           #82                 // float -5.0f
      93: fconst_0
      94: fconst_2
      95: fconst_2
      96: fconst_1
      97: aload_0
      98: invokevirtual #78                 // Method net/minecraft/client/model/geom/builders/CubeListBuilder.addBox:(FFFFFFLnet/minecraft/client/model/geom/builders/CubeDeformation;)Lnet/minecraft/client/model/geom/builders/CubeListBuilder;
     101: iconst_0
     102: bipush        10
     104: invokevirtual #70                 // Method net/minecraft/client/model/geom/builders/CubeListBuilder.texOffs:(II)Lnet/minecraft/client/model/geom/builders/CubeListBuilder;
     107: ldc           #83                 // float -0.5f
     109: ldc           #84                 // float -0.001f
     111: ldc           #82                 // float -5.0f
     113: ldc           #85                 // float 3.0f
     115: ldc           #85                 // float 3.0f
     117: ldc           #77                 // float 4.0f
     119: aload_0
     120: invokevirtual #78                 // Method net/minecraft/client/model/geom/builders/CubeListBuilder.addBox:(FFFFFFLnet/minecraft/client/model/geom/builders/CubeDeformation;)Lnet/minecraft/client/model/geom/builders/CubeListBuilder;
     123: getstatic     #86                 // Field net/minecraft/client/model/geom/PartPose.ZERO:Lnet/minecraft/client/model/geom/PartPose;
     126: invokevirtual #64                 // Method net/minecraft/client/model/geom/builders/PartDefinition.addOrReplaceChild:(Ljava/lang/String;Lnet/minecraft/client/model/geom/builders/CubeListBuilder;Lnet/minecraft/client/model/geom/PartPose;)Lnet/minecraft/client/model/geom/builders/PartDefinition;
     129: pop
     130: aload_2
     131: ldc           #90                 // String body
     133: invokestatic  #50                 // Method net/minecraft/client/model/geom/builders/CubeListBuilder.create:()Lnet/minecraft/client/model/geom/builders/CubeListBuilder;
     136: bipush        18
     138: bipush        14
     140: invokevirtual #70                 // Method net/minecraft/client/model/geom/builders/CubeListBuilder.texOffs:(II)Lnet/minecraft/client/model/geom/builders/CubeListBuilder;
     143: ldc           #75                 // float -3.0f
     145: ldc           #74                 // float -2.0f
     147: ldc           #75                 // float -3.0f
     149: ldc           #76                 // float 6.0f
     151: ldc           #92                 // float 9.0f
     153: ldc           #76                 // float 6.0f
     155: aload_0
     156: invokevirtual #78                 // Method net/minecraft/client/model/geom/builders/CubeListBuilder.addBox:(FFFFFFLnet/minecraft/client/model/geom/builders/CubeDeformation;)Lnet/minecraft/client/model/geom/builders/CubeListBuilder;
     159: fconst_0
     160: ldc           #93                 // float 14.0f
     162: fconst_2
     163: ldc           #96                 // float 1.5707964f
     165: fconst_0
     166: fconst_0
     167: invokestatic  #97                 // Method net/minecraft/client/model/geom/PartPose.offsetAndRotation:(FFFFFF)Lnet/minecraft/client/model/geom/PartPose;
     170: invokevirtual #64                 // Method net/minecraft/client/model/geom/builders/PartDefinition.addOrReplaceChild:(Ljava/lang/String;Lnet/minecraft/client/model/geom/builders/CubeListBuilder;Lnet/minecraft/client/model/geom/PartPose;)Lnet/minecraft/client/model/geom/builders/PartDefinition;
     173: pop
     174: aload_2
     175: ldc           #24                 // String upper_body
     177: invokestatic  #50                 // Method net/minecraft/client/model/geom/builders/CubeListBuilder.create:()Lnet/minecraft/client/model/geom/builders/CubeListBuilder;
     180: bipush        21
     182: iconst_0
     183: invokevirtual #70                 // Method net/minecraft/client/model/geom/builders/CubeListBuilder.texOffs:(II)Lnet/minecraft/client/model/geom/builders/CubeListBuilder;
     186: ldc           #75                 // float -3.0f
     188: ldc           #75                 // float -3.0f
     190: ldc           #75                 // float -3.0f
     192: ldc           #101                // float 8.0f
     194: ldc           #76                 // float 6.0f
     196: ldc           #102                // float 7.0f
     198: aload_0
     199: invokevirtual #78                 // Method net/minecraft/client/model/geom/builders/CubeListBuilder.addBox:(FFFFFFLnet/minecraft/client/model/geom/builders/CubeDeformation;)Lnet/minecraft/client/model/geom/builders/CubeListBuilder;
     202: ldc           #56                 // float -1.0f
     204: ldc           #93                 // float 14.0f
     206: ldc           #75                 // float -3.0f
     208: ldc           #96                 // float 1.5707964f
     210: fconst_0
     211: fconst_0
     212: invokestatic  #97                 // Method net/minecraft/client/model/geom/PartPose.offsetAndRotation:(FFFFFF)Lnet/minecraft/client/model/geom/PartPose;
     215: invokevirtual #64                 // Method net/minecraft/client/model/geom/builders/PartDefinition.addOrReplaceChild:(Ljava/lang/String;Lnet/minecraft/client/model/geom/builders/CubeListBuilder;Lnet/minecraft/client/model/geom/PartPose;)Lnet/minecraft/client/model/geom/builders/PartDefinition;
     218: pop
     219: invokestatic  #50                 // Method net/minecraft/client/model/geom/builders/CubeListBuilder.create:()Lnet/minecraft/client/model/geom/builders/CubeListBuilder;
     222: iconst_0
     223: bipush        18
     225: invokevirtual #70                 // Method net/minecraft/client/model/geom/builders/CubeListBuilder.texOffs:(II)Lnet/minecraft/client/model/geom/builders/CubeListBuilder;
     228: fconst_0
     229: fconst_0
     230: ldc           #56                 // float -1.0f
     232: fconst_2
     233: ldc           #101                // float 8.0f
     235: fconst_2
     236: aload_0
     237: invokevirtual #78                 // Method net/minecraft/client/model/geom/builders/CubeListBuilder.addBox:(FFFFFFLnet/minecraft/client/model/geom/builders/CubeDeformation;)Lnet/minecraft/client/model/geom/builders/CubeListBuilder;
     240: astore        5
     242: invokestatic  #50                 // Method net/minecraft/client/model/geom/builders/CubeListBuilder.create:()Lnet/minecraft/client/model/geom/builders/CubeListBuilder;
     245: invokevirtual #103                // Method net/minecraft/client/model/geom/builders/CubeListBuilder.mirror:()Lnet/minecraft/client/model/geom/builders/CubeListBuilder;
     248: iconst_0
     249: bipush        18
     251: invokevirtual #70                 // Method net/minecraft/client/model/geom/builders/CubeListBuilder.texOffs:(II)Lnet/minecraft/client/model/geom/builders/CubeListBuilder;
     254: fconst_0
     255: fconst_0
     256: ldc           #56                 // float -1.0f
     258: fconst_2
     259: ldc           #101                // float 8.0f
     261: fconst_2
     262: aload_0
     263: invokevirtual #78                 // Method net/minecraft/client/model/geom/builders/CubeListBuilder.addBox:(FFFFFFLnet/minecraft/client/model/geom/builders/CubeDeformation;)Lnet/minecraft/client/model/geom/builders/CubeListBuilder;
     266: astore        6
     268: aload_2
     269: ldc           #106                // String right_hind_leg
     271: aload         6
     273: ldc           #108                // float -2.5f
     275: ldc           #109                // float 16.0f
     277: ldc           #102                // float 7.0f
     279: invokestatic  #58                 // Method net/minecraft/client/model/geom/PartPose.offset:(FFF)Lnet/minecraft/client/model/geom/PartPose;
     282: invokevirtual #64                 // Method net/minecraft/client/model/geom/builders/PartDefinition.addOrReplaceChild:(Ljava/lang/String;Lnet/minecraft/client/model/geom/builders/CubeListBuilder;Lnet/minecraft/client/model/geom/PartPose;)Lnet/minecraft/client/model/geom/builders/PartDefinition;
     285: pop
     286: aload_2
     287: ldc           #110                // String left_hind_leg
     289: aload         5
     291: ldc           #112                // float 0.5f
     293: ldc           #109                // float 16.0f
     295: ldc           #102                // float 7.0f
     297: invokestatic  #58                 // Method net/minecraft/client/model/geom/PartPose.offset:(FFF)Lnet/minecraft/client/model/geom/PartPose;
     300: invokevirtual #64                 // Method net/minecraft/client/model/geom/builders/PartDefinition.addOrReplaceChild:(Ljava/lang/String;Lnet/minecraft/client/model/geom/builders/CubeListBuilder;Lnet/minecraft/client/model/geom/PartPose;)Lnet/minecraft/client/model/geom/builders/PartDefinition;
     303: pop
     304: aload_2
     305: ldc           #113                // String right_front_leg
     307: aload         6
     309: ldc           #108                // float -2.5f
     311: ldc           #109                // float 16.0f
     313: ldc           #115                // float -4.0f
     315: invokestatic  #58                 // Method net/minecraft/client/model/geom/PartPose.offset:(FFF)Lnet/minecraft/client/model/geom/PartPose;
     318: invokevirtual #64                 // Method net/minecraft/client/model/geom/builders/PartDefinition.addOrReplaceChild:(Ljava/lang/String;Lnet/minecraft/client/model/geom/builders/CubeListBuilder;Lnet/minecraft/client/model/geom/PartPose;)Lnet/minecraft/client/model/geom/builders/PartDefinition;
     321: pop
     322: aload_2
     323: ldc           #116                // String left_front_leg
     325: aload         5
     327: ldc           #112                // float 0.5f
     329: ldc           #109                // float 16.0f
     331: ldc           #115                // float -4.0f
     333: invokestatic  #58                 // Method net/minecraft/client/model/geom/PartPose.offset:(FFF)Lnet/minecraft/client/model/geom/PartPose;
     336: invokevirtual #64                 // Method net/minecraft/client/model/geom/builders/PartDefinition.addOrReplaceChild:(Ljava/lang/String;Lnet/minecraft/client/model/geom/builders/CubeListBuilder;Lnet/minecraft/client/model/geom/PartPose;)Lnet/minecraft/client/model/geom/builders/PartDefinition;
     339: pop
     340: aload_2
     341: ldc           #118                // String tail
     343: invokestatic  #50                 // Method net/minecraft/client/model/geom/builders/CubeListBuilder.create:()Lnet/minecraft/client/model/geom/builders/CubeListBuilder;
     346: ldc           #56                 // float -1.0f
     348: ldc           #119                // float 12.0f
     350: ldc           #101                // float 8.0f
     352: ldc           #120                // float 0.62831855f
     354: fconst_0
     355: fconst_0
     356: invokestatic  #97                 // Method net/minecraft/client/model/geom/PartPose.offsetAndRotation:(FFFFFF)Lnet/minecraft/client/model/geom/PartPose;
     359: invokevirtual #64                 // Method net/minecraft/client/model/geom/builders/PartDefinition.addOrReplaceChild:(Ljava/lang/String;Lnet/minecraft/client/model/geom/builders/CubeListBuilder;Lnet/minecraft/client/model/geom/PartPose;)Lnet/minecraft/client/model/geom/builders/PartDefinition;
     362: astore        7
     364: aload         7
     366: ldc           #32                 // String real_tail
     368: invokestatic  #50                 // Method net/minecraft/client/model/geom/builders/CubeListBuilder.create:()Lnet/minecraft/client/model/geom/builders/CubeListBuilder;
     371: bipush        9
     373: bipush        18
     375: invokevirtual #70                 // Method net/minecraft/client/model/geom/builders/CubeListBuilder.texOffs:(II)Lnet/minecraft/client/model/geom/builders/CubeListBuilder;
     378: fconst_0
     379: fconst_0
     380: ldc           #56                 // float -1.0f
     382: fconst_2
     383: ldc           #101                // float 8.0f
     385: fconst_2
     386: aload_0
     387: invokevirtual #78                 // Method net/minecraft/client/model/geom/builders/CubeListBuilder.addBox:(FFFFFFLnet/minecraft/client/model/geom/builders/CubeDeformation;)Lnet/minecraft/client/model/geom/builders/CubeListBuilder;
     390: getstatic     #86                 // Field net/minecraft/client/model/geom/PartPose.ZERO:Lnet/minecraft/client/model/geom/PartPose;
     393: invokevirtual #64                 // Method net/minecraft/client/model/geom/builders/PartDefinition.addOrReplaceChild:(Ljava/lang/String;Lnet/minecraft/client/model/geom/builders/CubeListBuilder;Lnet/minecraft/client/model/geom/PartPose;)Lnet/minecraft/client/model/geom/builders/PartDefinition;
     396: pop
     397: aload_1
     398: areturn

  protected void setSittingPose(net.minecraft.client.renderer.entity.state.WolfRenderState);
    Code:
       0: aload_0
       1: aload_1
       2: invokespecial #121                // Method net/minecraft/client/model/animal/wolf/WolfModel.setSittingPose:(Lnet/minecraft/client/renderer/entity/state/WolfRenderState;)V
       5: aload_0
       6: getfield      #26                 // Field upperBody:Lnet/minecraft/client/model/geom/ModelPart;
       9: dup
      10: getfield      #125                // Field net/minecraft/client/model/geom/ModelPart.y:F
      13: fconst_2
      14: fadd
      15: putfield      #125                // Field net/minecraft/client/model/geom/ModelPart.y:F
      18: aload_0
      19: getfield      #26                 // Field upperBody:Lnet/minecraft/client/model/geom/ModelPart;
      22: ldc           #129                // float 1.2566371f
      24: putfield      #130                // Field net/minecraft/client/model/geom/ModelPart.xRot:F
      27: aload_0
      28: getfield      #26                 // Field upperBody:Lnet/minecraft/client/model/geom/ModelPart;
      31: fconst_0
      32: putfield      #133                // Field net/minecraft/client/model/geom/ModelPart.yRot:F
      35: return

  protected void shakeOffWater(net.minecraft.client.renderer.entity.state.WolfRenderState);
    Code:
       0: aload_0
       1: aload_1
       2: invokespecial #136                // Method net/minecraft/client/model/animal/wolf/WolfModel.shakeOffWater:(Lnet/minecraft/client/renderer/entity/state/WolfRenderState;)V
       5: aload_0
       6: getfield      #21                 // Field realHead:Lnet/minecraft/client/model/geom/ModelPart;
       9: aload_1
      10: getfield      #139                // Field net/minecraft/client/renderer/entity/state/WolfRenderState.headRollAngle:F
      13: aload_1
      14: fconst_0
      15: invokevirtual #144                // Method net/minecraft/client/renderer/entity/state/WolfRenderState.getBodyRollAngle:(F)F
      18: fadd
      19: putfield      #148                // Field net/minecraft/client/model/geom/ModelPart.zRot:F
      22: aload_0
      23: getfield      #26                 // Field upperBody:Lnet/minecraft/client/model/geom/ModelPart;
      26: aload_1
      27: ldc           #151                // float -0.08f
      29: invokevirtual #144                // Method net/minecraft/client/renderer/entity/state/WolfRenderState.getBodyRollAngle:(F)F
      32: putfield      #148                // Field net/minecraft/client/model/geom/ModelPart.zRot:F
      35: aload_0
      36: getfield      #34                 // Field realTail:Lnet/minecraft/client/model/geom/ModelPart;
      39: aload_1
      40: ldc           #152                // float -0.2f
      42: invokevirtual #144                // Method net/minecraft/client/renderer/entity/state/WolfRenderState.getBodyRollAngle:(F)F
      45: putfield      #148                // Field net/minecraft/client/model/geom/ModelPart.zRot:F
      48: return
}
