# javap snapshot - Minecraft 26.1.2 client.jar
# Class: net.minecraft.client.model.animal.camel.AdultCamelModel
# Pilot entry: net.minecraft.client.model.animal.camel.AdultCamelModel
# Factory method: createBodyLayer
# Command: javap -c -constants
# Content: full class disassembly
# Generated: 2026-05-19T05:01:59.0081133-04:00
Compiled from "AdultCamelModel.java"
public class net.minecraft.client.model.animal.camel.AdultCamelModel extends net.minecraft.client.model.animal.camel.CamelModel {
  public net.minecraft.client.model.animal.camel.AdultCamelModel(net.minecraft.client.model.geom.ModelPart);
    Code:
       0: aload_0
       1: aload_1
       2: getstatic     #1                  // Field net/minecraft/client/animation/definitions/CamelAnimation.CAMEL_WALK:Lnet/minecraft/client/animation/AnimationDefinition;
       5: getstatic     #7                  // Field net/minecraft/client/animation/definitions/CamelAnimation.CAMEL_SIT:Lnet/minecraft/client/animation/AnimationDefinition;
       8: getstatic     #10                 // Field net/minecraft/client/animation/definitions/CamelAnimation.CAMEL_SIT_POSE:Lnet/minecraft/client/animation/AnimationDefinition;
      11: getstatic     #13                 // Field net/minecraft/client/animation/definitions/CamelAnimation.CAMEL_STANDUP:Lnet/minecraft/client/animation/AnimationDefinition;
      14: getstatic     #16                 // Field net/minecraft/client/animation/definitions/CamelAnimation.CAMEL_IDLE:Lnet/minecraft/client/animation/AnimationDefinition;
      17: getstatic     #19                 // Field net/minecraft/client/animation/definitions/CamelAnimation.CAMEL_DASH:Lnet/minecraft/client/animation/AnimationDefinition;
      20: invokespecial #22                 // Method net/minecraft/client/model/animal/camel/CamelModel."<init>":(Lnet/minecraft/client/model/geom/ModelPart;Lnet/minecraft/client/animation/AnimationDefinition;Lnet/minecraft/client/animation/AnimationDefinition;Lnet/minecraft/client/animation/AnimationDefinition;Lnet/minecraft/client/animation/AnimationDefinition;Lnet/minecraft/client/animation/AnimationDefinition;Lnet/minecraft/client/animation/AnimationDefinition;)V
      23: return

  public static net.minecraft.client.model.geom.builders.LayerDefinition createBodyLayer();
    Code:
       0: invokestatic  #28                 // Method createBodyMesh:()Lnet/minecraft/client/model/geom/builders/MeshDefinition;
       3: sipush        128
       6: sipush        128
       9: invokestatic  #34                 // Method net/minecraft/client/model/geom/builders/LayerDefinition.create:(Lnet/minecraft/client/model/geom/builders/MeshDefinition;II)Lnet/minecraft/client/model/geom/builders/LayerDefinition;
      12: areturn

  protected static net.minecraft.client.model.geom.builders.MeshDefinition createBodyMesh();
    Code:
       0: new           #40                 // class net/minecraft/client/model/geom/builders/MeshDefinition
       3: dup
       4: invokespecial #42                 // Method net/minecraft/client/model/geom/builders/MeshDefinition."<init>":()V
       7: astore_0
       8: aload_0
       9: invokevirtual #45                 // Method net/minecraft/client/model/geom/builders/MeshDefinition.getRoot:()Lnet/minecraft/client/model/geom/builders/PartDefinition;
      12: astore_1
      13: aload_1
      14: ldc           #51                 // String body
      16: invokestatic  #53                 // Method net/minecraft/client/model/geom/builders/CubeListBuilder.create:()Lnet/minecraft/client/model/geom/builders/CubeListBuilder;
      19: iconst_0
      20: bipush        25
      22: invokevirtual #58                 // Method net/minecraft/client/model/geom/builders/CubeListBuilder.texOffs:(II)Lnet/minecraft/client/model/geom/builders/CubeListBuilder;
      25: ldc           #62                 // float -7.5f
      27: ldc           #63                 // float -12.0f
      29: ldc           #64                 // float -23.5f
      31: ldc           #65                 // float 15.0f
      33: ldc           #66                 // float 12.0f
      35: ldc           #67                 // float 27.0f
      37: invokevirtual #68                 // Method net/minecraft/client/model/geom/builders/CubeListBuilder.addBox:(FFFFFF)Lnet/minecraft/client/model/geom/builders/CubeListBuilder;
      40: fconst_0
      41: ldc           #72                 // float 4.0f
      43: ldc           #73                 // float 9.5f
      45: invokestatic  #74                 // Method net/minecraft/client/model/geom/PartPose.offset:(FFF)Lnet/minecraft/client/model/geom/PartPose;
      48: invokevirtual #80                 // Method net/minecraft/client/model/geom/builders/PartDefinition.addOrReplaceChild:(Ljava/lang/String;Lnet/minecraft/client/model/geom/builders/CubeListBuilder;Lnet/minecraft/client/model/geom/PartPose;)Lnet/minecraft/client/model/geom/builders/PartDefinition;
      51: astore_2
      52: aload_2
      53: ldc           #86                 // String hump
      55: invokestatic  #53                 // Method net/minecraft/client/model/geom/builders/CubeListBuilder.create:()Lnet/minecraft/client/model/geom/builders/CubeListBuilder;
      58: bipush        74
      60: iconst_0
      61: invokevirtual #58                 // Method net/minecraft/client/model/geom/builders/CubeListBuilder.texOffs:(II)Lnet/minecraft/client/model/geom/builders/CubeListBuilder;
      64: ldc           #88                 // float -4.5f
      66: ldc           #89                 // float -5.0f
      68: ldc           #90                 // float -5.5f
      70: ldc           #91                 // float 9.0f
      72: ldc           #92                 // float 5.0f
      74: ldc           #93                 // float 11.0f
      76: invokevirtual #68                 // Method net/minecraft/client/model/geom/builders/CubeListBuilder.addBox:(FFFFFF)Lnet/minecraft/client/model/geom/builders/CubeListBuilder;
      79: fconst_0
      80: ldc           #63                 // float -12.0f
      82: ldc           #94                 // float -10.0f
      84: invokestatic  #74                 // Method net/minecraft/client/model/geom/PartPose.offset:(FFF)Lnet/minecraft/client/model/geom/PartPose;
      87: invokevirtual #80                 // Method net/minecraft/client/model/geom/builders/PartDefinition.addOrReplaceChild:(Ljava/lang/String;Lnet/minecraft/client/model/geom/builders/CubeListBuilder;Lnet/minecraft/client/model/geom/PartPose;)Lnet/minecraft/client/model/geom/builders/PartDefinition;
      90: pop
      91: aload_2
      92: ldc           #95                 // String tail
      94: invokestatic  #53                 // Method net/minecraft/client/model/geom/builders/CubeListBuilder.create:()Lnet/minecraft/client/model/geom/builders/CubeListBuilder;
      97: bipush        122
      99: iconst_0
     100: invokevirtual #58                 // Method net/minecraft/client/model/geom/builders/CubeListBuilder.texOffs:(II)Lnet/minecraft/client/model/geom/builders/CubeListBuilder;
     103: ldc           #97                 // float -1.5f
     105: fconst_0
     106: fconst_0
     107: ldc           #98                 // float 3.0f
     109: ldc           #99                 // float 14.0f
     111: fconst_0
     112: invokevirtual #68                 // Method net/minecraft/client/model/geom/builders/CubeListBuilder.addBox:(FFFFFF)Lnet/minecraft/client/model/geom/builders/CubeListBuilder;
     115: fconst_0
     116: ldc           #100                // float -9.0f
     118: ldc           #101                // float 3.5f
     120: invokestatic  #74                 // Method net/minecraft/client/model/geom/PartPose.offset:(FFF)Lnet/minecraft/client/model/geom/PartPose;
     123: invokevirtual #80                 // Method net/minecraft/client/model/geom/builders/PartDefinition.addOrReplaceChild:(Ljava/lang/String;Lnet/minecraft/client/model/geom/builders/CubeListBuilder;Lnet/minecraft/client/model/geom/PartPose;)Lnet/minecraft/client/model/geom/builders/PartDefinition;
     126: pop
     127: aload_2
     128: ldc           #102                // String head
     130: invokestatic  #53                 // Method net/minecraft/client/model/geom/builders/CubeListBuilder.create:()Lnet/minecraft/client/model/geom/builders/CubeListBuilder;
     133: bipush        60
     135: bipush        24
     137: invokevirtual #58                 // Method net/minecraft/client/model/geom/builders/CubeListBuilder.texOffs:(II)Lnet/minecraft/client/model/geom/builders/CubeListBuilder;
     140: ldc           #104                // float -3.5f
     142: ldc           #105                // float -7.0f
     144: ldc           #106                // float -15.0f
     146: ldc           #107                // float 7.0f
     148: ldc           #108                // float 8.0f
     150: ldc           #109                // float 19.0f
     152: invokevirtual #68                 // Method net/minecraft/client/model/geom/builders/CubeListBuilder.addBox:(FFFFFF)Lnet/minecraft/client/model/geom/builders/CubeListBuilder;
     155: bipush        21
     157: iconst_0
     158: invokevirtual #58                 // Method net/minecraft/client/model/geom/builders/CubeListBuilder.texOffs:(II)Lnet/minecraft/client/model/geom/builders/CubeListBuilder;
     161: ldc           #104                // float -3.5f
     163: ldc           #110                // float -21.0f
     165: ldc           #106                // float -15.0f
     167: ldc           #107                // float 7.0f
     169: ldc           #99                 // float 14.0f
     171: ldc           #107                // float 7.0f
     173: invokevirtual #68                 // Method net/minecraft/client/model/geom/builders/CubeListBuilder.addBox:(FFFFFF)Lnet/minecraft/client/model/geom/builders/CubeListBuilder;
     176: bipush        50
     178: iconst_0
     179: invokevirtual #58                 // Method net/minecraft/client/model/geom/builders/CubeListBuilder.texOffs:(II)Lnet/minecraft/client/model/geom/builders/CubeListBuilder;
     182: ldc           #111                // float -2.5f
     184: ldc           #110                // float -21.0f
     186: ldc           #110                // float -21.0f
     188: ldc           #92                 // float 5.0f
     190: ldc           #92                 // float 5.0f
     192: ldc           #112                // float 6.0f
     194: invokevirtual #68                 // Method net/minecraft/client/model/geom/builders/CubeListBuilder.addBox:(FFFFFF)Lnet/minecraft/client/model/geom/builders/CubeListBuilder;
     197: fconst_0
     198: ldc           #113                // float -3.0f
     200: ldc           #114                // float -19.5f
     202: invokestatic  #74                 // Method net/minecraft/client/model/geom/PartPose.offset:(FFF)Lnet/minecraft/client/model/geom/PartPose;
     205: invokevirtual #80                 // Method net/minecraft/client/model/geom/builders/PartDefinition.addOrReplaceChild:(Ljava/lang/String;Lnet/minecraft/client/model/geom/builders/CubeListBuilder;Lnet/minecraft/client/model/geom/PartPose;)Lnet/minecraft/client/model/geom/builders/PartDefinition;
     208: astore_3
     209: aload_3
     210: ldc           #115                // String left_ear
     212: invokestatic  #53                 // Method net/minecraft/client/model/geom/builders/CubeListBuilder.create:()Lnet/minecraft/client/model/geom/builders/CubeListBuilder;
     215: bipush        45
     217: iconst_0
     218: invokevirtual #58                 // Method net/minecraft/client/model/geom/builders/CubeListBuilder.texOffs:(II)Lnet/minecraft/client/model/geom/builders/CubeListBuilder;
     221: ldc           #117                // float -0.5f
     223: ldc           #118                // float 0.5f
     225: ldc           #119                // float -1.0f
     227: ldc           #98                 // float 3.0f
     229: fconst_1
     230: fconst_2
     231: invokevirtual #68                 // Method net/minecraft/client/model/geom/builders/CubeListBuilder.addBox:(FFFFFF)Lnet/minecraft/client/model/geom/builders/CubeListBuilder;
     234: ldc           #120                // float 2.5f
     236: ldc           #110                // float -21.0f
     238: ldc           #121                // float -9.5f
     240: invokestatic  #74                 // Method net/minecraft/client/model/geom/PartPose.offset:(FFF)Lnet/minecraft/client/model/geom/PartPose;
     243: invokevirtual #80                 // Method net/minecraft/client/model/geom/builders/PartDefinition.addOrReplaceChild:(Ljava/lang/String;Lnet/minecraft/client/model/geom/builders/CubeListBuilder;Lnet/minecraft/client/model/geom/PartPose;)Lnet/minecraft/client/model/geom/builders/PartDefinition;
     246: pop
     247: aload_3
     248: ldc           #122                // String right_ear
     250: invokestatic  #53                 // Method net/minecraft/client/model/geom/builders/CubeListBuilder.create:()Lnet/minecraft/client/model/geom/builders/CubeListBuilder;
     253: bipush        67
     255: iconst_0
     256: invokevirtual #58                 // Method net/minecraft/client/model/geom/builders/CubeListBuilder.texOffs:(II)Lnet/minecraft/client/model/geom/builders/CubeListBuilder;
     259: ldc           #111                // float -2.5f
     261: ldc           #118                // float 0.5f
     263: ldc           #119                // float -1.0f
     265: ldc           #98                 // float 3.0f
     267: fconst_1
     268: fconst_2
     269: invokevirtual #68                 // Method net/minecraft/client/model/geom/builders/CubeListBuilder.addBox:(FFFFFF)Lnet/minecraft/client/model/geom/builders/CubeListBuilder;
     272: ldc           #111                // float -2.5f
     274: ldc           #110                // float -21.0f
     276: ldc           #121                // float -9.5f
     278: invokestatic  #74                 // Method net/minecraft/client/model/geom/PartPose.offset:(FFF)Lnet/minecraft/client/model/geom/PartPose;
     281: invokevirtual #80                 // Method net/minecraft/client/model/geom/builders/PartDefinition.addOrReplaceChild:(Ljava/lang/String;Lnet/minecraft/client/model/geom/builders/CubeListBuilder;Lnet/minecraft/client/model/geom/PartPose;)Lnet/minecraft/client/model/geom/builders/PartDefinition;
     284: pop
     285: aload_1
     286: ldc           #124                // String left_hind_leg
     288: invokestatic  #53                 // Method net/minecraft/client/model/geom/builders/CubeListBuilder.create:()Lnet/minecraft/client/model/geom/builders/CubeListBuilder;
     291: bipush        58
     293: bipush        16
     295: invokevirtual #58                 // Method net/minecraft/client/model/geom/builders/CubeListBuilder.texOffs:(II)Lnet/minecraft/client/model/geom/builders/CubeListBuilder;
     298: ldc           #111                // float -2.5f
     300: fconst_2
     301: ldc           #111                // float -2.5f
     303: ldc           #92                 // float 5.0f
     305: ldc           #126                // float 21.0f
     307: ldc           #92                 // float 5.0f
     309: invokevirtual #68                 // Method net/minecraft/client/model/geom/builders/CubeListBuilder.addBox:(FFFFFF)Lnet/minecraft/client/model/geom/builders/CubeListBuilder;
     312: ldc           #127                // float 4.9f
     314: fconst_1
     315: ldc           #73                 // float 9.5f
     317: invokestatic  #74                 // Method net/minecraft/client/model/geom/PartPose.offset:(FFF)Lnet/minecraft/client/model/geom/PartPose;
     320: invokevirtual #80                 // Method net/minecraft/client/model/geom/builders/PartDefinition.addOrReplaceChild:(Ljava/lang/String;Lnet/minecraft/client/model/geom/builders/CubeListBuilder;Lnet/minecraft/client/model/geom/PartPose;)Lnet/minecraft/client/model/geom/builders/PartDefinition;
     323: pop
     324: aload_1
     325: ldc           #128                // String right_hind_leg
     327: invokestatic  #53                 // Method net/minecraft/client/model/geom/builders/CubeListBuilder.create:()Lnet/minecraft/client/model/geom/builders/CubeListBuilder;
     330: bipush        94
     332: bipush        16
     334: invokevirtual #58                 // Method net/minecraft/client/model/geom/builders/CubeListBuilder.texOffs:(II)Lnet/minecraft/client/model/geom/builders/CubeListBuilder;
     337: ldc           #111                // float -2.5f
     339: fconst_2
     340: ldc           #111                // float -2.5f
     342: ldc           #92                 // float 5.0f
     344: ldc           #126                // float 21.0f
     346: ldc           #92                 // float 5.0f
     348: invokevirtual #68                 // Method net/minecraft/client/model/geom/builders/CubeListBuilder.addBox:(FFFFFF)Lnet/minecraft/client/model/geom/builders/CubeListBuilder;
     351: ldc           #130                // float -4.9f
     353: fconst_1
     354: ldc           #73                 // float 9.5f
     356: invokestatic  #74                 // Method net/minecraft/client/model/geom/PartPose.offset:(FFF)Lnet/minecraft/client/model/geom/PartPose;
     359: invokevirtual #80                 // Method net/minecraft/client/model/geom/builders/PartDefinition.addOrReplaceChild:(Ljava/lang/String;Lnet/minecraft/client/model/geom/builders/CubeListBuilder;Lnet/minecraft/client/model/geom/PartPose;)Lnet/minecraft/client/model/geom/builders/PartDefinition;
     362: pop
     363: aload_1
     364: ldc           #131                // String left_front_leg
     366: invokestatic  #53                 // Method net/minecraft/client/model/geom/builders/CubeListBuilder.create:()Lnet/minecraft/client/model/geom/builders/CubeListBuilder;
     369: iconst_0
     370: iconst_0
     371: invokevirtual #58                 // Method net/minecraft/client/model/geom/builders/CubeListBuilder.texOffs:(II)Lnet/minecraft/client/model/geom/builders/CubeListBuilder;
     374: ldc           #111                // float -2.5f
     376: fconst_2
     377: ldc           #111                // float -2.5f
     379: ldc           #92                 // float 5.0f
     381: ldc           #126                // float 21.0f
     383: ldc           #92                 // float 5.0f
     385: invokevirtual #68                 // Method net/minecraft/client/model/geom/builders/CubeListBuilder.addBox:(FFFFFF)Lnet/minecraft/client/model/geom/builders/CubeListBuilder;
     388: ldc           #127                // float 4.9f
     390: fconst_1
     391: ldc           #133                // float -10.5f
     393: invokestatic  #74                 // Method net/minecraft/client/model/geom/PartPose.offset:(FFF)Lnet/minecraft/client/model/geom/PartPose;
     396: invokevirtual #80                 // Method net/minecraft/client/model/geom/builders/PartDefinition.addOrReplaceChild:(Ljava/lang/String;Lnet/minecraft/client/model/geom/builders/CubeListBuilder;Lnet/minecraft/client/model/geom/PartPose;)Lnet/minecraft/client/model/geom/builders/PartDefinition;
     399: pop
     400: aload_1
     401: ldc           #134                // String right_front_leg
     403: invokestatic  #53                 // Method net/minecraft/client/model/geom/builders/CubeListBuilder.create:()Lnet/minecraft/client/model/geom/builders/CubeListBuilder;
     406: iconst_0
     407: bipush        26
     409: invokevirtual #58                 // Method net/minecraft/client/model/geom/builders/CubeListBuilder.texOffs:(II)Lnet/minecraft/client/model/geom/builders/CubeListBuilder;
     412: ldc           #111                // float -2.5f
     414: fconst_2
     415: ldc           #111                // float -2.5f
     417: ldc           #92                 // float 5.0f
     419: ldc           #126                // float 21.0f
     421: ldc           #92                 // float 5.0f
     423: invokevirtual #68                 // Method net/minecraft/client/model/geom/builders/CubeListBuilder.addBox:(FFFFFF)Lnet/minecraft/client/model/geom/builders/CubeListBuilder;
     426: ldc           #130                // float -4.9f
     428: fconst_1
     429: ldc           #133                // float -10.5f
     431: invokestatic  #74                 // Method net/minecraft/client/model/geom/PartPose.offset:(FFF)Lnet/minecraft/client/model/geom/PartPose;
     434: invokevirtual #80                 // Method net/minecraft/client/model/geom/builders/PartDefinition.addOrReplaceChild:(Ljava/lang/String;Lnet/minecraft/client/model/geom/builders/CubeListBuilder;Lnet/minecraft/client/model/geom/PartPose;)Lnet/minecraft/client/model/geom/builders/PartDefinition;
     437: pop
     438: aload_0
     439: areturn
}
