# javap snapshot - Minecraft 26.1.2 client.jar
# Class: net.minecraft.client.model.animal.fox.BabyFoxModel
# Pilot entry: net.minecraft.client.model.animal.fox.BabyFoxModel
# Factory method: createBodyLayer
# Command: javap -c -constants
# Content: full class disassembly
# Generated: 2026-05-19T05:02:30.3815821-04:00
Compiled from "BabyFoxModel.java"
public class net.minecraft.client.model.animal.fox.BabyFoxModel extends net.minecraft.client.model.animal.fox.FoxModel {
  public net.minecraft.client.model.animal.fox.BabyFoxModel(net.minecraft.client.model.geom.ModelPart);
    Code:
       0: aload_0
       1: aload_1
       2: invokespecial #1                  // Method net/minecraft/client/model/animal/fox/FoxModel."<init>":(Lnet/minecraft/client/model/geom/ModelPart;)V
       5: aload_0
       6: getstatic     #7                  // Field net/minecraft/client/animation/definitions/FoxBabyAnimation.FOX_BABY_WALK:Lnet/minecraft/client/animation/AnimationDefinition;
       9: aload_1
      10: invokevirtual #13                 // Method net/minecraft/client/animation/AnimationDefinition.bake:(Lnet/minecraft/client/model/geom/ModelPart;)Lnet/minecraft/client/animation/KeyframeAnimation;
      13: putfield      #19                 // Field babyWalkAnimation:Lnet/minecraft/client/animation/KeyframeAnimation;
      16: return

  public static net.minecraft.client.model.geom.builders.LayerDefinition createBodyLayer();
    Code:
       0: new           #25                 // class net/minecraft/client/model/geom/builders/MeshDefinition
       3: dup
       4: invokespecial #27                 // Method net/minecraft/client/model/geom/builders/MeshDefinition."<init>":()V
       7: astore_0
       8: aload_0
       9: invokevirtual #30                 // Method net/minecraft/client/model/geom/builders/MeshDefinition.getRoot:()Lnet/minecraft/client/model/geom/builders/PartDefinition;
      12: astore_1
      13: aload_1
      14: ldc           #36                 // String head
      16: invokestatic  #38                 // Method net/minecraft/client/model/geom/builders/CubeListBuilder.create:()Lnet/minecraft/client/model/geom/builders/CubeListBuilder;
      19: iconst_0
      20: iconst_0
      21: invokevirtual #44                 // Method net/minecraft/client/model/geom/builders/CubeListBuilder.texOffs:(II)Lnet/minecraft/client/model/geom/builders/CubeListBuilder;
      24: ldc           #48                 // float -3.0f
      26: ldc           #49                 // float -2.125f
      28: ldc           #50                 // float -5.125f
      30: ldc           #51                 // float 6.0f
      32: ldc           #52                 // float 5.0f
      34: ldc           #52                 // float 5.0f
      36: new           #53                 // class net/minecraft/client/model/geom/builders/CubeDeformation
      39: dup
      40: fconst_0
      41: invokespecial #55                 // Method net/minecraft/client/model/geom/builders/CubeDeformation."<init>":(F)V
      44: invokevirtual #58                 // Method net/minecraft/client/model/geom/builders/CubeListBuilder.addBox:(FFFFFFLnet/minecraft/client/model/geom/builders/CubeDeformation;)Lnet/minecraft/client/model/geom/builders/CubeListBuilder;
      47: bipush        18
      49: bipush        20
      51: invokevirtual #44                 // Method net/minecraft/client/model/geom/builders/CubeListBuilder.texOffs:(II)Lnet/minecraft/client/model/geom/builders/CubeListBuilder;
      54: ldc           #62                 // float -1.0f
      56: ldc           #63                 // float 0.875f
      58: ldc           #64                 // float -7.125f
      60: fconst_2
      61: fconst_2
      62: fconst_2
      63: new           #53                 // class net/minecraft/client/model/geom/builders/CubeDeformation
      66: dup
      67: fconst_0
      68: invokespecial #55                 // Method net/minecraft/client/model/geom/builders/CubeDeformation."<init>":(F)V
      71: invokevirtual #58                 // Method net/minecraft/client/model/geom/builders/CubeListBuilder.addBox:(FFFFFFLnet/minecraft/client/model/geom/builders/CubeDeformation;)Lnet/minecraft/client/model/geom/builders/CubeListBuilder;
      74: bipush        22
      76: bipush        8
      78: invokevirtual #44                 // Method net/minecraft/client/model/geom/builders/CubeListBuilder.texOffs:(II)Lnet/minecraft/client/model/geom/builders/CubeListBuilder;
      81: ldc           #48                 // float -3.0f
      83: ldc           #65                 // float -4.125f
      85: ldc           #65                 // float -4.125f
      87: fconst_2
      88: fconst_2
      89: fconst_1
      90: new           #53                 // class net/minecraft/client/model/geom/builders/CubeDeformation
      93: dup
      94: fconst_0
      95: invokespecial #55                 // Method net/minecraft/client/model/geom/builders/CubeDeformation."<init>":(F)V
      98: invokevirtual #58                 // Method net/minecraft/client/model/geom/builders/CubeListBuilder.addBox:(FFFFFFLnet/minecraft/client/model/geom/builders/CubeDeformation;)Lnet/minecraft/client/model/geom/builders/CubeListBuilder;
     101: bipush        22
     103: bipush        11
     105: invokevirtual #44                 // Method net/minecraft/client/model/geom/builders/CubeListBuilder.texOffs:(II)Lnet/minecraft/client/model/geom/builders/CubeListBuilder;
     108: fconst_1
     109: ldc           #65                 // float -4.125f
     111: ldc           #65                 // float -4.125f
     113: fconst_2
     114: fconst_2
     115: fconst_1
     116: new           #53                 // class net/minecraft/client/model/geom/builders/CubeDeformation
     119: dup
     120: fconst_0
     121: invokespecial #55                 // Method net/minecraft/client/model/geom/builders/CubeDeformation."<init>":(F)V
     124: invokevirtual #58                 // Method net/minecraft/client/model/geom/builders/CubeListBuilder.addBox:(FFFFFFLnet/minecraft/client/model/geom/builders/CubeDeformation;)Lnet/minecraft/client/model/geom/builders/CubeListBuilder;
     127: fconst_0
     128: ldc           #66                 // float 18.125f
     130: ldc           #67                 // float 0.125f
     132: invokestatic  #68                 // Method net/minecraft/client/model/geom/PartPose.offset:(FFF)Lnet/minecraft/client/model/geom/PartPose;
     135: invokevirtual #74                 // Method net/minecraft/client/model/geom/builders/PartDefinition.addOrReplaceChild:(Ljava/lang/String;Lnet/minecraft/client/model/geom/builders/CubeListBuilder;Lnet/minecraft/client/model/geom/PartPose;)Lnet/minecraft/client/model/geom/builders/PartDefinition;
     138: pop
     139: aload_1
     140: ldc           #80                 // String right_hind_leg
     142: invokestatic  #38                 // Method net/minecraft/client/model/geom/builders/CubeListBuilder.create:()Lnet/minecraft/client/model/geom/builders/CubeListBuilder;
     145: bipush        22
     147: iconst_4
     148: invokevirtual #44                 // Method net/minecraft/client/model/geom/builders/CubeListBuilder.texOffs:(II)Lnet/minecraft/client/model/geom/builders/CubeListBuilder;
     151: ldc           #62                 // float -1.0f
     153: fconst_0
     154: ldc           #62                 // float -1.0f
     156: fconst_2
     157: fconst_2
     158: fconst_2
     159: new           #53                 // class net/minecraft/client/model/geom/builders/CubeDeformation
     162: dup
     163: fconst_0
     164: invokespecial #55                 // Method net/minecraft/client/model/geom/builders/CubeDeformation."<init>":(F)V
     167: invokevirtual #58                 // Method net/minecraft/client/model/geom/builders/CubeListBuilder.addBox:(FFFFFFLnet/minecraft/client/model/geom/builders/CubeDeformation;)Lnet/minecraft/client/model/geom/builders/CubeListBuilder;
     170: ldc           #82                 // float -1.5f
     172: ldc           #83                 // float 22.0f
     174: ldc           #84                 // float 4.0f
     176: invokestatic  #68                 // Method net/minecraft/client/model/geom/PartPose.offset:(FFF)Lnet/minecraft/client/model/geom/PartPose;
     179: invokevirtual #74                 // Method net/minecraft/client/model/geom/builders/PartDefinition.addOrReplaceChild:(Ljava/lang/String;Lnet/minecraft/client/model/geom/builders/CubeListBuilder;Lnet/minecraft/client/model/geom/PartPose;)Lnet/minecraft/client/model/geom/builders/PartDefinition;
     182: pop
     183: aload_1
     184: ldc           #85                 // String left_hind_leg
     186: invokestatic  #38                 // Method net/minecraft/client/model/geom/builders/CubeListBuilder.create:()Lnet/minecraft/client/model/geom/builders/CubeListBuilder;
     189: bipush        22
     191: iconst_0
     192: invokevirtual #44                 // Method net/minecraft/client/model/geom/builders/CubeListBuilder.texOffs:(II)Lnet/minecraft/client/model/geom/builders/CubeListBuilder;
     195: ldc           #62                 // float -1.0f
     197: fconst_0
     198: ldc           #62                 // float -1.0f
     200: fconst_2
     201: fconst_2
     202: fconst_2
     203: new           #53                 // class net/minecraft/client/model/geom/builders/CubeDeformation
     206: dup
     207: fconst_0
     208: invokespecial #55                 // Method net/minecraft/client/model/geom/builders/CubeDeformation."<init>":(F)V
     211: invokevirtual #58                 // Method net/minecraft/client/model/geom/builders/CubeListBuilder.addBox:(FFFFFFLnet/minecraft/client/model/geom/builders/CubeDeformation;)Lnet/minecraft/client/model/geom/builders/CubeListBuilder;
     214: ldc           #87                 // float 1.5f
     216: ldc           #83                 // float 22.0f
     218: ldc           #84                 // float 4.0f
     220: invokestatic  #68                 // Method net/minecraft/client/model/geom/PartPose.offset:(FFF)Lnet/minecraft/client/model/geom/PartPose;
     223: invokevirtual #74                 // Method net/minecraft/client/model/geom/builders/PartDefinition.addOrReplaceChild:(Ljava/lang/String;Lnet/minecraft/client/model/geom/builders/CubeListBuilder;Lnet/minecraft/client/model/geom/PartPose;)Lnet/minecraft/client/model/geom/builders/PartDefinition;
     226: pop
     227: aload_1
     228: ldc           #88                 // String right_front_leg
     230: invokestatic  #38                 // Method net/minecraft/client/model/geom/builders/CubeListBuilder.create:()Lnet/minecraft/client/model/geom/builders/CubeListBuilder;
     233: bipush        22
     235: iconst_4
     236: invokevirtual #44                 // Method net/minecraft/client/model/geom/builders/CubeListBuilder.texOffs:(II)Lnet/minecraft/client/model/geom/builders/CubeListBuilder;
     239: ldc           #62                 // float -1.0f
     241: fconst_0
     242: ldc           #62                 // float -1.0f
     244: fconst_2
     245: fconst_2
     246: fconst_2
     247: new           #53                 // class net/minecraft/client/model/geom/builders/CubeDeformation
     250: dup
     251: fconst_0
     252: invokespecial #55                 // Method net/minecraft/client/model/geom/builders/CubeDeformation."<init>":(F)V
     255: invokevirtual #58                 // Method net/minecraft/client/model/geom/builders/CubeListBuilder.addBox:(FFFFFFLnet/minecraft/client/model/geom/builders/CubeDeformation;)Lnet/minecraft/client/model/geom/builders/CubeListBuilder;
     258: ldc           #82                 // float -1.5f
     260: ldc           #83                 // float 22.0f
     262: fconst_0
     263: invokestatic  #68                 // Method net/minecraft/client/model/geom/PartPose.offset:(FFF)Lnet/minecraft/client/model/geom/PartPose;
     266: invokevirtual #74                 // Method net/minecraft/client/model/geom/builders/PartDefinition.addOrReplaceChild:(Ljava/lang/String;Lnet/minecraft/client/model/geom/builders/CubeListBuilder;Lnet/minecraft/client/model/geom/PartPose;)Lnet/minecraft/client/model/geom/builders/PartDefinition;
     269: pop
     270: aload_1
     271: ldc           #90                 // String left_front_leg
     273: invokestatic  #38                 // Method net/minecraft/client/model/geom/builders/CubeListBuilder.create:()Lnet/minecraft/client/model/geom/builders/CubeListBuilder;
     276: bipush        22
     278: iconst_0
     279: invokevirtual #44                 // Method net/minecraft/client/model/geom/builders/CubeListBuilder.texOffs:(II)Lnet/minecraft/client/model/geom/builders/CubeListBuilder;
     282: ldc           #62                 // float -1.0f
     284: fconst_0
     285: ldc           #62                 // float -1.0f
     287: fconst_2
     288: fconst_2
     289: fconst_2
     290: new           #53                 // class net/minecraft/client/model/geom/builders/CubeDeformation
     293: dup
     294: fconst_0
     295: invokespecial #55                 // Method net/minecraft/client/model/geom/builders/CubeDeformation."<init>":(F)V
     298: invokevirtual #58                 // Method net/minecraft/client/model/geom/builders/CubeListBuilder.addBox:(FFFFFFLnet/minecraft/client/model/geom/builders/CubeDeformation;)Lnet/minecraft/client/model/geom/builders/CubeListBuilder;
     301: ldc           #87                 // float 1.5f
     303: ldc           #83                 // float 22.0f
     305: fconst_0
     306: invokestatic  #68                 // Method net/minecraft/client/model/geom/PartPose.offset:(FFF)Lnet/minecraft/client/model/geom/PartPose;
     309: invokevirtual #74                 // Method net/minecraft/client/model/geom/builders/PartDefinition.addOrReplaceChild:(Ljava/lang/String;Lnet/minecraft/client/model/geom/builders/CubeListBuilder;Lnet/minecraft/client/model/geom/PartPose;)Lnet/minecraft/client/model/geom/builders/PartDefinition;
     312: pop
     313: aload_1
     314: ldc           #92                 // String body
     316: invokestatic  #38                 // Method net/minecraft/client/model/geom/builders/CubeListBuilder.create:()Lnet/minecraft/client/model/geom/builders/CubeListBuilder;
     319: iconst_0
     320: bipush        10
     322: invokevirtual #44                 // Method net/minecraft/client/model/geom/builders/CubeListBuilder.texOffs:(II)Lnet/minecraft/client/model/geom/builders/CubeListBuilder;
     325: ldc           #94                 // float -2.5f
     327: ldc           #95                 // float -2.0f
     329: ldc           #48                 // float -3.0f
     331: ldc           #52                 // float 5.0f
     333: ldc           #84                 // float 4.0f
     335: ldc           #51                 // float 6.0f
     337: new           #53                 // class net/minecraft/client/model/geom/builders/CubeDeformation
     340: dup
     341: fconst_0
     342: invokespecial #55                 // Method net/minecraft/client/model/geom/builders/CubeDeformation."<init>":(F)V
     345: invokevirtual #58                 // Method net/minecraft/client/model/geom/builders/CubeListBuilder.addBox:(FFFFFFLnet/minecraft/client/model/geom/builders/CubeDeformation;)Lnet/minecraft/client/model/geom/builders/CubeListBuilder;
     348: fconst_0
     349: ldc           #96                 // float 20.0f
     351: fconst_2
     352: invokestatic  #68                 // Method net/minecraft/client/model/geom/PartPose.offset:(FFF)Lnet/minecraft/client/model/geom/PartPose;
     355: invokevirtual #74                 // Method net/minecraft/client/model/geom/builders/PartDefinition.addOrReplaceChild:(Ljava/lang/String;Lnet/minecraft/client/model/geom/builders/CubeListBuilder;Lnet/minecraft/client/model/geom/PartPose;)Lnet/minecraft/client/model/geom/builders/PartDefinition;
     358: astore_2
     359: aload_2
     360: ldc           #97                 // String tail
     362: invokestatic  #38                 // Method net/minecraft/client/model/geom/builders/CubeListBuilder.create:()Lnet/minecraft/client/model/geom/builders/CubeListBuilder;
     365: iconst_0
     366: bipush        20
     368: invokevirtual #44                 // Method net/minecraft/client/model/geom/builders/CubeListBuilder.texOffs:(II)Lnet/minecraft/client/model/geom/builders/CubeListBuilder;
     371: ldc           #82                 // float -1.5f
     373: ldc           #99                 // float -1.48f
     375: ldc           #62                 // float -1.0f
     377: ldc           #100                // float 3.0f
     379: ldc           #100                // float 3.0f
     381: ldc           #51                 // float 6.0f
     383: new           #53                 // class net/minecraft/client/model/geom/builders/CubeDeformation
     386: dup
     387: fconst_0
     388: invokespecial #55                 // Method net/minecraft/client/model/geom/builders/CubeDeformation."<init>":(F)V
     391: invokevirtual #58                 // Method net/minecraft/client/model/geom/builders/CubeListBuilder.addBox:(FFFFFFLnet/minecraft/client/model/geom/builders/CubeDeformation;)Lnet/minecraft/client/model/geom/builders/CubeListBuilder;
     394: fconst_0
     395: ldc           #101                // float -0.5f
     397: ldc           #100                // float 3.0f
     399: invokestatic  #68                 // Method net/minecraft/client/model/geom/PartPose.offset:(FFF)Lnet/minecraft/client/model/geom/PartPose;
     402: invokevirtual #74                 // Method net/minecraft/client/model/geom/builders/PartDefinition.addOrReplaceChild:(Ljava/lang/String;Lnet/minecraft/client/model/geom/builders/CubeListBuilder;Lnet/minecraft/client/model/geom/PartPose;)Lnet/minecraft/client/model/geom/builders/PartDefinition;
     405: pop
     406: aload_0
     407: bipush        32
     409: bipush        32
     411: invokestatic  #102                // Method net/minecraft/client/model/geom/builders/LayerDefinition.create:(Lnet/minecraft/client/model/geom/builders/MeshDefinition;II)Lnet/minecraft/client/model/geom/builders/LayerDefinition;
     414: areturn

  protected void setSittingPose(net.minecraft.client.renderer.entity.state.FoxRenderState);
    Code:
       0: aload_0
       1: aload_1
       2: invokespecial #107                // Method net/minecraft/client/model/animal/fox/FoxModel.setSittingPose:(Lnet/minecraft/client/renderer/entity/state/FoxRenderState;)V
       5: aload_0
       6: getfield      #111                // Field body:Lnet/minecraft/client/model/geom/ModelPart;
       9: ldc           #116                // float -0.959931f
      11: putfield      #117                // Field net/minecraft/client/model/geom/ModelPart.xRot:F
      14: aload_0
      15: getfield      #111                // Field body:Lnet/minecraft/client/model/geom/ModelPart;
      18: dup
      19: getfield      #123                // Field net/minecraft/client/model/geom/ModelPart.z:F
      22: ldc           #126                // float 4.5f
      24: aload_1
      25: getfield      #127                // Field net/minecraft/client/renderer/entity/state/FoxRenderState.ageScale:F
      28: fmul
      29: fsub
      30: putfield      #123                // Field net/minecraft/client/model/geom/ModelPart.z:F
      33: aload_0
      34: getfield      #111                // Field body:Lnet/minecraft/client/model/geom/ModelPart;
      37: dup
      38: getfield      #132                // Field net/minecraft/client/model/geom/ModelPart.y:F
      41: ldc           #100                // float 3.0f
      43: aload_1
      44: getfield      #127                // Field net/minecraft/client/renderer/entity/state/FoxRenderState.ageScale:F
      47: fmul
      48: fadd
      49: putfield      #132                // Field net/minecraft/client/model/geom/ModelPart.y:F
      52: aload_0
      53: getfield      #135                // Field tail:Lnet/minecraft/client/model/geom/ModelPart;
      56: dup
      57: getfield      #132                // Field net/minecraft/client/model/geom/ModelPart.y:F
      60: ldc           #137                // float 0.6f
      62: fsub
      63: putfield      #132                // Field net/minecraft/client/model/geom/ModelPart.y:F
      66: aload_0
      67: getfield      #135                // Field tail:Lnet/minecraft/client/model/geom/ModelPart;
      70: dup
      71: getfield      #123                // Field net/minecraft/client/model/geom/ModelPart.z:F
      74: fconst_2
      75: aload_1
      76: getfield      #127                // Field net/minecraft/client/renderer/entity/state/FoxRenderState.ageScale:F
      79: fmul
      80: fsub
      81: putfield      #123                // Field net/minecraft/client/model/geom/ModelPart.z:F
      84: aload_0
      85: getfield      #135                // Field tail:Lnet/minecraft/client/model/geom/ModelPart;
      88: ldc           #138                // float 0.95993114f
      90: putfield      #117                // Field net/minecraft/client/model/geom/ModelPart.xRot:F
      93: aload_0
      94: getfield      #139                // Field head:Lnet/minecraft/client/model/geom/ModelPart;
      97: dup
      98: getfield      #132                // Field net/minecraft/client/model/geom/ModelPart.y:F
     101: ldc           #141                // float 0.75f
     103: fsub
     104: putfield      #132                // Field net/minecraft/client/model/geom/ModelPart.y:F
     107: aload_0
     108: getfield      #139                // Field head:Lnet/minecraft/client/model/geom/ModelPart;
     111: dup
     112: getfield      #123                // Field net/minecraft/client/model/geom/ModelPart.z:F
     115: fconst_0
     116: fadd
     117: putfield      #123                // Field net/minecraft/client/model/geom/ModelPart.z:F
     120: aload_0
     121: getfield      #142                // Field rightFrontLeg:Lnet/minecraft/client/model/geom/ModelPart;
     124: ldc           #145                // float -0.2617994f
     126: putfield      #117                // Field net/minecraft/client/model/geom/ModelPart.xRot:F
     129: aload_0
     130: getfield      #146                // Field leftFrontLeg:Lnet/minecraft/client/model/geom/ModelPart;
     133: ldc           #145                // float -0.2617994f
     135: putfield      #117                // Field net/minecraft/client/model/geom/ModelPart.xRot:F
     138: aload_0
     139: getfield      #142                // Field rightFrontLeg:Lnet/minecraft/client/model/geom/ModelPart;
     142: dup
     143: getfield      #123                // Field net/minecraft/client/model/geom/ModelPart.z:F
     146: ldc           #87                 // float 1.5f
     148: fsub
     149: putfield      #123                // Field net/minecraft/client/model/geom/ModelPart.z:F
     152: aload_0
     153: getfield      #146                // Field leftFrontLeg:Lnet/minecraft/client/model/geom/ModelPart;
     156: dup
     157: getfield      #123                // Field net/minecraft/client/model/geom/ModelPart.z:F
     160: ldc           #87                 // float 1.5f
     162: fsub
     163: putfield      #123                // Field net/minecraft/client/model/geom/ModelPart.z:F
     166: aload_0
     167: getfield      #142                // Field rightFrontLeg:Lnet/minecraft/client/model/geom/ModelPart;
     170: dup
     171: getfield      #149                // Field net/minecraft/client/model/geom/ModelPart.x:F
     174: ldc           #152                // float 0.01f
     176: fadd
     177: putfield      #149                // Field net/minecraft/client/model/geom/ModelPart.x:F
     180: aload_0
     181: getfield      #146                // Field leftFrontLeg:Lnet/minecraft/client/model/geom/ModelPart;
     184: dup
     185: getfield      #149                // Field net/minecraft/client/model/geom/ModelPart.x:F
     188: ldc           #152                // float 0.01f
     190: fsub
     191: putfield      #149                // Field net/minecraft/client/model/geom/ModelPart.x:F
     194: aload_0
     195: getfield      #153                // Field rightHindLeg:Lnet/minecraft/client/model/geom/ModelPart;
     198: dup
     199: getfield      #123                // Field net/minecraft/client/model/geom/ModelPart.z:F
     202: ldc           #156                // float 3.75f
     204: fsub
     205: putfield      #123                // Field net/minecraft/client/model/geom/ModelPart.z:F
     208: aload_0
     209: getfield      #157                // Field leftHindLeg:Lnet/minecraft/client/model/geom/ModelPart;
     212: dup
     213: getfield      #123                // Field net/minecraft/client/model/geom/ModelPart.z:F
     216: ldc           #156                // float 3.75f
     218: fsub
     219: putfield      #123                // Field net/minecraft/client/model/geom/ModelPart.z:F
     222: aload_0
     223: getfield      #153                // Field rightHindLeg:Lnet/minecraft/client/model/geom/ModelPart;
     226: dup
     227: getfield      #149                // Field net/minecraft/client/model/geom/ModelPart.x:F
     230: ldc           #152                // float 0.01f
     232: fadd
     233: putfield      #149                // Field net/minecraft/client/model/geom/ModelPart.x:F
     236: aload_0
     237: getfield      #157                // Field leftHindLeg:Lnet/minecraft/client/model/geom/ModelPart;
     240: dup
     241: getfield      #149                // Field net/minecraft/client/model/geom/ModelPart.x:F
     244: ldc           #152                // float 0.01f
     246: fsub
     247: putfield      #149                // Field net/minecraft/client/model/geom/ModelPart.x:F
     250: return

  protected void setSleepingPose(net.minecraft.client.renderer.entity.state.FoxRenderState);
    Code:
       0: aload_0
       1: aload_1
       2: invokespecial #160                // Method net/minecraft/client/model/animal/fox/FoxModel.setSleepingPose:(Lnet/minecraft/client/renderer/entity/state/FoxRenderState;)V
       5: aload_0
       6: getfield      #111                // Field body:Lnet/minecraft/client/model/geom/ModelPart;
       9: ldc           #163                // float -1.5707964f
      11: putfield      #164                // Field net/minecraft/client/model/geom/ModelPart.zRot:F
      14: aload_0
      15: getfield      #111                // Field body:Lnet/minecraft/client/model/geom/ModelPart;
      18: ldc           #167                // float -0.17453292f
      20: putfield      #117                // Field net/minecraft/client/model/geom/ModelPart.xRot:F
      23: aload_0
      24: getfield      #111                // Field body:Lnet/minecraft/client/model/geom/ModelPart;
      27: dup
      28: getfield      #132                // Field net/minecraft/client/model/geom/ModelPart.y:F
      31: ldc           #87                 // float 1.5f
      33: fadd
      34: putfield      #132                // Field net/minecraft/client/model/geom/ModelPart.y:F
      37: aload_0
      38: getfield      #111                // Field body:Lnet/minecraft/client/model/geom/ModelPart;
      41: dup
      42: getfield      #123                // Field net/minecraft/client/model/geom/ModelPart.z:F
      45: ldc           #87                 // float 1.5f
      47: fsub
      48: putfield      #123                // Field net/minecraft/client/model/geom/ModelPart.z:F
      51: aload_0
      52: getfield      #111                // Field body:Lnet/minecraft/client/model/geom/ModelPart;
      55: dup
      56: getfield      #149                // Field net/minecraft/client/model/geom/ModelPart.x:F
      59: ldc           #87                 // float 1.5f
      61: fsub
      62: putfield      #149                // Field net/minecraft/client/model/geom/ModelPart.x:F
      65: aload_0
      66: getfield      #135                // Field tail:Lnet/minecraft/client/model/geom/ModelPart;
      69: ldc           #168                // float -2.6179938f
      71: putfield      #117                // Field net/minecraft/client/model/geom/ModelPart.xRot:F
      74: aload_0
      75: getfield      #135                // Field tail:Lnet/minecraft/client/model/geom/ModelPart;
      78: ldc           #169                // float -2.1816616f
      80: putfield      #117                // Field net/minecraft/client/model/geom/ModelPart.xRot:F
      83: aload_0
      84: getfield      #135                // Field tail:Lnet/minecraft/client/model/geom/ModelPart;
      87: dup
      88: getfield      #149                // Field net/minecraft/client/model/geom/ModelPart.x:F
      91: ldc           #170                // float 0.7f
      93: fsub
      94: putfield      #149                // Field net/minecraft/client/model/geom/ModelPart.x:F
      97: aload_0
      98: getfield      #135                // Field tail:Lnet/minecraft/client/model/geom/ModelPart;
     101: dup
     102: getfield      #123                // Field net/minecraft/client/model/geom/ModelPart.z:F
     105: ldc           #137                // float 0.6f
     107: fadd
     108: putfield      #123                // Field net/minecraft/client/model/geom/ModelPart.z:F
     111: aload_0
     112: getfield      #135                // Field tail:Lnet/minecraft/client/model/geom/ModelPart;
     115: dup
     116: getfield      #132                // Field net/minecraft/client/model/geom/ModelPart.y:F
     119: ldc           #171                // float 0.9f
     121: fadd
     122: putfield      #132                // Field net/minecraft/client/model/geom/ModelPart.y:F
     125: aload_0
     126: getfield      #139                // Field head:Lnet/minecraft/client/model/geom/ModelPart;
     129: dup
     130: getfield      #149                // Field net/minecraft/client/model/geom/ModelPart.x:F
     133: fconst_2
     134: fsub
     135: putfield      #149                // Field net/minecraft/client/model/geom/ModelPart.x:F
     138: aload_0
     139: getfield      #139                // Field head:Lnet/minecraft/client/model/geom/ModelPart;
     142: dup
     143: getfield      #132                // Field net/minecraft/client/model/geom/ModelPart.y:F
     146: ldc           #172                // float 2.8f
     148: fadd
     149: putfield      #132                // Field net/minecraft/client/model/geom/ModelPart.y:F
     152: aload_0
     153: getfield      #139                // Field head:Lnet/minecraft/client/model/geom/ModelPart;
     156: dup
     157: getfield      #123                // Field net/minecraft/client/model/geom/ModelPart.z:F
     160: ldc           #84                 // float 4.0f
     162: fsub
     163: putfield      #123                // Field net/minecraft/client/model/geom/ModelPart.z:F
     166: aload_0
     167: getfield      #139                // Field head:Lnet/minecraft/client/model/geom/ModelPart;
     170: ldc           #173                // float -2.0943952f
     172: putfield      #174                // Field net/minecraft/client/model/geom/ModelPart.yRot:F
     175: aload_0
     176: getfield      #139                // Field head:Lnet/minecraft/client/model/geom/ModelPart;
     179: fconst_0
     180: putfield      #164                // Field net/minecraft/client/model/geom/ModelPart.zRot:F
     183: return

  protected void setWalkingPose(net.minecraft.client.renderer.entity.state.FoxRenderState);
    Code:
       0: aload_0
       1: aload_1
       2: invokespecial #177                // Method net/minecraft/client/model/animal/fox/FoxModel.setWalkingPose:(Lnet/minecraft/client/renderer/entity/state/FoxRenderState;)V
       5: aload_0
       6: getfield      #19                 // Field babyWalkAnimation:Lnet/minecraft/client/animation/KeyframeAnimation;
       9: aload_1
      10: getfield      #180                // Field net/minecraft/client/renderer/entity/state/FoxRenderState.walkAnimationPos:F
      13: aload_1
      14: getfield      #183                // Field net/minecraft/client/renderer/entity/state/FoxRenderState.walkAnimationSpeed:F
      17: fconst_1
      18: ldc           #186                // float 2.5f
      20: invokevirtual #187                // Method net/minecraft/client/animation/KeyframeAnimation.applyWalk:(FFFF)V
      23: return

  protected void setCrouchingPose(net.minecraft.client.renderer.entity.state.FoxRenderState);
    Code:
       0: aload_0
       1: aload_1
       2: invokespecial #193                // Method net/minecraft/client/model/animal/fox/FoxModel.setCrouchingPose:(Lnet/minecraft/client/renderer/entity/state/FoxRenderState;)V
       5: aload_0
       6: getfield      #111                // Field body:Lnet/minecraft/client/model/geom/ModelPart;
       9: dup
      10: getfield      #132                // Field net/minecraft/client/model/geom/ModelPart.y:F
      13: aload_1
      14: getfield      #196                // Field net/minecraft/client/renderer/entity/state/FoxRenderState.crouchAmount:F
      17: ldc           #51                 // float 6.0f
      19: fdiv
      20: fadd
      21: putfield      #132                // Field net/minecraft/client/model/geom/ModelPart.y:F
      24: return
}
