# javap snapshot - Minecraft 26.1.2 client.jar
# Class: net.minecraft.client.model.animal.cow.CowModel
# Command: javap -c -constants
# Generated: 2026-05-19T03:40:37.7712365-04:00
Compiled from "CowModel.java"
public class net.minecraft.client.model.animal.cow.CowModel extends net.minecraft.client.model.QuadrupedModel<net.minecraft.client.renderer.entity.state.LivingEntityRenderState> {
  public static final net.minecraft.client.model.geom.builders.MeshTransformer BABY_TRANSFORMER;

  public net.minecraft.client.model.animal.cow.CowModel(net.minecraft.client.model.geom.ModelPart);
    Code:
       0: aload_0
       1: aload_1
       2: invokespecial #1                  // Method net/minecraft/client/model/QuadrupedModel."<init>":(Lnet/minecraft/client/model/geom/ModelPart;)V
       5: return

  public static net.minecraft.client.model.geom.builders.LayerDefinition createBodyLayer();
    Code:
       0: invokestatic  #7                  // Method createBaseCowModel:()Lnet/minecraft/client/model/geom/builders/MeshDefinition;
       3: astore_0
       4: aload_0
       5: bipush        64
       7: bipush        64
       9: invokestatic  #13                 // Method net/minecraft/client/model/geom/builders/LayerDefinition.create:(Lnet/minecraft/client/model/geom/builders/MeshDefinition;II)Lnet/minecraft/client/model/geom/builders/LayerDefinition;
      12: areturn

  static net.minecraft.client.model.geom.builders.MeshDefinition createBaseCowModel();
    Code:
       0: new           #19                 // class net/minecraft/client/model/geom/builders/MeshDefinition
       3: dup
       4: invokespecial #21                 // Method net/minecraft/client/model/geom/builders/MeshDefinition."<init>":()V
       7: astore_0
       8: aload_0
       9: invokevirtual #24                 // Method net/minecraft/client/model/geom/builders/MeshDefinition.getRoot:()Lnet/minecraft/client/model/geom/builders/PartDefinition;
      12: astore_1
      13: aload_1
      14: ldc           #30                 // String head
      16: invokestatic  #32                 // Method net/minecraft/client/model/geom/builders/CubeListBuilder.create:()Lnet/minecraft/client/model/geom/builders/CubeListBuilder;
      19: iconst_0
      20: iconst_0
      21: invokevirtual #37                 // Method net/minecraft/client/model/geom/builders/CubeListBuilder.texOffs:(II)Lnet/minecraft/client/model/geom/builders/CubeListBuilder;
      24: ldc           #41                 // float -4.0f
      26: ldc           #41                 // float -4.0f
      28: ldc           #42                 // float -6.0f
      30: ldc           #43                 // float 8.0f
      32: ldc           #43                 // float 8.0f
      34: ldc           #44                 // float 6.0f
      36: invokevirtual #45                 // Method net/minecraft/client/model/geom/builders/CubeListBuilder.addBox:(FFFFFF)Lnet/minecraft/client/model/geom/builders/CubeListBuilder;
      39: iconst_1
      40: bipush        33
      42: invokevirtual #37                 // Method net/minecraft/client/model/geom/builders/CubeListBuilder.texOffs:(II)Lnet/minecraft/client/model/geom/builders/CubeListBuilder;
      45: ldc           #49                 // float -3.0f
      47: fconst_1
      48: ldc           #50                 // float -7.0f
      50: ldc           #44                 // float 6.0f
      52: ldc           #51                 // float 3.0f
      54: fconst_1
      55: invokevirtual #45                 // Method net/minecraft/client/model/geom/builders/CubeListBuilder.addBox:(FFFFFF)Lnet/minecraft/client/model/geom/builders/CubeListBuilder;
      58: bipush        22
      60: iconst_0
      61: invokevirtual #37                 // Method net/minecraft/client/model/geom/builders/CubeListBuilder.texOffs:(II)Lnet/minecraft/client/model/geom/builders/CubeListBuilder;
      64: ldc           #52                 // String right_horn
      66: ldc           #54                 // float -5.0f
      68: ldc           #54                 // float -5.0f
      70: ldc           #54                 // float -5.0f
      72: fconst_1
      73: ldc           #51                 // float 3.0f
      75: fconst_1
      76: invokevirtual #55                 // Method net/minecraft/client/model/geom/builders/CubeListBuilder.addBox:(Ljava/lang/String;FFFFFF)Lnet/minecraft/client/model/geom/builders/CubeListBuilder;
      79: bipush        22
      81: iconst_0
      82: invokevirtual #37                 // Method net/minecraft/client/model/geom/builders/CubeListBuilder.texOffs:(II)Lnet/minecraft/client/model/geom/builders/CubeListBuilder;
      85: ldc           #58                 // String left_horn
      87: ldc           #60                 // float 4.0f
      89: ldc           #54                 // float -5.0f
      91: ldc           #54                 // float -5.0f
      93: fconst_1
      94: ldc           #51                 // float 3.0f
      96: fconst_1
      97: invokevirtual #55                 // Method net/minecraft/client/model/geom/builders/CubeListBuilder.addBox:(Ljava/lang/String;FFFFFF)Lnet/minecraft/client/model/geom/builders/CubeListBuilder;
     100: fconst_0
     101: ldc           #60                 // float 4.0f
     103: ldc           #61                 // float -8.0f
     105: invokestatic  #62                 // Method net/minecraft/client/model/geom/PartPose.offset:(FFF)Lnet/minecraft/client/model/geom/PartPose;
     108: invokevirtual #68                 // Method net/minecraft/client/model/geom/builders/PartDefinition.addOrReplaceChild:(Ljava/lang/String;Lnet/minecraft/client/model/geom/builders/CubeListBuilder;Lnet/minecraft/client/model/geom/PartPose;)Lnet/minecraft/client/model/geom/builders/PartDefinition;
     111: pop
     112: aload_1
     113: ldc           #74                 // String body
     115: invokestatic  #32                 // Method net/minecraft/client/model/geom/builders/CubeListBuilder.create:()Lnet/minecraft/client/model/geom/builders/CubeListBuilder;
     118: bipush        18
     120: iconst_4
     121: invokevirtual #37                 // Method net/minecraft/client/model/geom/builders/CubeListBuilder.texOffs:(II)Lnet/minecraft/client/model/geom/builders/CubeListBuilder;
     124: ldc           #42                 // float -6.0f
     126: ldc           #76                 // float -10.0f
     128: ldc           #50                 // float -7.0f
     130: ldc           #77                 // float 12.0f
     132: ldc           #78                 // float 18.0f
     134: ldc           #79                 // float 10.0f
     136: invokevirtual #45                 // Method net/minecraft/client/model/geom/builders/CubeListBuilder.addBox:(FFFFFF)Lnet/minecraft/client/model/geom/builders/CubeListBuilder;
     139: bipush        52
     141: iconst_0
     142: invokevirtual #37                 // Method net/minecraft/client/model/geom/builders/CubeListBuilder.texOffs:(II)Lnet/minecraft/client/model/geom/builders/CubeListBuilder;
     145: ldc           #80                 // float -2.0f
     147: fconst_2
     148: ldc           #61                 // float -8.0f
     150: ldc           #60                 // float 4.0f
     152: ldc           #44                 // float 6.0f
     154: fconst_1
     155: invokevirtual #45                 // Method net/minecraft/client/model/geom/builders/CubeListBuilder.addBox:(FFFFFF)Lnet/minecraft/client/model/geom/builders/CubeListBuilder;
     158: fconst_0
     159: ldc           #81                 // float 5.0f
     161: fconst_2
     162: ldc           #84                 // float 1.5707964f
     164: fconst_0
     165: fconst_0
     166: invokestatic  #85                 // Method net/minecraft/client/model/geom/PartPose.offsetAndRotation:(FFFFFF)Lnet/minecraft/client/model/geom/PartPose;
     169: invokevirtual #68                 // Method net/minecraft/client/model/geom/builders/PartDefinition.addOrReplaceChild:(Ljava/lang/String;Lnet/minecraft/client/model/geom/builders/CubeListBuilder;Lnet/minecraft/client/model/geom/PartPose;)Lnet/minecraft/client/model/geom/builders/PartDefinition;
     172: pop
     173: invokestatic  #32                 // Method net/minecraft/client/model/geom/builders/CubeListBuilder.create:()Lnet/minecraft/client/model/geom/builders/CubeListBuilder;
     176: invokevirtual #89                 // Method net/minecraft/client/model/geom/builders/CubeListBuilder.mirror:()Lnet/minecraft/client/model/geom/builders/CubeListBuilder;
     179: iconst_0
     180: bipush        16
     182: invokevirtual #37                 // Method net/minecraft/client/model/geom/builders/CubeListBuilder.texOffs:(II)Lnet/minecraft/client/model/geom/builders/CubeListBuilder;
     185: ldc           #80                 // float -2.0f
     187: fconst_0
     188: ldc           #80                 // float -2.0f
     190: ldc           #60                 // float 4.0f
     192: ldc           #77                 // float 12.0f
     194: ldc           #60                 // float 4.0f
     196: invokevirtual #45                 // Method net/minecraft/client/model/geom/builders/CubeListBuilder.addBox:(FFFFFF)Lnet/minecraft/client/model/geom/builders/CubeListBuilder;
     199: astore_2
     200: invokestatic  #32                 // Method net/minecraft/client/model/geom/builders/CubeListBuilder.create:()Lnet/minecraft/client/model/geom/builders/CubeListBuilder;
     203: iconst_0
     204: bipush        16
     206: invokevirtual #37                 // Method net/minecraft/client/model/geom/builders/CubeListBuilder.texOffs:(II)Lnet/minecraft/client/model/geom/builders/CubeListBuilder;
     209: ldc           #80                 // float -2.0f
     211: fconst_0
     212: ldc           #80                 // float -2.0f
     214: ldc           #60                 // float 4.0f
     216: ldc           #77                 // float 12.0f
     218: ldc           #60                 // float 4.0f
     220: invokevirtual #45                 // Method net/minecraft/client/model/geom/builders/CubeListBuilder.addBox:(FFFFFF)Lnet/minecraft/client/model/geom/builders/CubeListBuilder;
     223: astore_3
     224: aload_1
     225: ldc           #92                 // String right_hind_leg
     227: aload_3
     228: ldc           #41                 // float -4.0f
     230: ldc           #77                 // float 12.0f
     232: ldc           #94                 // float 7.0f
     234: invokestatic  #62                 // Method net/minecraft/client/model/geom/PartPose.offset:(FFF)Lnet/minecraft/client/model/geom/PartPose;
     237: invokevirtual #68                 // Method net/minecraft/client/model/geom/builders/PartDefinition.addOrReplaceChild:(Ljava/lang/String;Lnet/minecraft/client/model/geom/builders/CubeListBuilder;Lnet/minecraft/client/model/geom/PartPose;)Lnet/minecraft/client/model/geom/builders/PartDefinition;
     240: pop
     241: aload_1
     242: ldc           #95                 // String left_hind_leg
     244: aload_2
     245: ldc           #60                 // float 4.0f
     247: ldc           #77                 // float 12.0f
     249: ldc           #94                 // float 7.0f
     251: invokestatic  #62                 // Method net/minecraft/client/model/geom/PartPose.offset:(FFF)Lnet/minecraft/client/model/geom/PartPose;
     254: invokevirtual #68                 // Method net/minecraft/client/model/geom/builders/PartDefinition.addOrReplaceChild:(Ljava/lang/String;Lnet/minecraft/client/model/geom/builders/CubeListBuilder;Lnet/minecraft/client/model/geom/PartPose;)Lnet/minecraft/client/model/geom/builders/PartDefinition;
     257: pop
     258: aload_1
     259: ldc           #97                 // String right_front_leg
     261: aload_3
     262: ldc           #41                 // float -4.0f
     264: ldc           #77                 // float 12.0f
     266: ldc           #54                 // float -5.0f
     268: invokestatic  #62                 // Method net/minecraft/client/model/geom/PartPose.offset:(FFF)Lnet/minecraft/client/model/geom/PartPose;
     271: invokevirtual #68                 // Method net/minecraft/client/model/geom/builders/PartDefinition.addOrReplaceChild:(Ljava/lang/String;Lnet/minecraft/client/model/geom/builders/CubeListBuilder;Lnet/minecraft/client/model/geom/PartPose;)Lnet/minecraft/client/model/geom/builders/PartDefinition;
     274: pop
     275: aload_1
     276: ldc           #99                 // String left_front_leg
     278: aload_2
     279: ldc           #60                 // float 4.0f
     281: ldc           #77                 // float 12.0f
     283: ldc           #54                 // float -5.0f
     285: invokestatic  #62                 // Method net/minecraft/client/model/geom/PartPose.offset:(FFF)Lnet/minecraft/client/model/geom/PartPose;
     288: invokevirtual #68                 // Method net/minecraft/client/model/geom/builders/PartDefinition.addOrReplaceChild:(Ljava/lang/String;Lnet/minecraft/client/model/geom/builders/CubeListBuilder;Lnet/minecraft/client/model/geom/PartPose;)Lnet/minecraft/client/model/geom/builders/PartDefinition;
     291: pop
     292: aload_0
     293: areturn

  public net.minecraft.client.model.geom.ModelPart getHead();
    Code:
       0: aload_0
       1: getfield      #101                // Field head:Lnet/minecraft/client/model/geom/ModelPart;
       4: areturn

  static {};
    Code:
       0: new           #104                // class net/minecraft/client/model/BabyModelTransform
       3: dup
       4: iconst_0
       5: ldc           #43                 // float 8.0f
       7: ldc           #44                 // float 6.0f
       9: ldc           #30                 // String head
      11: invokestatic  #106                // InterfaceMethod java/util/Set.of:(Ljava/lang/Object;)Ljava/util/Set;
      14: invokespecial #112                // Method net/minecraft/client/model/BabyModelTransform."<init>":(ZFFLjava/util/Set;)V
      17: putstatic     #115                // Field BABY_TRANSFORMER:Lnet/minecraft/client/model/geom/builders/MeshTransformer;
      20: return
}
