# javap snapshot - Minecraft 26.1.2 client.jar
# Class: net.minecraft.client.model.animal.sniffer.SnifferModel
# Pilot entry: net.minecraft.client.model.animal.sniffer.SnifferModel
# Factory method: createBodyLayer
# Command: javap -c -constants
# Content: full class disassembly
# Generated: 2026-05-19T05:03:12.0128102-04:00
Compiled from "SnifferModel.java"
public class net.minecraft.client.model.animal.sniffer.SnifferModel extends net.minecraft.client.model.EntityModel<net.minecraft.client.renderer.entity.state.SnifferRenderState> {
  public net.minecraft.client.model.animal.sniffer.SnifferModel(net.minecraft.client.model.geom.ModelPart);
    Code:
       0: aload_0
       1: aload_1
       2: invokespecial #1                  // Method net/minecraft/client/model/EntityModel."<init>":(Lnet/minecraft/client/model/geom/ModelPart;)V
       5: aload_0
       6: aload_1
       7: ldc           #7                  // String bone
       9: invokevirtual #9                  // Method net/minecraft/client/model/geom/ModelPart.getChild:(Ljava/lang/String;)Lnet/minecraft/client/model/geom/ModelPart;
      12: ldc           #15                 // String body
      14: invokevirtual #9                  // Method net/minecraft/client/model/geom/ModelPart.getChild:(Ljava/lang/String;)Lnet/minecraft/client/model/geom/ModelPart;
      17: ldc           #17                 // String head
      19: invokevirtual #9                  // Method net/minecraft/client/model/geom/ModelPart.getChild:(Ljava/lang/String;)Lnet/minecraft/client/model/geom/ModelPart;
      22: putfield      #19                 // Field head:Lnet/minecraft/client/model/geom/ModelPart;
      25: aload_0
      26: getstatic     #24                 // Field net/minecraft/client/animation/definitions/SnifferAnimation.SNIFFER_SNIFF_SEARCH:Lnet/minecraft/client/animation/AnimationDefinition;
      29: aload_1
      30: invokevirtual #30                 // Method net/minecraft/client/animation/AnimationDefinition.bake:(Lnet/minecraft/client/model/geom/ModelPart;)Lnet/minecraft/client/animation/KeyframeAnimation;
      33: putfield      #36                 // Field sniffSearchAnimation:Lnet/minecraft/client/animation/KeyframeAnimation;
      36: aload_0
      37: getstatic     #40                 // Field net/minecraft/client/animation/definitions/SnifferAnimation.SNIFFER_WALK:Lnet/minecraft/client/animation/AnimationDefinition;
      40: aload_1
      41: invokevirtual #30                 // Method net/minecraft/client/animation/AnimationDefinition.bake:(Lnet/minecraft/client/model/geom/ModelPart;)Lnet/minecraft/client/animation/KeyframeAnimation;
      44: putfield      #43                 // Field walkAnimation:Lnet/minecraft/client/animation/KeyframeAnimation;
      47: aload_0
      48: getstatic     #46                 // Field net/minecraft/client/animation/definitions/SnifferAnimation.SNIFFER_DIG:Lnet/minecraft/client/animation/AnimationDefinition;
      51: aload_1
      52: invokevirtual #30                 // Method net/minecraft/client/animation/AnimationDefinition.bake:(Lnet/minecraft/client/model/geom/ModelPart;)Lnet/minecraft/client/animation/KeyframeAnimation;
      55: putfield      #49                 // Field digAnimation:Lnet/minecraft/client/animation/KeyframeAnimation;
      58: aload_0
      59: getstatic     #52                 // Field net/minecraft/client/animation/definitions/SnifferAnimation.SNIFFER_LONGSNIFF:Lnet/minecraft/client/animation/AnimationDefinition;
      62: aload_1
      63: invokevirtual #30                 // Method net/minecraft/client/animation/AnimationDefinition.bake:(Lnet/minecraft/client/model/geom/ModelPart;)Lnet/minecraft/client/animation/KeyframeAnimation;
      66: putfield      #55                 // Field longSniffAnimation:Lnet/minecraft/client/animation/KeyframeAnimation;
      69: aload_0
      70: getstatic     #58                 // Field net/minecraft/client/animation/definitions/SnifferAnimation.SNIFFER_STAND_UP:Lnet/minecraft/client/animation/AnimationDefinition;
      73: aload_1
      74: invokevirtual #30                 // Method net/minecraft/client/animation/AnimationDefinition.bake:(Lnet/minecraft/client/model/geom/ModelPart;)Lnet/minecraft/client/animation/KeyframeAnimation;
      77: putfield      #61                 // Field standUpAnimation:Lnet/minecraft/client/animation/KeyframeAnimation;
      80: aload_0
      81: getstatic     #64                 // Field net/minecraft/client/animation/definitions/SnifferAnimation.SNIFFER_HAPPY:Lnet/minecraft/client/animation/AnimationDefinition;
      84: aload_1
      85: invokevirtual #30                 // Method net/minecraft/client/animation/AnimationDefinition.bake:(Lnet/minecraft/client/model/geom/ModelPart;)Lnet/minecraft/client/animation/KeyframeAnimation;
      88: putfield      #67                 // Field happyAnimation:Lnet/minecraft/client/animation/KeyframeAnimation;
      91: aload_0
      92: getstatic     #70                 // Field net/minecraft/client/animation/definitions/SnifferAnimation.SNIFFER_SNIFFSNIFF:Lnet/minecraft/client/animation/AnimationDefinition;
      95: aload_1
      96: invokevirtual #30                 // Method net/minecraft/client/animation/AnimationDefinition.bake:(Lnet/minecraft/client/model/geom/ModelPart;)Lnet/minecraft/client/animation/KeyframeAnimation;
      99: putfield      #73                 // Field sniffSniffAnimation:Lnet/minecraft/client/animation/KeyframeAnimation;
     102: return

  public static net.minecraft.client.model.geom.builders.LayerDefinition createBodyLayer();
    Code:
       0: new           #76                 // class net/minecraft/client/model/geom/builders/MeshDefinition
       3: dup
       4: invokespecial #78                 // Method net/minecraft/client/model/geom/builders/MeshDefinition."<init>":()V
       7: astore_0
       8: aload_0
       9: invokevirtual #81                 // Method net/minecraft/client/model/geom/builders/MeshDefinition.getRoot:()Lnet/minecraft/client/model/geom/builders/PartDefinition;
      12: astore_1
      13: aload_1
      14: ldc           #7                  // String bone
      16: invokestatic  #85                 // Method net/minecraft/client/model/geom/builders/CubeListBuilder.create:()Lnet/minecraft/client/model/geom/builders/CubeListBuilder;
      19: fconst_0
      20: ldc           #91                 // float 5.0f
      22: fconst_0
      23: invokestatic  #92                 // Method net/minecraft/client/model/geom/PartPose.offset:(FFF)Lnet/minecraft/client/model/geom/PartPose;
      26: invokevirtual #98                 // Method net/minecraft/client/model/geom/builders/PartDefinition.addOrReplaceChild:(Ljava/lang/String;Lnet/minecraft/client/model/geom/builders/CubeListBuilder;Lnet/minecraft/client/model/geom/PartPose;)Lnet/minecraft/client/model/geom/builders/PartDefinition;
      29: astore_2
      30: aload_2
      31: ldc           #15                 // String body
      33: invokestatic  #85                 // Method net/minecraft/client/model/geom/builders/CubeListBuilder.create:()Lnet/minecraft/client/model/geom/builders/CubeListBuilder;
      36: bipush        62
      38: bipush        68
      40: invokevirtual #104                // Method net/minecraft/client/model/geom/builders/CubeListBuilder.texOffs:(II)Lnet/minecraft/client/model/geom/builders/CubeListBuilder;
      43: ldc           #108                // float -12.5f
      45: ldc           #109                // float -14.0f
      47: ldc           #110                // float -20.0f
      49: ldc           #111                // float 25.0f
      51: ldc           #112                // float 29.0f
      53: ldc           #113                // float 40.0f
      55: new           #114                // class net/minecraft/client/model/geom/builders/CubeDeformation
      58: dup
      59: fconst_0
      60: invokespecial #116                // Method net/minecraft/client/model/geom/builders/CubeDeformation."<init>":(F)V
      63: invokevirtual #119                // Method net/minecraft/client/model/geom/builders/CubeListBuilder.addBox:(FFFFFFLnet/minecraft/client/model/geom/builders/CubeDeformation;)Lnet/minecraft/client/model/geom/builders/CubeListBuilder;
      66: bipush        62
      68: iconst_0
      69: invokevirtual #104                // Method net/minecraft/client/model/geom/builders/CubeListBuilder.texOffs:(II)Lnet/minecraft/client/model/geom/builders/CubeListBuilder;
      72: ldc           #108                // float -12.5f
      74: ldc           #109                // float -14.0f
      76: ldc           #110                // float -20.0f
      78: ldc           #111                // float 25.0f
      80: ldc           #123                // float 24.0f
      82: ldc           #113                // float 40.0f
      84: new           #114                // class net/minecraft/client/model/geom/builders/CubeDeformation
      87: dup
      88: ldc           #124                // float 0.5f
      90: invokespecial #116                // Method net/minecraft/client/model/geom/builders/CubeDeformation."<init>":(F)V
      93: invokevirtual #119                // Method net/minecraft/client/model/geom/builders/CubeListBuilder.addBox:(FFFFFFLnet/minecraft/client/model/geom/builders/CubeDeformation;)Lnet/minecraft/client/model/geom/builders/CubeListBuilder;
      96: bipush        87
      98: bipush        68
     100: invokevirtual #104                // Method net/minecraft/client/model/geom/builders/CubeListBuilder.texOffs:(II)Lnet/minecraft/client/model/geom/builders/CubeListBuilder;
     103: ldc           #108                // float -12.5f
     105: ldc           #125                // float 12.0f
     107: ldc           #110                // float -20.0f
     109: ldc           #111                // float 25.0f
     111: fconst_0
     112: ldc           #113                // float 40.0f
     114: new           #114                // class net/minecraft/client/model/geom/builders/CubeDeformation
     117: dup
     118: fconst_0
     119: invokespecial #116                // Method net/minecraft/client/model/geom/builders/CubeDeformation."<init>":(F)V
     122: invokevirtual #119                // Method net/minecraft/client/model/geom/builders/CubeListBuilder.addBox:(FFFFFFLnet/minecraft/client/model/geom/builders/CubeDeformation;)Lnet/minecraft/client/model/geom/builders/CubeListBuilder;
     125: fconst_0
     126: fconst_0
     127: fconst_0
     128: invokestatic  #92                 // Method net/minecraft/client/model/geom/PartPose.offset:(FFF)Lnet/minecraft/client/model/geom/PartPose;
     131: invokevirtual #98                 // Method net/minecraft/client/model/geom/builders/PartDefinition.addOrReplaceChild:(Ljava/lang/String;Lnet/minecraft/client/model/geom/builders/CubeListBuilder;Lnet/minecraft/client/model/geom/PartPose;)Lnet/minecraft/client/model/geom/builders/PartDefinition;
     134: astore_3
     135: aload_2
     136: ldc           #126                // String right_front_leg
     138: invokestatic  #85                 // Method net/minecraft/client/model/geom/builders/CubeListBuilder.create:()Lnet/minecraft/client/model/geom/builders/CubeListBuilder;
     141: bipush        32
     143: bipush        87
     145: invokevirtual #104                // Method net/minecraft/client/model/geom/builders/CubeListBuilder.texOffs:(II)Lnet/minecraft/client/model/geom/builders/CubeListBuilder;
     148: ldc           #128                // float -3.5f
     150: ldc           #129                // float -1.0f
     152: ldc           #130                // float -4.0f
     154: ldc           #131                // float 7.0f
     156: ldc           #132                // float 10.0f
     158: ldc           #133                // float 8.0f
     160: new           #114                // class net/minecraft/client/model/geom/builders/CubeDeformation
     163: dup
     164: fconst_0
     165: invokespecial #116                // Method net/minecraft/client/model/geom/builders/CubeDeformation."<init>":(F)V
     168: invokevirtual #119                // Method net/minecraft/client/model/geom/builders/CubeListBuilder.addBox:(FFFFFFLnet/minecraft/client/model/geom/builders/CubeDeformation;)Lnet/minecraft/client/model/geom/builders/CubeListBuilder;
     171: ldc           #134                // float -7.5f
     173: ldc           #132                // float 10.0f
     175: ldc           #135                // float -15.0f
     177: invokestatic  #92                 // Method net/minecraft/client/model/geom/PartPose.offset:(FFF)Lnet/minecraft/client/model/geom/PartPose;
     180: invokevirtual #98                 // Method net/minecraft/client/model/geom/builders/PartDefinition.addOrReplaceChild:(Ljava/lang/String;Lnet/minecraft/client/model/geom/builders/CubeListBuilder;Lnet/minecraft/client/model/geom/PartPose;)Lnet/minecraft/client/model/geom/builders/PartDefinition;
     183: pop
     184: aload_2
     185: ldc           #136                // String right_mid_leg
     187: invokestatic  #85                 // Method net/minecraft/client/model/geom/builders/CubeListBuilder.create:()Lnet/minecraft/client/model/geom/builders/CubeListBuilder;
     190: bipush        32
     192: bipush        105
     194: invokevirtual #104                // Method net/minecraft/client/model/geom/builders/CubeListBuilder.texOffs:(II)Lnet/minecraft/client/model/geom/builders/CubeListBuilder;
     197: ldc           #128                // float -3.5f
     199: ldc           #129                // float -1.0f
     201: ldc           #130                // float -4.0f
     203: ldc           #131                // float 7.0f
     205: ldc           #132                // float 10.0f
     207: ldc           #133                // float 8.0f
     209: new           #114                // class net/minecraft/client/model/geom/builders/CubeDeformation
     212: dup
     213: fconst_0
     214: invokespecial #116                // Method net/minecraft/client/model/geom/builders/CubeDeformation."<init>":(F)V
     217: invokevirtual #119                // Method net/minecraft/client/model/geom/builders/CubeListBuilder.addBox:(FFFFFFLnet/minecraft/client/model/geom/builders/CubeDeformation;)Lnet/minecraft/client/model/geom/builders/CubeListBuilder;
     220: ldc           #134                // float -7.5f
     222: ldc           #132                // float 10.0f
     224: fconst_0
     225: invokestatic  #92                 // Method net/minecraft/client/model/geom/PartPose.offset:(FFF)Lnet/minecraft/client/model/geom/PartPose;
     228: invokevirtual #98                 // Method net/minecraft/client/model/geom/builders/PartDefinition.addOrReplaceChild:(Ljava/lang/String;Lnet/minecraft/client/model/geom/builders/CubeListBuilder;Lnet/minecraft/client/model/geom/PartPose;)Lnet/minecraft/client/model/geom/builders/PartDefinition;
     231: pop
     232: aload_2
     233: ldc           #138                // String right_hind_leg
     235: invokestatic  #85                 // Method net/minecraft/client/model/geom/builders/CubeListBuilder.create:()Lnet/minecraft/client/model/geom/builders/CubeListBuilder;
     238: bipush        32
     240: bipush        123
     242: invokevirtual #104                // Method net/minecraft/client/model/geom/builders/CubeListBuilder.texOffs:(II)Lnet/minecraft/client/model/geom/builders/CubeListBuilder;
     245: ldc           #128                // float -3.5f
     247: ldc           #129                // float -1.0f
     249: ldc           #130                // float -4.0f
     251: ldc           #131                // float 7.0f
     253: ldc           #132                // float 10.0f
     255: ldc           #133                // float 8.0f
     257: new           #114                // class net/minecraft/client/model/geom/builders/CubeDeformation
     260: dup
     261: fconst_0
     262: invokespecial #116                // Method net/minecraft/client/model/geom/builders/CubeDeformation."<init>":(F)V
     265: invokevirtual #119                // Method net/minecraft/client/model/geom/builders/CubeListBuilder.addBox:(FFFFFFLnet/minecraft/client/model/geom/builders/CubeDeformation;)Lnet/minecraft/client/model/geom/builders/CubeListBuilder;
     268: ldc           #134                // float -7.5f
     270: ldc           #132                // float 10.0f
     272: ldc           #140                // float 15.0f
     274: invokestatic  #92                 // Method net/minecraft/client/model/geom/PartPose.offset:(FFF)Lnet/minecraft/client/model/geom/PartPose;
     277: invokevirtual #98                 // Method net/minecraft/client/model/geom/builders/PartDefinition.addOrReplaceChild:(Ljava/lang/String;Lnet/minecraft/client/model/geom/builders/CubeListBuilder;Lnet/minecraft/client/model/geom/PartPose;)Lnet/minecraft/client/model/geom/builders/PartDefinition;
     280: pop
     281: aload_2
     282: ldc           #141                // String left_front_leg
     284: invokestatic  #85                 // Method net/minecraft/client/model/geom/builders/CubeListBuilder.create:()Lnet/minecraft/client/model/geom/builders/CubeListBuilder;
     287: iconst_0
     288: bipush        87
     290: invokevirtual #104                // Method net/minecraft/client/model/geom/builders/CubeListBuilder.texOffs:(II)Lnet/minecraft/client/model/geom/builders/CubeListBuilder;
     293: ldc           #128                // float -3.5f
     295: ldc           #129                // float -1.0f
     297: ldc           #130                // float -4.0f
     299: ldc           #131                // float 7.0f
     301: ldc           #132                // float 10.0f
     303: ldc           #133                // float 8.0f
     305: new           #114                // class net/minecraft/client/model/geom/builders/CubeDeformation
     308: dup
     309: fconst_0
     310: invokespecial #116                // Method net/minecraft/client/model/geom/builders/CubeDeformation."<init>":(F)V
     313: invokevirtual #119                // Method net/minecraft/client/model/geom/builders/CubeListBuilder.addBox:(FFFFFFLnet/minecraft/client/model/geom/builders/CubeDeformation;)Lnet/minecraft/client/model/geom/builders/CubeListBuilder;
     316: ldc           #143                // float 7.5f
     318: ldc           #132                // float 10.0f
     320: ldc           #135                // float -15.0f
     322: invokestatic  #92                 // Method net/minecraft/client/model/geom/PartPose.offset:(FFF)Lnet/minecraft/client/model/geom/PartPose;
     325: invokevirtual #98                 // Method net/minecraft/client/model/geom/builders/PartDefinition.addOrReplaceChild:(Ljava/lang/String;Lnet/minecraft/client/model/geom/builders/CubeListBuilder;Lnet/minecraft/client/model/geom/PartPose;)Lnet/minecraft/client/model/geom/builders/PartDefinition;
     328: pop
     329: aload_2
     330: ldc           #144                // String left_mid_leg
     332: invokestatic  #85                 // Method net/minecraft/client/model/geom/builders/CubeListBuilder.create:()Lnet/minecraft/client/model/geom/builders/CubeListBuilder;
     335: iconst_0
     336: bipush        105
     338: invokevirtual #104                // Method net/minecraft/client/model/geom/builders/CubeListBuilder.texOffs:(II)Lnet/minecraft/client/model/geom/builders/CubeListBuilder;
     341: ldc           #128                // float -3.5f
     343: ldc           #129                // float -1.0f
     345: ldc           #130                // float -4.0f
     347: ldc           #131                // float 7.0f
     349: ldc           #132                // float 10.0f
     351: ldc           #133                // float 8.0f
     353: new           #114                // class net/minecraft/client/model/geom/builders/CubeDeformation
     356: dup
     357: fconst_0
     358: invokespecial #116                // Method net/minecraft/client/model/geom/builders/CubeDeformation."<init>":(F)V
     361: invokevirtual #119                // Method net/minecraft/client/model/geom/builders/CubeListBuilder.addBox:(FFFFFFLnet/minecraft/client/model/geom/builders/CubeDeformation;)Lnet/minecraft/client/model/geom/builders/CubeListBuilder;
     364: ldc           #143                // float 7.5f
     366: ldc           #132                // float 10.0f
     368: fconst_0
     369: invokestatic  #92                 // Method net/minecraft/client/model/geom/PartPose.offset:(FFF)Lnet/minecraft/client/model/geom/PartPose;
     372: invokevirtual #98                 // Method net/minecraft/client/model/geom/builders/PartDefinition.addOrReplaceChild:(Ljava/lang/String;Lnet/minecraft/client/model/geom/builders/CubeListBuilder;Lnet/minecraft/client/model/geom/PartPose;)Lnet/minecraft/client/model/geom/builders/PartDefinition;
     375: pop
     376: aload_2
     377: ldc           #146                // String left_hind_leg
     379: invokestatic  #85                 // Method net/minecraft/client/model/geom/builders/CubeListBuilder.create:()Lnet/minecraft/client/model/geom/builders/CubeListBuilder;
     382: iconst_0
     383: bipush        123
     385: invokevirtual #104                // Method net/minecraft/client/model/geom/builders/CubeListBuilder.texOffs:(II)Lnet/minecraft/client/model/geom/builders/CubeListBuilder;
     388: ldc           #128                // float -3.5f
     390: ldc           #129                // float -1.0f
     392: ldc           #130                // float -4.0f
     394: ldc           #131                // float 7.0f
     396: ldc           #132                // float 10.0f
     398: ldc           #133                // float 8.0f
     400: new           #114                // class net/minecraft/client/model/geom/builders/CubeDeformation
     403: dup
     404: fconst_0
     405: invokespecial #116                // Method net/minecraft/client/model/geom/builders/CubeDeformation."<init>":(F)V
     408: invokevirtual #119                // Method net/minecraft/client/model/geom/builders/CubeListBuilder.addBox:(FFFFFFLnet/minecraft/client/model/geom/builders/CubeDeformation;)Lnet/minecraft/client/model/geom/builders/CubeListBuilder;
     411: ldc           #143                // float 7.5f
     413: ldc           #132                // float 10.0f
     415: ldc           #140                // float 15.0f
     417: invokestatic  #92                 // Method net/minecraft/client/model/geom/PartPose.offset:(FFF)Lnet/minecraft/client/model/geom/PartPose;
     420: invokevirtual #98                 // Method net/minecraft/client/model/geom/builders/PartDefinition.addOrReplaceChild:(Ljava/lang/String;Lnet/minecraft/client/model/geom/builders/CubeListBuilder;Lnet/minecraft/client/model/geom/PartPose;)Lnet/minecraft/client/model/geom/builders/PartDefinition;
     423: pop
     424: aload_3
     425: ldc           #17                 // String head
     427: invokestatic  #85                 // Method net/minecraft/client/model/geom/builders/CubeListBuilder.create:()Lnet/minecraft/client/model/geom/builders/CubeListBuilder;
     430: bipush        8
     432: bipush        15
     434: invokevirtual #104                // Method net/minecraft/client/model/geom/builders/CubeListBuilder.texOffs:(II)Lnet/minecraft/client/model/geom/builders/CubeListBuilder;
     437: ldc           #148                // float -6.5f
     439: ldc           #134                // float -7.5f
     441: ldc           #149                // float -11.5f
     443: ldc           #150                // float 13.0f
     445: ldc           #151                // float 18.0f
     447: ldc           #152                // float 11.0f
     449: new           #114                // class net/minecraft/client/model/geom/builders/CubeDeformation
     452: dup
     453: fconst_0
     454: invokespecial #116                // Method net/minecraft/client/model/geom/builders/CubeDeformation."<init>":(F)V
     457: invokevirtual #119                // Method net/minecraft/client/model/geom/builders/CubeListBuilder.addBox:(FFFFFFLnet/minecraft/client/model/geom/builders/CubeDeformation;)Lnet/minecraft/client/model/geom/builders/CubeListBuilder;
     460: bipush        8
     462: iconst_4
     463: invokevirtual #104                // Method net/minecraft/client/model/geom/builders/CubeListBuilder.texOffs:(II)Lnet/minecraft/client/model/geom/builders/CubeListBuilder;
     466: ldc           #148                // float -6.5f
     468: ldc           #143                // float 7.5f
     470: ldc           #149                // float -11.5f
     472: ldc           #150                // float 13.0f
     474: fconst_0
     475: ldc           #152                // float 11.0f
     477: new           #114                // class net/minecraft/client/model/geom/builders/CubeDeformation
     480: dup
     481: fconst_0
     482: invokespecial #116                // Method net/minecraft/client/model/geom/builders/CubeDeformation."<init>":(F)V
     485: invokevirtual #119                // Method net/minecraft/client/model/geom/builders/CubeListBuilder.addBox:(FFFFFFLnet/minecraft/client/model/geom/builders/CubeDeformation;)Lnet/minecraft/client/model/geom/builders/CubeListBuilder;
     488: fconst_0
     489: ldc           #153                // float 6.5f
     491: ldc           #154                // float -19.48f
     493: invokestatic  #92                 // Method net/minecraft/client/model/geom/PartPose.offset:(FFF)Lnet/minecraft/client/model/geom/PartPose;
     496: invokevirtual #98                 // Method net/minecraft/client/model/geom/builders/PartDefinition.addOrReplaceChild:(Ljava/lang/String;Lnet/minecraft/client/model/geom/builders/CubeListBuilder;Lnet/minecraft/client/model/geom/PartPose;)Lnet/minecraft/client/model/geom/builders/PartDefinition;
     499: astore        4
     501: aload         4
     503: ldc           #155                // String left_ear
     505: invokestatic  #85                 // Method net/minecraft/client/model/geom/builders/CubeListBuilder.create:()Lnet/minecraft/client/model/geom/builders/CubeListBuilder;
     508: iconst_2
     509: iconst_0
     510: invokevirtual #104                // Method net/minecraft/client/model/geom/builders/CubeListBuilder.texOffs:(II)Lnet/minecraft/client/model/geom/builders/CubeListBuilder;
     513: fconst_0
     514: fconst_0
     515: ldc           #157                // float -3.0f
     517: fconst_1
     518: ldc           #158                // float 19.0f
     520: ldc           #131                // float 7.0f
     522: new           #114                // class net/minecraft/client/model/geom/builders/CubeDeformation
     525: dup
     526: fconst_0
     527: invokespecial #116                // Method net/minecraft/client/model/geom/builders/CubeDeformation."<init>":(F)V
     530: invokevirtual #119                // Method net/minecraft/client/model/geom/builders/CubeListBuilder.addBox:(FFFFFFLnet/minecraft/client/model/geom/builders/CubeDeformation;)Lnet/minecraft/client/model/geom/builders/CubeListBuilder;
     533: ldc           #159                // float 6.51f
     535: ldc           #134                // float -7.5f
     537: ldc           #160                // float -4.51f
     539: invokestatic  #92                 // Method net/minecraft/client/model/geom/PartPose.offset:(FFF)Lnet/minecraft/client/model/geom/PartPose;
     542: invokevirtual #98                 // Method net/minecraft/client/model/geom/builders/PartDefinition.addOrReplaceChild:(Ljava/lang/String;Lnet/minecraft/client/model/geom/builders/CubeListBuilder;Lnet/minecraft/client/model/geom/PartPose;)Lnet/minecraft/client/model/geom/builders/PartDefinition;
     545: pop
     546: aload         4
     548: ldc           #161                // String right_ear
     550: invokestatic  #85                 // Method net/minecraft/client/model/geom/builders/CubeListBuilder.create:()Lnet/minecraft/client/model/geom/builders/CubeListBuilder;
     553: bipush        48
     555: iconst_0
     556: invokevirtual #104                // Method net/minecraft/client/model/geom/builders/CubeListBuilder.texOffs:(II)Lnet/minecraft/client/model/geom/builders/CubeListBuilder;
     559: ldc           #129                // float -1.0f
     561: fconst_0
     562: ldc           #157                // float -3.0f
     564: fconst_1
     565: ldc           #158                // float 19.0f
     567: ldc           #131                // float 7.0f
     569: new           #114                // class net/minecraft/client/model/geom/builders/CubeDeformation
     572: dup
     573: fconst_0
     574: invokespecial #116                // Method net/minecraft/client/model/geom/builders/CubeDeformation."<init>":(F)V
     577: invokevirtual #119                // Method net/minecraft/client/model/geom/builders/CubeListBuilder.addBox:(FFFFFFLnet/minecraft/client/model/geom/builders/CubeDeformation;)Lnet/minecraft/client/model/geom/builders/CubeListBuilder;
     580: ldc           #163                // float -6.51f
     582: ldc           #134                // float -7.5f
     584: ldc           #160                // float -4.51f
     586: invokestatic  #92                 // Method net/minecraft/client/model/geom/PartPose.offset:(FFF)Lnet/minecraft/client/model/geom/PartPose;
     589: invokevirtual #98                 // Method net/minecraft/client/model/geom/builders/PartDefinition.addOrReplaceChild:(Ljava/lang/String;Lnet/minecraft/client/model/geom/builders/CubeListBuilder;Lnet/minecraft/client/model/geom/PartPose;)Lnet/minecraft/client/model/geom/builders/PartDefinition;
     592: pop
     593: aload         4
     595: ldc           #164                // String nose
     597: invokestatic  #85                 // Method net/minecraft/client/model/geom/builders/CubeListBuilder.create:()Lnet/minecraft/client/model/geom/builders/CubeListBuilder;
     600: bipush        10
     602: bipush        45
     604: invokevirtual #104                // Method net/minecraft/client/model/geom/builders/CubeListBuilder.texOffs:(II)Lnet/minecraft/client/model/geom/builders/CubeListBuilder;
     607: ldc           #148                // float -6.5f
     609: ldc           #166                // float -2.0f
     611: ldc           #167                // float -9.0f
     613: ldc           #150                // float 13.0f
     615: fconst_2
     616: ldc           #168                // float 9.0f
     618: new           #114                // class net/minecraft/client/model/geom/builders/CubeDeformation
     621: dup
     622: fconst_0
     623: invokespecial #116                // Method net/minecraft/client/model/geom/builders/CubeDeformation."<init>":(F)V
     626: invokevirtual #119                // Method net/minecraft/client/model/geom/builders/CubeListBuilder.addBox:(FFFFFFLnet/minecraft/client/model/geom/builders/CubeDeformation;)Lnet/minecraft/client/model/geom/builders/CubeListBuilder;
     629: fconst_0
     630: ldc           #169                // float -4.5f
     632: ldc           #149                // float -11.5f
     634: invokestatic  #92                 // Method net/minecraft/client/model/geom/PartPose.offset:(FFF)Lnet/minecraft/client/model/geom/PartPose;
     637: invokevirtual #98                 // Method net/minecraft/client/model/geom/builders/PartDefinition.addOrReplaceChild:(Ljava/lang/String;Lnet/minecraft/client/model/geom/builders/CubeListBuilder;Lnet/minecraft/client/model/geom/PartPose;)Lnet/minecraft/client/model/geom/builders/PartDefinition;
     640: pop
     641: aload         4
     643: ldc           #170                // String lower_beak
     645: invokestatic  #85                 // Method net/minecraft/client/model/geom/builders/CubeListBuilder.create:()Lnet/minecraft/client/model/geom/builders/CubeListBuilder;
     648: bipush        10
     650: bipush        57
     652: invokevirtual #104                // Method net/minecraft/client/model/geom/builders/CubeListBuilder.texOffs:(II)Lnet/minecraft/client/model/geom/builders/CubeListBuilder;
     655: ldc           #148                // float -6.5f
     657: ldc           #172                // float -7.0f
     659: ldc           #173                // float -8.0f
     661: ldc           #150                // float 13.0f
     663: ldc           #125                // float 12.0f
     665: ldc           #168                // float 9.0f
     667: new           #114                // class net/minecraft/client/model/geom/builders/CubeDeformation
     670: dup
     671: fconst_0
     672: invokespecial #116                // Method net/minecraft/client/model/geom/builders/CubeDeformation."<init>":(F)V
     675: invokevirtual #119                // Method net/minecraft/client/model/geom/builders/CubeListBuilder.addBox:(FFFFFFLnet/minecraft/client/model/geom/builders/CubeDeformation;)Lnet/minecraft/client/model/geom/builders/CubeListBuilder;
     678: fconst_0
     679: ldc           #174                // float 2.5f
     681: ldc           #108                // float -12.5f
     683: invokestatic  #92                 // Method net/minecraft/client/model/geom/PartPose.offset:(FFF)Lnet/minecraft/client/model/geom/PartPose;
     686: invokevirtual #98                 // Method net/minecraft/client/model/geom/builders/PartDefinition.addOrReplaceChild:(Ljava/lang/String;Lnet/minecraft/client/model/geom/builders/CubeListBuilder;Lnet/minecraft/client/model/geom/PartPose;)Lnet/minecraft/client/model/geom/builders/PartDefinition;
     689: pop
     690: aload_0
     691: sipush        192
     694: sipush        192
     697: invokestatic  #175                // Method net/minecraft/client/model/geom/builders/LayerDefinition.create:(Lnet/minecraft/client/model/geom/builders/MeshDefinition;II)Lnet/minecraft/client/model/geom/builders/LayerDefinition;
     700: areturn

  public void setupAnim(net.minecraft.client.renderer.entity.state.SnifferRenderState);
    Code:
       0: aload_0
       1: aload_1
       2: invokespecial #180                // Method net/minecraft/client/model/EntityModel.setupAnim:(Ljava/lang/Object;)V
       5: aload_0
       6: getfield      #19                 // Field head:Lnet/minecraft/client/model/geom/ModelPart;
       9: aload_1
      10: getfield      #184                // Field net/minecraft/client/renderer/entity/state/SnifferRenderState.xRot:F
      13: ldc           #192                // float 0.017453292f
      15: fmul
      16: putfield      #193                // Field net/minecraft/client/model/geom/ModelPart.xRot:F
      19: aload_0
      20: getfield      #19                 // Field head:Lnet/minecraft/client/model/geom/ModelPart;
      23: aload_1
      24: getfield      #194                // Field net/minecraft/client/renderer/entity/state/SnifferRenderState.yRot:F
      27: ldc           #192                // float 0.017453292f
      29: fmul
      30: putfield      #197                // Field net/minecraft/client/model/geom/ModelPart.yRot:F
      33: aload_1
      34: getfield      #198                // Field net/minecraft/client/renderer/entity/state/SnifferRenderState.isSearching:Z
      37: ifeq          62
      40: aload_0
      41: getfield      #36                 // Field sniffSearchAnimation:Lnet/minecraft/client/animation/KeyframeAnimation;
      44: aload_1
      45: getfield      #202                // Field net/minecraft/client/renderer/entity/state/SnifferRenderState.walkAnimationPos:F
      48: aload_1
      49: getfield      #205                // Field net/minecraft/client/renderer/entity/state/SnifferRenderState.walkAnimationSpeed:F
      52: ldc           #168                // float 9.0f
      54: ldc           #208                // float 100.0f
      56: invokevirtual #209                // Method net/minecraft/client/animation/KeyframeAnimation.applyWalk:(FFFF)V
      59: goto          81
      62: aload_0
      63: getfield      #43                 // Field walkAnimation:Lnet/minecraft/client/animation/KeyframeAnimation;
      66: aload_1
      67: getfield      #202                // Field net/minecraft/client/renderer/entity/state/SnifferRenderState.walkAnimationPos:F
      70: aload_1
      71: getfield      #205                // Field net/minecraft/client/renderer/entity/state/SnifferRenderState.walkAnimationSpeed:F
      74: ldc           #168                // float 9.0f
      76: ldc           #208                // float 100.0f
      78: invokevirtual #209                // Method net/minecraft/client/animation/KeyframeAnimation.applyWalk:(FFFF)V
      81: aload_0
      82: getfield      #49                 // Field digAnimation:Lnet/minecraft/client/animation/KeyframeAnimation;
      85: aload_1
      86: getfield      #215                // Field net/minecraft/client/renderer/entity/state/SnifferRenderState.diggingAnimationState:Lnet/minecraft/world/entity/AnimationState;
      89: aload_1
      90: getfield      #219                // Field net/minecraft/client/renderer/entity/state/SnifferRenderState.ageInTicks:F
      93: invokevirtual #222                // Method net/minecraft/client/animation/KeyframeAnimation.apply:(Lnet/minecraft/world/entity/AnimationState;F)V
      96: aload_0
      97: getfield      #55                 // Field longSniffAnimation:Lnet/minecraft/client/animation/KeyframeAnimation;
     100: aload_1
     101: getfield      #226                // Field net/minecraft/client/renderer/entity/state/SnifferRenderState.sniffingAnimationState:Lnet/minecraft/world/entity/AnimationState;
     104: aload_1
     105: getfield      #219                // Field net/minecraft/client/renderer/entity/state/SnifferRenderState.ageInTicks:F
     108: invokevirtual #222                // Method net/minecraft/client/animation/KeyframeAnimation.apply:(Lnet/minecraft/world/entity/AnimationState;F)V
     111: aload_0
     112: getfield      #61                 // Field standUpAnimation:Lnet/minecraft/client/animation/KeyframeAnimation;
     115: aload_1
     116: getfield      #229                // Field net/minecraft/client/renderer/entity/state/SnifferRenderState.risingAnimationState:Lnet/minecraft/world/entity/AnimationState;
     119: aload_1
     120: getfield      #219                // Field net/minecraft/client/renderer/entity/state/SnifferRenderState.ageInTicks:F
     123: invokevirtual #222                // Method net/minecraft/client/animation/KeyframeAnimation.apply:(Lnet/minecraft/world/entity/AnimationState;F)V
     126: aload_0
     127: getfield      #67                 // Field happyAnimation:Lnet/minecraft/client/animation/KeyframeAnimation;
     130: aload_1
     131: getfield      #232                // Field net/minecraft/client/renderer/entity/state/SnifferRenderState.feelingHappyAnimationState:Lnet/minecraft/world/entity/AnimationState;
     134: aload_1
     135: getfield      #219                // Field net/minecraft/client/renderer/entity/state/SnifferRenderState.ageInTicks:F
     138: invokevirtual #222                // Method net/minecraft/client/animation/KeyframeAnimation.apply:(Lnet/minecraft/world/entity/AnimationState;F)V
     141: aload_0
     142: getfield      #73                 // Field sniffSniffAnimation:Lnet/minecraft/client/animation/KeyframeAnimation;
     145: aload_1
     146: getfield      #235                // Field net/minecraft/client/renderer/entity/state/SnifferRenderState.scentingAnimationState:Lnet/minecraft/world/entity/AnimationState;
     149: aload_1
     150: getfield      #219                // Field net/minecraft/client/renderer/entity/state/SnifferRenderState.ageInTicks:F
     153: invokevirtual #222                // Method net/minecraft/client/animation/KeyframeAnimation.apply:(Lnet/minecraft/world/entity/AnimationState;F)V
     156: return

  public void setupAnim(java.lang.Object);
    Code:
       0: aload_0
       1: aload_1
       2: checkcast     #185                // class net/minecraft/client/renderer/entity/state/SnifferRenderState
       5: invokevirtual #238                // Method setupAnim:(Lnet/minecraft/client/renderer/entity/state/SnifferRenderState;)V
       8: return
}
