Compiled from "SourceFile"
public class ggd {
  public static final gfz a;

  public static final gfz b;

  public static final gfz c;

  public static final gfz d;

  public ggd();
    Code:
       0: aload_0
       1: invokespecial #28                 // Method java/lang/Object."<init>":()V
       4: return

  static {};
    Code:
       0: ldc           #32                 // float 0.5f
       2: invokestatic  #35                 // Method gfz$a.a:(F)Lgfz$a;
       5: ldc           #37                 // String body
       7: new           #14                 // class gfy
      10: dup
      11: getstatic     #40                 // Field gfy$d.b:Lgfy$c;
      14: iconst_2
      15: anewarray     #42                 // class gga
      18: dup
      19: iconst_0
      20: new           #42                 // class gga
      23: dup
      24: fconst_0
      25: fconst_0
      26: fconst_0
      27: fconst_0
      28: invokestatic  #47                 // Method ggc.b:(FFF)Lorg/joml/Vector3f;
      31: getstatic     #50                 // Field gfy$b.a:Lgfy$a;
      34: invokespecial #53                 // Method gga."<init>":(FLorg/joml/Vector3fc;Lgfy$a;)V
      37: aastore
      38: dup
      39: iconst_1
      40: new           #42                 // class gga
      43: dup
      44: ldc           #54                 // float 0.1667f
      46: fconst_0
      47: fconst_0
      48: fconst_0
      49: invokestatic  #47                 // Method ggc.b:(FFF)Lorg/joml/Vector3f;
      52: getstatic     #50                 // Field gfy$b.a:Lgfy$a;
      55: invokespecial #53                 // Method gga."<init>":(FLorg/joml/Vector3fc;Lgfy$a;)V
      58: aastore
      59: invokespecial #57                 // Method gfy."<init>":(Lgfy$c;[Lgga;)V
      62: invokevirtual #60                 // Method gfz$a.a:(Ljava/lang/String;Lgfy;)Lgfz$a;
      65: ldc           #37                 // String body
      67: new           #14                 // class gfy
      70: dup
      71: getstatic     #62                 // Field gfy$d.a:Lgfy$c;
      74: iconst_5
      75: anewarray     #42                 // class gga
      78: dup
      79: iconst_0
      80: new           #42                 // class gga
      83: dup
      84: fconst_0
      85: fconst_0
      86: fconst_0
      87: fconst_0
      88: invokestatic  #64                 // Method ggc.a:(FFF)Lorg/joml/Vector3f;
      91: getstatic     #50                 // Field gfy$b.a:Lgfy$a;
      94: invokespecial #53                 // Method gga."<init>":(FLorg/joml/Vector3fc;Lgfy$a;)V
      97: aastore
      98: dup
      99: iconst_1
     100: new           #42                 // class gga
     103: dup
     104: ldc           #54                 // float 0.1667f
     106: fconst_0
     107: ldc           #65                 // float 5.0f
     109: fconst_0
     110: invokestatic  #64                 // Method ggc.a:(FFF)Lorg/joml/Vector3f;
     113: getstatic     #50                 // Field gfy$b.a:Lgfy$a;
     116: invokespecial #53                 // Method gga."<init>":(FLorg/joml/Vector3fc;Lgfy$a;)V
     119: aastore
     120: dup
     121: iconst_2
     122: new           #42                 // class gga
     125: dup
     126: ldc           #66                 // float 0.2083f
     128: fconst_0
     129: ldc           #67                 // float 6.0f
     131: ldc           #68                 // float -1.0f
     133: invokestatic  #64                 // Method ggc.a:(FFF)Lorg/joml/Vector3f;
     136: getstatic     #50                 // Field gfy$b.a:Lgfy$a;
     139: invokespecial #53                 // Method gga."<init>":(FLorg/joml/Vector3fc;Lgfy$a;)V
     142: aastore
     143: dup
     144: iconst_3
     145: new           #42                 // class gga
     148: dup
     149: ldc           #69                 // float 0.25f
     151: fconst_0
     152: ldc           #67                 // float 6.0f
     154: ldc           #68                 // float -1.0f
     156: invokestatic  #64                 // Method ggc.a:(FFF)Lorg/joml/Vector3f;
     159: getstatic     #50                 // Field gfy$b.a:Lgfy$a;
     162: invokespecial #53                 // Method gga."<init>":(FLorg/joml/Vector3fc;Lgfy$a;)V
     165: aastore
     166: dup
     167: iconst_4
     168: new           #42                 // class gga
     171: dup
     172: ldc           #70                 // float 0.375f
     174: fconst_0
     175: ldc           #68                 // float -1.0f
     177: ldc           #68                 // float -1.0f
     179: invokestatic  #64                 // Method ggc.a:(FFF)Lorg/joml/Vector3f;
     182: getstatic     #50                 // Field gfy$b.a:Lgfy$a;
     185: invokespecial #53                 // Method gga."<init>":(FLorg/joml/Vector3fc;Lgfy$a;)V
     188: aastore
     189: invokespecial #57                 // Method gfy."<init>":(Lgfy$c;[Lgga;)V
     192: invokevirtual #60                 // Method gfz$a.a:(Ljava/lang/String;Lgfy;)Lgfz$a;
     195: ldc           #72                 // String tail
     197: new           #14                 // class gfy
     200: dup
     201: getstatic     #40                 // Field gfy$d.b:Lgfy$c;
     204: iconst_2
     205: anewarray     #42                 // class gga
     208: dup
     209: iconst_0
     210: new           #42                 // class gga
     213: dup
     214: fconst_0
     215: fconst_0
     216: fconst_0
     217: fconst_0
     218: invokestatic  #47                 // Method ggc.b:(FFF)Lorg/joml/Vector3f;
     221: getstatic     #50                 // Field gfy$b.a:Lgfy$a;
     224: invokespecial #53                 // Method gga."<init>":(FLorg/joml/Vector3fc;Lgfy$a;)V
     227: aastore
     228: dup
     229: iconst_1
     230: new           #42                 // class gga
     233: dup
     234: ldc           #54                 // float 0.1667f
     236: fconst_0
     237: fconst_0
     238: fconst_0
     239: invokestatic  #47                 // Method ggc.b:(FFF)Lorg/joml/Vector3f;
     242: getstatic     #50                 // Field gfy$b.a:Lgfy$a;
     245: invokespecial #53                 // Method gga."<init>":(FLorg/joml/Vector3fc;Lgfy$a;)V
     248: aastore
     249: invokespecial #57                 // Method gfy."<init>":(Lgfy$c;[Lgga;)V
     252: invokevirtual #60                 // Method gfz$a.a:(Ljava/lang/String;Lgfy;)Lgfz$a;
     255: ldc           #72                 // String tail
     257: new           #14                 // class gfy
     260: dup
     261: getstatic     #62                 // Field gfy$d.a:Lgfy$c;
     264: iconst_4
     265: anewarray     #42                 // class gga
     268: dup
     269: iconst_0
     270: new           #42                 // class gga
     273: dup
     274: fconst_0
     275: fconst_0
     276: fconst_0
     277: fconst_0
     278: invokestatic  #64                 // Method ggc.a:(FFF)Lorg/joml/Vector3f;
     281: getstatic     #50                 // Field gfy$b.a:Lgfy$a;
     284: invokespecial #53                 // Method gga."<init>":(FLorg/joml/Vector3fc;Lgfy$a;)V
     287: aastore
     288: dup
     289: iconst_1
     290: new           #42                 // class gga
     293: dup
     294: ldc           #54                 // float 0.1667f
     296: fconst_0
     297: fconst_0
     298: fconst_0
     299: invokestatic  #64                 // Method ggc.a:(FFF)Lorg/joml/Vector3f;
     302: getstatic     #50                 // Field gfy$b.a:Lgfy$a;
     305: invokespecial #53                 // Method gga."<init>":(FLorg/joml/Vector3fc;Lgfy$a;)V
     308: aastore
     309: dup
     310: iconst_2
     311: new           #42                 // class gga
     314: dup
     315: ldc           #66                 // float 0.2083f
     317: fconst_0
     318: fconst_0
     319: ldc           #73                 // float -2.0f
     321: invokestatic  #64                 // Method ggc.a:(FFF)Lorg/joml/Vector3f;
     324: getstatic     #50                 // Field gfy$b.a:Lgfy$a;
     327: invokespecial #53                 // Method gga."<init>":(FLorg/joml/Vector3fc;Lgfy$a;)V
     330: aastore
     331: dup
     332: iconst_3
     333: new           #42                 // class gga
     336: dup
     337: ldc           #69                 // float 0.25f
     339: fconst_0
     340: fconst_0
     341: ldc           #73                 // float -2.0f
     343: invokestatic  #64                 // Method ggc.a:(FFF)Lorg/joml/Vector3f;
     346: getstatic     #50                 // Field gfy$b.a:Lgfy$a;
     349: invokespecial #53                 // Method gga."<init>":(FLorg/joml/Vector3fc;Lgfy$a;)V
     352: aastore
     353: invokespecial #57                 // Method gfy."<init>":(Lgfy$c;[Lgga;)V
     356: invokevirtual #60                 // Method gfz$a.a:(Ljava/lang/String;Lgfy;)Lgfz$a;
     359: ldc           #75                 // String head
     361: new           #14                 // class gfy
     364: dup
     365: getstatic     #40                 // Field gfy$d.b:Lgfy$c;
     368: iconst_3
     369: anewarray     #42                 // class gga
     372: dup
     373: iconst_0
     374: new           #42                 // class gga
     377: dup
     378: fconst_0
     379: fconst_0
     380: fconst_0
     381: fconst_0
     382: invokestatic  #47                 // Method ggc.b:(FFF)Lorg/joml/Vector3f;
     385: getstatic     #50                 // Field gfy$b.a:Lgfy$a;
     388: invokespecial #53                 // Method gga."<init>":(FLorg/joml/Vector3fc;Lgfy$a;)V
     391: aastore
     392: dup
     393: iconst_1
     394: new           #42                 // class gga
     397: dup
     398: ldc           #54                 // float 0.1667f
     400: ldc           #76                 // float 17.5f
     402: fconst_0
     403: fconst_0
     404: invokestatic  #47                 // Method ggc.b:(FFF)Lorg/joml/Vector3f;
     407: getstatic     #50                 // Field gfy$b.a:Lgfy$a;
     410: invokespecial #53                 // Method gga."<init>":(FLorg/joml/Vector3fc;Lgfy$a;)V
     413: aastore
     414: dup
     415: iconst_2
     416: new           #42                 // class gga
     419: dup
     420: ldc           #69                 // float 0.25f
     422: ldc           #77                 // float -72.5f
     424: fconst_0
     425: fconst_0
     426: invokestatic  #47                 // Method ggc.b:(FFF)Lorg/joml/Vector3f;
     429: getstatic     #50                 // Field gfy$b.a:Lgfy$a;
     432: invokespecial #53                 // Method gga."<init>":(FLorg/joml/Vector3fc;Lgfy$a;)V
     435: aastore
     436: invokespecial #57                 // Method gfy."<init>":(Lgfy$c;[Lgga;)V
     439: invokevirtual #60                 // Method gfz$a.a:(Ljava/lang/String;Lgfy;)Lgfz$a;
     442: ldc           #75                 // String head
     444: new           #14                 // class gfy
     447: dup
     448: getstatic     #62                 // Field gfy$d.a:Lgfy$c;
     451: bipush        6
     453: anewarray     #42                 // class gga
     456: dup
     457: iconst_0
     458: new           #42                 // class gga
     461: dup
     462: fconst_0
     463: fconst_0
     464: fconst_0
     465: fconst_0
     466: invokestatic  #64                 // Method ggc.a:(FFF)Lorg/joml/Vector3f;
     469: getstatic     #50                 // Field gfy$b.a:Lgfy$a;
     472: invokespecial #53                 // Method gga."<init>":(FLorg/joml/Vector3fc;Lgfy$a;)V
     475: aastore
     476: dup
     477: iconst_1
     478: new           #42                 // class gga
     481: dup
     482: ldc           #54                 // float 0.1667f
     484: fconst_0
     485: ldc           #68                 // float -1.0f
     487: fconst_0
     488: invokestatic  #64                 // Method ggc.a:(FFF)Lorg/joml/Vector3f;
     491: getstatic     #50                 // Field gfy$b.a:Lgfy$a;
     494: invokespecial #53                 // Method gga."<init>":(FLorg/joml/Vector3fc;Lgfy$a;)V
     497: aastore
     498: dup
     499: iconst_2
     500: new           #42                 // class gga
     503: dup
     504: ldc           #66                 // float 0.2083f
     506: fconst_0
     507: fconst_2
     508: fconst_1
     509: invokestatic  #64                 // Method ggc.a:(FFF)Lorg/joml/Vector3f;
     512: getstatic     #50                 // Field gfy$b.a:Lgfy$a;
     515: invokespecial #53                 // Method gga."<init>":(FLorg/joml/Vector3fc;Lgfy$a;)V
     518: aastore
     519: dup
     520: iconst_3
     521: new           #42                 // class gga
     524: dup
     525: ldc           #69                 // float 0.25f
     527: fconst_0
     528: fconst_2
     529: fconst_1
     530: invokestatic  #64                 // Method ggc.a:(FFF)Lorg/joml/Vector3f;
     533: getstatic     #50                 // Field gfy$b.a:Lgfy$a;
     536: invokespecial #53                 // Method gga."<init>":(FLorg/joml/Vector3fc;Lgfy$a;)V
     539: aastore
     540: dup
     541: iconst_4
     542: new           #42                 // class gga
     545: dup
     546: ldc           #78                 // float 0.2917f
     548: fconst_0
     549: fconst_2
     550: ldc           #67                 // float 6.0f
     552: invokestatic  #64                 // Method ggc.a:(FFF)Lorg/joml/Vector3f;
     555: getstatic     #50                 // Field gfy$b.a:Lgfy$a;
     558: invokespecial #53                 // Method gga."<init>":(FLorg/joml/Vector3fc;Lgfy$a;)V
     561: aastore
     562: dup
     563: iconst_5
     564: new           #42                 // class gga
     567: dup
     568: ldc           #70                 // float 0.375f
     570: fconst_0
     571: fconst_2
     572: ldc           #79                 // float 7.0f
     574: invokestatic  #64                 // Method ggc.a:(FFF)Lorg/joml/Vector3f;
     577: getstatic     #50                 // Field gfy$b.a:Lgfy$a;
     580: invokespecial #53                 // Method gga."<init>":(FLorg/joml/Vector3fc;Lgfy$a;)V
     583: aastore
     584: invokespecial #57                 // Method gfy."<init>":(Lgfy$c;[Lgga;)V
     587: invokevirtual #60                 // Method gfz$a.a:(Ljava/lang/String;Lgfy;)Lgfz$a;
     590: ldc           #81                 // String right_hind_leg
     592: new           #14                 // class gfy
     595: dup
     596: getstatic     #40                 // Field gfy$d.b:Lgfy$c;
     599: iconst_2
     600: anewarray     #42                 // class gga
     603: dup
     604: iconst_0
     605: new           #42                 // class gga
     608: dup
     609: fconst_0
     610: fconst_0
     611: fconst_0
     612: fconst_0
     613: invokestatic  #47                 // Method ggc.b:(FFF)Lorg/joml/Vector3f;
     616: getstatic     #50                 // Field gfy$b.a:Lgfy$a;
     619: invokespecial #53                 // Method gga."<init>":(FLorg/joml/Vector3fc;Lgfy$a;)V
     622: aastore
     623: dup
     624: iconst_1
     625: new           #42                 // class gga
     628: dup
     629: ldc           #54                 // float 0.1667f
     631: ldc           #82                 // float -35.0f
     633: fconst_0
     634: fconst_0
     635: invokestatic  #47                 // Method ggc.b:(FFF)Lorg/joml/Vector3f;
     638: getstatic     #50                 // Field gfy$b.a:Lgfy$a;
     641: invokespecial #53                 // Method gga."<init>":(FLorg/joml/Vector3fc;Lgfy$a;)V
     644: aastore
     645: invokespecial #57                 // Method gfy."<init>":(Lgfy$c;[Lgga;)V
     648: invokevirtual #60                 // Method gfz$a.a:(Ljava/lang/String;Lgfy;)Lgfz$a;
     651: ldc           #81                 // String right_hind_leg
     653: new           #14                 // class gfy
     656: dup
     657: getstatic     #62                 // Field gfy$d.a:Lgfy$c;
     660: bipush        6
     662: anewarray     #42                 // class gga
     665: dup
     666: iconst_0
     667: new           #42                 // class gga
     670: dup
     671: fconst_0
     672: fconst_0
     673: fconst_0
     674: fconst_0
     675: invokestatic  #64                 // Method ggc.a:(FFF)Lorg/joml/Vector3f;
     678: getstatic     #50                 // Field gfy$b.a:Lgfy$a;
     681: invokespecial #53                 // Method gga."<init>":(FLorg/joml/Vector3fc;Lgfy$a;)V
     684: aastore
     685: dup
     686: iconst_1
     687: new           #42                 // class gga
     690: dup
     691: ldc           #54                 // float 0.1667f
     693: fconst_0
     694: ldc           #65                 // float 5.0f
     696: ldc           #73                 // float -2.0f
     698: invokestatic  #64                 // Method ggc.a:(FFF)Lorg/joml/Vector3f;
     701: getstatic     #50                 // Field gfy$b.a:Lgfy$a;
     704: invokespecial #53                 // Method gga."<init>":(FLorg/joml/Vector3fc;Lgfy$a;)V
     707: aastore
     708: dup
     709: iconst_2
     710: new           #42                 // class gga
     713: dup
     714: ldc           #83                 // float 0.1875f
     716: fconst_0
     717: ldc           #84                 // float 8.0f
     719: ldc           #85                 // float -3.0f
     721: invokestatic  #64                 // Method ggc.a:(FFF)Lorg/joml/Vector3f;
     724: getstatic     #50                 // Field gfy$b.a:Lgfy$a;
     727: invokespecial #53                 // Method gga."<init>":(FLorg/joml/Vector3fc;Lgfy$a;)V
     730: aastore
     731: dup
     732: iconst_3
     733: new           #42                 // class gga
     736: dup
     737: ldc           #66                 // float 0.2083f
     739: fconst_0
     740: ldc           #84                 // float 8.0f
     742: ldc           #73                 // float -2.0f
     744: invokestatic  #64                 // Method ggc.a:(FFF)Lorg/joml/Vector3f;
     747: getstatic     #50                 // Field gfy$b.a:Lgfy$a;
     750: invokespecial #53                 // Method gga."<init>":(FLorg/joml/Vector3fc;Lgfy$a;)V
     753: aastore
     754: dup
     755: iconst_4
     756: new           #42                 // class gga
     759: dup
     760: ldc           #69                 // float 0.25f
     762: fconst_0
     763: ldc           #84                 // float 8.0f
     765: ldc           #73                 // float -2.0f
     767: invokestatic  #64                 // Method ggc.a:(FFF)Lorg/joml/Vector3f;
     770: getstatic     #50                 // Field gfy$b.a:Lgfy$a;
     773: invokespecial #53                 // Method gga."<init>":(FLorg/joml/Vector3fc;Lgfy$a;)V
     776: aastore
     777: dup
     778: iconst_5
     779: new           #42                 // class gga
     782: dup
     783: ldc           #70                 // float 0.375f
     785: fconst_1
     786: ldc           #86                 // float 3.0f
     788: ldc           #87                 // float -6.0f
     790: invokestatic  #64                 // Method ggc.a:(FFF)Lorg/joml/Vector3f;
     793: getstatic     #50                 // Field gfy$b.a:Lgfy$a;
     796: invokespecial #53                 // Method gga."<init>":(FLorg/joml/Vector3fc;Lgfy$a;)V
     799: aastore
     800: invokespecial #57                 // Method gfy."<init>":(Lgfy$c;[Lgga;)V
     803: invokevirtual #60                 // Method gfz$a.a:(Ljava/lang/String;Lgfy;)Lgfz$a;
     806: ldc           #89                 // String left_hind_leg
     808: new           #14                 // class gfy
     811: dup
     812: getstatic     #40                 // Field gfy$d.b:Lgfy$c;
     815: iconst_2
     816: anewarray     #42                 // class gga
     819: dup
     820: iconst_0
     821: new           #42                 // class gga
     824: dup
     825: fconst_0
     826: fconst_0
     827: fconst_0
     828: fconst_0
     829: invokestatic  #47                 // Method ggc.b:(FFF)Lorg/joml/Vector3f;
     832: getstatic     #50                 // Field gfy$b.a:Lgfy$a;
     835: invokespecial #53                 // Method gga."<init>":(FLorg/joml/Vector3fc;Lgfy$a;)V
     838: aastore
     839: dup
     840: iconst_1
     841: new           #42                 // class gga
     844: dup
     845: ldc           #54                 // float 0.1667f
     847: ldc           #90                 // float -45.0f
     849: fconst_0
     850: fconst_0
     851: invokestatic  #47                 // Method ggc.b:(FFF)Lorg/joml/Vector3f;
     854: getstatic     #50                 // Field gfy$b.a:Lgfy$a;
     857: invokespecial #53                 // Method gga."<init>":(FLorg/joml/Vector3fc;Lgfy$a;)V
     860: aastore
     861: invokespecial #57                 // Method gfy."<init>":(Lgfy$c;[Lgga;)V
     864: invokevirtual #60                 // Method gfz$a.a:(Ljava/lang/String;Lgfy;)Lgfz$a;
     867: ldc           #89                 // String left_hind_leg
     869: new           #14                 // class gfy
     872: dup
     873: getstatic     #62                 // Field gfy$d.a:Lgfy$c;
     876: bipush        6
     878: anewarray     #42                 // class gga
     881: dup
     882: iconst_0
     883: new           #42                 // class gga
     886: dup
     887: fconst_0
     888: fconst_0
     889: fconst_0
     890: fconst_0
     891: invokestatic  #64                 // Method ggc.a:(FFF)Lorg/joml/Vector3f;
     894: getstatic     #50                 // Field gfy$b.a:Lgfy$a;
     897: invokespecial #53                 // Method gga."<init>":(FLorg/joml/Vector3fc;Lgfy$a;)V
     900: aastore
     901: dup
     902: iconst_1
     903: new           #42                 // class gga
     906: dup
     907: ldc           #54                 // float 0.1667f
     909: fconst_0
     910: ldc           #65                 // float 5.0f
     912: ldc           #73                 // float -2.0f
     914: invokestatic  #64                 // Method ggc.a:(FFF)Lorg/joml/Vector3f;
     917: getstatic     #50                 // Field gfy$b.a:Lgfy$a;
     920: invokespecial #53                 // Method gga."<init>":(FLorg/joml/Vector3fc;Lgfy$a;)V
     923: aastore
     924: dup
     925: iconst_2
     926: new           #42                 // class gga
     929: dup
     930: ldc           #83                 // float 0.1875f
     932: fconst_0
     933: ldc           #84                 // float 8.0f
     935: ldc           #85                 // float -3.0f
     937: invokestatic  #64                 // Method ggc.a:(FFF)Lorg/joml/Vector3f;
     940: getstatic     #50                 // Field gfy$b.a:Lgfy$a;
     943: invokespecial #53                 // Method gga."<init>":(FLorg/joml/Vector3fc;Lgfy$a;)V
     946: aastore
     947: dup
     948: iconst_3
     949: new           #42                 // class gga
     952: dup
     953: ldc           #66                 // float 0.2083f
     955: fconst_0
     956: ldc           #84                 // float 8.0f
     958: ldc           #73                 // float -2.0f
     960: invokestatic  #64                 // Method ggc.a:(FFF)Lorg/joml/Vector3f;
     963: getstatic     #50                 // Field gfy$b.a:Lgfy$a;
     966: invokespecial #53                 // Method gga."<init>":(FLorg/joml/Vector3fc;Lgfy$a;)V
     969: aastore
     970: dup
     971: iconst_4
     972: new           #42                 // class gga
     975: dup
     976: ldc           #69                 // float 0.25f
     978: fconst_0
     979: ldc           #84                 // float 8.0f
     981: ldc           #73                 // float -2.0f
     983: invokestatic  #64                 // Method ggc.a:(FFF)Lorg/joml/Vector3f;
     986: getstatic     #50                 // Field gfy$b.a:Lgfy$a;
     989: invokespecial #53                 // Method gga."<init>":(FLorg/joml/Vector3fc;Lgfy$a;)V
     992: aastore
     993: dup
     994: iconst_5
     995: new           #42                 // class gga
     998: dup
     999: ldc           #70                 // float 0.375f
    1001: ldc           #68                 // float -1.0f
    1003: ldc           #86                 // float 3.0f
    1005: ldc           #87                 // float -6.0f
    1007: invokestatic  #64                 // Method ggc.a:(FFF)Lorg/joml/Vector3f;
    1010: getstatic     #50                 // Field gfy$b.a:Lgfy$a;
    1013: invokespecial #53                 // Method gga."<init>":(FLorg/joml/Vector3fc;Lgfy$a;)V
    1016: aastore
    1017: invokespecial #57                 // Method gfy."<init>":(Lgfy$c;[Lgga;)V
    1020: invokevirtual #60                 // Method gfz$a.a:(Ljava/lang/String;Lgfy;)Lgfz$a;
    1023: ldc           #92                 // String right_front_leg
    1025: new           #14                 // class gfy
    1028: dup
    1029: getstatic     #40                 // Field gfy$d.b:Lgfy$c;
    1032: iconst_4
    1033: anewarray     #42                 // class gga
    1036: dup
    1037: iconst_0
    1038: new           #42                 // class gga
    1041: dup
    1042: fconst_0
    1043: fconst_0
    1044: fconst_0
    1045: fconst_0
    1046: invokestatic  #47                 // Method ggc.b:(FFF)Lorg/joml/Vector3f;
    1049: getstatic     #50                 // Field gfy$b.a:Lgfy$a;
    1052: invokespecial #53                 // Method gga."<init>":(FLorg/joml/Vector3fc;Lgfy$a;)V
    1055: aastore
    1056: dup
    1057: iconst_1
    1058: new           #42                 // class gga
    1061: dup
    1062: ldc           #54                 // float 0.1667f
    1064: ldc           #93                 // float -27.5f
    1066: fconst_0
    1067: fconst_0
    1068: invokestatic  #47                 // Method ggc.b:(FFF)Lorg/joml/Vector3f;
    1071: getstatic     #50                 // Field gfy$b.a:Lgfy$a;
    1074: invokespecial #53                 // Method gga."<init>":(FLorg/joml/Vector3fc;Lgfy$a;)V
    1077: aastore
    1078: dup
    1079: iconst_2
    1080: new           #42                 // class gga
    1083: dup
    1084: ldc           #66                 // float 0.2083f
    1086: ldc           #94                 // float -32.5f
    1088: fconst_0
    1089: fconst_0
    1090: invokestatic  #47                 // Method ggc.b:(FFF)Lorg/joml/Vector3f;
    1093: getstatic     #50                 // Field gfy$b.a:Lgfy$a;
    1096: invokespecial #53                 // Method gga."<init>":(FLorg/joml/Vector3fc;Lgfy$a;)V
    1099: aastore
    1100: dup
    1101: iconst_3
    1102: new           #42                 // class gga
    1105: dup
    1106: ldc           #69                 // float 0.25f
    1108: ldc           #95                 // float -85.0f
    1110: fconst_0
    1111: fconst_0
    1112: invokestatic  #47                 // Method ggc.b:(FFF)Lorg/joml/Vector3f;
    1115: getstatic     #50                 // Field gfy$b.a:Lgfy$a;
    1118: invokespecial #53                 // Method gga."<init>":(FLorg/joml/Vector3fc;Lgfy$a;)V
    1121: aastore
    1122: invokespecial #57                 // Method gfy."<init>":(Lgfy$c;[Lgga;)V
    1125: invokevirtual #60                 // Method gfz$a.a:(Ljava/lang/String;Lgfy;)Lgfz$a;
    1128: ldc           #92                 // String right_front_leg
    1130: new           #14                 // class gfy
    1133: dup
    1134: getstatic     #62                 // Field gfy$d.a:Lgfy$c;
    1137: bipush        6
    1139: anewarray     #42                 // class gga
    1142: dup
    1143: iconst_0
    1144: new           #42                 // class gga
    1147: dup
    1148: fconst_0
    1149: fconst_0
    1150: fconst_0
    1151: fconst_0
    1152: invokestatic  #64                 // Method ggc.a:(FFF)Lorg/joml/Vector3f;
    1155: getstatic     #50                 // Field gfy$b.a:Lgfy$a;
    1158: invokespecial #53                 // Method gga."<init>":(FLorg/joml/Vector3fc;Lgfy$a;)V
    1161: aastore
    1162: dup
    1163: iconst_1
    1164: new           #42                 // class gga
    1167: dup
    1168: ldc           #54                 // float 0.1667f
    1170: fconst_0
    1171: ldc           #65                 // float 5.0f
    1173: fconst_0
    1174: invokestatic  #64                 // Method ggc.a:(FFF)Lorg/joml/Vector3f;
    1177: getstatic     #50                 // Field gfy$b.a:Lgfy$a;
    1180: invokespecial #53                 // Method gga."<init>":(FLorg/joml/Vector3fc;Lgfy$a;)V
    1183: aastore
    1184: dup
    1185: iconst_2
    1186: new           #42                 // class gga
    1189: dup
    1190: ldc           #83                 // float 0.1875f
    1192: ldc           #96                 // float -0.5f
    1194: ldc           #97                 // float 11.5f
    1196: ldc           #32                 // float 0.5f
    1198: invokestatic  #64                 // Method ggc.a:(FFF)Lorg/joml/Vector3f;
    1201: getstatic     #50                 // Field gfy$b.a:Lgfy$a;
    1204: invokespecial #53                 // Method gga."<init>":(FLorg/joml/Vector3fc;Lgfy$a;)V
    1207: aastore
    1208: dup
    1209: iconst_3
    1210: new           #42                 // class gga
    1213: dup
    1214: ldc           #66                 // float 0.2083f
    1216: ldc           #68                 // float -1.0f
    1218: ldc           #98                 // float 9.0f
    1220: ldc           #68                 // float -1.0f
    1222: invokestatic  #64                 // Method ggc.a:(FFF)Lorg/joml/Vector3f;
    1225: getstatic     #50                 // Field gfy$b.a:Lgfy$a;
    1228: invokespecial #53                 // Method gga."<init>":(FLorg/joml/Vector3fc;Lgfy$a;)V
    1231: aastore
    1232: dup
    1233: iconst_4
    1234: new           #42                 // class gga
    1237: dup
    1238: ldc           #69                 // float 0.25f
    1240: ldc           #68                 // float -1.0f
    1242: ldc           #98                 // float 9.0f
    1244: ldc           #68                 // float -1.0f
    1246: invokestatic  #64                 // Method ggc.a:(FFF)Lorg/joml/Vector3f;
    1249: getstatic     #50                 // Field gfy$b.a:Lgfy$a;
    1252: invokespecial #53                 // Method gga."<init>":(FLorg/joml/Vector3fc;Lgfy$a;)V
    1255: aastore
    1256: dup
    1257: iconst_5
    1258: new           #42                 // class gga
    1261: dup
    1262: ldc           #70                 // float 0.375f
    1264: ldc           #68                 // float -1.0f
    1266: fconst_2
    1267: ldc           #86                 // float 3.0f
    1269: invokestatic  #64                 // Method ggc.a:(FFF)Lorg/joml/Vector3f;
    1272: getstatic     #50                 // Field gfy$b.a:Lgfy$a;
    1275: invokespecial #53                 // Method gga."<init>":(FLorg/joml/Vector3fc;Lgfy$a;)V
    1278: aastore
    1279: invokespecial #57                 // Method gfy."<init>":(Lgfy$c;[Lgga;)V
    1282: invokevirtual #60                 // Method gfz$a.a:(Ljava/lang/String;Lgfy;)Lgfz$a;
    1285: ldc           #100                // String left_front_leg
    1287: new           #14                 // class gfy
    1290: dup
    1291: getstatic     #40                 // Field gfy$d.b:Lgfy$c;
    1294: iconst_4
    1295: anewarray     #42                 // class gga
    1298: dup
    1299: iconst_0
    1300: new           #42                 // class gga
    1303: dup
    1304: fconst_0
    1305: fconst_0
    1306: fconst_0
    1307: fconst_0
    1308: invokestatic  #47                 // Method ggc.b:(FFF)Lorg/joml/Vector3f;
    1311: getstatic     #50                 // Field gfy$b.a:Lgfy$a;
    1314: invokespecial #53                 // Method gga."<init>":(FLorg/joml/Vector3fc;Lgfy$a;)V
    1317: aastore
    1318: dup
    1319: iconst_1
    1320: new           #42                 // class gga
    1323: dup
    1324: ldc           #54                 // float 0.1667f
    1326: ldc           #101                // float -12.5f
    1328: fconst_0
    1329: fconst_0
    1330: invokestatic  #47                 // Method ggc.b:(FFF)Lorg/joml/Vector3f;
    1333: getstatic     #50                 // Field gfy$b.a:Lgfy$a;
    1336: invokespecial #53                 // Method gga."<init>":(FLorg/joml/Vector3fc;Lgfy$a;)V
    1339: aastore
    1340: dup
    1341: iconst_2
    1342: new           #42                 // class gga
    1345: dup
    1346: ldc           #66                 // float 0.2083f
    1348: ldc           #82                 // float -35.0f
    1350: fconst_0
    1351: fconst_0
    1352: invokestatic  #47                 // Method ggc.b:(FFF)Lorg/joml/Vector3f;
    1355: getstatic     #50                 // Field gfy$b.a:Lgfy$a;
    1358: invokespecial #53                 // Method gga."<init>":(FLorg/joml/Vector3fc;Lgfy$a;)V
    1361: aastore
    1362: dup
    1363: iconst_3
    1364: new           #42                 // class gga
    1367: dup
    1368: ldc           #69                 // float 0.25f
    1370: ldc           #95                 // float -85.0f
    1372: fconst_0
    1373: fconst_0
    1374: invokestatic  #47                 // Method ggc.b:(FFF)Lorg/joml/Vector3f;
    1377: getstatic     #50                 // Field gfy$b.a:Lgfy$a;
    1380: invokespecial #53                 // Method gga."<init>":(FLorg/joml/Vector3fc;Lgfy$a;)V
    1383: aastore
    1384: invokespecial #57                 // Method gfy."<init>":(Lgfy$c;[Lgga;)V
    1387: invokevirtual #60                 // Method gfz$a.a:(Ljava/lang/String;Lgfy;)Lgfz$a;
    1390: ldc           #100                // String left_front_leg
    1392: new           #14                 // class gfy
    1395: dup
    1396: getstatic     #62                 // Field gfy$d.a:Lgfy$c;
    1399: bipush        6
    1401: anewarray     #42                 // class gga
    1404: dup
    1405: iconst_0
    1406: new           #42                 // class gga
    1409: dup
    1410: fconst_0
    1411: fconst_0
    1412: fconst_0
    1413: fconst_0
    1414: invokestatic  #64                 // Method ggc.a:(FFF)Lorg/joml/Vector3f;
    1417: getstatic     #50                 // Field gfy$b.a:Lgfy$a;
    1420: invokespecial #53                 // Method gga."<init>":(FLorg/joml/Vector3fc;Lgfy$a;)V
    1423: aastore
    1424: dup
    1425: iconst_1
    1426: new           #42                 // class gga
    1429: dup
    1430: ldc           #54                 // float 0.1667f
    1432: fconst_0
    1433: ldc           #65                 // float 5.0f
    1435: fconst_0
    1436: invokestatic  #64                 // Method ggc.a:(FFF)Lorg/joml/Vector3f;
    1439: getstatic     #50                 // Field gfy$b.a:Lgfy$a;
    1442: invokespecial #53                 // Method gga."<init>":(FLorg/joml/Vector3fc;Lgfy$a;)V
    1445: aastore
    1446: dup
    1447: iconst_2
    1448: new           #42                 // class gga
    1451: dup
    1452: ldc           #83                 // float 0.1875f
    1454: ldc           #32                 // float 0.5f
    1456: ldc           #97                 // float 11.5f
    1458: ldc           #32                 // float 0.5f
    1460: invokestatic  #64                 // Method ggc.a:(FFF)Lorg/joml/Vector3f;
    1463: getstatic     #50                 // Field gfy$b.a:Lgfy$a;
    1466: invokespecial #53                 // Method gga."<init>":(FLorg/joml/Vector3fc;Lgfy$a;)V
    1469: aastore
    1470: dup
    1471: iconst_3
    1472: new           #42                 // class gga
    1475: dup
    1476: ldc           #66                 // float 0.2083f
    1478: fconst_1
    1479: ldc           #98                 // float 9.0f
    1481: ldc           #68                 // float -1.0f
    1483: invokestatic  #64                 // Method ggc.a:(FFF)Lorg/joml/Vector3f;
    1486: getstatic     #50                 // Field gfy$b.a:Lgfy$a;
    1489: invokespecial #53                 // Method gga."<init>":(FLorg/joml/Vector3fc;Lgfy$a;)V
    1492: aastore
    1493: dup
    1494: iconst_4
    1495: new           #42                 // class gga
    1498: dup
    1499: ldc           #69                 // float 0.25f
    1501: fconst_1
    1502: ldc           #98                 // float 9.0f
    1504: ldc           #68                 // float -1.0f
    1506: invokestatic  #64                 // Method ggc.a:(FFF)Lorg/joml/Vector3f;
    1509: getstatic     #50                 // Field gfy$b.a:Lgfy$a;
    1512: invokespecial #53                 // Method gga."<init>":(FLorg/joml/Vector3fc;Lgfy$a;)V
    1515: aastore
    1516: dup
    1517: iconst_5
    1518: new           #42                 // class gga
    1521: dup
    1522: ldc           #70                 // float 0.375f
    1524: fconst_1
    1525: fconst_2
    1526: ldc           #86                 // float 3.0f
    1528: invokestatic  #64                 // Method ggc.a:(FFF)Lorg/joml/Vector3f;
    1531: getstatic     #50                 // Field gfy$b.a:Lgfy$a;
    1534: invokespecial #53                 // Method gga."<init>":(FLorg/joml/Vector3fc;Lgfy$a;)V
    1537: aastore
    1538: invokespecial #57                 // Method gfy."<init>":(Lgfy$c;[Lgga;)V
    1541: invokevirtual #60                 // Method gfz$a.a:(Ljava/lang/String;Lgfy;)Lgfz$a;
    1544: ldc           #103                // String cube
    1546: new           #14                 // class gfy
    1549: dup
    1550: getstatic     #40                 // Field gfy$d.b:Lgfy$c;
    1553: iconst_5
    1554: anewarray     #42                 // class gga
    1557: dup
    1558: iconst_0
    1559: new           #42                 // class gga
    1562: dup
    1563: fconst_0
    1564: fconst_0
    1565: fconst_0
    1566: fconst_0
    1567: invokestatic  #47                 // Method ggc.b:(FFF)Lorg/joml/Vector3f;
    1570: getstatic     #50                 // Field gfy$b.a:Lgfy$a;
    1573: invokespecial #53                 // Method gga."<init>":(FLorg/joml/Vector3fc;Lgfy$a;)V
    1576: aastore
    1577: dup
    1578: iconst_1
    1579: new           #42                 // class gga
    1582: dup
    1583: ldc           #54                 // float 0.1667f
    1585: fconst_0
    1586: fconst_0
    1587: fconst_0
    1588: invokestatic  #47                 // Method ggc.b:(FFF)Lorg/joml/Vector3f;
    1591: getstatic     #50                 // Field gfy$b.a:Lgfy$a;
    1594: invokespecial #53                 // Method gga."<init>":(FLorg/joml/Vector3fc;Lgfy$a;)V
    1597: aastore
    1598: dup
    1599: iconst_2
    1600: new           #42                 // class gga
    1603: dup
    1604: ldc           #104                // float 0.4167f
    1606: ldc           #105                // float -2.5f
    1608: fconst_0
    1609: fconst_0
    1610: invokestatic  #47                 // Method ggc.b:(FFF)Lorg/joml/Vector3f;
    1613: getstatic     #50                 // Field gfy$b.a:Lgfy$a;
    1616: invokespecial #53                 // Method gga."<init>":(FLorg/joml/Vector3fc;Lgfy$a;)V
    1619: aastore
    1620: dup
    1621: iconst_3
    1622: new           #42                 // class gga
    1625: dup
    1626: ldc           #106                // float 0.4583f
    1628: ldc           #65                 // float 5.0f
    1630: fconst_0
    1631: fconst_0
    1632: invokestatic  #47                 // Method ggc.b:(FFF)Lorg/joml/Vector3f;
    1635: getstatic     #50                 // Field gfy$b.a:Lgfy$a;
    1638: invokespecial #53                 // Method gga."<init>":(FLorg/joml/Vector3fc;Lgfy$a;)V
    1641: aastore
    1642: dup
    1643: iconst_4
    1644: new           #42                 // class gga
    1647: dup
    1648: ldc           #32                 // float 0.5f
    1650: fconst_0
    1651: fconst_0
    1652: fconst_0
    1653: invokestatic  #47                 // Method ggc.b:(FFF)Lorg/joml/Vector3f;
    1656: getstatic     #50                 // Field gfy$b.a:Lgfy$a;
    1659: invokespecial #53                 // Method gga."<init>":(FLorg/joml/Vector3fc;Lgfy$a;)V
    1662: aastore
    1663: invokespecial #57                 // Method gfy."<init>":(Lgfy$c;[Lgga;)V
    1666: invokevirtual #60                 // Method gfz$a.a:(Ljava/lang/String;Lgfy;)Lgfz$a;
    1669: ldc           #103                // String cube
    1671: new           #14                 // class gfy
    1674: dup
    1675: getstatic     #62                 // Field gfy$d.a:Lgfy$c;
    1678: bipush        8
    1680: anewarray     #42                 // class gga
    1683: dup
    1684: iconst_0
    1685: new           #42                 // class gga
    1688: dup
    1689: fconst_0
    1690: fconst_0
    1691: ldc           #86                 // float 3.0f
    1693: fconst_0
    1694: invokestatic  #64                 // Method ggc.a:(FFF)Lorg/joml/Vector3f;
    1697: getstatic     #50                 // Field gfy$b.a:Lgfy$a;
    1700: invokespecial #53                 // Method gga."<init>":(FLorg/joml/Vector3fc;Lgfy$a;)V
    1703: aastore
    1704: dup
    1705: iconst_1
    1706: new           #42                 // class gga
    1709: dup
    1710: ldc           #54                 // float 0.1667f
    1712: fconst_0
    1713: ldc           #84                 // float 8.0f
    1715: fconst_0
    1716: invokestatic  #64                 // Method ggc.a:(FFF)Lorg/joml/Vector3f;
    1719: getstatic     #50                 // Field gfy$b.a:Lgfy$a;
    1722: invokespecial #53                 // Method gga."<init>":(FLorg/joml/Vector3fc;Lgfy$a;)V
    1725: aastore
    1726: dup
    1727: iconst_2
    1728: new           #42                 // class gga
    1731: dup
    1732: ldc           #66                 // float 0.2083f
    1734: fconst_0
    1735: ldc           #79                 // float 7.0f
    1737: fconst_0
    1738: invokestatic  #64                 // Method ggc.a:(FFF)Lorg/joml/Vector3f;
    1741: getstatic     #50                 // Field gfy$b.a:Lgfy$a;
    1744: invokespecial #53                 // Method gga."<init>":(FLorg/joml/Vector3fc;Lgfy$a;)V
    1747: aastore
    1748: dup
    1749: iconst_3
    1750: new           #42                 // class gga
    1753: dup
    1754: ldc           #69                 // float 0.25f
    1756: fconst_0
    1757: ldc           #79                 // float 7.0f
    1759: fconst_0
    1760: invokestatic  #64                 // Method ggc.a:(FFF)Lorg/joml/Vector3f;
    1763: getstatic     #50                 // Field gfy$b.a:Lgfy$a;
    1766: invokespecial #53                 // Method gga."<init>":(FLorg/joml/Vector3fc;Lgfy$a;)V
    1769: aastore
    1770: dup
    1771: iconst_4
    1772: new           #42                 // class gga
    1775: dup
    1776: ldc           #70                 // float 0.375f
    1778: fconst_0
    1779: fconst_0
    1780: fconst_0
    1781: invokestatic  #64                 // Method ggc.a:(FFF)Lorg/joml/Vector3f;
    1784: getstatic     #50                 // Field gfy$b.a:Lgfy$a;
    1787: invokespecial #53                 // Method gga."<init>":(FLorg/joml/Vector3fc;Lgfy$a;)V
    1790: aastore
    1791: dup
    1792: iconst_5
    1793: new           #42                 // class gga
    1796: dup
    1797: ldc           #104                // float 0.4167f
    1799: fconst_0
    1800: fconst_1
    1801: fconst_0
    1802: invokestatic  #64                 // Method ggc.a:(FFF)Lorg/joml/Vector3f;
    1805: getstatic     #50                 // Field gfy$b.a:Lgfy$a;
    1808: invokespecial #53                 // Method gga."<init>":(FLorg/joml/Vector3fc;Lgfy$a;)V
    1811: aastore
    1812: dup
    1813: bipush        6
    1815: new           #42                 // class gga
    1818: dup
    1819: ldc           #106                // float 0.4583f
    1821: fconst_0
    1822: ldc           #107                // float 0.6f
    1824: fconst_0
    1825: invokestatic  #64                 // Method ggc.a:(FFF)Lorg/joml/Vector3f;
    1828: getstatic     #50                 // Field gfy$b.a:Lgfy$a;
    1831: invokespecial #53                 // Method gga."<init>":(FLorg/joml/Vector3fc;Lgfy$a;)V
    1834: aastore
    1835: dup
    1836: bipush        7
    1838: new           #42                 // class gga
    1841: dup
    1842: ldc           #32                 // float 0.5f
    1844: fconst_0
    1845: fconst_0
    1846: fconst_0
    1847: invokestatic  #64                 // Method ggc.a:(FFF)Lorg/joml/Vector3f;
    1850: getstatic     #50                 // Field gfy$b.a:Lgfy$a;
    1853: invokespecial #53                 // Method gga."<init>":(FLorg/joml/Vector3fc;Lgfy$a;)V
    1856: aastore
    1857: invokespecial #57                 // Method gfy."<init>":(Lgfy$c;[Lgga;)V
    1860: invokevirtual #60                 // Method gfz$a.a:(Ljava/lang/String;Lgfy;)Lgfz$a;
    1863: invokevirtual #110                // Method gfz$a.b:()Lgfz;
    1866: putstatic     #112                // Field a:Lgfz;
    1869: ldc           #113                // float 1.4583f
    1871: invokestatic  #35                 // Method gfz$a.a:(F)Lgfz$a;
    1874: invokevirtual #116                // Method gfz$a.a:()Lgfz$a;
    1877: ldc           #37                 // String body
    1879: new           #14                 // class gfy
    1882: dup
    1883: getstatic     #40                 // Field gfy$d.b:Lgfy$c;
    1886: bipush        9
    1888: anewarray     #42                 // class gga
    1891: dup
    1892: iconst_0
    1893: new           #42                 // class gga
    1896: dup
    1897: fconst_0
    1898: fconst_0
    1899: fconst_0
    1900: fconst_0
    1901: invokestatic  #47                 // Method ggc.b:(FFF)Lorg/joml/Vector3f;
    1904: getstatic     #118                // Field gfy$b.b:Lgfy$a;
    1907: invokespecial #53                 // Method gga."<init>":(FLorg/joml/Vector3fc;Lgfy$a;)V
    1910: aastore
    1911: dup
    1912: iconst_1
    1913: new           #42                 // class gga
    1916: dup
    1917: ldc           #69                 // float 0.25f
    1919: fconst_0
    1920: fconst_0
    1921: ldc           #119                // float 4.6f
    1923: invokestatic  #47                 // Method ggc.b:(FFF)Lorg/joml/Vector3f;
    1926: getstatic     #118                // Field gfy$b.b:Lgfy$a;
    1929: invokespecial #53                 // Method gga."<init>":(FLorg/joml/Vector3fc;Lgfy$a;)V
    1932: aastore
    1933: dup
    1934: iconst_2
    1935: new           #42                 // class gga
    1938: dup
    1939: ldc           #78                 // float 0.2917f
    1941: fconst_0
    1942: fconst_0
    1943: ldc           #120                // float 6.81f
    1945: invokestatic  #47                 // Method ggc.b:(FFF)Lorg/joml/Vector3f;
    1948: getstatic     #118                // Field gfy$b.b:Lgfy$a;
    1951: invokespecial #53                 // Method gga."<init>":(FLorg/joml/Vector3fc;Lgfy$a;)V
    1954: aastore
    1955: dup
    1956: iconst_3
    1957: new           #42                 // class gga
    1960: dup
    1961: ldc           #32                 // float 0.5f
    1963: fconst_0
    1964: fconst_0
    1965: fconst_0
    1966: invokestatic  #47                 // Method ggc.b:(FFF)Lorg/joml/Vector3f;
    1969: getstatic     #118                // Field gfy$b.b:Lgfy$a;
    1972: invokespecial #53                 // Method gga."<init>":(FLorg/joml/Vector3fc;Lgfy$a;)V
    1975: aastore
    1976: dup
    1977: iconst_4
    1978: new           #42                 // class gga
    1981: dup
    1982: ldc           #121                // float 0.7083f
    1984: fconst_0
    1985: fconst_0
    1986: fconst_0
    1987: invokestatic  #47                 // Method ggc.b:(FFF)Lorg/joml/Vector3f;
    1990: getstatic     #118                // Field gfy$b.b:Lgfy$a;
    1993: invokespecial #53                 // Method gga."<init>":(FLorg/joml/Vector3fc;Lgfy$a;)V
    1996: aastore
    1997: dup
    1998: iconst_5
    1999: new           #42                 // class gga
    2002: dup
    2003: ldc           #122                // float 0.9583f
    2005: fconst_0
    2006: fconst_0
    2007: ldc           #123                // float -4.6f
    2009: invokestatic  #47                 // Method ggc.b:(FFF)Lorg/joml/Vector3f;
    2012: getstatic     #118                // Field gfy$b.b:Lgfy$a;
    2015: invokespecial #53                 // Method gga."<init>":(FLorg/joml/Vector3fc;Lgfy$a;)V
    2018: aastore
    2019: dup
    2020: bipush        6
    2022: new           #42                 // class gga
    2025: dup
    2026: fconst_1
    2027: fconst_0
    2028: fconst_0
    2029: ldc           #124                // float -6.89f
    2031: invokestatic  #47                 // Method ggc.b:(FFF)Lorg/joml/Vector3f;
    2034: getstatic     #118                // Field gfy$b.b:Lgfy$a;
    2037: invokespecial #53                 // Method gga."<init>":(FLorg/joml/Vector3fc;Lgfy$a;)V
    2040: aastore
    2041: dup
    2042: bipush        7
    2044: new           #42                 // class gga
    2047: dup
    2048: ldc           #125                // float 1.25f
    2050: fconst_0
    2051: fconst_0
    2052: fconst_0
    2053: invokestatic  #47                 // Method ggc.b:(FFF)Lorg/joml/Vector3f;
    2056: getstatic     #118                // Field gfy$b.b:Lgfy$a;
    2059: invokespecial #53                 // Method gga."<init>":(FLorg/joml/Vector3fc;Lgfy$a;)V
    2062: aastore
    2063: dup
    2064: bipush        8
    2066: new           #42                 // class gga
    2069: dup
    2070: ldc           #113                // float 1.4583f
    2072: fconst_0
    2073: fconst_0
    2074: fconst_0
    2075: invokestatic  #47                 // Method ggc.b:(FFF)Lorg/joml/Vector3f;
    2078: getstatic     #118                // Field gfy$b.b:Lgfy$a;
    2081: invokespecial #53                 // Method gga."<init>":(FLorg/joml/Vector3fc;Lgfy$a;)V
    2084: aastore
    2085: invokespecial #57                 // Method gfy."<init>":(Lgfy$c;[Lgga;)V
    2088: invokevirtual #60                 // Method gfz$a.a:(Ljava/lang/String;Lgfy;)Lgfz$a;
    2091: ldc           #37                 // String body
    2093: new           #14                 // class gfy
    2096: dup
    2097: getstatic     #62                 // Field gfy$d.a:Lgfy$c;
    2100: bipush        7
    2102: anewarray     #42                 // class gga
    2105: dup
    2106: iconst_0
    2107: new           #42                 // class gga
    2110: dup
    2111: fconst_0
    2112: fconst_0
    2113: fconst_0
    2114: fconst_0
    2115: invokestatic  #64                 // Method ggc.a:(FFF)Lorg/joml/Vector3f;
    2118: getstatic     #118                // Field gfy$b.b:Lgfy$a;
    2121: invokespecial #53                 // Method gga."<init>":(FLorg/joml/Vector3fc;Lgfy$a;)V
    2124: aastore
    2125: dup
    2126: iconst_1
    2127: new           #42                 // class gga
    2130: dup
    2131: ldc           #69                 // float 0.25f
    2133: fconst_0
    2134: ldc           #126                // float -0.2f
    2136: fconst_0
    2137: invokestatic  #64                 // Method ggc.a:(FFF)Lorg/joml/Vector3f;
    2140: getstatic     #118                // Field gfy$b.b:Lgfy$a;
    2143: invokespecial #53                 // Method gga."<init>":(FLorg/joml/Vector3fc;Lgfy$a;)V
    2146: aastore
    2147: dup
    2148: iconst_2
    2149: new           #42                 // class gga
    2152: dup
    2153: ldc           #32                 // float 0.5f
    2155: fconst_0
    2156: fconst_0
    2157: fconst_0
    2158: invokestatic  #64                 // Method ggc.a:(FFF)Lorg/joml/Vector3f;
    2161: getstatic     #118                // Field gfy$b.b:Lgfy$a;
    2164: invokespecial #53                 // Method gga."<init>":(FLorg/joml/Vector3fc;Lgfy$a;)V
    2167: aastore
    2168: dup
    2169: iconst_3
    2170: new           #42                 // class gga
    2173: dup
    2174: ldc           #121                // float 0.7083f
    2176: fconst_0
    2177: fconst_0
    2178: fconst_0
    2179: invokestatic  #64                 // Method ggc.a:(FFF)Lorg/joml/Vector3f;
    2182: getstatic     #118                // Field gfy$b.b:Lgfy$a;
    2185: invokespecial #53                 // Method gga."<init>":(FLorg/joml/Vector3fc;Lgfy$a;)V
    2188: aastore
    2189: dup
    2190: iconst_4
    2191: new           #42                 // class gga
    2194: dup
    2195: ldc           #122                // float 0.9583f
    2197: fconst_0
    2198: ldc           #126                // float -0.2f
    2200: fconst_0
    2201: invokestatic  #64                 // Method ggc.a:(FFF)Lorg/joml/Vector3f;
    2204: getstatic     #118                // Field gfy$b.b:Lgfy$a;
    2207: invokespecial #53                 // Method gga."<init>":(FLorg/joml/Vector3fc;Lgfy$a;)V
    2210: aastore
    2211: dup
    2212: iconst_5
    2213: new           #42                 // class gga
    2216: dup
    2217: ldc           #125                // float 1.25f
    2219: fconst_0
    2220: fconst_0
    2221: fconst_0
    2222: invokestatic  #64                 // Method ggc.a:(FFF)Lorg/joml/Vector3f;
    2225: getstatic     #118                // Field gfy$b.b:Lgfy$a;
    2228: invokespecial #53                 // Method gga."<init>":(FLorg/joml/Vector3fc;Lgfy$a;)V
    2231: aastore
    2232: dup
    2233: bipush        6
    2235: new           #42                 // class gga
    2238: dup
    2239: ldc           #113                // float 1.4583f
    2241: fconst_0
    2242: fconst_0
    2243: fconst_0
    2244: invokestatic  #64                 // Method ggc.a:(FFF)Lorg/joml/Vector3f;
    2247: getstatic     #118                // Field gfy$b.b:Lgfy$a;
    2250: invokespecial #53                 // Method gga."<init>":(FLorg/joml/Vector3fc;Lgfy$a;)V
    2253: aastore
    2254: invokespecial #57                 // Method gfy."<init>":(Lgfy$c;[Lgga;)V
    2257: invokevirtual #60                 // Method gfz$a.a:(Ljava/lang/String;Lgfy;)Lgfz$a;
    2260: ldc           #72                 // String tail
    2262: new           #14                 // class gfy
    2265: dup
    2266: getstatic     #40                 // Field gfy$d.b:Lgfy$c;
    2269: iconst_5
    2270: anewarray     #42                 // class gga
    2273: dup
    2274: iconst_0
    2275: new           #42                 // class gga
    2278: dup
    2279: fconst_0
    2280: fconst_0
    2281: fconst_0
    2282: fconst_0
    2283: invokestatic  #47                 // Method ggc.b:(FFF)Lorg/joml/Vector3f;
    2286: getstatic     #50                 // Field gfy$b.a:Lgfy$a;
    2289: invokespecial #53                 // Method gga."<init>":(FLorg/joml/Vector3fc;Lgfy$a;)V
    2292: aastore
    2293: dup
    2294: iconst_1
    2295: new           #42                 // class gga
    2298: dup
    2299: ldc           #32                 // float 0.5f
    2301: ldc           #127                // float -9.17f
    2303: fconst_0
    2304: fconst_0
    2305: invokestatic  #47                 // Method ggc.b:(FFF)Lorg/joml/Vector3f;
    2308: getstatic     #50                 // Field gfy$b.a:Lgfy$a;
    2311: invokespecial #53                 // Method gga."<init>":(FLorg/joml/Vector3fc;Lgfy$a;)V
    2314: aastore
    2315: dup
    2316: iconst_2
    2317: new           #42                 // class gga
    2320: dup
    2321: ldc           #128                // float 0.75f
    2323: ldc           #65                 // float 5.0f
    2325: fconst_0
    2326: fconst_0
    2327: invokestatic  #47                 // Method ggc.b:(FFF)Lorg/joml/Vector3f;
    2330: getstatic     #50                 // Field gfy$b.a:Lgfy$a;
    2333: invokespecial #53                 // Method gga."<init>":(FLorg/joml/Vector3fc;Lgfy$a;)V
    2336: aastore
    2337: dup
    2338: iconst_3
    2339: new           #42                 // class gga
    2342: dup
    2343: ldc           #129                // float 1.2083f
    2345: ldc           #130                // float -8.24f
    2347: fconst_0
    2348: fconst_0
    2349: invokestatic  #47                 // Method ggc.b:(FFF)Lorg/joml/Vector3f;
    2352: getstatic     #50                 // Field gfy$b.a:Lgfy$a;
    2355: invokespecial #53                 // Method gga."<init>":(FLorg/joml/Vector3fc;Lgfy$a;)V
    2358: aastore
    2359: dup
    2360: iconst_4
    2361: new           #42                 // class gga
    2364: dup
    2365: ldc           #113                // float 1.4583f
    2367: fconst_0
    2368: fconst_0
    2369: fconst_0
    2370: invokestatic  #47                 // Method ggc.b:(FFF)Lorg/joml/Vector3f;
    2373: getstatic     #50                 // Field gfy$b.a:Lgfy$a;
    2376: invokespecial #53                 // Method gga."<init>":(FLorg/joml/Vector3fc;Lgfy$a;)V
    2379: aastore
    2380: invokespecial #57                 // Method gfy."<init>":(Lgfy$c;[Lgga;)V
    2383: invokevirtual #60                 // Method gfz$a.a:(Ljava/lang/String;Lgfy;)Lgfz$a;
    2386: ldc           #81                 // String right_hind_leg
    2388: new           #14                 // class gfy
    2391: dup
    2392: getstatic     #40                 // Field gfy$d.b:Lgfy$c;
    2395: bipush        7
    2397: anewarray     #42                 // class gga
    2400: dup
    2401: iconst_0
    2402: new           #42                 // class gga
    2405: dup
    2406: fconst_0
    2407: ldc           #131                // float -50.0f
    2409: fconst_0
    2410: fconst_0
    2411: invokestatic  #47                 // Method ggc.b:(FFF)Lorg/joml/Vector3f;
    2414: getstatic     #50                 // Field gfy$b.a:Lgfy$a;
    2417: invokespecial #53                 // Method gga."<init>":(FLorg/joml/Vector3fc;Lgfy$a;)V
    2420: aastore
    2421: dup
    2422: iconst_1
    2423: new           #42                 // class gga
    2426: dup
    2427: ldc           #69                 // float 0.25f
    2429: fconst_0
    2430: fconst_0
    2431: fconst_0
    2432: invokestatic  #47                 // Method ggc.b:(FFF)Lorg/joml/Vector3f;
    2435: getstatic     #50                 // Field gfy$b.a:Lgfy$a;
    2438: invokespecial #53                 // Method gga."<init>":(FLorg/joml/Vector3fc;Lgfy$a;)V
    2441: aastore
    2442: dup
    2443: iconst_2
    2444: new           #42                 // class gga
    2447: dup
    2448: ldc           #32                 // float 0.5f
    2450: fconst_0
    2451: fconst_0
    2452: fconst_0
    2453: invokestatic  #47                 // Method ggc.b:(FFF)Lorg/joml/Vector3f;
    2456: getstatic     #50                 // Field gfy$b.a:Lgfy$a;
    2459: invokespecial #53                 // Method gga."<init>":(FLorg/joml/Vector3fc;Lgfy$a;)V
    2462: aastore
    2463: dup
    2464: iconst_3
    2465: new           #42                 // class gga
    2468: dup
    2469: ldc           #128                // float 0.75f
    2471: ldc           #132                // float 50.0f
    2473: fconst_0
    2474: fconst_0
    2475: invokestatic  #47                 // Method ggc.b:(FFF)Lorg/joml/Vector3f;
    2478: getstatic     #50                 // Field gfy$b.a:Lgfy$a;
    2481: invokespecial #53                 // Method gga."<init>":(FLorg/joml/Vector3fc;Lgfy$a;)V
    2484: aastore
    2485: dup
    2486: iconst_4
    2487: new           #42                 // class gga
    2490: dup
    2491: fconst_1
    2492: ldc           #132                // float 50.0f
    2494: fconst_0
    2495: fconst_0
    2496: invokestatic  #47                 // Method ggc.b:(FFF)Lorg/joml/Vector3f;
    2499: getstatic     #50                 // Field gfy$b.a:Lgfy$a;
    2502: invokespecial #53                 // Method gga."<init>":(FLorg/joml/Vector3fc;Lgfy$a;)V
    2505: aastore
    2506: dup
    2507: iconst_5
    2508: new           #42                 // class gga
    2511: dup
    2512: ldc           #133                // float 1.2917f
    2514: ldc           #134                // float -20.0f
    2516: fconst_0
    2517: fconst_0
    2518: invokestatic  #47                 // Method ggc.b:(FFF)Lorg/joml/Vector3f;
    2521: getstatic     #50                 // Field gfy$b.a:Lgfy$a;
    2524: invokespecial #53                 // Method gga."<init>":(FLorg/joml/Vector3fc;Lgfy$a;)V
    2527: aastore
    2528: dup
    2529: bipush        6
    2531: new           #42                 // class gga
    2534: dup
    2535: ldc           #113                // float 1.4583f
    2537: ldc           #131                // float -50.0f
    2539: fconst_0
    2540: fconst_0
    2541: invokestatic  #47                 // Method ggc.b:(FFF)Lorg/joml/Vector3f;
    2544: getstatic     #50                 // Field gfy$b.a:Lgfy$a;
    2547: invokespecial #53                 // Method gga."<init>":(FLorg/joml/Vector3fc;Lgfy$a;)V
    2550: aastore
    2551: invokespecial #57                 // Method gfy."<init>":(Lgfy$c;[Lgga;)V
    2554: invokevirtual #60                 // Method gfz$a.a:(Ljava/lang/String;Lgfy;)Lgfz$a;
    2557: ldc           #81                 // String right_hind_leg
    2559: new           #14                 // class gfy
    2562: dup
    2563: getstatic     #62                 // Field gfy$d.a:Lgfy$c;
    2566: bipush        6
    2568: anewarray     #42                 // class gga
    2571: dup
    2572: iconst_0
    2573: new           #42                 // class gga
    2576: dup
    2577: fconst_0
    2578: fconst_0
    2579: fconst_0
    2580: fconst_0
    2581: invokestatic  #64                 // Method ggc.a:(FFF)Lorg/joml/Vector3f;
    2584: getstatic     #50                 // Field gfy$b.a:Lgfy$a;
    2587: invokespecial #53                 // Method gga."<init>":(FLorg/joml/Vector3fc;Lgfy$a;)V
    2590: aastore
    2591: dup
    2592: iconst_1
    2593: new           #42                 // class gga
    2596: dup
    2597: ldc           #69                 // float 0.25f
    2599: fconst_0
    2600: fconst_0
    2601: ldc           #96                 // float -0.5f
    2603: invokestatic  #64                 // Method ggc.a:(FFF)Lorg/joml/Vector3f;
    2606: getstatic     #50                 // Field gfy$b.a:Lgfy$a;
    2609: invokespecial #53                 // Method gga."<init>":(FLorg/joml/Vector3fc;Lgfy$a;)V
    2612: aastore
    2613: dup
    2614: iconst_2
    2615: new           #42                 // class gga
    2618: dup
    2619: ldc           #32                 // float 0.5f
    2621: fconst_0
    2622: fconst_0
    2623: fconst_0
    2624: invokestatic  #64                 // Method ggc.a:(FFF)Lorg/joml/Vector3f;
    2627: getstatic     #50                 // Field gfy$b.a:Lgfy$a;
    2630: invokespecial #53                 // Method gga."<init>":(FLorg/joml/Vector3fc;Lgfy$a;)V
    2633: aastore
    2634: dup
    2635: iconst_3
    2636: new           #42                 // class gga
    2639: dup
    2640: fconst_1
    2641: fconst_0
    2642: fconst_0
    2643: ldc           #96                 // float -0.5f
    2645: invokestatic  #64                 // Method ggc.a:(FFF)Lorg/joml/Vector3f;
    2648: getstatic     #50                 // Field gfy$b.a:Lgfy$a;
    2651: invokespecial #53                 // Method gga."<init>":(FLorg/joml/Vector3fc;Lgfy$a;)V
    2654: aastore
    2655: dup
    2656: iconst_4
    2657: new           #42                 // class gga
    2660: dup
    2661: ldc           #133                // float 1.2917f
    2663: fconst_0
    2664: fconst_1
    2665: ldc           #135                // float -0.18f
    2667: invokestatic  #64                 // Method ggc.a:(FFF)Lorg/joml/Vector3f;
    2670: getstatic     #50                 // Field gfy$b.a:Lgfy$a;
    2673: invokespecial #53                 // Method gga."<init>":(FLorg/joml/Vector3fc;Lgfy$a;)V
    2676: aastore
    2677: dup
    2678: iconst_5
    2679: new           #42                 // class gga
    2682: dup
    2683: ldc           #113                // float 1.4583f
    2685: fconst_0
    2686: fconst_0
    2687: fconst_0
    2688: invokestatic  #64                 // Method ggc.a:(FFF)Lorg/joml/Vector3f;
    2691: getstatic     #50                 // Field gfy$b.a:Lgfy$a;
    2694: invokespecial #53                 // Method gga."<init>":(FLorg/joml/Vector3fc;Lgfy$a;)V
    2697: aastore
    2698: invokespecial #57                 // Method gfy."<init>":(Lgfy$c;[Lgga;)V
    2701: invokevirtual #60                 // Method gfz$a.a:(Ljava/lang/String;Lgfy;)Lgfz$a;
    2704: ldc           #89                 // String left_hind_leg
    2706: new           #14                 // class gfy
    2709: dup
    2710: getstatic     #40                 // Field gfy$d.b:Lgfy$c;
    2713: bipush        7
    2715: anewarray     #42                 // class gga
    2718: dup
    2719: iconst_0
    2720: new           #42                 // class gga
    2723: dup
    2724: fconst_0
    2725: ldc           #132                // float 50.0f
    2727: fconst_0
    2728: fconst_0
    2729: invokestatic  #47                 // Method ggc.b:(FFF)Lorg/joml/Vector3f;
    2732: getstatic     #50                 // Field gfy$b.a:Lgfy$a;
    2735: invokespecial #53                 // Method gga."<init>":(FLorg/joml/Vector3fc;Lgfy$a;)V
    2738: aastore
    2739: dup
    2740: iconst_1
    2741: new           #42                 // class gga
    2744: dup
    2745: ldc           #69                 // float 0.25f
    2747: ldc           #132                // float 50.0f
    2749: fconst_0
    2750: fconst_0
    2751: invokestatic  #47                 // Method ggc.b:(FFF)Lorg/joml/Vector3f;
    2754: getstatic     #50                 // Field gfy$b.a:Lgfy$a;
    2757: invokespecial #53                 // Method gga."<init>":(FLorg/joml/Vector3fc;Lgfy$a;)V
    2760: aastore
    2761: dup
    2762: iconst_2
    2763: new           #42                 // class gga
    2766: dup
    2767: ldc           #136                // float 0.5417f
    2769: ldc           #134                // float -20.0f
    2771: fconst_0
    2772: fconst_0
    2773: invokestatic  #47                 // Method ggc.b:(FFF)Lorg/joml/Vector3f;
    2776: getstatic     #50                 // Field gfy$b.a:Lgfy$a;
    2779: invokespecial #53                 // Method gga."<init>":(FLorg/joml/Vector3fc;Lgfy$a;)V
    2782: aastore
    2783: dup
    2784: iconst_3
    2785: new           #42                 // class gga
    2788: dup
    2789: ldc           #121                // float 0.7083f
    2791: ldc           #131                // float -50.0f
    2793: fconst_0
    2794: fconst_0
    2795: invokestatic  #47                 // Method ggc.b:(FFF)Lorg/joml/Vector3f;
    2798: getstatic     #50                 // Field gfy$b.a:Lgfy$a;
    2801: invokespecial #53                 // Method gga."<init>":(FLorg/joml/Vector3fc;Lgfy$a;)V
    2804: aastore
    2805: dup
    2806: iconst_4
    2807: new           #42                 // class gga
    2810: dup
    2811: ldc           #122                // float 0.9583f
    2813: fconst_0
    2814: fconst_0
    2815: fconst_0
    2816: invokestatic  #47                 // Method ggc.b:(FFF)Lorg/joml/Vector3f;
    2819: getstatic     #50                 // Field gfy$b.a:Lgfy$a;
    2822: invokespecial #53                 // Method gga."<init>":(FLorg/joml/Vector3fc;Lgfy$a;)V
    2825: aastore
    2826: dup
    2827: iconst_5
    2828: new           #42                 // class gga
    2831: dup
    2832: ldc           #129                // float 1.2083f
    2834: fconst_0
    2835: fconst_0
    2836: fconst_0
    2837: invokestatic  #47                 // Method ggc.b:(FFF)Lorg/joml/Vector3f;
    2840: getstatic     #50                 // Field gfy$b.a:Lgfy$a;
    2843: invokespecial #53                 // Method gga."<init>":(FLorg/joml/Vector3fc;Lgfy$a;)V
    2846: aastore
    2847: dup
    2848: bipush        6
    2850: new           #42                 // class gga
    2853: dup
    2854: ldc           #113                // float 1.4583f
    2856: ldc           #132                // float 50.0f
    2858: fconst_0
    2859: fconst_0
    2860: invokestatic  #47                 // Method ggc.b:(FFF)Lorg/joml/Vector3f;
    2863: getstatic     #50                 // Field gfy$b.a:Lgfy$a;
    2866: invokespecial #53                 // Method gga."<init>":(FLorg/joml/Vector3fc;Lgfy$a;)V
    2869: aastore
    2870: invokespecial #57                 // Method gfy."<init>":(Lgfy$c;[Lgga;)V
    2873: invokevirtual #60                 // Method gfz$a.a:(Ljava/lang/String;Lgfy;)Lgfz$a;
    2876: ldc           #89                 // String left_hind_leg
    2878: new           #14                 // class gfy
    2881: dup
    2882: getstatic     #62                 // Field gfy$d.a:Lgfy$c;
    2885: bipush        7
    2887: anewarray     #42                 // class gga
    2890: dup
    2891: iconst_0
    2892: new           #42                 // class gga
    2895: dup
    2896: fconst_0
    2897: fconst_0
    2898: fconst_0
    2899: ldc           #137                // float -0.25f
    2901: invokestatic  #64                 // Method ggc.a:(FFF)Lorg/joml/Vector3f;
    2904: getstatic     #50                 // Field gfy$b.a:Lgfy$a;
    2907: invokespecial #53                 // Method gga."<init>":(FLorg/joml/Vector3fc;Lgfy$a;)V
    2910: aastore
    2911: dup
    2912: iconst_1
    2913: new           #42                 // class gga
    2916: dup
    2917: ldc           #69                 // float 0.25f
    2919: fconst_0
    2920: fconst_0
    2921: ldc           #96                 // float -0.5f
    2923: invokestatic  #64                 // Method ggc.a:(FFF)Lorg/joml/Vector3f;
    2926: getstatic     #50                 // Field gfy$b.a:Lgfy$a;
    2929: invokespecial #53                 // Method gga."<init>":(FLorg/joml/Vector3fc;Lgfy$a;)V
    2932: aastore
    2933: dup
    2934: iconst_2
    2935: new           #42                 // class gga
    2938: dup
    2939: ldc           #136                // float 0.5417f
    2941: fconst_0
    2942: fconst_1
    2943: ldc           #135                // float -0.18f
    2945: invokestatic  #64                 // Method ggc.a:(FFF)Lorg/joml/Vector3f;
    2948: getstatic     #50                 // Field gfy$b.a:Lgfy$a;
    2951: invokespecial #53                 // Method gga."<init>":(FLorg/joml/Vector3fc;Lgfy$a;)V
    2954: aastore
    2955: dup
    2956: iconst_3
    2957: new           #42                 // class gga
    2960: dup
    2961: ldc           #121                // float 0.7083f
    2963: fconst_0
    2964: fconst_0
    2965: fconst_0
    2966: invokestatic  #64                 // Method ggc.a:(FFF)Lorg/joml/Vector3f;
    2969: getstatic     #50                 // Field gfy$b.a:Lgfy$a;
    2972: invokespecial #53                 // Method gga."<init>":(FLorg/joml/Vector3fc;Lgfy$a;)V
    2975: aastore
    2976: dup
    2977: iconst_4
    2978: new           #42                 // class gga
    2981: dup
    2982: ldc           #122                // float 0.9583f
    2984: fconst_0
    2985: fconst_0
    2986: ldc           #96                 // float -0.5f
    2988: invokestatic  #64                 // Method ggc.a:(FFF)Lorg/joml/Vector3f;
    2991: getstatic     #50                 // Field gfy$b.a:Lgfy$a;
    2994: invokespecial #53                 // Method gga."<init>":(FLorg/joml/Vector3fc;Lgfy$a;)V
    2997: aastore
    2998: dup
    2999: iconst_5
    3000: new           #42                 // class gga
    3003: dup
    3004: ldc           #129                // float 1.2083f
    3006: fconst_0
    3007: fconst_0
    3008: fconst_0
    3009: invokestatic  #64                 // Method ggc.a:(FFF)Lorg/joml/Vector3f;
    3012: getstatic     #50                 // Field gfy$b.a:Lgfy$a;
    3015: invokespecial #53                 // Method gga."<init>":(FLorg/joml/Vector3fc;Lgfy$a;)V
    3018: aastore
    3019: dup
    3020: bipush        6
    3022: new           #42                 // class gga
    3025: dup
    3026: ldc           #113                // float 1.4583f
    3028: fconst_0
    3029: fconst_0
    3030: ldc           #137                // float -0.25f
    3032: invokestatic  #64                 // Method ggc.a:(FFF)Lorg/joml/Vector3f;
    3035: getstatic     #50                 // Field gfy$b.a:Lgfy$a;
    3038: invokespecial #53                 // Method gga."<init>":(FLorg/joml/Vector3fc;Lgfy$a;)V
    3041: aastore
    3042: invokespecial #57                 // Method gfy."<init>":(Lgfy$c;[Lgga;)V
    3045: invokevirtual #60                 // Method gfz$a.a:(Ljava/lang/String;Lgfy;)Lgfz$a;
    3048: ldc           #92                 // String right_front_leg
    3050: new           #14                 // class gfy
    3053: dup
    3054: getstatic     #40                 // Field gfy$d.b:Lgfy$c;
    3057: bipush        7
    3059: anewarray     #42                 // class gga
    3062: dup
    3063: iconst_0
    3064: new           #42                 // class gga
    3067: dup
    3068: fconst_0
    3069: ldc           #132                // float 50.0f
    3071: fconst_0
    3072: fconst_0
    3073: invokestatic  #47                 // Method ggc.b:(FFF)Lorg/joml/Vector3f;
    3076: getstatic     #50                 // Field gfy$b.a:Lgfy$a;
    3079: invokespecial #53                 // Method gga."<init>":(FLorg/joml/Vector3fc;Lgfy$a;)V
    3082: aastore
    3083: dup
    3084: iconst_1
    3085: new           #42                 // class gga
    3088: dup
    3089: ldc           #78                 // float 0.2917f
    3091: ldc           #132                // float 50.0f
    3093: fconst_0
    3094: fconst_0
    3095: invokestatic  #47                 // Method ggc.b:(FFF)Lorg/joml/Vector3f;
    3098: getstatic     #50                 // Field gfy$b.a:Lgfy$a;
    3101: invokespecial #53                 // Method gga."<init>":(FLorg/joml/Vector3fc;Lgfy$a;)V
    3104: aastore
    3105: dup
    3106: iconst_2
    3107: new           #42                 // class gga
    3110: dup
    3111: ldc           #136                // float 0.5417f
    3113: ldc           #134                // float -20.0f
    3115: fconst_0
    3116: fconst_0
    3117: invokestatic  #47                 // Method ggc.b:(FFF)Lorg/joml/Vector3f;
    3120: getstatic     #50                 // Field gfy$b.a:Lgfy$a;
    3123: invokespecial #53                 // Method gga."<init>":(FLorg/joml/Vector3fc;Lgfy$a;)V
    3126: aastore
    3127: dup
    3128: iconst_3
    3129: new           #42                 // class gga
    3132: dup
    3133: ldc           #121                // float 0.7083f
    3135: ldc           #131                // float -50.0f
    3137: fconst_0
    3138: fconst_0
    3139: invokestatic  #47                 // Method ggc.b:(FFF)Lorg/joml/Vector3f;
    3142: getstatic     #50                 // Field gfy$b.a:Lgfy$a;
    3145: invokespecial #53                 // Method gga."<init>":(FLorg/joml/Vector3fc;Lgfy$a;)V
    3148: aastore
    3149: dup
    3150: iconst_4
    3151: new           #42                 // class gga
    3154: dup
    3155: ldc           #122                // float 0.9583f
    3157: fconst_0
    3158: fconst_0
    3159: fconst_0
    3160: invokestatic  #47                 // Method ggc.b:(FFF)Lorg/joml/Vector3f;
    3163: getstatic     #50                 // Field gfy$b.a:Lgfy$a;
    3166: invokespecial #53                 // Method gga."<init>":(FLorg/joml/Vector3fc;Lgfy$a;)V
    3169: aastore
    3170: dup
    3171: iconst_5
    3172: new           #42                 // class gga
    3175: dup
    3176: ldc           #129                // float 1.2083f
    3178: fconst_0
    3179: fconst_0
    3180: fconst_0
    3181: invokestatic  #47                 // Method ggc.b:(FFF)Lorg/joml/Vector3f;
    3184: getstatic     #50                 // Field gfy$b.a:Lgfy$a;
    3187: invokespecial #53                 // Method gga."<init>":(FLorg/joml/Vector3fc;Lgfy$a;)V
    3190: aastore
    3191: dup
    3192: bipush        6
    3194: new           #42                 // class gga
    3197: dup
    3198: ldc           #113                // float 1.4583f
    3200: ldc           #132                // float 50.0f
    3202: fconst_0
    3203: fconst_0
    3204: invokestatic  #47                 // Method ggc.b:(FFF)Lorg/joml/Vector3f;
    3207: getstatic     #50                 // Field gfy$b.a:Lgfy$a;
    3210: invokespecial #53                 // Method gga."<init>":(FLorg/joml/Vector3fc;Lgfy$a;)V
    3213: aastore
    3214: invokespecial #57                 // Method gfy."<init>":(Lgfy$c;[Lgga;)V
    3217: invokevirtual #60                 // Method gfz$a.a:(Ljava/lang/String;Lgfy;)Lgfz$a;
    3220: ldc           #92                 // String right_front_leg
    3222: new           #14                 // class gfy
    3225: dup
    3226: getstatic     #62                 // Field gfy$d.a:Lgfy$c;
    3229: bipush        7
    3231: anewarray     #42                 // class gga
    3234: dup
    3235: iconst_0
    3236: new           #42                 // class gga
    3239: dup
    3240: fconst_0
    3241: fconst_0
    3242: fconst_0
    3243: ldc           #137                // float -0.25f
    3245: invokestatic  #64                 // Method ggc.a:(FFF)Lorg/joml/Vector3f;
    3248: getstatic     #50                 // Field gfy$b.a:Lgfy$a;
    3251: invokespecial #53                 // Method gga."<init>":(FLorg/joml/Vector3fc;Lgfy$a;)V
    3254: aastore
    3255: dup
    3256: iconst_1
    3257: new           #42                 // class gga
    3260: dup
    3261: ldc           #69                 // float 0.25f
    3263: fconst_0
    3264: fconst_0
    3265: ldc           #96                 // float -0.5f
    3267: invokestatic  #64                 // Method ggc.a:(FFF)Lorg/joml/Vector3f;
    3270: getstatic     #50                 // Field gfy$b.a:Lgfy$a;
    3273: invokespecial #53                 // Method gga."<init>":(FLorg/joml/Vector3fc;Lgfy$a;)V
    3276: aastore
    3277: dup
    3278: iconst_2
    3279: new           #42                 // class gga
    3282: dup
    3283: ldc           #136                // float 0.5417f
    3285: fconst_0
    3286: fconst_1
    3287: ldc           #135                // float -0.18f
    3289: invokestatic  #64                 // Method ggc.a:(FFF)Lorg/joml/Vector3f;
    3292: getstatic     #50                 // Field gfy$b.a:Lgfy$a;
    3295: invokespecial #53                 // Method gga."<init>":(FLorg/joml/Vector3fc;Lgfy$a;)V
    3298: aastore
    3299: dup
    3300: iconst_3
    3301: new           #42                 // class gga
    3304: dup
    3305: ldc           #121                // float 0.7083f
    3307: fconst_0
    3308: fconst_0
    3309: fconst_0
    3310: invokestatic  #64                 // Method ggc.a:(FFF)Lorg/joml/Vector3f;
    3313: getstatic     #50                 // Field gfy$b.a:Lgfy$a;
    3316: invokespecial #53                 // Method gga."<init>":(FLorg/joml/Vector3fc;Lgfy$a;)V
    3319: aastore
    3320: dup
    3321: iconst_4
    3322: new           #42                 // class gga
    3325: dup
    3326: ldc           #122                // float 0.9583f
    3328: fconst_0
    3329: fconst_0
    3330: ldc           #96                 // float -0.5f
    3332: invokestatic  #64                 // Method ggc.a:(FFF)Lorg/joml/Vector3f;
    3335: getstatic     #50                 // Field gfy$b.a:Lgfy$a;
    3338: invokespecial #53                 // Method gga."<init>":(FLorg/joml/Vector3fc;Lgfy$a;)V
    3341: aastore
    3342: dup
    3343: iconst_5
    3344: new           #42                 // class gga
    3347: dup
    3348: ldc           #129                // float 1.2083f
    3350: fconst_0
    3351: fconst_0
    3352: fconst_0
    3353: invokestatic  #64                 // Method ggc.a:(FFF)Lorg/joml/Vector3f;
    3356: getstatic     #50                 // Field gfy$b.a:Lgfy$a;
    3359: invokespecial #53                 // Method gga."<init>":(FLorg/joml/Vector3fc;Lgfy$a;)V
    3362: aastore
    3363: dup
    3364: bipush        6
    3366: new           #42                 // class gga
    3369: dup
    3370: ldc           #113                // float 1.4583f
    3372: fconst_0
    3373: fconst_0
    3374: ldc           #137                // float -0.25f
    3376: invokestatic  #64                 // Method ggc.a:(FFF)Lorg/joml/Vector3f;
    3379: getstatic     #50                 // Field gfy$b.a:Lgfy$a;
    3382: invokespecial #53                 // Method gga."<init>":(FLorg/joml/Vector3fc;Lgfy$a;)V
    3385: aastore
    3386: invokespecial #57                 // Method gfy."<init>":(Lgfy$c;[Lgga;)V
    3389: invokevirtual #60                 // Method gfz$a.a:(Ljava/lang/String;Lgfy;)Lgfz$a;
    3392: ldc           #100                // String left_front_leg
    3394: new           #14                 // class gfy
    3397: dup
    3398: getstatic     #40                 // Field gfy$d.b:Lgfy$c;
    3401: bipush        7
    3403: anewarray     #42                 // class gga
    3406: dup
    3407: iconst_0
    3408: new           #42                 // class gga
    3411: dup
    3412: fconst_0
    3413: ldc           #131                // float -50.0f
    3415: fconst_0
    3416: fconst_0
    3417: invokestatic  #47                 // Method ggc.b:(FFF)Lorg/joml/Vector3f;
    3420: getstatic     #50                 // Field gfy$b.a:Lgfy$a;
    3423: invokespecial #53                 // Method gga."<init>":(FLorg/joml/Vector3fc;Lgfy$a;)V
    3426: aastore
    3427: dup
    3428: iconst_1
    3429: new           #42                 // class gga
    3432: dup
    3433: ldc           #69                 // float 0.25f
    3435: fconst_0
    3436: fconst_0
    3437: fconst_0
    3438: invokestatic  #47                 // Method ggc.b:(FFF)Lorg/joml/Vector3f;
    3441: getstatic     #50                 // Field gfy$b.a:Lgfy$a;
    3444: invokespecial #53                 // Method gga."<init>":(FLorg/joml/Vector3fc;Lgfy$a;)V
    3447: aastore
    3448: dup
    3449: iconst_2
    3450: new           #42                 // class gga
    3453: dup
    3454: ldc           #32                 // float 0.5f
    3456: fconst_0
    3457: fconst_0
    3458: fconst_0
    3459: invokestatic  #47                 // Method ggc.b:(FFF)Lorg/joml/Vector3f;
    3462: getstatic     #50                 // Field gfy$b.a:Lgfy$a;
    3465: invokespecial #53                 // Method gga."<init>":(FLorg/joml/Vector3fc;Lgfy$a;)V
    3468: aastore
    3469: dup
    3470: iconst_3
    3471: new           #42                 // class gga
    3474: dup
    3475: ldc           #128                // float 0.75f
    3477: ldc           #132                // float 50.0f
    3479: fconst_0
    3480: fconst_0
    3481: invokestatic  #47                 // Method ggc.b:(FFF)Lorg/joml/Vector3f;
    3484: getstatic     #50                 // Field gfy$b.a:Lgfy$a;
    3487: invokespecial #53                 // Method gga."<init>":(FLorg/joml/Vector3fc;Lgfy$a;)V
    3490: aastore
    3491: dup
    3492: iconst_4
    3493: new           #42                 // class gga
    3496: dup
    3497: fconst_1
    3498: ldc           #132                // float 50.0f
    3500: fconst_0
    3501: fconst_0
    3502: invokestatic  #47                 // Method ggc.b:(FFF)Lorg/joml/Vector3f;
    3505: getstatic     #50                 // Field gfy$b.a:Lgfy$a;
    3508: invokespecial #53                 // Method gga."<init>":(FLorg/joml/Vector3fc;Lgfy$a;)V
    3511: aastore
    3512: dup
    3513: iconst_5
    3514: new           #42                 // class gga
    3517: dup
    3518: ldc           #133                // float 1.2917f
    3520: ldc           #134                // float -20.0f
    3522: fconst_0
    3523: fconst_0
    3524: invokestatic  #47                 // Method ggc.b:(FFF)Lorg/joml/Vector3f;
    3527: getstatic     #50                 // Field gfy$b.a:Lgfy$a;
    3530: invokespecial #53                 // Method gga."<init>":(FLorg/joml/Vector3fc;Lgfy$a;)V
    3533: aastore
    3534: dup
    3535: bipush        6
    3537: new           #42                 // class gga
    3540: dup
    3541: ldc           #113                // float 1.4583f
    3543: ldc           #131                // float -50.0f
    3545: fconst_0
    3546: fconst_0
    3547: invokestatic  #47                 // Method ggc.b:(FFF)Lorg/joml/Vector3f;
    3550: getstatic     #50                 // Field gfy$b.a:Lgfy$a;
    3553: invokespecial #53                 // Method gga."<init>":(FLorg/joml/Vector3fc;Lgfy$a;)V
    3556: aastore
    3557: invokespecial #57                 // Method gfy."<init>":(Lgfy$c;[Lgga;)V
    3560: invokevirtual #60                 // Method gfz$a.a:(Ljava/lang/String;Lgfy;)Lgfz$a;
    3563: ldc           #100                // String left_front_leg
    3565: new           #14                 // class gfy
    3568: dup
    3569: getstatic     #62                 // Field gfy$d.a:Lgfy$c;
    3572: bipush        6
    3574: anewarray     #42                 // class gga
    3577: dup
    3578: iconst_0
    3579: new           #42                 // class gga
    3582: dup
    3583: fconst_0
    3584: fconst_0
    3585: fconst_0
    3586: fconst_0
    3587: invokestatic  #64                 // Method ggc.a:(FFF)Lorg/joml/Vector3f;
    3590: getstatic     #50                 // Field gfy$b.a:Lgfy$a;
    3593: invokespecial #53                 // Method gga."<init>":(FLorg/joml/Vector3fc;Lgfy$a;)V
    3596: aastore
    3597: dup
    3598: iconst_1
    3599: new           #42                 // class gga
    3602: dup
    3603: ldc           #69                 // float 0.25f
    3605: fconst_0
    3606: fconst_0
    3607: ldc           #96                 // float -0.5f
    3609: invokestatic  #64                 // Method ggc.a:(FFF)Lorg/joml/Vector3f;
    3612: getstatic     #50                 // Field gfy$b.a:Lgfy$a;
    3615: invokespecial #53                 // Method gga."<init>":(FLorg/joml/Vector3fc;Lgfy$a;)V
    3618: aastore
    3619: dup
    3620: iconst_2
    3621: new           #42                 // class gga
    3624: dup
    3625: ldc           #32                 // float 0.5f
    3627: fconst_0
    3628: fconst_0
    3629: fconst_0
    3630: invokestatic  #64                 // Method ggc.a:(FFF)Lorg/joml/Vector3f;
    3633: getstatic     #50                 // Field gfy$b.a:Lgfy$a;
    3636: invokespecial #53                 // Method gga."<init>":(FLorg/joml/Vector3fc;Lgfy$a;)V
    3639: aastore
    3640: dup
    3641: iconst_3
    3642: new           #42                 // class gga
    3645: dup
    3646: fconst_1
    3647: fconst_0
    3648: fconst_0
    3649: ldc           #96                 // float -0.5f
    3651: invokestatic  #64                 // Method ggc.a:(FFF)Lorg/joml/Vector3f;
    3654: getstatic     #50                 // Field gfy$b.a:Lgfy$a;
    3657: invokespecial #53                 // Method gga."<init>":(FLorg/joml/Vector3fc;Lgfy$a;)V
    3660: aastore
    3661: dup
    3662: iconst_4
    3663: new           #42                 // class gga
    3666: dup
    3667: ldc           #133                // float 1.2917f
    3669: fconst_0
    3670: fconst_1
    3671: ldc           #135                // float -0.18f
    3673: invokestatic  #64                 // Method ggc.a:(FFF)Lorg/joml/Vector3f;
    3676: getstatic     #50                 // Field gfy$b.a:Lgfy$a;
    3679: invokespecial #53                 // Method gga."<init>":(FLorg/joml/Vector3fc;Lgfy$a;)V
    3682: aastore
    3683: dup
    3684: iconst_5
    3685: new           #42                 // class gga
    3688: dup
    3689: ldc           #113                // float 1.4583f
    3691: fconst_0
    3692: fconst_0
    3693: fconst_0
    3694: invokestatic  #64                 // Method ggc.a:(FFF)Lorg/joml/Vector3f;
    3697: getstatic     #50                 // Field gfy$b.a:Lgfy$a;
    3700: invokespecial #53                 // Method gga."<init>":(FLorg/joml/Vector3fc;Lgfy$a;)V
    3703: aastore
    3704: invokespecial #57                 // Method gfy."<init>":(Lgfy$c;[Lgga;)V
    3707: invokevirtual #60                 // Method gfz$a.a:(Ljava/lang/String;Lgfy;)Lgfz$a;
    3710: ldc           #75                 // String head
    3712: new           #14                 // class gfy
    3715: dup
    3716: getstatic     #40                 // Field gfy$d.b:Lgfy$c;
    3719: bipush        7
    3721: anewarray     #42                 // class gga
    3724: dup
    3725: iconst_0
    3726: new           #42                 // class gga
    3729: dup
    3730: fconst_0
    3731: fconst_0
    3732: fconst_0
    3733: fconst_0
    3734: invokestatic  #47                 // Method ggc.b:(FFF)Lorg/joml/Vector3f;
    3737: getstatic     #50                 // Field gfy$b.a:Lgfy$a;
    3740: invokespecial #53                 // Method gga."<init>":(FLorg/joml/Vector3fc;Lgfy$a;)V
    3743: aastore
    3744: dup
    3745: iconst_1
    3746: new           #42                 // class gga
    3749: dup
    3750: ldc           #69                 // float 0.25f
    3752: fconst_0
    3753: fconst_0
    3754: ldc           #105                // float -2.5f
    3756: invokestatic  #47                 // Method ggc.b:(FFF)Lorg/joml/Vector3f;
    3759: getstatic     #50                 // Field gfy$b.a:Lgfy$a;
    3762: invokespecial #53                 // Method gga."<init>":(FLorg/joml/Vector3fc;Lgfy$a;)V
    3765: aastore
    3766: dup
    3767: iconst_2
    3768: new           #42                 // class gga
    3771: dup
    3772: ldc           #32                 // float 0.5f
    3774: fconst_0
    3775: fconst_0
    3776: fconst_0
    3777: invokestatic  #47                 // Method ggc.b:(FFF)Lorg/joml/Vector3f;
    3780: getstatic     #50                 // Field gfy$b.a:Lgfy$a;
    3783: invokespecial #53                 // Method gga."<init>":(FLorg/joml/Vector3fc;Lgfy$a;)V
    3786: aastore
    3787: dup
    3788: iconst_3
    3789: new           #42                 // class gga
    3792: dup
    3793: ldc           #121                // float 0.7083f
    3795: fconst_0
    3796: fconst_0
    3797: fconst_0
    3798: invokestatic  #47                 // Method ggc.b:(FFF)Lorg/joml/Vector3f;
    3801: getstatic     #50                 // Field gfy$b.a:Lgfy$a;
    3804: invokespecial #53                 // Method gga."<init>":(FLorg/joml/Vector3fc;Lgfy$a;)V
    3807: aastore
    3808: dup
    3809: iconst_4
    3810: new           #42                 // class gga
    3813: dup
    3814: fconst_1
    3815: fconst_0
    3816: fconst_0
    3817: ldc           #138                // float 2.5f
    3819: invokestatic  #47                 // Method ggc.b:(FFF)Lorg/joml/Vector3f;
    3822: getstatic     #50                 // Field gfy$b.a:Lgfy$a;
    3825: invokespecial #53                 // Method gga."<init>":(FLorg/joml/Vector3fc;Lgfy$a;)V
    3828: aastore
    3829: dup
    3830: iconst_5
    3831: new           #42                 // class gga
    3834: dup
    3835: ldc           #125                // float 1.25f
    3837: fconst_0
    3838: fconst_0
    3839: fconst_0
    3840: invokestatic  #47                 // Method ggc.b:(FFF)Lorg/joml/Vector3f;
    3843: getstatic     #50                 // Field gfy$b.a:Lgfy$a;
    3846: invokespecial #53                 // Method gga."<init>":(FLorg/joml/Vector3fc;Lgfy$a;)V
    3849: aastore
    3850: dup
    3851: bipush        6
    3853: new           #42                 // class gga
    3856: dup
    3857: ldc           #113                // float 1.4583f
    3859: fconst_0
    3860: fconst_0
    3861: fconst_0
    3862: invokestatic  #47                 // Method ggc.b:(FFF)Lorg/joml/Vector3f;
    3865: getstatic     #50                 // Field gfy$b.a:Lgfy$a;
    3868: invokespecial #53                 // Method gga."<init>":(FLorg/joml/Vector3fc;Lgfy$a;)V
    3871: aastore
    3872: invokespecial #57                 // Method gfy."<init>":(Lgfy$c;[Lgga;)V
    3875: invokevirtual #60                 // Method gfz$a.a:(Ljava/lang/String;Lgfy;)Lgfz$a;
    3878: invokevirtual #110                // Method gfz$a.b:()Lgfz;
    3881: putstatic     #140                // Field b:Lgfz;
    3884: ldc           #138                // float 2.5f
    3886: invokestatic  #35                 // Method gfz$a.a:(F)Lgfz$a;
    3889: ldc           #75                 // String head
    3891: new           #14                 // class gfy
    3894: dup
    3895: getstatic     #40                 // Field gfy$d.b:Lgfy$c;
    3898: bipush        12
    3900: anewarray     #42                 // class gga
    3903: dup
    3904: iconst_0
    3905: new           #42                 // class gga
    3908: dup
    3909: fconst_0
    3910: ldc           #141                // float -70.0f
    3912: fconst_0
    3913: fconst_0
    3914: invokestatic  #47                 // Method ggc.b:(FFF)Lorg/joml/Vector3f;
    3917: getstatic     #50                 // Field gfy$b.a:Lgfy$a;
    3920: invokespecial #53                 // Method gga."<init>":(FLorg/joml/Vector3fc;Lgfy$a;)V
    3923: aastore
    3924: dup
    3925: iconst_1
    3926: new           #42                 // class gga
    3929: dup
    3930: ldc           #142                // float 0.15f
    3932: ldc           #143                // float -65.0f
    3934: fconst_0
    3935: fconst_0
    3936: invokestatic  #47                 // Method ggc.b:(FFF)Lorg/joml/Vector3f;
    3939: getstatic     #50                 // Field gfy$b.a:Lgfy$a;
    3942: invokespecial #53                 // Method gga."<init>":(FLorg/joml/Vector3fc;Lgfy$a;)V
    3945: aastore
    3946: dup
    3947: iconst_2
    3948: new           #42                 // class gga
    3951: dup
    3952: ldc           #144                // float 0.4f
    3954: ldc           #131                // float -50.0f
    3956: fconst_0
    3957: fconst_0
    3958: invokestatic  #47                 // Method ggc.b:(FFF)Lorg/joml/Vector3f;
    3961: getstatic     #50                 // Field gfy$b.a:Lgfy$a;
    3964: invokespecial #53                 // Method gga."<init>":(FLorg/joml/Vector3fc;Lgfy$a;)V
    3967: aastore
    3968: dup
    3969: iconst_3
    3970: new           #42                 // class gga
    3973: dup
    3974: ldc           #32                 // float 0.5f
    3976: fconst_0
    3977: fconst_0
    3978: fconst_0
    3979: invokestatic  #47                 // Method ggc.b:(FFF)Lorg/joml/Vector3f;
    3982: getstatic     #50                 // Field gfy$b.a:Lgfy$a;
    3985: invokespecial #53                 // Method gga."<init>":(FLorg/joml/Vector3fc;Lgfy$a;)V
    3988: aastore
    3989: dup
    3990: iconst_4
    3991: new           #42                 // class gga
    3994: dup
    3995: ldc           #145                // float 0.7f
    3997: fconst_0
    3998: fconst_0
    3999: fconst_0
    4000: invokestatic  #47                 // Method ggc.b:(FFF)Lorg/joml/Vector3f;
    4003: getstatic     #50                 // Field gfy$b.a:Lgfy$a;
    4006: invokespecial #53                 // Method gga."<init>":(FLorg/joml/Vector3fc;Lgfy$a;)V
    4009: aastore
    4010: dup
    4011: iconst_5
    4012: new           #42                 // class gga
    4015: dup
    4016: ldc           #146                // float 0.9f
    4018: ldc           #147                // float -7.5f
    4020: fconst_0
    4021: ldc           #148                // float 45.0f
    4023: invokestatic  #47                 // Method ggc.b:(FFF)Lorg/joml/Vector3f;
    4026: getstatic     #118                // Field gfy$b.b:Lgfy$a;
    4029: invokespecial #53                 // Method gga."<init>":(FLorg/joml/Vector3fc;Lgfy$a;)V
    4032: aastore
    4033: dup
    4034: bipush        6
    4036: new           #42                 // class gga
    4039: dup
    4040: ldc           #149                // float 1.15f
    4042: ldc           #147                // float -7.5f
    4044: fconst_0
    4045: ldc           #148                // float 45.0f
    4047: invokestatic  #47                 // Method ggc.b:(FFF)Lorg/joml/Vector3f;
    4050: getstatic     #50                 // Field gfy$b.a:Lgfy$a;
    4053: invokespecial #53                 // Method gga."<init>":(FLorg/joml/Vector3fc;Lgfy$a;)V
    4056: aastore
    4057: dup
    4058: bipush        7
    4060: new           #42                 // class gga
    4063: dup
    4064: ldc           #150                // float 1.3f
    4066: ldc           #151                // float -0.8639f
    4068: ldc           #152                // float -1.4959f
    4070: ldc           #153                // float -39.1287f
    4072: invokestatic  #47                 // Method ggc.b:(FFF)Lorg/joml/Vector3f;
    4075: getstatic     #118                // Field gfy$b.b:Lgfy$a;
    4078: invokespecial #53                 // Method gga."<init>":(FLorg/joml/Vector3fc;Lgfy$a;)V
    4081: aastore
    4082: dup
    4083: bipush        8
    4085: new           #42                 // class gga
    4088: dup
    4089: ldc           #154                // float 1.6f
    4091: ldc           #151                // float -0.8639f
    4093: ldc           #152                // float -1.4959f
    4095: ldc           #153                // float -39.1287f
    4097: invokestatic  #47                 // Method ggc.b:(FFF)Lorg/joml/Vector3f;
    4100: getstatic     #50                 // Field gfy$b.a:Lgfy$a;
    4103: invokespecial #53                 // Method gga."<init>":(FLorg/joml/Vector3fc;Lgfy$a;)V
    4106: aastore
    4107: dup
    4108: bipush        9
    4110: new           #42                 // class gga
    4113: dup
    4114: ldc           #155                // float 1.75f
    4116: fconst_0
    4117: fconst_0
    4118: fconst_0
    4119: invokestatic  #47                 // Method ggc.b:(FFF)Lorg/joml/Vector3f;
    4122: getstatic     #50                 // Field gfy$b.a:Lgfy$a;
    4125: invokespecial #53                 // Method gga."<init>":(FLorg/joml/Vector3fc;Lgfy$a;)V
    4128: aastore
    4129: dup
    4130: bipush        10
    4132: new           #42                 // class gga
    4135: dup
    4136: ldc           #156                // float 1.8f
    4138: ldc           #157                // float -25.0f
    4140: fconst_0
    4141: fconst_0
    4142: invokestatic  #47                 // Method ggc.b:(FFF)Lorg/joml/Vector3f;
    4145: getstatic     #50                 // Field gfy$b.a:Lgfy$a;
    4148: invokespecial #53                 // Method gga."<init>":(FLorg/joml/Vector3fc;Lgfy$a;)V
    4151: aastore
    4152: dup
    4153: bipush        11
    4155: new           #42                 // class gga
    4158: dup
    4159: ldc           #158                // float 1.85f
    4161: ldc           #141                // float -70.0f
    4163: fconst_0
    4164: fconst_0
    4165: invokestatic  #47                 // Method ggc.b:(FFF)Lorg/joml/Vector3f;
    4168: getstatic     #50                 // Field gfy$b.a:Lgfy$a;
    4171: invokespecial #53                 // Method gga."<init>":(FLorg/joml/Vector3fc;Lgfy$a;)V
    4174: aastore
    4175: invokespecial #57                 // Method gfy."<init>":(Lgfy$c;[Lgga;)V
    4178: invokevirtual #60                 // Method gfz$a.a:(Ljava/lang/String;Lgfy;)Lgfz$a;
    4181: ldc           #75                 // String head
    4183: new           #14                 // class gfy
    4186: dup
    4187: getstatic     #62                 // Field gfy$d.a:Lgfy$c;
    4190: bipush        15
    4192: anewarray     #42                 // class gga
    4195: dup
    4196: iconst_0
    4197: new           #42                 // class gga
    4200: dup
    4201: fconst_0
    4202: fconst_0
    4203: fconst_1
    4204: ldc           #79                 // float 7.0f
    4206: invokestatic  #64                 // Method ggc.a:(FFF)Lorg/joml/Vector3f;
    4209: getstatic     #50                 // Field gfy$b.a:Lgfy$a;
    4212: invokespecial #53                 // Method gga."<init>":(FLorg/joml/Vector3fc;Lgfy$a;)V
    4215: aastore
    4216: dup
    4217: iconst_1
    4218: new           #42                 // class gga
    4221: dup
    4222: ldc           #159                // float 0.05f
    4224: fconst_0
    4225: fconst_1
    4226: ldc           #160                // float 4.0f
    4228: invokestatic  #64                 // Method ggc.a:(FFF)Lorg/joml/Vector3f;
    4231: getstatic     #50                 // Field gfy$b.a:Lgfy$a;
    4234: invokespecial #53                 // Method gga."<init>":(FLorg/joml/Vector3fc;Lgfy$a;)V
    4237: aastore
    4238: dup
    4239: iconst_2
    4240: new           #42                 // class gga
    4243: dup
    4244: ldc           #142                // float 0.15f
    4246: fconst_0
    4247: fconst_1
    4248: ldc           #160                // float 4.0f
    4250: invokestatic  #64                 // Method ggc.a:(FFF)Lorg/joml/Vector3f;
    4253: getstatic     #50                 // Field gfy$b.a:Lgfy$a;
    4256: invokespecial #53                 // Method gga."<init>":(FLorg/joml/Vector3fc;Lgfy$a;)V
    4259: aastore
    4260: dup
    4261: iconst_3
    4262: new           #42                 // class gga
    4265: dup
    4266: ldc           #69                 // float 0.25f
    4268: fconst_0
    4269: fconst_1
    4270: ldc           #65                 // float 5.0f
    4272: invokestatic  #64                 // Method ggc.a:(FFF)Lorg/joml/Vector3f;
    4275: getstatic     #50                 // Field gfy$b.a:Lgfy$a;
    4278: invokespecial #53                 // Method gga."<init>":(FLorg/joml/Vector3fc;Lgfy$a;)V
    4281: aastore
    4282: dup
    4283: iconst_4
    4284: new           #42                 // class gga
    4287: dup
    4288: ldc           #161                // float 0.35f
    4290: fconst_0
    4291: fconst_1
    4292: ldc           #162                // float 0.2f
    4294: invokestatic  #64                 // Method ggc.a:(FFF)Lorg/joml/Vector3f;
    4297: getstatic     #50                 // Field gfy$b.a:Lgfy$a;
    4300: invokespecial #53                 // Method gga."<init>":(FLorg/joml/Vector3fc;Lgfy$a;)V
    4303: aastore
    4304: dup
    4305: iconst_5
    4306: new           #42                 // class gga
    4309: dup
    4310: ldc           #144                // float 0.4f
    4312: fconst_0
    4313: fconst_1
    4314: ldc           #162                // float 0.2f
    4316: invokestatic  #64                 // Method ggc.a:(FFF)Lorg/joml/Vector3f;
    4319: getstatic     #50                 // Field gfy$b.a:Lgfy$a;
    4322: invokespecial #53                 // Method gga."<init>":(FLorg/joml/Vector3fc;Lgfy$a;)V
    4325: aastore
    4326: dup
    4327: bipush        6
    4329: new           #42                 // class gga
    4332: dup
    4333: ldc           #32                 // float 0.5f
    4335: fconst_0
    4336: ldc           #163                // float 2.1f
    4338: ldc           #164                // float 1.2f
    4340: invokestatic  #64                 // Method ggc.a:(FFF)Lorg/joml/Vector3f;
    4343: getstatic     #50                 // Field gfy$b.a:Lgfy$a;
    4346: invokespecial #53                 // Method gga."<init>":(FLorg/joml/Vector3fc;Lgfy$a;)V
    4349: aastore
    4350: dup
    4351: bipush        7
    4353: new           #42                 // class gga
    4356: dup
    4357: ldc           #107                // float 0.6f
    4359: fconst_0
    4360: ldc           #165                // float 1.1f
    4362: ldc           #162                // float 0.2f
    4364: invokestatic  #64                 // Method ggc.a:(FFF)Lorg/joml/Vector3f;
    4367: getstatic     #50                 // Field gfy$b.a:Lgfy$a;
    4370: invokespecial #53                 // Method gga."<init>":(FLorg/joml/Vector3fc;Lgfy$a;)V
    4373: aastore
    4374: dup
    4375: bipush        8
    4377: new           #42                 // class gga
    4380: dup
    4381: ldc           #145                // float 0.7f
    4383: fconst_0
    4384: ldc           #165                // float 1.1f
    4386: ldc           #162                // float 0.2f
    4388: invokestatic  #64                 // Method ggc.a:(FFF)Lorg/joml/Vector3f;
    4391: getstatic     #50                 // Field gfy$b.a:Lgfy$a;
    4394: invokespecial #53                 // Method gga."<init>":(FLorg/joml/Vector3fc;Lgfy$a;)V
    4397: aastore
    4398: dup
    4399: bipush        9
    4401: new           #42                 // class gga
    4404: dup
    4405: ldc           #155                // float 1.75f
    4407: fconst_0
    4408: ldc           #165                // float 1.1f
    4410: ldc           #162                // float 0.2f
    4412: invokestatic  #64                 // Method ggc.a:(FFF)Lorg/joml/Vector3f;
    4415: getstatic     #50                 // Field gfy$b.a:Lgfy$a;
    4418: invokespecial #53                 // Method gga."<init>":(FLorg/joml/Vector3fc;Lgfy$a;)V
    4421: aastore
    4422: dup
    4423: bipush        10
    4425: new           #42                 // class gga
    4428: dup
    4429: ldc           #156                // float 1.8f
    4431: fconst_0
    4432: ldc           #166                // float 0.1f
    4434: ldc           #162                // float 0.2f
    4436: invokestatic  #64                 // Method ggc.a:(FFF)Lorg/joml/Vector3f;
    4439: getstatic     #50                 // Field gfy$b.a:Lgfy$a;
    4442: invokespecial #53                 // Method gga."<init>":(FLorg/joml/Vector3fc;Lgfy$a;)V
    4445: aastore
    4446: dup
    4447: bipush        11
    4449: new           #42                 // class gga
    4452: dup
    4453: ldc           #167                // float 1.95f
    4455: fconst_0
    4456: ldc           #166                // float 0.1f
    4458: ldc           #168                // float 5.2f
    4460: invokestatic  #64                 // Method ggc.a:(FFF)Lorg/joml/Vector3f;
    4463: getstatic     #50                 // Field gfy$b.a:Lgfy$a;
    4466: invokespecial #53                 // Method gga."<init>":(FLorg/joml/Vector3fc;Lgfy$a;)V
    4469: aastore
    4470: dup
    4471: bipush        12
    4473: new           #42                 // class gga
    4476: dup
    4477: fconst_2
    4478: fconst_0
    4479: ldc           #166                // float 0.1f
    4481: ldc           #169                // float 7.2f
    4483: invokestatic  #64                 // Method ggc.a:(FFF)Lorg/joml/Vector3f;
    4486: getstatic     #50                 // Field gfy$b.a:Lgfy$a;
    4489: invokespecial #53                 // Method gga."<init>":(FLorg/joml/Vector3fc;Lgfy$a;)V
    4492: aastore
    4493: dup
    4494: bipush        13
    4496: new           #42                 // class gga
    4499: dup
    4500: ldc           #170                // float 2.15f
    4502: fconst_0
    4503: ldc           #166                // float 0.1f
    4505: ldc           #171                // float 8.2f
    4507: invokestatic  #64                 // Method ggc.a:(FFF)Lorg/joml/Vector3f;
    4510: getstatic     #50                 // Field gfy$b.a:Lgfy$a;
    4513: invokespecial #53                 // Method gga."<init>":(FLorg/joml/Vector3fc;Lgfy$a;)V
    4516: aastore
    4517: dup
    4518: bipush        14
    4520: new           #42                 // class gga
    4523: dup
    4524: ldc           #172                // float 2.3f
    4526: fconst_0
    4527: ldc           #166                // float 0.1f
    4529: ldc           #168                // float 5.2f
    4531: invokestatic  #64                 // Method ggc.a:(FFF)Lorg/joml/Vector3f;
    4534: getstatic     #50                 // Field gfy$b.a:Lgfy$a;
    4537: invokespecial #53                 // Method gga."<init>":(FLorg/joml/Vector3fc;Lgfy$a;)V
    4540: aastore
    4541: invokespecial #57                 // Method gfy."<init>":(Lgfy$c;[Lgga;)V
    4544: invokevirtual #60                 // Method gfz$a.a:(Ljava/lang/String;Lgfy;)Lgfz$a;
    4547: ldc           #81                 // String right_hind_leg
    4549: new           #14                 // class gfy
    4552: dup
    4553: getstatic     #62                 // Field gfy$d.a:Lgfy$c;
    4556: iconst_1
    4557: anewarray     #42                 // class gga
    4560: dup
    4561: iconst_0
    4562: new           #42                 // class gga
    4565: dup
    4566: fconst_0
    4567: fconst_0
    4568: ldc           #86                 // float 3.0f
    4570: ldc           #73                 // float -2.0f
    4572: invokestatic  #64                 // Method ggc.a:(FFF)Lorg/joml/Vector3f;
    4575: getstatic     #50                 // Field gfy$b.a:Lgfy$a;
    4578: invokespecial #53                 // Method gga."<init>":(FLorg/joml/Vector3fc;Lgfy$a;)V
    4581: aastore
    4582: invokespecial #57                 // Method gfy."<init>":(Lgfy$c;[Lgga;)V
    4585: invokevirtual #60                 // Method gfz$a.a:(Ljava/lang/String;Lgfy;)Lgfz$a;
    4588: ldc           #89                 // String left_hind_leg
    4590: new           #14                 // class gfy
    4593: dup
    4594: getstatic     #62                 // Field gfy$d.a:Lgfy$c;
    4597: iconst_1
    4598: anewarray     #42                 // class gga
    4601: dup
    4602: iconst_0
    4603: new           #42                 // class gga
    4606: dup
    4607: fconst_0
    4608: fconst_0
    4609: ldc           #86                 // float 3.0f
    4611: ldc           #73                 // float -2.0f
    4613: invokestatic  #64                 // Method ggc.a:(FFF)Lorg/joml/Vector3f;
    4616: getstatic     #50                 // Field gfy$b.a:Lgfy$a;
    4619: invokespecial #53                 // Method gga."<init>":(FLorg/joml/Vector3fc;Lgfy$a;)V
    4622: aastore
    4623: invokespecial #57                 // Method gfy."<init>":(Lgfy$c;[Lgga;)V
    4626: invokevirtual #60                 // Method gfz$a.a:(Ljava/lang/String;Lgfy;)Lgfz$a;
    4629: ldc           #92                 // String right_front_leg
    4631: new           #14                 // class gfy
    4634: dup
    4635: getstatic     #40                 // Field gfy$d.b:Lgfy$c;
    4638: bipush        7
    4640: anewarray     #42                 // class gga
    4643: dup
    4644: iconst_0
    4645: new           #42                 // class gga
    4648: dup
    4649: fconst_0
    4650: ldc           #173                // float -90.0f
    4652: fconst_0
    4653: fconst_0
    4654: invokestatic  #47                 // Method ggc.b:(FFF)Lorg/joml/Vector3f;
    4657: getstatic     #50                 // Field gfy$b.a:Lgfy$a;
    4660: invokespecial #53                 // Method gga."<init>":(FLorg/joml/Vector3fc;Lgfy$a;)V
    4663: aastore
    4664: dup
    4665: iconst_1
    4666: new           #42                 // class gga
    4669: dup
    4670: ldc           #174                // float 0.5833f
    4672: ldc           #173                // float -90.0f
    4674: fconst_0
    4675: fconst_0
    4676: invokestatic  #47                 // Method ggc.b:(FFF)Lorg/joml/Vector3f;
    4679: getstatic     #118                // Field gfy$b.b:Lgfy$a;
    4682: invokespecial #53                 // Method gga."<init>":(FLorg/joml/Vector3fc;Lgfy$a;)V
    4685: aastore
    4686: dup
    4687: iconst_2
    4688: new           #42                 // class gga
    4691: dup
    4692: ldc           #175                // float 0.8333f
    4694: ldc           #90                 // float -45.0f
    4696: fconst_0
    4697: fconst_0
    4698: invokestatic  #47                 // Method ggc.b:(FFF)Lorg/joml/Vector3f;
    4701: getstatic     #118                // Field gfy$b.b:Lgfy$a;
    4704: invokespecial #53                 // Method gga."<init>":(FLorg/joml/Vector3fc;Lgfy$a;)V
    4707: aastore
    4708: dup
    4709: iconst_3
    4710: new           #42                 // class gga
    4713: dup
    4714: fconst_1
    4715: ldc           #90                 // float -45.0f
    4717: fconst_0
    4718: fconst_0
    4719: invokestatic  #47                 // Method ggc.b:(FFF)Lorg/joml/Vector3f;
    4722: getstatic     #118                // Field gfy$b.b:Lgfy$a;
    4725: invokespecial #53                 // Method gga."<init>":(FLorg/joml/Vector3fc;Lgfy$a;)V
    4728: aastore
    4729: dup
    4730: iconst_4
    4731: new           #42                 // class gga
    4734: dup
    4735: ldc           #155                // float 1.75f
    4737: ldc           #90                 // float -45.0f
    4739: fconst_0
    4740: fconst_0
    4741: invokestatic  #47                 // Method ggc.b:(FFF)Lorg/joml/Vector3f;
    4744: getstatic     #118                // Field gfy$b.b:Lgfy$a;
    4747: invokespecial #53                 // Method gga."<init>":(FLorg/joml/Vector3fc;Lgfy$a;)V
    4750: aastore
    4751: dup
    4752: iconst_5
    4753: new           #42                 // class gga
    4756: dup
    4757: ldc           #156                // float 1.8f
    4759: ldc           #173                // float -90.0f
    4761: fconst_0
    4762: fconst_0
    4763: invokestatic  #47                 // Method ggc.b:(FFF)Lorg/joml/Vector3f;
    4766: getstatic     #118                // Field gfy$b.b:Lgfy$a;
    4769: invokespecial #53                 // Method gga."<init>":(FLorg/joml/Vector3fc;Lgfy$a;)V
    4772: aastore
    4773: dup
    4774: bipush        6
    4776: new           #42                 // class gga
    4779: dup
    4780: ldc           #167                // float 1.95f
    4782: ldc           #173                // float -90.0f
    4784: fconst_0
    4785: fconst_0
    4786: invokestatic  #47                 // Method ggc.b:(FFF)Lorg/joml/Vector3f;
    4789: getstatic     #118                // Field gfy$b.b:Lgfy$a;
    4792: invokespecial #53                 // Method gga."<init>":(FLorg/joml/Vector3fc;Lgfy$a;)V
    4795: aastore
    4796: invokespecial #57                 // Method gfy."<init>":(Lgfy$c;[Lgga;)V
    4799: invokevirtual #60                 // Method gfz$a.a:(Ljava/lang/String;Lgfy;)Lgfz$a;
    4802: ldc           #92                 // String right_front_leg
    4804: new           #14                 // class gfy
    4807: dup
    4808: getstatic     #62                 // Field gfy$d.a:Lgfy$c;
    4811: bipush        9
    4813: anewarray     #42                 // class gga
    4816: dup
    4817: iconst_0
    4818: new           #42                 // class gga
    4821: dup
    4822: fconst_0
    4823: ldc           #68                 // float -1.0f
    4825: fconst_2
    4826: fconst_2
    4827: invokestatic  #64                 // Method ggc.a:(FFF)Lorg/joml/Vector3f;
    4830: getstatic     #50                 // Field gfy$b.a:Lgfy$a;
    4833: invokespecial #53                 // Method gga."<init>":(FLorg/joml/Vector3fc;Lgfy$a;)V
    4836: aastore
    4837: dup
    4838: iconst_1
    4839: new           #42                 // class gga
    4842: dup
    4843: ldc           #174                // float 0.5833f
    4845: ldc           #68                 // float -1.0f
    4847: fconst_2
    4848: fconst_2
    4849: invokestatic  #64                 // Method ggc.a:(FFF)Lorg/joml/Vector3f;
    4852: getstatic     #118                // Field gfy$b.b:Lgfy$a;
    4855: invokespecial #53                 // Method gga."<init>":(FLorg/joml/Vector3fc;Lgfy$a;)V
    4858: aastore
    4859: dup
    4860: iconst_2
    4861: new           #42                 // class gga
    4864: dup
    4865: ldc           #176                // float 0.6667f
    4867: ldc           #68                 // float -1.0f
    4869: fconst_2
    4870: ldc           #73                 // float -2.0f
    4872: invokestatic  #64                 // Method ggc.a:(FFF)Lorg/joml/Vector3f;
    4875: getstatic     #118                // Field gfy$b.b:Lgfy$a;
    4878: invokespecial #53                 // Method gga."<init>":(FLorg/joml/Vector3fc;Lgfy$a;)V
    4881: aastore
    4882: dup
    4883: iconst_3
    4884: new           #42                 // class gga
    4887: dup
    4888: ldc           #175                // float 0.8333f
    4890: ldc           #68                 // float -1.0f
    4892: fconst_2
    4893: ldc           #68                 // float -1.0f
    4895: invokestatic  #64                 // Method ggc.a:(FFF)Lorg/joml/Vector3f;
    4898: getstatic     #118                // Field gfy$b.b:Lgfy$a;
    4901: invokespecial #53                 // Method gga."<init>":(FLorg/joml/Vector3fc;Lgfy$a;)V
    4904: aastore
    4905: dup
    4906: iconst_4
    4907: new           #42                 // class gga
    4910: dup
    4911: fconst_1
    4912: ldc           #68                 // float -1.0f
    4914: fconst_2
    4915: ldc           #68                 // float -1.0f
    4917: invokestatic  #64                 // Method ggc.a:(FFF)Lorg/joml/Vector3f;
    4920: getstatic     #118                // Field gfy$b.b:Lgfy$a;
    4923: invokespecial #53                 // Method gga."<init>":(FLorg/joml/Vector3fc;Lgfy$a;)V
    4926: aastore
    4927: dup
    4928: iconst_5
    4929: new           #42                 // class gga
    4932: dup
    4933: ldc           #155                // float 1.75f
    4935: ldc           #68                 // float -1.0f
    4937: fconst_2
    4938: ldc           #68                 // float -1.0f
    4940: invokestatic  #64                 // Method ggc.a:(FFF)Lorg/joml/Vector3f;
    4943: getstatic     #118                // Field gfy$b.b:Lgfy$a;
    4946: invokespecial #53                 // Method gga."<init>":(FLorg/joml/Vector3fc;Lgfy$a;)V
    4949: aastore
    4950: dup
    4951: bipush        6
    4953: new           #42                 // class gga
    4956: dup
    4957: ldc           #167                // float 1.95f
    4959: ldc           #68                 // float -1.0f
    4961: fconst_2
    4962: ldc           #68                 // float -1.0f
    4964: invokestatic  #64                 // Method ggc.a:(FFF)Lorg/joml/Vector3f;
    4967: getstatic     #118                // Field gfy$b.b:Lgfy$a;
    4970: invokespecial #53                 // Method gga."<init>":(FLorg/joml/Vector3fc;Lgfy$a;)V
    4973: aastore
    4974: dup
    4975: bipush        7
    4977: new           #42                 // class gga
    4980: dup
    4981: fconst_2
    4982: ldc           #68                 // float -1.0f
    4984: fconst_2
    4985: ldc           #86                 // float 3.0f
    4987: invokestatic  #64                 // Method ggc.a:(FFF)Lorg/joml/Vector3f;
    4990: getstatic     #118                // Field gfy$b.b:Lgfy$a;
    4993: invokespecial #53                 // Method gga."<init>":(FLorg/joml/Vector3fc;Lgfy$a;)V
    4996: aastore
    4997: dup
    4998: bipush        8
    5000: new           #42                 // class gga
    5003: dup
    5004: ldc           #170                // float 2.15f
    5006: ldc           #68                 // float -1.0f
    5008: ldc           #86                 // float 3.0f
    5010: ldc           #160                // float 4.0f
    5012: invokestatic  #64                 // Method ggc.a:(FFF)Lorg/joml/Vector3f;
    5015: getstatic     #118                // Field gfy$b.b:Lgfy$a;
    5018: invokespecial #53                 // Method gga."<init>":(FLorg/joml/Vector3fc;Lgfy$a;)V
    5021: aastore
    5022: invokespecial #57                 // Method gfy."<init>":(Lgfy$c;[Lgga;)V
    5025: invokevirtual #60                 // Method gfz$a.a:(Ljava/lang/String;Lgfy;)Lgfz$a;
    5028: ldc           #100                // String left_front_leg
    5030: new           #14                 // class gfy
    5033: dup
    5034: getstatic     #40                 // Field gfy$d.b:Lgfy$c;
    5037: bipush        7
    5039: anewarray     #42                 // class gga
    5042: dup
    5043: iconst_0
    5044: new           #42                 // class gga
    5047: dup
    5048: fconst_0
    5049: ldc           #173                // float -90.0f
    5051: fconst_0
    5052: fconst_0
    5053: invokestatic  #47                 // Method ggc.b:(FFF)Lorg/joml/Vector3f;
    5056: getstatic     #50                 // Field gfy$b.a:Lgfy$a;
    5059: invokespecial #53                 // Method gga."<init>":(FLorg/joml/Vector3fc;Lgfy$a;)V
    5062: aastore
    5063: dup
    5064: iconst_1
    5065: new           #42                 // class gga
    5068: dup
    5069: ldc           #176                // float 0.6667f
    5071: ldc           #173                // float -90.0f
    5073: fconst_0
    5074: fconst_0
    5075: invokestatic  #47                 // Method ggc.b:(FFF)Lorg/joml/Vector3f;
    5078: getstatic     #118                // Field gfy$b.b:Lgfy$a;
    5081: invokespecial #53                 // Method gga."<init>":(FLorg/joml/Vector3fc;Lgfy$a;)V
    5084: aastore
    5085: dup
    5086: iconst_2
    5087: new           #42                 // class gga
    5090: dup
    5091: ldc           #175                // float 0.8333f
    5093: ldc           #90                 // float -45.0f
    5095: fconst_0
    5096: fconst_0
    5097: invokestatic  #47                 // Method ggc.b:(FFF)Lorg/joml/Vector3f;
    5100: getstatic     #118                // Field gfy$b.b:Lgfy$a;
    5103: invokespecial #53                 // Method gga."<init>":(FLorg/joml/Vector3fc;Lgfy$a;)V
    5106: aastore
    5107: dup
    5108: iconst_3
    5109: new           #42                 // class gga
    5112: dup
    5113: fconst_1
    5114: ldc           #90                 // float -45.0f
    5116: fconst_0
    5117: fconst_0
    5118: invokestatic  #47                 // Method ggc.b:(FFF)Lorg/joml/Vector3f;
    5121: getstatic     #118                // Field gfy$b.b:Lgfy$a;
    5124: invokespecial #53                 // Method gga."<init>":(FLorg/joml/Vector3fc;Lgfy$a;)V
    5127: aastore
    5128: dup
    5129: iconst_4
    5130: new           #42                 // class gga
    5133: dup
    5134: ldc           #155                // float 1.75f
    5136: ldc           #90                 // float -45.0f
    5138: fconst_0
    5139: fconst_0
    5140: invokestatic  #47                 // Method ggc.b:(FFF)Lorg/joml/Vector3f;
    5143: getstatic     #118                // Field gfy$b.b:Lgfy$a;
    5146: invokespecial #53                 // Method gga."<init>":(FLorg/joml/Vector3fc;Lgfy$a;)V
    5149: aastore
    5150: dup
    5151: iconst_5
    5152: new           #42                 // class gga
    5155: dup
    5156: ldc           #156                // float 1.8f
    5158: ldc           #173                // float -90.0f
    5160: fconst_0
    5161: fconst_0
    5162: invokestatic  #47                 // Method ggc.b:(FFF)Lorg/joml/Vector3f;
    5165: getstatic     #118                // Field gfy$b.b:Lgfy$a;
    5168: invokespecial #53                 // Method gga."<init>":(FLorg/joml/Vector3fc;Lgfy$a;)V
    5171: aastore
    5172: dup
    5173: bipush        6
    5175: new           #42                 // class gga
    5178: dup
    5179: ldc           #167                // float 1.95f
    5181: ldc           #173                // float -90.0f
    5183: fconst_0
    5184: fconst_0
    5185: invokestatic  #47                 // Method ggc.b:(FFF)Lorg/joml/Vector3f;
    5188: getstatic     #118                // Field gfy$b.b:Lgfy$a;
    5191: invokespecial #53                 // Method gga."<init>":(FLorg/joml/Vector3fc;Lgfy$a;)V
    5194: aastore
    5195: invokespecial #57                 // Method gfy."<init>":(Lgfy$c;[Lgga;)V
    5198: invokevirtual #60                 // Method gfz$a.a:(Ljava/lang/String;Lgfy;)Lgfz$a;
    5201: ldc           #100                // String left_front_leg
    5203: new           #14                 // class gfy
    5206: dup
    5207: getstatic     #62                 // Field gfy$d.a:Lgfy$c;
    5210: bipush        9
    5212: anewarray     #42                 // class gga
    5215: dup
    5216: iconst_0
    5217: new           #42                 // class gga
    5220: dup
    5221: fconst_0
    5222: fconst_1
    5223: fconst_2
    5224: fconst_2
    5225: invokestatic  #64                 // Method ggc.a:(FFF)Lorg/joml/Vector3f;
    5228: getstatic     #50                 // Field gfy$b.a:Lgfy$a;
    5231: invokespecial #53                 // Method gga."<init>":(FLorg/joml/Vector3fc;Lgfy$a;)V
    5234: aastore
    5235: dup
    5236: iconst_1
    5237: new           #42                 // class gga
    5240: dup
    5241: ldc           #176                // float 0.6667f
    5243: fconst_1
    5244: fconst_2
    5245: fconst_2
    5246: invokestatic  #64                 // Method ggc.a:(FFF)Lorg/joml/Vector3f;
    5249: getstatic     #118                // Field gfy$b.b:Lgfy$a;
    5252: invokespecial #53                 // Method gga."<init>":(FLorg/joml/Vector3fc;Lgfy$a;)V
    5255: aastore
    5256: dup
    5257: iconst_2
    5258: new           #42                 // class gga
    5261: dup
    5262: ldc           #128                // float 0.75f
    5264: fconst_1
    5265: fconst_2
    5266: ldc           #73                 // float -2.0f
    5268: invokestatic  #64                 // Method ggc.a:(FFF)Lorg/joml/Vector3f;
    5271: getstatic     #118                // Field gfy$b.b:Lgfy$a;
    5274: invokespecial #53                 // Method gga."<init>":(FLorg/joml/Vector3fc;Lgfy$a;)V
    5277: aastore
    5278: dup
    5279: iconst_3
    5280: new           #42                 // class gga
    5283: dup
    5284: ldc           #175                // float 0.8333f
    5286: fconst_1
    5287: fconst_2
    5288: ldc           #68                 // float -1.0f
    5290: invokestatic  #64                 // Method ggc.a:(FFF)Lorg/joml/Vector3f;
    5293: getstatic     #118                // Field gfy$b.b:Lgfy$a;
    5296: invokespecial #53                 // Method gga."<init>":(FLorg/joml/Vector3fc;Lgfy$a;)V
    5299: aastore
    5300: dup
    5301: iconst_4
    5302: new           #42                 // class gga
    5305: dup
    5306: fconst_1
    5307: fconst_1
    5308: fconst_2
    5309: ldc           #68                 // float -1.0f
    5311: invokestatic  #64                 // Method ggc.a:(FFF)Lorg/joml/Vector3f;
    5314: getstatic     #118                // Field gfy$b.b:Lgfy$a;
    5317: invokespecial #53                 // Method gga."<init>":(FLorg/joml/Vector3fc;Lgfy$a;)V
    5320: aastore
    5321: dup
    5322: iconst_5
    5323: new           #42                 // class gga
    5326: dup
    5327: ldc           #155                // float 1.75f
    5329: fconst_1
    5330: fconst_2
    5331: ldc           #68                 // float -1.0f
    5333: invokestatic  #64                 // Method ggc.a:(FFF)Lorg/joml/Vector3f;
    5336: getstatic     #118                // Field gfy$b.b:Lgfy$a;
    5339: invokespecial #53                 // Method gga."<init>":(FLorg/joml/Vector3fc;Lgfy$a;)V
    5342: aastore
    5343: dup
    5344: bipush        6
    5346: new           #42                 // class gga
    5349: dup
    5350: ldc           #167                // float 1.95f
    5352: fconst_1
    5353: fconst_2
    5354: ldc           #68                 // float -1.0f
    5356: invokestatic  #64                 // Method ggc.a:(FFF)Lorg/joml/Vector3f;
    5359: getstatic     #118                // Field gfy$b.b:Lgfy$a;
    5362: invokespecial #53                 // Method gga."<init>":(FLorg/joml/Vector3fc;Lgfy$a;)V
    5365: aastore
    5366: dup
    5367: bipush        7
    5369: new           #42                 // class gga
    5372: dup
    5373: fconst_2
    5374: fconst_1
    5375: fconst_2
    5376: ldc           #86                 // float 3.0f
    5378: invokestatic  #64                 // Method ggc.a:(FFF)Lorg/joml/Vector3f;
    5381: getstatic     #118                // Field gfy$b.b:Lgfy$a;
    5384: invokespecial #53                 // Method gga."<init>":(FLorg/joml/Vector3fc;Lgfy$a;)V
    5387: aastore
    5388: dup
    5389: bipush        8
    5391: new           #42                 // class gga
    5394: dup
    5395: ldc           #170                // float 2.15f
    5397: fconst_1
    5398: ldc           #86                 // float 3.0f
    5400: ldc           #160                // float 4.0f
    5402: invokestatic  #64                 // Method ggc.a:(FFF)Lorg/joml/Vector3f;
    5405: getstatic     #118                // Field gfy$b.b:Lgfy$a;
    5408: invokespecial #53                 // Method gga."<init>":(FLorg/joml/Vector3fc;Lgfy$a;)V
    5411: aastore
    5412: invokespecial #57                 // Method gfy."<init>":(Lgfy$c;[Lgga;)V
    5415: invokevirtual #60                 // Method gfz$a.a:(Ljava/lang/String;Lgfy;)Lgfz$a;
    5418: ldc           #103                // String cube
    5420: new           #14                 // class gfy
    5423: dup
    5424: getstatic     #40                 // Field gfy$d.b:Lgfy$c;
    5427: bipush        11
    5429: anewarray     #42                 // class gga
    5432: dup
    5433: iconst_0
    5434: new           #42                 // class gga
    5437: dup
    5438: fconst_0
    5439: fconst_0
    5440: fconst_0
    5441: fconst_0
    5442: invokestatic  #47                 // Method ggc.b:(FFF)Lorg/joml/Vector3f;
    5445: getstatic     #50                 // Field gfy$b.a:Lgfy$a;
    5448: invokespecial #53                 // Method gga."<init>":(FLorg/joml/Vector3fc;Lgfy$a;)V
    5451: aastore
    5452: dup
    5453: iconst_1
    5454: new           #42                 // class gga
    5457: dup
    5458: ldc           #69                 // float 0.25f
    5460: fconst_0
    5461: fconst_0
    5462: fconst_0
    5463: invokestatic  #47                 // Method ggc.b:(FFF)Lorg/joml/Vector3f;
    5466: getstatic     #50                 // Field gfy$b.a:Lgfy$a;
    5469: invokespecial #53                 // Method gga."<init>":(FLorg/joml/Vector3fc;Lgfy$a;)V
    5472: aastore
    5473: dup
    5474: iconst_2
    5475: new           #42                 // class gga
    5478: dup
    5479: ldc           #161                // float 0.35f
    5481: ldc           #177                // float 15.0f
    5483: fconst_0
    5484: fconst_0
    5485: invokestatic  #47                 // Method ggc.b:(FFF)Lorg/joml/Vector3f;
    5488: getstatic     #50                 // Field gfy$b.a:Lgfy$a;
    5491: invokespecial #53                 // Method gga."<init>":(FLorg/joml/Vector3fc;Lgfy$a;)V
    5494: aastore
    5495: dup
    5496: iconst_3
    5497: new           #42                 // class gga
    5500: dup
    5501: ldc           #32                 // float 0.5f
    5503: ldc           #147                // float -7.5f
    5505: fconst_0
    5506: fconst_0
    5507: invokestatic  #47                 // Method ggc.b:(FFF)Lorg/joml/Vector3f;
    5510: getstatic     #50                 // Field gfy$b.a:Lgfy$a;
    5513: invokespecial #53                 // Method gga."<init>":(FLorg/joml/Vector3fc;Lgfy$a;)V
    5516: aastore
    5517: dup
    5518: iconst_4
    5519: new           #42                 // class gga
    5522: dup
    5523: ldc           #107                // float 0.6f
    5525: fconst_0
    5526: fconst_0
    5527: fconst_0
    5528: invokestatic  #47                 // Method ggc.b:(FFF)Lorg/joml/Vector3f;
    5531: getstatic     #50                 // Field gfy$b.a:Lgfy$a;
    5534: invokespecial #53                 // Method gga."<init>":(FLorg/joml/Vector3fc;Lgfy$a;)V
    5537: aastore
    5538: dup
    5539: iconst_5
    5540: new           #42                 // class gga
    5543: dup
    5544: fconst_2
    5545: fconst_0
    5546: fconst_0
    5547: fconst_0
    5548: invokestatic  #47                 // Method ggc.b:(FFF)Lorg/joml/Vector3f;
    5551: getstatic     #50                 // Field gfy$b.a:Lgfy$a;
    5554: invokespecial #53                 // Method gga."<init>":(FLorg/joml/Vector3fc;Lgfy$a;)V
    5557: aastore
    5558: dup
    5559: bipush        6
    5561: new           #42                 // class gga
    5564: dup
    5565: ldc           #178                // float 2.05f
    5567: ldc           #179                // float -17.5f
    5569: fconst_0
    5570: fconst_0
    5571: invokestatic  #47                 // Method ggc.b:(FFF)Lorg/joml/Vector3f;
    5574: getstatic     #50                 // Field gfy$b.a:Lgfy$a;
    5577: invokespecial #53                 // Method gga."<init>":(FLorg/joml/Vector3fc;Lgfy$a;)V
    5580: aastore
    5581: dup
    5582: bipush        7
    5584: new           #42                 // class gga
    5587: dup
    5588: ldc           #170                // float 2.15f
    5590: ldc           #157                // float -25.0f
    5592: fconst_0
    5593: fconst_0
    5594: invokestatic  #47                 // Method ggc.b:(FFF)Lorg/joml/Vector3f;
    5597: getstatic     #50                 // Field gfy$b.a:Lgfy$a;
    5600: invokespecial #53                 // Method gga."<init>":(FLorg/joml/Vector3fc;Lgfy$a;)V
    5603: aastore
    5604: dup
    5605: bipush        8
    5607: new           #42                 // class gga
    5610: dup
    5611: ldc           #180                // float 2.25f
    5613: fconst_0
    5614: fconst_0
    5615: fconst_0
    5616: invokestatic  #47                 // Method ggc.b:(FFF)Lorg/joml/Vector3f;
    5619: getstatic     #50                 // Field gfy$b.a:Lgfy$a;
    5622: invokespecial #53                 // Method gga."<init>":(FLorg/joml/Vector3fc;Lgfy$a;)V
    5625: aastore
    5626: dup
    5627: bipush        9
    5629: new           #42                 // class gga
    5632: dup
    5633: ldc           #172                // float 2.3f
    5635: ldc           #181                // float 12.5f
    5637: fconst_0
    5638: fconst_0
    5639: invokestatic  #47                 // Method ggc.b:(FFF)Lorg/joml/Vector3f;
    5642: getstatic     #50                 // Field gfy$b.a:Lgfy$a;
    5645: invokespecial #53                 // Method gga."<init>":(FLorg/joml/Vector3fc;Lgfy$a;)V
    5648: aastore
    5649: dup
    5650: bipush        10
    5652: new           #42                 // class gga
    5655: dup
    5656: ldc           #138                // float 2.5f
    5658: fconst_0
    5659: fconst_0
    5660: fconst_0
    5661: invokestatic  #47                 // Method ggc.b:(FFF)Lorg/joml/Vector3f;
    5664: getstatic     #50                 // Field gfy$b.a:Lgfy$a;
    5667: invokespecial #53                 // Method gga."<init>":(FLorg/joml/Vector3fc;Lgfy$a;)V
    5670: aastore
    5671: invokespecial #57                 // Method gfy."<init>":(Lgfy$c;[Lgga;)V
    5674: invokevirtual #60                 // Method gfz$a.a:(Ljava/lang/String;Lgfy;)Lgfz$a;
    5677: ldc           #103                // String cube
    5679: new           #14                 // class gfy
    5682: dup
    5683: getstatic     #62                 // Field gfy$d.a:Lgfy$c;
    5686: bipush        10
    5688: anewarray     #42                 // class gga
    5691: dup
    5692: iconst_0
    5693: new           #42                 // class gga
    5696: dup
    5697: ldc           #69                 // float 0.25f
    5699: fconst_0
    5700: fconst_0
    5701: fconst_0
    5702: invokestatic  #64                 // Method ggc.a:(FFF)Lorg/joml/Vector3f;
    5705: getstatic     #50                 // Field gfy$b.a:Lgfy$a;
    5708: invokespecial #53                 // Method gga."<init>":(FLorg/joml/Vector3fc;Lgfy$a;)V
    5711: aastore
    5712: dup
    5713: iconst_1
    5714: new           #42                 // class gga
    5717: dup
    5718: ldc           #161                // float 0.35f
    5720: fconst_0
    5721: ldc           #154                // float 1.6f
    5723: fconst_0
    5724: invokestatic  #64                 // Method ggc.a:(FFF)Lorg/joml/Vector3f;
    5727: getstatic     #50                 // Field gfy$b.a:Lgfy$a;
    5730: invokespecial #53                 // Method gga."<init>":(FLorg/joml/Vector3fc;Lgfy$a;)V
    5733: aastore
    5734: dup
    5735: iconst_2
    5736: new           #42                 // class gga
    5739: dup
    5740: ldc           #32                 // float 0.5f
    5742: fconst_0
    5743: ldc           #32                 // float 0.5f
    5745: fconst_0
    5746: invokestatic  #64                 // Method ggc.a:(FFF)Lorg/joml/Vector3f;
    5749: getstatic     #50                 // Field gfy$b.a:Lgfy$a;
    5752: invokespecial #53                 // Method gga."<init>":(FLorg/joml/Vector3fc;Lgfy$a;)V
    5755: aastore
    5756: dup
    5757: iconst_3
    5758: new           #42                 // class gga
    5761: dup
    5762: ldc           #107                // float 0.6f
    5764: fconst_0
    5765: fconst_0
    5766: fconst_0
    5767: invokestatic  #64                 // Method ggc.a:(FFF)Lorg/joml/Vector3f;
    5770: getstatic     #50                 // Field gfy$b.a:Lgfy$a;
    5773: invokespecial #53                 // Method gga."<init>":(FLorg/joml/Vector3fc;Lgfy$a;)V
    5776: aastore
    5777: dup
    5778: iconst_4
    5779: new           #42                 // class gga
    5782: dup
    5783: fconst_2
    5784: fconst_0
    5785: fconst_0
    5786: fconst_0
    5787: invokestatic  #64                 // Method ggc.a:(FFF)Lorg/joml/Vector3f;
    5790: getstatic     #50                 // Field gfy$b.a:Lgfy$a;
    5793: invokespecial #53                 // Method gga."<init>":(FLorg/joml/Vector3fc;Lgfy$a;)V
    5796: aastore
    5797: dup
    5798: iconst_5
    5799: new           #42                 // class gga
    5802: dup
    5803: ldc           #178                // float 2.05f
    5805: fconst_0
    5806: ldc           #164                // float 1.2f
    5808: fconst_0
    5809: invokestatic  #64                 // Method ggc.a:(FFF)Lorg/joml/Vector3f;
    5812: getstatic     #50                 // Field gfy$b.a:Lgfy$a;
    5815: invokespecial #53                 // Method gga."<init>":(FLorg/joml/Vector3fc;Lgfy$a;)V
    5818: aastore
    5819: dup
    5820: bipush        6
    5822: new           #42                 // class gga
    5825: dup
    5826: ldc           #170                // float 2.15f
    5828: fconst_0
    5829: ldc           #182                // float 1.7f
    5831: fconst_0
    5832: invokestatic  #64                 // Method ggc.a:(FFF)Lorg/joml/Vector3f;
    5835: getstatic     #50                 // Field gfy$b.a:Lgfy$a;
    5838: invokespecial #53                 // Method gga."<init>":(FLorg/joml/Vector3fc;Lgfy$a;)V
    5841: aastore
    5842: dup
    5843: bipush        7
    5845: new           #42                 // class gga
    5848: dup
    5849: ldc           #180                // float 2.25f
    5851: fconst_0
    5852: fconst_0
    5853: fconst_0
    5854: invokestatic  #64                 // Method ggc.a:(FFF)Lorg/joml/Vector3f;
    5857: getstatic     #50                 // Field gfy$b.a:Lgfy$a;
    5860: invokespecial #53                 // Method gga."<init>":(FLorg/joml/Vector3fc;Lgfy$a;)V
    5863: aastore
    5864: dup
    5865: bipush        8
    5867: new           #42                 // class gga
    5870: dup
    5871: ldc           #172                // float 2.3f
    5873: fconst_0
    5874: ldc           #150                // float 1.3f
    5876: fconst_0
    5877: invokestatic  #64                 // Method ggc.a:(FFF)Lorg/joml/Vector3f;
    5880: getstatic     #50                 // Field gfy$b.a:Lgfy$a;
    5883: invokespecial #53                 // Method gga."<init>":(FLorg/joml/Vector3fc;Lgfy$a;)V
    5886: aastore
    5887: dup
    5888: bipush        9
    5890: new           #42                 // class gga
    5893: dup
    5894: ldc           #138                // float 2.5f
    5896: fconst_0
    5897: fconst_0
    5898: fconst_0
    5899: invokestatic  #64                 // Method ggc.a:(FFF)Lorg/joml/Vector3f;
    5902: getstatic     #50                 // Field gfy$b.a:Lgfy$a;
    5905: invokespecial #53                 // Method gga."<init>":(FLorg/joml/Vector3fc;Lgfy$a;)V
    5908: aastore
    5909: invokespecial #57                 // Method gfy."<init>":(Lgfy$c;[Lgga;)V
    5912: invokevirtual #60                 // Method gfz$a.a:(Ljava/lang/String;Lgfy;)Lgfz$a;
    5915: invokevirtual #110                // Method gfz$a.b:()Lgfz;
    5918: putstatic     #184                // Field c:Lgfz;
    5921: ldc           #185                // float 1.5f
    5923: invokestatic  #35                 // Method gfz$a.a:(F)Lgfz$a;
    5926: ldc           #75                 // String head
    5928: new           #14                 // class gfy
    5931: dup
    5932: getstatic     #40                 // Field gfy$d.b:Lgfy$c;
    5935: bipush        11
    5937: anewarray     #42                 // class gga
    5940: dup
    5941: iconst_0
    5942: new           #42                 // class gga
    5945: dup
    5946: ldc           #166                // float 0.1f
    5948: ldc           #131                // float -50.0f
    5950: fconst_0
    5951: fconst_0
    5952: invokestatic  #47                 // Method ggc.b:(FFF)Lorg/joml/Vector3f;
    5955: getstatic     #50                 // Field gfy$b.a:Lgfy$a;
    5958: invokespecial #53                 // Method gga."<init>":(FLorg/joml/Vector3fc;Lgfy$a;)V
    5961: aastore
    5962: dup
    5963: iconst_1
    5964: new           #42                 // class gga
    5967: dup
    5968: ldc           #142                // float 0.15f
    5970: fconst_0
    5971: fconst_0
    5972: fconst_0
    5973: invokestatic  #47                 // Method ggc.b:(FFF)Lorg/joml/Vector3f;
    5976: getstatic     #50                 // Field gfy$b.a:Lgfy$a;
    5979: invokespecial #53                 // Method gga."<init>":(FLorg/joml/Vector3fc;Lgfy$a;)V
    5982: aastore
    5983: dup
    5984: iconst_2
    5985: new           #42                 // class gga
    5988: dup
    5989: ldc           #69                 // float 0.25f
    5991: fconst_0
    5992: fconst_0
    5993: fconst_0
    5994: invokestatic  #47                 // Method ggc.b:(FFF)Lorg/joml/Vector3f;
    5997: getstatic     #50                 // Field gfy$b.a:Lgfy$a;
    6000: invokespecial #53                 // Method gga."<init>":(FLorg/joml/Vector3fc;Lgfy$a;)V
    6003: aastore
    6004: dup
    6005: iconst_3
    6006: new           #42                 // class gga
    6009: dup
    6010: ldc           #144                // float 0.4f
    6012: fconst_0
    6013: fconst_0
    6014: fconst_0
    6015: invokestatic  #47                 // Method ggc.b:(FFF)Lorg/joml/Vector3f;
    6018: getstatic     #50                 // Field gfy$b.a:Lgfy$a;
    6021: invokespecial #53                 // Method gga."<init>":(FLorg/joml/Vector3fc;Lgfy$a;)V
    6024: aastore
    6025: dup
    6026: iconst_4
    6027: new           #42                 // class gga
    6030: dup
    6031: ldc           #186                // float 0.65f
    6033: fconst_0
    6034: fconst_0
    6035: fconst_0
    6036: invokestatic  #47                 // Method ggc.b:(FFF)Lorg/joml/Vector3f;
    6039: getstatic     #50                 // Field gfy$b.a:Lgfy$a;
    6042: invokespecial #53                 // Method gga."<init>":(FLorg/joml/Vector3fc;Lgfy$a;)V
    6045: aastore
    6046: dup
    6047: iconst_5
    6048: new           #42                 // class gga
    6051: dup
    6052: ldc           #145                // float 0.7f
    6054: fconst_0
    6055: fconst_0
    6056: fconst_0
    6057: invokestatic  #47                 // Method ggc.b:(FFF)Lorg/joml/Vector3f;
    6060: getstatic     #50                 // Field gfy$b.a:Lgfy$a;
    6063: invokespecial #53                 // Method gga."<init>":(FLorg/joml/Vector3fc;Lgfy$a;)V
    6066: aastore
    6067: dup
    6068: bipush        6
    6070: new           #42                 // class gga
    6073: dup
    6074: ldc           #187                // float 0.85f
    6076: ldc           #105                // float -2.5f
    6078: fconst_0
    6079: fconst_0
    6080: invokestatic  #47                 // Method ggc.b:(FFF)Lorg/joml/Vector3f;
    6083: getstatic     #50                 // Field gfy$b.a:Lgfy$a;
    6086: invokespecial #53                 // Method gga."<init>":(FLorg/joml/Vector3fc;Lgfy$a;)V
    6089: aastore
    6090: dup
    6091: bipush        7
    6093: new           #42                 // class gga
    6096: dup
    6097: ldc           #146                // float 0.9f
    6099: fconst_0
    6100: fconst_0
    6101: fconst_0
    6102: invokestatic  #47                 // Method ggc.b:(FFF)Lorg/joml/Vector3f;
    6105: getstatic     #50                 // Field gfy$b.a:Lgfy$a;
    6108: invokespecial #53                 // Method gga."<init>":(FLorg/joml/Vector3fc;Lgfy$a;)V
    6111: aastore
    6112: dup
    6113: bipush        8
    6115: new           #42                 // class gga
    6118: dup
    6119: ldc           #188                // float 0.95f
    6121: ldc           #147                // float -7.5f
    6123: fconst_0
    6124: fconst_0
    6125: invokestatic  #47                 // Method ggc.b:(FFF)Lorg/joml/Vector3f;
    6128: getstatic     #50                 // Field gfy$b.a:Lgfy$a;
    6131: invokespecial #53                 // Method gga."<init>":(FLorg/joml/Vector3fc;Lgfy$a;)V
    6134: aastore
    6135: dup
    6136: bipush        9
    6138: new           #42                 // class gga
    6141: dup
    6142: ldc           #189                // float 1.05f
    6144: fconst_0
    6145: fconst_0
    6146: fconst_0
    6147: invokestatic  #47                 // Method ggc.b:(FFF)Lorg/joml/Vector3f;
    6150: getstatic     #50                 // Field gfy$b.a:Lgfy$a;
    6153: invokespecial #53                 // Method gga."<init>":(FLorg/joml/Vector3fc;Lgfy$a;)V
    6156: aastore
    6157: dup
    6158: bipush        10
    6160: new           #42                 // class gga
    6163: dup
    6164: ldc           #165                // float 1.1f
    6166: ldc           #190                // float 7.5f
    6168: fconst_0
    6169: fconst_0
    6170: invokestatic  #47                 // Method ggc.b:(FFF)Lorg/joml/Vector3f;
    6173: getstatic     #50                 // Field gfy$b.a:Lgfy$a;
    6176: invokespecial #53                 // Method gga."<init>":(FLorg/joml/Vector3fc;Lgfy$a;)V
    6179: aastore
    6180: invokespecial #57                 // Method gfy."<init>":(Lgfy$c;[Lgga;)V
    6183: invokevirtual #60                 // Method gfz$a.a:(Ljava/lang/String;Lgfy;)Lgfz$a;
    6186: ldc           #75                 // String head
    6188: new           #14                 // class gfy
    6191: dup
    6192: getstatic     #62                 // Field gfy$d.a:Lgfy$c;
    6195: bipush        18
    6197: anewarray     #42                 // class gga
    6200: dup
    6201: iconst_0
    6202: new           #42                 // class gga
    6205: dup
    6206: fconst_0
    6207: fconst_0
    6208: fconst_1
    6209: ldc           #65                 // float 5.0f
    6211: invokestatic  #64                 // Method ggc.a:(FFF)Lorg/joml/Vector3f;
    6214: getstatic     #50                 // Field gfy$b.a:Lgfy$a;
    6217: invokespecial #53                 // Method gga."<init>":(FLorg/joml/Vector3fc;Lgfy$a;)V
    6220: aastore
    6221: dup
    6222: iconst_1
    6223: new           #42                 // class gga
    6226: dup
    6227: ldc           #159                // float 0.05f
    6229: fconst_0
    6230: fconst_1
    6231: ldc           #162                // float 0.2f
    6233: invokestatic  #64                 // Method ggc.a:(FFF)Lorg/joml/Vector3f;
    6236: getstatic     #50                 // Field gfy$b.a:Lgfy$a;
    6239: invokespecial #53                 // Method gga."<init>":(FLorg/joml/Vector3fc;Lgfy$a;)V
    6242: aastore
    6243: dup
    6244: iconst_2
    6245: new           #42                 // class gga
    6248: dup
    6249: ldc           #166                // float 0.1f
    6251: fconst_0
    6252: fconst_1
    6253: ldc           #162                // float 0.2f
    6255: invokestatic  #64                 // Method ggc.a:(FFF)Lorg/joml/Vector3f;
    6258: getstatic     #50                 // Field gfy$b.a:Lgfy$a;
    6261: invokespecial #53                 // Method gga."<init>":(FLorg/joml/Vector3fc;Lgfy$a;)V
    6264: aastore
    6265: dup
    6266: iconst_3
    6267: new           #42                 // class gga
    6270: dup
    6271: ldc           #142                // float 0.15f
    6273: fconst_0
    6274: ldc           #163                // float 2.1f
    6276: ldc           #164                // float 1.2f
    6278: invokestatic  #64                 // Method ggc.a:(FFF)Lorg/joml/Vector3f;
    6281: getstatic     #50                 // Field gfy$b.a:Lgfy$a;
    6284: invokespecial #53                 // Method gga."<init>":(FLorg/joml/Vector3fc;Lgfy$a;)V
    6287: aastore
    6288: dup
    6289: iconst_4
    6290: new           #42                 // class gga
    6293: dup
    6294: ldc           #69                 // float 0.25f
    6296: fconst_0
    6297: ldc           #191                // float 1.03f
    6299: ldc           #192                // float 0.13f
    6301: invokestatic  #64                 // Method ggc.a:(FFF)Lorg/joml/Vector3f;
    6304: getstatic     #50                 // Field gfy$b.a:Lgfy$a;
    6307: invokespecial #53                 // Method gga."<init>":(FLorg/joml/Vector3fc;Lgfy$a;)V
    6310: aastore
    6311: dup
    6312: iconst_5
    6313: new           #42                 // class gga
    6316: dup
    6317: ldc           #144                // float 0.4f
    6319: fconst_0
    6320: ldc           #191                // float 1.03f
    6322: ldc           #192                // float 0.13f
    6324: invokestatic  #64                 // Method ggc.a:(FFF)Lorg/joml/Vector3f;
    6327: getstatic     #50                 // Field gfy$b.a:Lgfy$a;
    6330: invokespecial #53                 // Method gga."<init>":(FLorg/joml/Vector3fc;Lgfy$a;)V
    6333: aastore
    6334: dup
    6335: bipush        6
    6337: new           #42                 // class gga
    6340: dup
    6341: ldc           #186                // float 0.65f
    6343: fconst_0
    6344: ldc           #191                // float 1.03f
    6346: ldc           #192                // float 0.13f
    6348: invokestatic  #64                 // Method ggc.a:(FFF)Lorg/joml/Vector3f;
    6351: getstatic     #50                 // Field gfy$b.a:Lgfy$a;
    6354: invokespecial #53                 // Method gga."<init>":(FLorg/joml/Vector3fc;Lgfy$a;)V
    6357: aastore
    6358: dup
    6359: bipush        7
    6361: new           #42                 // class gga
    6364: dup
    6365: ldc           #145                // float 0.7f
    6367: fconst_0
    6368: ldc           #165                // float 1.1f
    6370: ldc           #162                // float 0.2f
    6372: invokestatic  #64                 // Method ggc.a:(FFF)Lorg/joml/Vector3f;
    6375: getstatic     #50                 // Field gfy$b.a:Lgfy$a;
    6378: invokespecial #53                 // Method gga."<init>":(FLorg/joml/Vector3fc;Lgfy$a;)V
    6381: aastore
    6382: dup
    6383: bipush        8
    6385: new           #42                 // class gga
    6388: dup
    6389: ldc           #128                // float 0.75f
    6391: fconst_0
    6392: ldc           #193                // float 4.1f
    6394: ldc           #194                // float 2.2f
    6396: invokestatic  #64                 // Method ggc.a:(FFF)Lorg/joml/Vector3f;
    6399: getstatic     #50                 // Field gfy$b.a:Lgfy$a;
    6402: invokespecial #53                 // Method gga."<init>":(FLorg/joml/Vector3fc;Lgfy$a;)V
    6405: aastore
    6406: dup
    6407: bipush        9
    6409: new           #42                 // class gga
    6412: dup
    6413: ldc           #187                // float 0.85f
    6415: fconst_0
    6416: ldc           #195                // float 5.1f
    6418: ldc           #196                // float 3.2f
    6420: invokestatic  #64                 // Method ggc.a:(FFF)Lorg/joml/Vector3f;
    6423: getstatic     #50                 // Field gfy$b.a:Lgfy$a;
    6426: invokespecial #53                 // Method gga."<init>":(FLorg/joml/Vector3fc;Lgfy$a;)V
    6429: aastore
    6430: dup
    6431: bipush        10
    6433: new           #42                 // class gga
    6436: dup
    6437: ldc           #146                // float 0.9f
    6439: fconst_0
    6440: ldc           #166                // float 0.1f
    6442: ldc           #162                // float 0.2f
    6444: invokestatic  #64                 // Method ggc.a:(FFF)Lorg/joml/Vector3f;
    6447: getstatic     #50                 // Field gfy$b.a:Lgfy$a;
    6450: invokespecial #53                 // Method gga."<init>":(FLorg/joml/Vector3fc;Lgfy$a;)V
    6453: aastore
    6454: dup
    6455: bipush        11
    6457: new           #42                 // class gga
    6460: dup
    6461: ldc           #188                // float 0.95f
    6463: fconst_0
    6464: ldc           #146                // float 0.9f
    6466: ldc           #197                // float -0.8f
    6468: invokestatic  #64                 // Method ggc.a:(FFF)Lorg/joml/Vector3f;
    6471: getstatic     #50                 // Field gfy$b.a:Lgfy$a;
    6474: invokespecial #53                 // Method gga."<init>":(FLorg/joml/Vector3fc;Lgfy$a;)V
    6477: aastore
    6478: dup
    6479: bipush        12
    6481: new           #42                 // class gga
    6484: dup
    6485: ldc           #189                // float 1.05f
    6487: fconst_0
    6488: ldc           #146                // float 0.9f
    6490: fconst_0
    6491: invokestatic  #64                 // Method ggc.a:(FFF)Lorg/joml/Vector3f;
    6494: getstatic     #50                 // Field gfy$b.a:Lgfy$a;
    6497: invokespecial #53                 // Method gga."<init>":(FLorg/joml/Vector3fc;Lgfy$a;)V
    6500: aastore
    6501: dup
    6502: bipush        13
    6504: new           #42                 // class gga
    6507: dup
    6508: ldc           #165                // float 1.1f
    6510: fconst_0
    6511: ldc           #198                // float 2.6f
    6513: ldc           #162                // float 0.2f
    6515: invokestatic  #64                 // Method ggc.a:(FFF)Lorg/joml/Vector3f;
    6518: getstatic     #50                 // Field gfy$b.a:Lgfy$a;
    6521: invokespecial #53                 // Method gga."<init>":(FLorg/joml/Vector3fc;Lgfy$a;)V
    6524: aastore
    6525: dup
    6526: bipush        14
    6528: new           #42                 // class gga
    6531: dup
    6532: ldc           #149                // float 1.15f
    6534: fconst_0
    6535: ldc           #199                // float 2.4f
    6537: ldc           #162                // float 0.2f
    6539: invokestatic  #64                 // Method ggc.a:(FFF)Lorg/joml/Vector3f;
    6542: getstatic     #50                 // Field gfy$b.a:Lgfy$a;
    6545: invokespecial #53                 // Method gga."<init>":(FLorg/joml/Vector3fc;Lgfy$a;)V
    6548: aastore
    6549: dup
    6550: bipush        15
    6552: new           #42                 // class gga
    6555: dup
    6556: ldc           #164                // float 1.2f
    6558: fconst_0
    6559: fconst_0
    6560: ldc           #162                // float 0.2f
    6562: invokestatic  #64                 // Method ggc.a:(FFF)Lorg/joml/Vector3f;
    6565: getstatic     #50                 // Field gfy$b.a:Lgfy$a;
    6568: invokespecial #53                 // Method gga."<init>":(FLorg/joml/Vector3fc;Lgfy$a;)V
    6571: aastore
    6572: dup
    6573: bipush        16
    6575: new           #42                 // class gga
    6578: dup
    6579: ldc           #125                // float 1.25f
    6581: fconst_0
    6582: fconst_0
    6583: ldc           #162                // float 0.2f
    6585: invokestatic  #64                 // Method ggc.a:(FFF)Lorg/joml/Vector3f;
    6588: getstatic     #50                 // Field gfy$b.a:Lgfy$a;
    6591: invokespecial #53                 // Method gga."<init>":(FLorg/joml/Vector3fc;Lgfy$a;)V
    6594: aastore
    6595: dup
    6596: bipush        17
    6598: new           #42                 // class gga
    6601: dup
    6602: ldc           #150                // float 1.3f
    6604: fconst_0
    6605: fconst_0
    6606: ldc           #162                // float 0.2f
    6608: invokestatic  #64                 // Method ggc.a:(FFF)Lorg/joml/Vector3f;
    6611: getstatic     #50                 // Field gfy$b.a:Lgfy$a;
    6614: invokespecial #53                 // Method gga."<init>":(FLorg/joml/Vector3fc;Lgfy$a;)V
    6617: aastore
    6618: invokespecial #57                 // Method gfy."<init>":(Lgfy$c;[Lgga;)V
    6621: invokevirtual #60                 // Method gfz$a.a:(Ljava/lang/String;Lgfy;)Lgfz$a;
    6624: ldc           #81                 // String right_hind_leg
    6626: new           #14                 // class gfy
    6629: dup
    6630: getstatic     #40                 // Field gfy$d.b:Lgfy$c;
    6633: iconst_5
    6634: anewarray     #42                 // class gga
    6637: dup
    6638: iconst_0
    6639: new           #42                 // class gga
    6642: dup
    6643: ldc           #165                // float 1.1f
    6645: fconst_0
    6646: fconst_0
    6647: fconst_0
    6648: invokestatic  #47                 // Method ggc.b:(FFF)Lorg/joml/Vector3f;
    6651: getstatic     #50                 // Field gfy$b.a:Lgfy$a;
    6654: invokespecial #53                 // Method gga."<init>":(FLorg/joml/Vector3fc;Lgfy$a;)V
    6657: aastore
    6658: dup
    6659: iconst_1
    6660: new           #42                 // class gga
    6663: dup
    6664: ldc           #150                // float 1.3f
    6666: fconst_0
    6667: fconst_0
    6668: ldc           #200                // float 30.0f
    6670: invokestatic  #47                 // Method ggc.b:(FFF)Lorg/joml/Vector3f;
    6673: getstatic     #50                 // Field gfy$b.a:Lgfy$a;
    6676: invokespecial #53                 // Method gga."<init>":(FLorg/joml/Vector3fc;Lgfy$a;)V
    6679: aastore
    6680: dup
    6681: iconst_2
    6682: new           #42                 // class gga
    6685: dup
    6686: ldc           #201                // float 1.4f
    6688: fconst_0
    6689: fconst_0
    6690: fconst_0
    6691: invokestatic  #47                 // Method ggc.b:(FFF)Lorg/joml/Vector3f;
    6694: getstatic     #50                 // Field gfy$b.a:Lgfy$a;
    6697: invokespecial #53                 // Method gga."<init>":(FLorg/joml/Vector3fc;Lgfy$a;)V
    6700: aastore
    6701: dup
    6702: iconst_3
    6703: new           #42                 // class gga
    6706: dup
    6707: ldc           #202                // float 1.45f
    6709: fconst_0
    6710: fconst_0
    6711: fconst_0
    6712: invokestatic  #47                 // Method ggc.b:(FFF)Lorg/joml/Vector3f;
    6715: getstatic     #50                 // Field gfy$b.a:Lgfy$a;
    6718: invokespecial #53                 // Method gga."<init>":(FLorg/joml/Vector3fc;Lgfy$a;)V
    6721: aastore
    6722: dup
    6723: iconst_4
    6724: new           #42                 // class gga
    6727: dup
    6728: ldc           #185                // float 1.5f
    6730: fconst_0
    6731: fconst_0
    6732: fconst_0
    6733: invokestatic  #47                 // Method ggc.b:(FFF)Lorg/joml/Vector3f;
    6736: getstatic     #50                 // Field gfy$b.a:Lgfy$a;
    6739: invokespecial #53                 // Method gga."<init>":(FLorg/joml/Vector3fc;Lgfy$a;)V
    6742: aastore
    6743: invokespecial #57                 // Method gfy."<init>":(Lgfy$c;[Lgga;)V
    6746: invokevirtual #60                 // Method gfz$a.a:(Ljava/lang/String;Lgfy;)Lgfz$a;
    6749: ldc           #81                 // String right_hind_leg
    6751: new           #14                 // class gfy
    6754: dup
    6755: getstatic     #62                 // Field gfy$d.a:Lgfy$c;
    6758: bipush        6
    6760: anewarray     #42                 // class gga
    6763: dup
    6764: iconst_0
    6765: new           #42                 // class gga
    6768: dup
    6769: ldc           #165                // float 1.1f
    6771: fconst_0
    6772: ldc           #86                 // float 3.0f
    6774: ldc           #73                 // float -2.0f
    6776: invokestatic  #64                 // Method ggc.a:(FFF)Lorg/joml/Vector3f;
    6779: getstatic     #50                 // Field gfy$b.a:Lgfy$a;
    6782: invokespecial #53                 // Method gga."<init>":(FLorg/joml/Vector3fc;Lgfy$a;)V
    6785: aastore
    6786: dup
    6787: iconst_1
    6788: new           #42                 // class gga
    6791: dup
    6792: ldc           #164                // float 1.2f
    6794: fconst_0
    6795: ldc           #84                 // float 8.0f
    6797: ldc           #73                 // float -2.0f
    6799: invokestatic  #64                 // Method ggc.a:(FFF)Lorg/joml/Vector3f;
    6802: getstatic     #50                 // Field gfy$b.a:Lgfy$a;
    6805: invokespecial #53                 // Method gga."<init>":(FLorg/joml/Vector3fc;Lgfy$a;)V
    6808: aastore
    6809: dup
    6810: iconst_2
    6811: new           #42                 // class gga
    6814: dup
    6815: ldc           #150                // float 1.3f
    6817: ldc           #68                 // float -1.0f
    6819: ldc           #86                 // float 3.0f
    6821: fconst_0
    6822: invokestatic  #64                 // Method ggc.a:(FFF)Lorg/joml/Vector3f;
    6825: getstatic     #50                 // Field gfy$b.a:Lgfy$a;
    6828: invokespecial #53                 // Method gga."<init>":(FLorg/joml/Vector3fc;Lgfy$a;)V
    6831: aastore
    6832: dup
    6833: iconst_3
    6834: new           #42                 // class gga
    6837: dup
    6838: ldc           #201                // float 1.4f
    6840: fconst_0
    6841: fconst_0
    6842: fconst_0
    6843: invokestatic  #64                 // Method ggc.a:(FFF)Lorg/joml/Vector3f;
    6846: getstatic     #50                 // Field gfy$b.a:Lgfy$a;
    6849: invokespecial #53                 // Method gga."<init>":(FLorg/joml/Vector3fc;Lgfy$a;)V
    6852: aastore
    6853: dup
    6854: iconst_4
    6855: new           #42                 // class gga
    6858: dup
    6859: ldc           #202                // float 1.45f
    6861: fconst_0
    6862: fconst_0
    6863: fconst_0
    6864: invokestatic  #64                 // Method ggc.a:(FFF)Lorg/joml/Vector3f;
    6867: getstatic     #50                 // Field gfy$b.a:Lgfy$a;
    6870: invokespecial #53                 // Method gga."<init>":(FLorg/joml/Vector3fc;Lgfy$a;)V
    6873: aastore
    6874: dup
    6875: iconst_5
    6876: new           #42                 // class gga
    6879: dup
    6880: ldc           #185                // float 1.5f
    6882: fconst_0
    6883: fconst_0
    6884: fconst_0
    6885: invokestatic  #64                 // Method ggc.a:(FFF)Lorg/joml/Vector3f;
    6888: getstatic     #50                 // Field gfy$b.a:Lgfy$a;
    6891: invokespecial #53                 // Method gga."<init>":(FLorg/joml/Vector3fc;Lgfy$a;)V
    6894: aastore
    6895: invokespecial #57                 // Method gfy."<init>":(Lgfy$c;[Lgga;)V
    6898: invokevirtual #60                 // Method gfz$a.a:(Ljava/lang/String;Lgfy;)Lgfz$a;
    6901: ldc           #89                 // String left_hind_leg
    6903: new           #14                 // class gfy
    6906: dup
    6907: getstatic     #40                 // Field gfy$d.b:Lgfy$c;
    6910: iconst_5
    6911: anewarray     #42                 // class gga
    6914: dup
    6915: iconst_0
    6916: new           #42                 // class gga
    6919: dup
    6920: ldc           #165                // float 1.1f
    6922: fconst_0
    6923: fconst_0
    6924: fconst_0
    6925: invokestatic  #47                 // Method ggc.b:(FFF)Lorg/joml/Vector3f;
    6928: getstatic     #50                 // Field gfy$b.a:Lgfy$a;
    6931: invokespecial #53                 // Method gga."<init>":(FLorg/joml/Vector3fc;Lgfy$a;)V
    6934: aastore
    6935: dup
    6936: iconst_1
    6937: new           #42                 // class gga
    6940: dup
    6941: ldc           #150                // float 1.3f
    6943: fconst_0
    6944: fconst_0
    6945: ldc           #203                // float -30.0f
    6947: invokestatic  #47                 // Method ggc.b:(FFF)Lorg/joml/Vector3f;
    6950: getstatic     #50                 // Field gfy$b.a:Lgfy$a;
    6953: invokespecial #53                 // Method gga."<init>":(FLorg/joml/Vector3fc;Lgfy$a;)V
    6956: aastore
    6957: dup
    6958: iconst_2
    6959: new           #42                 // class gga
    6962: dup
    6963: ldc           #201                // float 1.4f
    6965: fconst_0
    6966: fconst_0
    6967: fconst_0
    6968: invokestatic  #47                 // Method ggc.b:(FFF)Lorg/joml/Vector3f;
    6971: getstatic     #50                 // Field gfy$b.a:Lgfy$a;
    6974: invokespecial #53                 // Method gga."<init>":(FLorg/joml/Vector3fc;Lgfy$a;)V
    6977: aastore
    6978: dup
    6979: iconst_3
    6980: new           #42                 // class gga
    6983: dup
    6984: ldc           #202                // float 1.45f
    6986: fconst_0
    6987: fconst_0
    6988: fconst_0
    6989: invokestatic  #47                 // Method ggc.b:(FFF)Lorg/joml/Vector3f;
    6992: getstatic     #50                 // Field gfy$b.a:Lgfy$a;
    6995: invokespecial #53                 // Method gga."<init>":(FLorg/joml/Vector3fc;Lgfy$a;)V
    6998: aastore
    6999: dup
    7000: iconst_4
    7001: new           #42                 // class gga
    7004: dup
    7005: ldc           #185                // float 1.5f
    7007: fconst_0
    7008: fconst_0
    7009: fconst_0
    7010: invokestatic  #47                 // Method ggc.b:(FFF)Lorg/joml/Vector3f;
    7013: getstatic     #50                 // Field gfy$b.a:Lgfy$a;
    7016: invokespecial #53                 // Method gga."<init>":(FLorg/joml/Vector3fc;Lgfy$a;)V
    7019: aastore
    7020: invokespecial #57                 // Method gfy."<init>":(Lgfy$c;[Lgga;)V
    7023: invokevirtual #60                 // Method gfz$a.a:(Ljava/lang/String;Lgfy;)Lgfz$a;
    7026: ldc           #89                 // String left_hind_leg
    7028: new           #14                 // class gfy
    7031: dup
    7032: getstatic     #62                 // Field gfy$d.a:Lgfy$c;
    7035: bipush        7
    7037: anewarray     #42                 // class gga
    7040: dup
    7041: iconst_0
    7042: new           #42                 // class gga
    7045: dup
    7046: ldc           #165                // float 1.1f
    7048: fconst_0
    7049: ldc           #86                 // float 3.0f
    7051: ldc           #73                 // float -2.0f
    7053: invokestatic  #64                 // Method ggc.a:(FFF)Lorg/joml/Vector3f;
    7056: getstatic     #50                 // Field gfy$b.a:Lgfy$a;
    7059: invokespecial #53                 // Method gga."<init>":(FLorg/joml/Vector3fc;Lgfy$a;)V
    7062: aastore
    7063: dup
    7064: iconst_1
    7065: new           #42                 // class gga
    7068: dup
    7069: ldc           #164                // float 1.2f
    7071: fconst_0
    7072: ldc           #84                 // float 8.0f
    7074: ldc           #73                 // float -2.0f
    7076: invokestatic  #64                 // Method ggc.a:(FFF)Lorg/joml/Vector3f;
    7079: getstatic     #50                 // Field gfy$b.a:Lgfy$a;
    7082: invokespecial #53                 // Method gga."<init>":(FLorg/joml/Vector3fc;Lgfy$a;)V
    7085: aastore
    7086: dup
    7087: iconst_2
    7088: new           #42                 // class gga
    7091: dup
    7092: ldc           #150                // float 1.3f
    7094: fconst_1
    7095: ldc           #86                 // float 3.0f
    7097: fconst_0
    7098: invokestatic  #64                 // Method ggc.a:(FFF)Lorg/joml/Vector3f;
    7101: getstatic     #50                 // Field gfy$b.a:Lgfy$a;
    7104: invokespecial #53                 // Method gga."<init>":(FLorg/joml/Vector3fc;Lgfy$a;)V
    7107: aastore
    7108: dup
    7109: iconst_3
    7110: new           #42                 // class gga
    7113: dup
    7114: ldc           #204                // float 1.35f
    7116: fconst_1
    7117: ldc           #86                 // float 3.0f
    7119: fconst_0
    7120: invokestatic  #64                 // Method ggc.a:(FFF)Lorg/joml/Vector3f;
    7123: getstatic     #50                 // Field gfy$b.a:Lgfy$a;
    7126: invokespecial #53                 // Method gga."<init>":(FLorg/joml/Vector3fc;Lgfy$a;)V
    7129: aastore
    7130: dup
    7131: iconst_4
    7132: new           #42                 // class gga
    7135: dup
    7136: ldc           #201                // float 1.4f
    7138: fconst_0
    7139: fconst_0
    7140: fconst_0
    7141: invokestatic  #64                 // Method ggc.a:(FFF)Lorg/joml/Vector3f;
    7144: getstatic     #50                 // Field gfy$b.a:Lgfy$a;
    7147: invokespecial #53                 // Method gga."<init>":(FLorg/joml/Vector3fc;Lgfy$a;)V
    7150: aastore
    7151: dup
    7152: iconst_5
    7153: new           #42                 // class gga
    7156: dup
    7157: ldc           #202                // float 1.45f
    7159: fconst_0
    7160: fconst_0
    7161: fconst_0
    7162: invokestatic  #64                 // Method ggc.a:(FFF)Lorg/joml/Vector3f;
    7165: getstatic     #50                 // Field gfy$b.a:Lgfy$a;
    7168: invokespecial #53                 // Method gga."<init>":(FLorg/joml/Vector3fc;Lgfy$a;)V
    7171: aastore
    7172: dup
    7173: bipush        6
    7175: new           #42                 // class gga
    7178: dup
    7179: ldc           #185                // float 1.5f
    7181: fconst_0
    7182: fconst_0
    7183: fconst_0
    7184: invokestatic  #64                 // Method ggc.a:(FFF)Lorg/joml/Vector3f;
    7187: getstatic     #50                 // Field gfy$b.a:Lgfy$a;
    7190: invokespecial #53                 // Method gga."<init>":(FLorg/joml/Vector3fc;Lgfy$a;)V
    7193: aastore
    7194: invokespecial #57                 // Method gfy."<init>":(Lgfy$c;[Lgga;)V
    7197: invokevirtual #60                 // Method gfz$a.a:(Ljava/lang/String;Lgfy;)Lgfz$a;
    7200: ldc           #92                 // String right_front_leg
    7202: new           #14                 // class gfy
    7205: dup
    7206: getstatic     #40                 // Field gfy$d.b:Lgfy$c;
    7209: bipush        10
    7211: anewarray     #42                 // class gga
    7214: dup
    7215: iconst_0
    7216: new           #42                 // class gga
    7219: dup
    7220: fconst_0
    7221: ldc           #173                // float -90.0f
    7223: fconst_0
    7224: fconst_0
    7225: invokestatic  #47                 // Method ggc.b:(FFF)Lorg/joml/Vector3f;
    7228: getstatic     #118                // Field gfy$b.b:Lgfy$a;
    7231: invokespecial #53                 // Method gga."<init>":(FLorg/joml/Vector3fc;Lgfy$a;)V
    7234: aastore
    7235: dup
    7236: iconst_1
    7237: new           #42                 // class gga
    7240: dup
    7241: ldc           #159                // float 0.05f
    7243: ldc           #173                // float -90.0f
    7245: fconst_0
    7246: fconst_0
    7247: invokestatic  #47                 // Method ggc.b:(FFF)Lorg/joml/Vector3f;
    7250: getstatic     #118                // Field gfy$b.b:Lgfy$a;
    7253: invokespecial #53                 // Method gga."<init>":(FLorg/joml/Vector3fc;Lgfy$a;)V
    7256: aastore
    7257: dup
    7258: iconst_2
    7259: new           #42                 // class gga
    7262: dup
    7263: ldc           #69                 // float 0.25f
    7265: ldc           #90                 // float -45.0f
    7267: fconst_0
    7268: fconst_0
    7269: invokestatic  #47                 // Method ggc.b:(FFF)Lorg/joml/Vector3f;
    7272: getstatic     #50                 // Field gfy$b.a:Lgfy$a;
    7275: invokespecial #53                 // Method gga."<init>":(FLorg/joml/Vector3fc;Lgfy$a;)V
    7278: aastore
    7279: dup
    7280: iconst_3
    7281: new           #42                 // class gga
    7284: dup
    7285: ldc           #205                // float 0.55f
    7287: ldc           #90                 // float -45.0f
    7289: fconst_0
    7290: fconst_0
    7291: invokestatic  #47                 // Method ggc.b:(FFF)Lorg/joml/Vector3f;
    7294: getstatic     #50                 // Field gfy$b.a:Lgfy$a;
    7297: invokespecial #53                 // Method gga."<init>":(FLorg/joml/Vector3fc;Lgfy$a;)V
    7300: aastore
    7301: dup
    7302: iconst_4
    7303: new           #42                 // class gga
    7306: dup
    7307: ldc           #107                // float 0.6f
    7309: ldc           #206                // float -92.5f
    7311: fconst_0
    7312: fconst_0
    7313: invokestatic  #47                 // Method ggc.b:(FFF)Lorg/joml/Vector3f;
    7316: getstatic     #118                // Field gfy$b.b:Lgfy$a;
    7319: invokespecial #53                 // Method gga."<init>":(FLorg/joml/Vector3fc;Lgfy$a;)V
    7322: aastore
    7323: dup
    7324: iconst_5
    7325: new           #42                 // class gga
    7328: dup
    7329: ldc           #165                // float 1.1f
    7331: ldc           #173                // float -90.0f
    7333: fconst_0
    7334: fconst_0
    7335: invokestatic  #47                 // Method ggc.b:(FFF)Lorg/joml/Vector3f;
    7338: getstatic     #118                // Field gfy$b.b:Lgfy$a;
    7341: invokespecial #53                 // Method gga."<init>":(FLorg/joml/Vector3fc;Lgfy$a;)V
    7344: aastore
    7345: dup
    7346: bipush        6
    7348: new           #42                 // class gga
    7351: dup
    7352: ldc           #150                // float 1.3f
    7354: fconst_0
    7355: fconst_0
    7356: ldc           #200                // float 30.0f
    7358: invokestatic  #47                 // Method ggc.b:(FFF)Lorg/joml/Vector3f;
    7361: getstatic     #118                // Field gfy$b.b:Lgfy$a;
    7364: invokespecial #53                 // Method gga."<init>":(FLorg/joml/Vector3fc;Lgfy$a;)V
    7367: aastore
    7368: dup
    7369: bipush        7
    7371: new           #42                 // class gga
    7374: dup
    7375: ldc           #201                // float 1.4f
    7377: fconst_0
    7378: fconst_0
    7379: fconst_0
    7380: invokestatic  #47                 // Method ggc.b:(FFF)Lorg/joml/Vector3f;
    7383: getstatic     #118                // Field gfy$b.b:Lgfy$a;
    7386: invokespecial #53                 // Method gga."<init>":(FLorg/joml/Vector3fc;Lgfy$a;)V
    7389: aastore
    7390: dup
    7391: bipush        8
    7393: new           #42                 // class gga
    7396: dup
    7397: ldc           #202                // float 1.45f
    7399: fconst_0
    7400: fconst_0
    7401: fconst_0
    7402: invokestatic  #47                 // Method ggc.b:(FFF)Lorg/joml/Vector3f;
    7405: getstatic     #50                 // Field gfy$b.a:Lgfy$a;
    7408: invokespecial #53                 // Method gga."<init>":(FLorg/joml/Vector3fc;Lgfy$a;)V
    7411: aastore
    7412: dup
    7413: bipush        9
    7415: new           #42                 // class gga
    7418: dup
    7419: ldc           #185                // float 1.5f
    7421: fconst_0
    7422: fconst_0
    7423: fconst_0
    7424: invokestatic  #47                 // Method ggc.b:(FFF)Lorg/joml/Vector3f;
    7427: getstatic     #118                // Field gfy$b.b:Lgfy$a;
    7430: invokespecial #53                 // Method gga."<init>":(FLorg/joml/Vector3fc;Lgfy$a;)V
    7433: aastore
    7434: invokespecial #57                 // Method gfy."<init>":(Lgfy$c;[Lgga;)V
    7437: invokevirtual #60                 // Method gfz$a.a:(Ljava/lang/String;Lgfy;)Lgfz$a;
    7440: ldc           #92                 // String right_front_leg
    7442: new           #14                 // class gfy
    7445: dup
    7446: getstatic     #62                 // Field gfy$d.a:Lgfy$c;
    7449: bipush        11
    7451: anewarray     #42                 // class gga
    7454: dup
    7455: iconst_0
    7456: new           #42                 // class gga
    7459: dup
    7460: fconst_0
    7461: ldc           #68                 // float -1.0f
    7463: fconst_2
    7464: fconst_2
    7465: invokestatic  #64                 // Method ggc.a:(FFF)Lorg/joml/Vector3f;
    7468: getstatic     #50                 // Field gfy$b.a:Lgfy$a;
    7471: invokespecial #53                 // Method gga."<init>":(FLorg/joml/Vector3fc;Lgfy$a;)V
    7474: aastore
    7475: dup
    7476: iconst_1
    7477: new           #42                 // class gga
    7480: dup
    7481: ldc           #159                // float 0.05f
    7483: ldc           #68                 // float -1.0f
    7485: fconst_2
    7486: fconst_2
    7487: invokestatic  #64                 // Method ggc.a:(FFF)Lorg/joml/Vector3f;
    7490: getstatic     #118                // Field gfy$b.b:Lgfy$a;
    7493: invokespecial #53                 // Method gga."<init>":(FLorg/joml/Vector3fc;Lgfy$a;)V
    7496: aastore
    7497: dup
    7498: iconst_2
    7499: new           #42                 // class gga
    7502: dup
    7503: ldc           #69                 // float 0.25f
    7505: ldc           #68                 // float -1.0f
    7507: fconst_2
    7508: ldc           #68                 // float -1.0f
    7510: invokestatic  #64                 // Method ggc.a:(FFF)Lorg/joml/Vector3f;
    7513: getstatic     #50                 // Field gfy$b.a:Lgfy$a;
    7516: invokespecial #53                 // Method gga."<init>":(FLorg/joml/Vector3fc;Lgfy$a;)V
    7519: aastore
    7520: dup
    7521: iconst_3
    7522: new           #42                 // class gga
    7525: dup
    7526: ldc           #205                // float 0.55f
    7528: ldc           #68                 // float -1.0f
    7530: fconst_2
    7531: ldc           #68                 // float -1.0f
    7533: invokestatic  #64                 // Method ggc.a:(FFF)Lorg/joml/Vector3f;
    7536: getstatic     #50                 // Field gfy$b.a:Lgfy$a;
    7539: invokespecial #53                 // Method gga."<init>":(FLorg/joml/Vector3fc;Lgfy$a;)V
    7542: aastore
    7543: dup
    7544: iconst_4
    7545: new           #42                 // class gga
    7548: dup
    7549: ldc           #145                // float 0.7f
    7551: ldc           #68                 // float -1.0f
    7553: fconst_2
    7554: ldc           #207                // float 2.63f
    7556: invokestatic  #64                 // Method ggc.a:(FFF)Lorg/joml/Vector3f;
    7559: getstatic     #118                // Field gfy$b.b:Lgfy$a;
    7562: invokespecial #53                 // Method gga."<init>":(FLorg/joml/Vector3fc;Lgfy$a;)V
    7565: aastore
    7566: dup
    7567: iconst_5
    7568: new           #42                 // class gga
    7571: dup
    7572: ldc           #165                // float 1.1f
    7574: ldc           #68                 // float -1.0f
    7576: fconst_2
    7577: fconst_2
    7578: invokestatic  #64                 // Method ggc.a:(FFF)Lorg/joml/Vector3f;
    7581: getstatic     #50                 // Field gfy$b.a:Lgfy$a;
    7584: invokespecial #53                 // Method gga."<init>":(FLorg/joml/Vector3fc;Lgfy$a;)V
    7587: aastore
    7588: dup
    7589: bipush        6
    7591: new           #42                 // class gga
    7594: dup
    7595: ldc           #164                // float 1.2f
    7597: ldc           #68                 // float -1.0f
    7599: ldc           #79                 // float 7.0f
    7601: fconst_2
    7602: invokestatic  #64                 // Method ggc.a:(FFF)Lorg/joml/Vector3f;
    7605: getstatic     #50                 // Field gfy$b.a:Lgfy$a;
    7608: invokespecial #53                 // Method gga."<init>":(FLorg/joml/Vector3fc;Lgfy$a;)V
    7611: aastore
    7612: dup
    7613: bipush        7
    7615: new           #42                 // class gga
    7618: dup
    7619: ldc           #150                // float 1.3f
    7621: ldc           #68                 // float -1.0f
    7623: ldc           #86                 // float 3.0f
    7625: fconst_0
    7626: invokestatic  #64                 // Method ggc.a:(FFF)Lorg/joml/Vector3f;
    7629: getstatic     #50                 // Field gfy$b.a:Lgfy$a;
    7632: invokespecial #53                 // Method gga."<init>":(FLorg/joml/Vector3fc;Lgfy$a;)V
    7635: aastore
    7636: dup
    7637: bipush        8
    7639: new           #42                 // class gga
    7642: dup
    7643: ldc           #201                // float 1.4f
    7645: fconst_0
    7646: fconst_0
    7647: fconst_0
    7648: invokestatic  #64                 // Method ggc.a:(FFF)Lorg/joml/Vector3f;
    7651: getstatic     #50                 // Field gfy$b.a:Lgfy$a;
    7654: invokespecial #53                 // Method gga."<init>":(FLorg/joml/Vector3fc;Lgfy$a;)V
    7657: aastore
    7658: dup
    7659: bipush        9
    7661: new           #42                 // class gga
    7664: dup
    7665: ldc           #202                // float 1.45f
    7667: fconst_0
    7668: fconst_0
    7669: fconst_0
    7670: invokestatic  #64                 // Method ggc.a:(FFF)Lorg/joml/Vector3f;
    7673: getstatic     #50                 // Field gfy$b.a:Lgfy$a;
    7676: invokespecial #53                 // Method gga."<init>":(FLorg/joml/Vector3fc;Lgfy$a;)V
    7679: aastore
    7680: dup
    7681: bipush        10
    7683: new           #42                 // class gga
    7686: dup
    7687: ldc           #185                // float 1.5f
    7689: fconst_0
    7690: fconst_0
    7691: fconst_0
    7692: invokestatic  #64                 // Method ggc.a:(FFF)Lorg/joml/Vector3f;
    7695: getstatic     #50                 // Field gfy$b.a:Lgfy$a;
    7698: invokespecial #53                 // Method gga."<init>":(FLorg/joml/Vector3fc;Lgfy$a;)V
    7701: aastore
    7702: invokespecial #57                 // Method gfy."<init>":(Lgfy$c;[Lgga;)V
    7705: invokevirtual #60                 // Method gfz$a.a:(Ljava/lang/String;Lgfy;)Lgfz$a;
    7708: ldc           #100                // String left_front_leg
    7710: new           #14                 // class gfy
    7713: dup
    7714: getstatic     #40                 // Field gfy$d.b:Lgfy$c;
    7717: bipush        10
    7719: anewarray     #42                 // class gga
    7722: dup
    7723: iconst_0
    7724: new           #42                 // class gga
    7727: dup
    7728: fconst_0
    7729: ldc           #173                // float -90.0f
    7731: fconst_0
    7732: fconst_0
    7733: invokestatic  #47                 // Method ggc.b:(FFF)Lorg/joml/Vector3f;
    7736: getstatic     #118                // Field gfy$b.b:Lgfy$a;
    7739: invokespecial #53                 // Method gga."<init>":(FLorg/joml/Vector3fc;Lgfy$a;)V
    7742: aastore
    7743: dup
    7744: iconst_1
    7745: new           #42                 // class gga
    7748: dup
    7749: ldc           #159                // float 0.05f
    7751: ldc           #173                // float -90.0f
    7753: fconst_0
    7754: fconst_0
    7755: invokestatic  #47                 // Method ggc.b:(FFF)Lorg/joml/Vector3f;
    7758: getstatic     #118                // Field gfy$b.b:Lgfy$a;
    7761: invokespecial #53                 // Method gga."<init>":(FLorg/joml/Vector3fc;Lgfy$a;)V
    7764: aastore
    7765: dup
    7766: iconst_2
    7767: new           #42                 // class gga
    7770: dup
    7771: ldc           #69                 // float 0.25f
    7773: ldc           #90                 // float -45.0f
    7775: fconst_0
    7776: fconst_0
    7777: invokestatic  #47                 // Method ggc.b:(FFF)Lorg/joml/Vector3f;
    7780: getstatic     #50                 // Field gfy$b.a:Lgfy$a;
    7783: invokespecial #53                 // Method gga."<init>":(FLorg/joml/Vector3fc;Lgfy$a;)V
    7786: aastore
    7787: dup
    7788: iconst_3
    7789: new           #42                 // class gga
    7792: dup
    7793: ldc           #205                // float 0.55f
    7795: ldc           #90                 // float -45.0f
    7797: fconst_0
    7798: fconst_0
    7799: invokestatic  #47                 // Method ggc.b:(FFF)Lorg/joml/Vector3f;
    7802: getstatic     #50                 // Field gfy$b.a:Lgfy$a;
    7805: invokespecial #53                 // Method gga."<init>":(FLorg/joml/Vector3fc;Lgfy$a;)V
    7808: aastore
    7809: dup
    7810: iconst_4
    7811: new           #42                 // class gga
    7814: dup
    7815: ldc           #107                // float 0.6f
    7817: ldc           #208                // float -87.5f
    7819: fconst_0
    7820: fconst_0
    7821: invokestatic  #47                 // Method ggc.b:(FFF)Lorg/joml/Vector3f;
    7824: getstatic     #118                // Field gfy$b.b:Lgfy$a;
    7827: invokespecial #53                 // Method gga."<init>":(FLorg/joml/Vector3fc;Lgfy$a;)V
    7830: aastore
    7831: dup
    7832: iconst_5
    7833: new           #42                 // class gga
    7836: dup
    7837: ldc           #165                // float 1.1f
    7839: ldc           #173                // float -90.0f
    7841: fconst_0
    7842: fconst_0
    7843: invokestatic  #47                 // Method ggc.b:(FFF)Lorg/joml/Vector3f;
    7846: getstatic     #118                // Field gfy$b.b:Lgfy$a;
    7849: invokespecial #53                 // Method gga."<init>":(FLorg/joml/Vector3fc;Lgfy$a;)V
    7852: aastore
    7853: dup
    7854: bipush        6
    7856: new           #42                 // class gga
    7859: dup
    7860: ldc           #150                // float 1.3f
    7862: fconst_0
    7863: fconst_0
    7864: ldc           #203                // float -30.0f
    7866: invokestatic  #47                 // Method ggc.b:(FFF)Lorg/joml/Vector3f;
    7869: getstatic     #118                // Field gfy$b.b:Lgfy$a;
    7872: invokespecial #53                 // Method gga."<init>":(FLorg/joml/Vector3fc;Lgfy$a;)V
    7875: aastore
    7876: dup
    7877: bipush        7
    7879: new           #42                 // class gga
    7882: dup
    7883: ldc           #201                // float 1.4f
    7885: fconst_0
    7886: fconst_0
    7887: fconst_0
    7888: invokestatic  #47                 // Method ggc.b:(FFF)Lorg/joml/Vector3f;
    7891: getstatic     #118                // Field gfy$b.b:Lgfy$a;
    7894: invokespecial #53                 // Method gga."<init>":(FLorg/joml/Vector3fc;Lgfy$a;)V
    7897: aastore
    7898: dup
    7899: bipush        8
    7901: new           #42                 // class gga
    7904: dup
    7905: ldc           #202                // float 1.45f
    7907: fconst_0
    7908: fconst_0
    7909: fconst_0
    7910: invokestatic  #47                 // Method ggc.b:(FFF)Lorg/joml/Vector3f;
    7913: getstatic     #50                 // Field gfy$b.a:Lgfy$a;
    7916: invokespecial #53                 // Method gga."<init>":(FLorg/joml/Vector3fc;Lgfy$a;)V
    7919: aastore
    7920: dup
    7921: bipush        9
    7923: new           #42                 // class gga
    7926: dup
    7927: ldc           #185                // float 1.5f
    7929: fconst_0
    7930: fconst_0
    7931: fconst_0
    7932: invokestatic  #47                 // Method ggc.b:(FFF)Lorg/joml/Vector3f;
    7935: getstatic     #118                // Field gfy$b.b:Lgfy$a;
    7938: invokespecial #53                 // Method gga."<init>":(FLorg/joml/Vector3fc;Lgfy$a;)V
    7941: aastore
    7942: invokespecial #57                 // Method gfy."<init>":(Lgfy$c;[Lgga;)V
    7945: invokevirtual #60                 // Method gfz$a.a:(Ljava/lang/String;Lgfy;)Lgfz$a;
    7948: ldc           #100                // String left_front_leg
    7950: new           #14                 // class gfy
    7953: dup
    7954: getstatic     #62                 // Field gfy$d.a:Lgfy$c;
    7957: bipush        14
    7959: anewarray     #42                 // class gga
    7962: dup
    7963: iconst_0
    7964: new           #42                 // class gga
    7967: dup
    7968: fconst_0
    7969: fconst_1
    7970: fconst_2
    7971: fconst_2
    7972: invokestatic  #64                 // Method ggc.a:(FFF)Lorg/joml/Vector3f;
    7975: getstatic     #118                // Field gfy$b.b:Lgfy$a;
    7978: invokespecial #53                 // Method gga."<init>":(FLorg/joml/Vector3fc;Lgfy$a;)V
    7981: aastore
    7982: dup
    7983: iconst_1
    7984: new           #42                 // class gga
    7987: dup
    7988: ldc           #159                // float 0.05f
    7990: fconst_1
    7991: fconst_2
    7992: fconst_2
    7993: invokestatic  #64                 // Method ggc.a:(FFF)Lorg/joml/Vector3f;
    7996: getstatic     #118                // Field gfy$b.b:Lgfy$a;
    7999: invokespecial #53                 // Method gga."<init>":(FLorg/joml/Vector3fc;Lgfy$a;)V
    8002: aastore
    8003: dup
    8004: iconst_2
    8005: new           #42                 // class gga
    8008: dup
    8009: ldc           #142                // float 0.15f
    8011: fconst_1
    8012: fconst_2
    8013: fconst_0
    8014: invokestatic  #64                 // Method ggc.a:(FFF)Lorg/joml/Vector3f;
    8017: getstatic     #118                // Field gfy$b.b:Lgfy$a;
    8020: invokespecial #53                 // Method gga."<init>":(FLorg/joml/Vector3fc;Lgfy$a;)V
    8023: aastore
    8024: dup
    8025: iconst_3
    8026: new           #42                 // class gga
    8029: dup
    8030: ldc           #69                 // float 0.25f
    8032: fconst_1
    8033: fconst_2
    8034: ldc           #68                 // float -1.0f
    8036: invokestatic  #64                 // Method ggc.a:(FFF)Lorg/joml/Vector3f;
    8039: getstatic     #50                 // Field gfy$b.a:Lgfy$a;
    8042: invokespecial #53                 // Method gga."<init>":(FLorg/joml/Vector3fc;Lgfy$a;)V
    8045: aastore
    8046: dup
    8047: iconst_4
    8048: new           #42                 // class gga
    8051: dup
    8052: ldc           #205                // float 0.55f
    8054: fconst_1
    8055: fconst_2
    8056: ldc           #68                 // float -1.0f
    8058: invokestatic  #64                 // Method ggc.a:(FFF)Lorg/joml/Vector3f;
    8061: getstatic     #50                 // Field gfy$b.a:Lgfy$a;
    8064: invokespecial #53                 // Method gga."<init>":(FLorg/joml/Vector3fc;Lgfy$a;)V
    8067: aastore
    8068: dup
    8069: iconst_5
    8070: new           #42                 // class gga
    8073: dup
    8074: ldc           #145                // float 0.7f
    8076: fconst_1
    8077: fconst_2
    8078: ldc           #209                // float 1.88f
    8080: invokestatic  #64                 // Method ggc.a:(FFF)Lorg/joml/Vector3f;
    8083: getstatic     #118                // Field gfy$b.b:Lgfy$a;
    8086: invokespecial #53                 // Method gga."<init>":(FLorg/joml/Vector3fc;Lgfy$a;)V
    8089: aastore
    8090: dup
    8091: bipush        6
    8093: new           #42                 // class gga
    8096: dup
    8097: ldc           #128                // float 0.75f
    8099: fconst_1
    8100: fconst_2
    8101: ldc           #210                // float 2.67f
    8103: invokestatic  #64                 // Method ggc.a:(FFF)Lorg/joml/Vector3f;
    8106: getstatic     #118                // Field gfy$b.b:Lgfy$a;
    8109: invokespecial #53                 // Method gga."<init>":(FLorg/joml/Vector3fc;Lgfy$a;)V
    8112: aastore
    8113: dup
    8114: bipush        7
    8116: new           #42                 // class gga
    8119: dup
    8120: ldc           #165                // float 1.1f
    8122: fconst_1
    8123: fconst_2
    8124: fconst_2
    8125: invokestatic  #64                 // Method ggc.a:(FFF)Lorg/joml/Vector3f;
    8128: getstatic     #118                // Field gfy$b.b:Lgfy$a;
    8131: invokespecial #53                 // Method gga."<init>":(FLorg/joml/Vector3fc;Lgfy$a;)V
    8134: aastore
    8135: dup
    8136: bipush        8
    8138: new           #42                 // class gga
    8141: dup
    8142: ldc           #164                // float 1.2f
    8144: fconst_1
    8145: ldc           #84                 // float 8.0f
    8147: fconst_2
    8148: invokestatic  #64                 // Method ggc.a:(FFF)Lorg/joml/Vector3f;
    8151: getstatic     #118                // Field gfy$b.b:Lgfy$a;
    8154: invokespecial #53                 // Method gga."<init>":(FLorg/joml/Vector3fc;Lgfy$a;)V
    8157: aastore
    8158: dup
    8159: bipush        9
    8161: new           #42                 // class gga
    8164: dup
    8165: ldc           #125                // float 1.25f
    8167: ldc           #211                // float 1.06f
    8169: ldc           #212                // float 5.06f
    8171: fconst_1
    8172: invokestatic  #64                 // Method ggc.a:(FFF)Lorg/joml/Vector3f;
    8175: getstatic     #118                // Field gfy$b.b:Lgfy$a;
    8178: invokespecial #53                 // Method gga."<init>":(FLorg/joml/Vector3fc;Lgfy$a;)V
    8181: aastore
    8182: dup
    8183: bipush        10
    8185: new           #42                 // class gga
    8188: dup
    8189: ldc           #150                // float 1.3f
    8191: fconst_1
    8192: ldc           #86                 // float 3.0f
    8194: fconst_0
    8195: invokestatic  #64                 // Method ggc.a:(FFF)Lorg/joml/Vector3f;
    8198: getstatic     #118                // Field gfy$b.b:Lgfy$a;
    8201: invokespecial #53                 // Method gga."<init>":(FLorg/joml/Vector3fc;Lgfy$a;)V
    8204: aastore
    8205: dup
    8206: bipush        11
    8208: new           #42                 // class gga
    8211: dup
    8212: ldc           #201                // float 1.4f
    8214: fconst_0
    8215: fconst_0
    8216: fconst_0
    8217: invokestatic  #64                 // Method ggc.a:(FFF)Lorg/joml/Vector3f;
    8220: getstatic     #118                // Field gfy$b.b:Lgfy$a;
    8223: invokespecial #53                 // Method gga."<init>":(FLorg/joml/Vector3fc;Lgfy$a;)V
    8226: aastore
    8227: dup
    8228: bipush        12
    8230: new           #42                 // class gga
    8233: dup
    8234: ldc           #202                // float 1.45f
    8236: fconst_0
    8237: fconst_0
    8238: fconst_0
    8239: invokestatic  #64                 // Method ggc.a:(FFF)Lorg/joml/Vector3f;
    8242: getstatic     #50                 // Field gfy$b.a:Lgfy$a;
    8245: invokespecial #53                 // Method gga."<init>":(FLorg/joml/Vector3fc;Lgfy$a;)V
    8248: aastore
    8249: dup
    8250: bipush        13
    8252: new           #42                 // class gga
    8255: dup
    8256: ldc           #185                // float 1.5f
    8258: fconst_0
    8259: fconst_0
    8260: fconst_0
    8261: invokestatic  #64                 // Method ggc.a:(FFF)Lorg/joml/Vector3f;
    8264: getstatic     #118                // Field gfy$b.b:Lgfy$a;
    8267: invokespecial #53                 // Method gga."<init>":(FLorg/joml/Vector3fc;Lgfy$a;)V
    8270: aastore
    8271: invokespecial #57                 // Method gfy."<init>":(Lgfy$c;[Lgga;)V
    8274: invokevirtual #60                 // Method gfz$a.a:(Ljava/lang/String;Lgfy;)Lgfz$a;
    8277: ldc           #103                // String cube
    8279: new           #14                 // class gfy
    8282: dup
    8283: getstatic     #40                 // Field gfy$d.b:Lgfy$c;
    8286: bipush        11
    8288: anewarray     #42                 // class gga
    8291: dup
    8292: iconst_0
    8293: new           #42                 // class gga
    8296: dup
    8297: fconst_0
    8298: fconst_0
    8299: fconst_0
    8300: fconst_0
    8301: invokestatic  #47                 // Method ggc.b:(FFF)Lorg/joml/Vector3f;
    8304: getstatic     #50                 // Field gfy$b.a:Lgfy$a;
    8307: invokespecial #53                 // Method gga."<init>":(FLorg/joml/Vector3fc;Lgfy$a;)V
    8310: aastore
    8311: dup
    8312: iconst_1
    8313: new           #42                 // class gga
    8316: dup
    8317: ldc           #159                // float 0.05f
    8319: ldc           #177                // float 15.0f
    8321: fconst_0
    8322: fconst_0
    8323: invokestatic  #47                 // Method ggc.b:(FFF)Lorg/joml/Vector3f;
    8326: getstatic     #50                 // Field gfy$b.a:Lgfy$a;
    8329: invokespecial #53                 // Method gga."<init>":(FLorg/joml/Vector3fc;Lgfy$a;)V
    8332: aastore
    8333: dup
    8334: iconst_2
    8335: new           #42                 // class gga
    8338: dup
    8339: ldc           #142                // float 0.15f
    8341: ldc           #147                // float -7.5f
    8343: fconst_0
    8344: fconst_0
    8345: invokestatic  #47                 // Method ggc.b:(FFF)Lorg/joml/Vector3f;
    8348: getstatic     #50                 // Field gfy$b.a:Lgfy$a;
    8351: invokespecial #53                 // Method gga."<init>":(FLorg/joml/Vector3fc;Lgfy$a;)V
    8354: aastore
    8355: dup
    8356: iconst_3
    8357: new           #42                 // class gga
    8360: dup
    8361: ldc           #69                 // float 0.25f
    8363: fconst_0
    8364: fconst_0
    8365: fconst_0
    8366: invokestatic  #47                 // Method ggc.b:(FFF)Lorg/joml/Vector3f;
    8369: getstatic     #50                 // Field gfy$b.a:Lgfy$a;
    8372: invokespecial #53                 // Method gga."<init>":(FLorg/joml/Vector3fc;Lgfy$a;)V
    8375: aastore
    8376: dup
    8377: iconst_4
    8378: new           #42                 // class gga
    8381: dup
    8382: ldc           #145                // float 0.7f
    8384: fconst_0
    8385: fconst_0
    8386: fconst_0
    8387: invokestatic  #47                 // Method ggc.b:(FFF)Lorg/joml/Vector3f;
    8390: getstatic     #50                 // Field gfy$b.a:Lgfy$a;
    8393: invokespecial #53                 // Method gga."<init>":(FLorg/joml/Vector3fc;Lgfy$a;)V
    8396: aastore
    8397: dup
    8398: iconst_5
    8399: new           #42                 // class gga
    8402: dup
    8403: ldc           #128                // float 0.75f
    8405: ldc           #179                // float -17.5f
    8407: fconst_0
    8408: fconst_0
    8409: invokestatic  #47                 // Method ggc.b:(FFF)Lorg/joml/Vector3f;
    8412: getstatic     #50                 // Field gfy$b.a:Lgfy$a;
    8415: invokespecial #53                 // Method gga."<init>":(FLorg/joml/Vector3fc;Lgfy$a;)V
    8418: aastore
    8419: dup
    8420: bipush        6
    8422: new           #42                 // class gga
    8425: dup
    8426: ldc           #187                // float 0.85f
    8428: ldc           #157                // float -25.0f
    8430: fconst_0
    8431: fconst_0
    8432: invokestatic  #47                 // Method ggc.b:(FFF)Lorg/joml/Vector3f;
    8435: getstatic     #50                 // Field gfy$b.a:Lgfy$a;
    8438: invokespecial #53                 // Method gga."<init>":(FLorg/joml/Vector3fc;Lgfy$a;)V
    8441: aastore
    8442: dup
    8443: bipush        7
    8445: new           #42                 // class gga
    8448: dup
    8449: ldc           #146                // float 0.9f
    8451: fconst_0
    8452: fconst_0
    8453: fconst_0
    8454: invokestatic  #47                 // Method ggc.b:(FFF)Lorg/joml/Vector3f;
    8457: getstatic     #50                 // Field gfy$b.a:Lgfy$a;
    8460: invokespecial #53                 // Method gga."<init>":(FLorg/joml/Vector3fc;Lgfy$a;)V
    8463: aastore
    8464: dup
    8465: bipush        8
    8467: new           #42                 // class gga
    8470: dup
    8471: ldc           #188                // float 0.95f
    8473: ldc           #181                // float 12.5f
    8475: fconst_0
    8476: fconst_0
    8477: invokestatic  #47                 // Method ggc.b:(FFF)Lorg/joml/Vector3f;
    8480: getstatic     #50                 // Field gfy$b.a:Lgfy$a;
    8483: invokespecial #53                 // Method gga."<init>":(FLorg/joml/Vector3fc;Lgfy$a;)V
    8486: aastore
    8487: dup
    8488: bipush        9
    8490: new           #42                 // class gga
    8493: dup
    8494: ldc           #189                // float 1.05f
    8496: fconst_0
    8497: fconst_0
    8498: fconst_0
    8499: invokestatic  #47                 // Method ggc.b:(FFF)Lorg/joml/Vector3f;
    8502: getstatic     #50                 // Field gfy$b.a:Lgfy$a;
    8505: invokespecial #53                 // Method gga."<init>":(FLorg/joml/Vector3fc;Lgfy$a;)V
    8508: aastore
    8509: dup
    8510: bipush        10
    8512: new           #42                 // class gga
    8515: dup
    8516: ldc           #165                // float 1.1f
    8518: fconst_0
    8519: fconst_0
    8520: fconst_0
    8521: invokestatic  #47                 // Method ggc.b:(FFF)Lorg/joml/Vector3f;
    8524: getstatic     #50                 // Field gfy$b.a:Lgfy$a;
    8527: invokespecial #53                 // Method gga."<init>":(FLorg/joml/Vector3fc;Lgfy$a;)V
    8530: aastore
    8531: invokespecial #57                 // Method gfy."<init>":(Lgfy$c;[Lgga;)V
    8534: invokevirtual #60                 // Method gfz$a.a:(Ljava/lang/String;Lgfy;)Lgfz$a;
    8537: ldc           #103                // String cube
    8539: new           #14                 // class gfy
    8542: dup
    8543: getstatic     #62                 // Field gfy$d.a:Lgfy$c;
    8546: bipush        13
    8548: anewarray     #42                 // class gga
    8551: dup
    8552: iconst_0
    8553: new           #42                 // class gga
    8556: dup
    8557: fconst_0
    8558: fconst_0
    8559: fconst_0
    8560: fconst_0
    8561: invokestatic  #64                 // Method ggc.a:(FFF)Lorg/joml/Vector3f;
    8564: getstatic     #50                 // Field gfy$b.a:Lgfy$a;
    8567: invokespecial #53                 // Method gga."<init>":(FLorg/joml/Vector3fc;Lgfy$a;)V
    8570: aastore
    8571: dup
    8572: iconst_1
    8573: new           #42                 // class gga
    8576: dup
    8577: ldc           #159                // float 0.05f
    8579: fconst_0
    8580: ldc           #154                // float 1.6f
    8582: fconst_0
    8583: invokestatic  #64                 // Method ggc.a:(FFF)Lorg/joml/Vector3f;
    8586: getstatic     #50                 // Field gfy$b.a:Lgfy$a;
    8589: invokespecial #53                 // Method gga."<init>":(FLorg/joml/Vector3fc;Lgfy$a;)V
    8592: aastore
    8593: dup
    8594: iconst_2
    8595: new           #42                 // class gga
    8598: dup
    8599: ldc           #142                // float 0.15f
    8601: fconst_0
    8602: ldc           #32                 // float 0.5f
    8604: fconst_0
    8605: invokestatic  #64                 // Method ggc.a:(FFF)Lorg/joml/Vector3f;
    8608: getstatic     #50                 // Field gfy$b.a:Lgfy$a;
    8611: invokespecial #53                 // Method gga."<init>":(FLorg/joml/Vector3fc;Lgfy$a;)V
    8614: aastore
    8615: dup
    8616: iconst_3
    8617: new           #42                 // class gga
    8620: dup
    8621: ldc           #69                 // float 0.25f
    8623: fconst_0
    8624: fconst_0
    8625: fconst_0
    8626: invokestatic  #64                 // Method ggc.a:(FFF)Lorg/joml/Vector3f;
    8629: getstatic     #50                 // Field gfy$b.a:Lgfy$a;
    8632: invokespecial #53                 // Method gga."<init>":(FLorg/joml/Vector3fc;Lgfy$a;)V
    8635: aastore
    8636: dup
    8637: iconst_4
    8638: new           #42                 // class gga
    8641: dup
    8642: ldc           #145                // float 0.7f
    8644: fconst_0
    8645: fconst_0
    8646: fconst_0
    8647: invokestatic  #64                 // Method ggc.a:(FFF)Lorg/joml/Vector3f;
    8650: getstatic     #50                 // Field gfy$b.a:Lgfy$a;
    8653: invokespecial #53                 // Method gga."<init>":(FLorg/joml/Vector3fc;Lgfy$a;)V
    8656: aastore
    8657: dup
    8658: iconst_5
    8659: new           #42                 // class gga
    8662: dup
    8663: ldc           #128                // float 0.75f
    8665: fconst_0
    8666: ldc           #164                // float 1.2f
    8668: fconst_0
    8669: invokestatic  #64                 // Method ggc.a:(FFF)Lorg/joml/Vector3f;
    8672: getstatic     #50                 // Field gfy$b.a:Lgfy$a;
    8675: invokespecial #53                 // Method gga."<init>":(FLorg/joml/Vector3fc;Lgfy$a;)V
    8678: aastore
    8679: dup
    8680: bipush        6
    8682: new           #42                 // class gga
    8685: dup
    8686: ldc           #187                // float 0.85f
    8688: fconst_0
    8689: ldc           #182                // float 1.7f
    8691: fconst_0
    8692: invokestatic  #64                 // Method ggc.a:(FFF)Lorg/joml/Vector3f;
    8695: getstatic     #50                 // Field gfy$b.a:Lgfy$a;
    8698: invokespecial #53                 // Method gga."<init>":(FLorg/joml/Vector3fc;Lgfy$a;)V
    8701: aastore
    8702: dup
    8703: bipush        7
    8705: new           #42                 // class gga
    8708: dup
    8709: ldc           #146                // float 0.9f
    8711: fconst_0
    8712: fconst_0
    8713: fconst_0
    8714: invokestatic  #64                 // Method ggc.a:(FFF)Lorg/joml/Vector3f;
    8717: getstatic     #50                 // Field gfy$b.a:Lgfy$a;
    8720: invokespecial #53                 // Method gga."<init>":(FLorg/joml/Vector3fc;Lgfy$a;)V
    8723: aastore
    8724: dup
    8725: bipush        8
    8727: new           #42                 // class gga
    8730: dup
    8731: ldc           #188                // float 0.95f
    8733: fconst_0
    8734: ldc           #150                // float 1.3f
    8736: fconst_0
    8737: invokestatic  #64                 // Method ggc.a:(FFF)Lorg/joml/Vector3f;
    8740: getstatic     #50                 // Field gfy$b.a:Lgfy$a;
    8743: invokespecial #53                 // Method gga."<init>":(FLorg/joml/Vector3fc;Lgfy$a;)V
    8746: aastore
    8747: dup
    8748: bipush        9
    8750: new           #42                 // class gga
    8753: dup
    8754: ldc           #189                // float 1.05f
    8756: fconst_0
    8757: fconst_0
    8758: fconst_0
    8759: invokestatic  #64                 // Method ggc.a:(FFF)Lorg/joml/Vector3f;
    8762: getstatic     #50                 // Field gfy$b.a:Lgfy$a;
    8765: invokespecial #53                 // Method gga."<init>":(FLorg/joml/Vector3fc;Lgfy$a;)V
    8768: aastore
    8769: dup
    8770: bipush        10
    8772: new           #42                 // class gga
    8775: dup
    8776: ldc           #164                // float 1.2f
    8778: fconst_0
    8779: ldc           #65                 // float 5.0f
    8781: fconst_0
    8782: invokestatic  #64                 // Method ggc.a:(FFF)Lorg/joml/Vector3f;
    8785: getstatic     #50                 // Field gfy$b.a:Lgfy$a;
    8788: invokespecial #53                 // Method gga."<init>":(FLorg/joml/Vector3fc;Lgfy$a;)V
    8791: aastore
    8792: dup
    8793: bipush        11
    8795: new           #42                 // class gga
    8798: dup
    8799: ldc           #125                // float 1.25f
    8801: fconst_0
    8802: ldc           #84                 // float 8.0f
    8804: fconst_0
    8805: invokestatic  #64                 // Method ggc.a:(FFF)Lorg/joml/Vector3f;
    8808: getstatic     #50                 // Field gfy$b.a:Lgfy$a;
    8811: invokespecial #53                 // Method gga."<init>":(FLorg/joml/Vector3fc;Lgfy$a;)V
    8814: aastore
    8815: dup
    8816: bipush        12
    8818: new           #42                 // class gga
    8821: dup
    8822: ldc           #185                // float 1.5f
    8824: fconst_0
    8825: fconst_1
    8826: fconst_0
    8827: invokestatic  #64                 // Method ggc.a:(FFF)Lorg/joml/Vector3f;
    8830: getstatic     #50                 // Field gfy$b.a:Lgfy$a;
    8833: invokespecial #53                 // Method gga."<init>":(FLorg/joml/Vector3fc;Lgfy$a;)V
    8836: aastore
    8837: invokespecial #57                 // Method gfy."<init>":(Lgfy$c;[Lgga;)V
    8840: invokevirtual #60                 // Method gfz$a.a:(Ljava/lang/String;Lgfy;)Lgfz$a;
    8843: ldc           #37                 // String body
    8845: new           #14                 // class gfy
    8848: dup
    8849: getstatic     #62                 // Field gfy$d.a:Lgfy$c;
    8852: bipush        6
    8854: anewarray     #42                 // class gga
    8857: dup
    8858: iconst_0
    8859: new           #42                 // class gga
    8862: dup
    8863: ldc           #165                // float 1.1f
    8865: fconst_0
    8866: fconst_0
    8867: fconst_0
    8868: invokestatic  #64                 // Method ggc.a:(FFF)Lorg/joml/Vector3f;
    8871: getstatic     #50                 // Field gfy$b.a:Lgfy$a;
    8874: invokespecial #53                 // Method gga."<init>":(FLorg/joml/Vector3fc;Lgfy$a;)V
    8877: aastore
    8878: dup
    8879: iconst_1
    8880: new           #42                 // class gga
    8883: dup
    8884: ldc           #164                // float 1.2f
    8886: fconst_0
    8887: ldc           #160                // float 4.0f
    8889: fconst_0
    8890: invokestatic  #64                 // Method ggc.a:(FFF)Lorg/joml/Vector3f;
    8893: getstatic     #50                 // Field gfy$b.a:Lgfy$a;
    8896: invokespecial #53                 // Method gga."<init>":(FLorg/joml/Vector3fc;Lgfy$a;)V
    8899: aastore
    8900: dup
    8901: iconst_2
    8902: new           #42                 // class gga
    8905: dup
    8906: ldc           #125                // float 1.25f
    8908: fconst_0
    8909: ldc           #65                 // float 5.0f
    8911: fconst_0
    8912: invokestatic  #64                 // Method ggc.a:(FFF)Lorg/joml/Vector3f;
    8915: getstatic     #50                 // Field gfy$b.a:Lgfy$a;
    8918: invokespecial #53                 // Method gga."<init>":(FLorg/joml/Vector3fc;Lgfy$a;)V
    8921: aastore
    8922: dup
    8923: iconst_3
    8924: new           #42                 // class gga
    8927: dup
    8928: ldc           #150                // float 1.3f
    8930: fconst_0
    8931: ldc           #160                // float 4.0f
    8933: fconst_0
    8934: invokestatic  #64                 // Method ggc.a:(FFF)Lorg/joml/Vector3f;
    8937: getstatic     #50                 // Field gfy$b.a:Lgfy$a;
    8940: invokespecial #53                 // Method gga."<init>":(FLorg/joml/Vector3fc;Lgfy$a;)V
    8943: aastore
    8944: dup
    8945: iconst_4
    8946: new           #42                 // class gga
    8949: dup
    8950: ldc           #201                // float 1.4f
    8952: fconst_0
    8953: ldc           #68                 // float -1.0f
    8955: fconst_0
    8956: invokestatic  #64                 // Method ggc.a:(FFF)Lorg/joml/Vector3f;
    8959: getstatic     #50                 // Field gfy$b.a:Lgfy$a;
    8962: invokespecial #53                 // Method gga."<init>":(FLorg/joml/Vector3fc;Lgfy$a;)V
    8965: aastore
    8966: dup
    8967: iconst_5
    8968: new           #42                 // class gga
    8971: dup
    8972: ldc           #185                // float 1.5f
    8974: fconst_0
    8975: fconst_0
    8976: fconst_0
    8977: invokestatic  #64                 // Method ggc.a:(FFF)Lorg/joml/Vector3f;
    8980: getstatic     #50                 // Field gfy$b.a:Lgfy$a;
    8983: invokespecial #53                 // Method gga."<init>":(FLorg/joml/Vector3fc;Lgfy$a;)V
    8986: aastore
    8987: invokespecial #57                 // Method gfy."<init>":(Lgfy$c;[Lgga;)V
    8990: invokevirtual #60                 // Method gfz$a.a:(Ljava/lang/String;Lgfy;)Lgfz$a;
    8993: invokevirtual #110                // Method gfz$a.b:()Lgfz;
    8996: putstatic     #214                // Field d:Lgfz;
    8999: return
}